Workbook
Name zsupermetrics_refreshAllSilent: #REF!
Name zsupermetrics_refreshAll: #REF!
Name zsupermetrics_forceRefresh: #REF!

Sheet Acompanhamento Geral
A1: DATA | B1: DIA | C1: AÇÃO DO DIA | D1: VALOR INVESTIDO | E1: FATURAMENTO | F1: ROAS | G1: CPS | H1: TAXA DE CONVERSÃO | I1: CPA | J1: PEDIDOS | K1: SESSÕES | L1: TICKET MÉDIO | M1: META INVESTIMENTO | N1: META FATURAMENTO | O1: META ROAS | P1: CPS META | Q1: META TAXA DE CONVERSÃO | R1: CPA META | S1: META SESSÕES | T1: META TICKET MÉDIO
A2: JANEIRO | B2: 31 | D2: =IFERROR(SUM(D3:D33),"") -> 1695.67 | E2: =iferror(SUM(E3:E33),"") -> 0 | F2: =iferror(E2/D2,"") -> 0 | G2: =iferror(D2/K2,"") -> 10.467099 | H2: =iferror(J2/K2,"") -> 0.012345679 | I2: =iferror(D2/J2,"") -> 847.835 | J2: =iferror(SUM(J3:J33),"") -> 2 | K2: =IFERROR(SUM(K3:K33),"") -> 162 | L2: =iferror(E2/J2,"") -> 0 | M2: =iferror(Planejador!$I$4,"") | N2: =iferror(Planejador!$I$13,"") | O2: =iferror(Planejador!$I$14,"") | P2: =iferror(Planejador!$I$5,"") | Q2: =Iferror(Planejador!$I$7,"") | R2: =iferror(Planejador!$I$11,"") | S2: =iferror(Planejador!$I$10,"") | T2: =iferror(Planejador!$I$6,"")
A3: 46023 | B3: =TEXT(A3,"dddd") -> quinta-feira | D3: =SUMIF('ADV - GG'!A:A,A3,'ADV - GG'!C:C)+SUMIF('ADV - FB'!A:A,$A3,'ADV - FB'!E:E) -> 13.26 | F3: =IFERROR(E3/D3,"") -> 0 | G3: =IFERROR(D3/K3,"") | H3: =iferror(J3/K3,"") | I3: =iferror(D3/J3,"") | J3: =SUMIF('ADV - GG'!A:A,A3,'ADV - GG'!H:H)+SUMIF('ADV - FB'!A:A,$A3,'ADV - FB'!I:I) -> 0 | K3: =SUMIF('ADV - GA4'!A:A,A3,'ADV - GA4'!C:C) -> 0 | L3: =IFERROR(E3/J3,"") | M3: =$M$2/$B$2 -> 0 | N3: =$N$2/$B$2 -> 0 | O3: =iferror(Planejador!$I$14,"") | P3: =Planejador!$I$5 | Q3: =Planejador!$I$7 | R3: =Planejador!$I$11 -> #DIV/0! | S3: =$S$2/$B$2 -> 0 | T3: =Planejador!$I$6
A4: 46024 | B4: =TEXT(A4,"dddd") -> sexta-feira | D4: =SUMIF('ADV - GG'!A:A,A4,'ADV - GG'!C:C)+SUMIF('ADV - FB'!A:A,$A4,'ADV - FB'!E:E) -> 35.08 | F4: =IFERROR(E4/D4,"") -> 0 | G4: =IFERROR(D4/K4,"") -> 35.08 | H4: =iferror(J4/K4,"") -> 0 | I4: =iferror(D4/J4,"") | J4: =SUMIF('ADV - GG'!A:A,A4,'ADV - GG'!H:H)+SUMIF('ADV - FB'!A:A,$A4,'ADV - FB'!I:I) -> 0 | K4: =SUMIF('ADV - GA4'!A:A,A4,'ADV - GA4'!C:C) -> 1 | L4: =IFERROR(E4/J4,"") | M4: =$M$2/$B$2 -> 0 | N4: =$N$2/$B$2 -> 0 | O4: =iferror(Planejador!$I$14,"") | P4: =Planejador!$I$5 | Q4: =Planejador!$I$7 | R4: =Planejador!$I$11 -> #DIV/0! | S4: =$S$2/$B$2 -> 0 | T4: =Planejador!$I$6
A5: 46025 | B5: =TEXT(A5,"dddd") -> sábado | D5: =SUMIF('ADV - GG'!A:A,A5,'ADV - GG'!C:C)+SUMIF('ADV - FB'!A:A,$A5,'ADV - FB'!E:E) -> 26.1 | F5: =IFERROR(E5/D5,"") -> 0 | G5: =IFERROR(D5/K5,"") -> 13.05 | H5: =iferror(J5/K5,"") -> 0 | I5: =iferror(D5/J5,"") | J5: =SUMIF('ADV - GG'!A:A,A5,'ADV - GG'!H:H)+SUMIF('ADV - FB'!A:A,$A5,'ADV - FB'!I:I) -> 0 | K5: =SUMIF('ADV - GA4'!A:A,A5,'ADV - GA4'!C:C) -> 2 | L5: =IFERROR(E5/J5,"") | M5: =$M$2/$B$2 -> 0 | N5: =$N$2/$B$2 -> 0 | O5: =iferror(Planejador!$I$14,"") | P5: =Planejador!$I$5 | Q5: =Planejador!$I$7 | R5: =Planejador!$I$11 -> #DIV/0! | S5: =$S$2/$B$2 -> 0 | T5: =Planejador!$I$6
A6: 46026 | B6: =TEXT(A6,"dddd") -> domingo | D6: =SUMIF('ADV - GG'!A:A,A6,'ADV - GG'!C:C)+SUMIF('ADV - FB'!A:A,$A6,'ADV - FB'!E:E) -> 43.39 | F6: =IFERROR(E6/D6,"") -> 0 | G6: =IFERROR(D6/K6,"") -> 14.463333 | H6: =iferror(J6/K6,"") -> 0 | I6: =iferror(D6/J6,"") | J6: =SUMIF('ADV - GG'!A:A,A6,'ADV - GG'!H:H)+SUMIF('ADV - FB'!A:A,$A6,'ADV - FB'!I:I) -> 0 | K6: =SUMIF('ADV - GA4'!A:A,A6,'ADV - GA4'!C:C) -> 3 | L6: =IFERROR(E6/J6,"") | M6: =$M$2/$B$2 -> 0 | N6: =$N$2/$B$2 -> 0 | O6: =iferror(Planejador!$I$14,"") | P6: =Planejador!$I$5 | Q6: =Planejador!$I$7 | R6: =Planejador!$I$11 -> #DIV/0! | S6: =$S$2/$B$2 -> 0 | T6: =Planejador!$I$6
A7: 46027 | B7: =TEXT(A7,"dddd") -> segunda-feira | D7: =SUMIF('ADV - GG'!A:A,A7,'ADV - GG'!C:C)+SUMIF('ADV - FB'!A:A,$A7,'ADV - FB'!E:E) -> 27.17 | F7: =IFERROR(E7/D7,"") -> 0 | G7: =IFERROR(D7/K7,"") -> 3.39625 | H7: =iferror(J7/K7,"") -> 0.25 | I7: =iferror(D7/J7,"") -> 13.585 | J7: =SUMIF('ADV - GG'!A:A,A7,'ADV - GG'!H:H)+SUMIF('ADV - FB'!A:A,$A7,'ADV - FB'!I:I) -> 2 | K7: =SUMIF('ADV - GA4'!A:A,A7,'ADV - GA4'!C:C) -> 8 | L7: =IFERROR(E7/J7,"") -> 0 | M7: =$M$2/$B$2 -> 0 | N7: =$N$2/$B$2 -> 0 | O7: =iferror(Planejador!$I$14,"") | P7: =Planejador!$I$5 | Q7: =Planejador!$I$7 | R7: =Planejador!$I$11 -> #DIV/0! | S7: =$S$2/$B$2 -> 0 | T7: =Planejador!$I$6
A8: 46028 | B8: =TEXT(A8,"dddd") -> terça-feira | D8: =SUMIF('ADV - GG'!A:A,A8,'ADV - GG'!C:C)+SUMIF('ADV - FB'!A:A,$A8,'ADV - FB'!E:E) -> 18.77 | F8: =IFERROR(E8/D8,"") -> 0 | G8: =IFERROR(D8/K8,"") -> 3.754 | H8: =iferror(J8/K8,"") -> 0 | I8: =iferror(D8/J8,"") | J8: =SUMIF('ADV - GG'!A:A,A8,'ADV - GG'!H:H)+SUMIF('ADV - FB'!A:A,$A8,'ADV - FB'!I:I) -> 0 | K8: =SUMIF('ADV - GA4'!A:A,A8,'ADV - GA4'!C:C) -> 5 | L8: =IFERROR(E8/J8,"") | M8: =$M$2/$B$2 -> 0 | N8: =$N$2/$B$2 -> 0 | O8: =iferror(Planejador!$I$14,"") | P8: =Planejador!$I$5 | Q8: =Planejador!$I$7 | R8: =Planejador!$I$11 -> #DIV/0! | S8: =$S$2/$B$2 -> 0 | T8: =Planejador!$I$6
A9: 46029 | B9: =TEXT(A9,"dddd") -> quarta-feira | D9: =SUMIF('ADV - GG'!A:A,A9,'ADV - GG'!C:C)+SUMIF('ADV - FB'!A:A,$A9,'ADV - FB'!E:E) -> 16.91 | F9: =IFERROR(E9/D9,"") -> 0 | G9: =IFERROR(D9/K9,"") -> 3.382 | H9: =iferror(J9/K9,"") -> 0 | I9: =iferror(D9/J9,"") | J9: =SUMIF('ADV - GG'!A:A,A9,'ADV - GG'!H:H)+SUMIF('ADV - FB'!A:A,$A9,'ADV - FB'!I:I) -> 0 | K9: =SUMIF('ADV - GA4'!A:A,A9,'ADV - GA4'!C:C) -> 5 | L9: =IFERROR(E9/J9,"") | M9: =$M$2/$B$2 -> 0 | N9: =$N$2/$B$2 -> 0 | O9: =iferror(Planejador!$I$14,"") | P9: =Planejador!$I$5 | Q9: =Planejador!$I$7 | R9: =Planejador!$I$11 -> #DIV/0! | S9: =$S$2/$B$2 -> 0 | T9: =Planejador!$I$6
A10: 46030 | B10: =TEXT(A10,"dddd") -> quinta-feira | D10: =SUMIF('ADV - GG'!A:A,A10,'ADV - GG'!C:C)+SUMIF('ADV - FB'!A:A,$A10,'ADV - FB'!E:E) -> 24.63 | F10: =IFERROR(E10/D10,"") -> 0 | G10: =IFERROR(D10/K10,"") -> 24.63 | H10: =iferror(J10/K10,"") -> 0 | I10: =iferror(D10/J10,"") | J10: =SUMIF('ADV - GG'!A:A,A10,'ADV - GG'!H:H)+SUMIF('ADV - FB'!A:A,$A10,'ADV - FB'!I:I) -> 0 | K10: =SUMIF('ADV - GA4'!A:A,A10,'ADV - GA4'!C:C) -> 1 | L10: =IFERROR(E10/J10,"") | M10: =$M$2/$B$2 -> 0 | N10: =$N$2/$B$2 -> 0 | O10: =iferror(Planejador!$I$14,"") | P10: =Planejador!$I$5 | Q10: =Planejador!$I$7 | R10: =Planejador!$I$11 -> #DIV/0! | S10: =$S$2/$B$2 -> 0 | T10: =Planejador!$I$6
A11: 46031 | B11: =TEXT(A11,"dddd") -> sexta-feira | D11: =SUMIF('ADV - GG'!A:A,A11,'ADV - GG'!C:C)+SUMIF('ADV - FB'!A:A,$A11,'ADV - FB'!E:E) -> 20.05 | F11: =IFERROR(E11/D11,"") -> 0 | G11: =IFERROR(D11/K11,"") -> 2.8642857 | H11: =iferror(J11/K11,"") -> 0 | I11: =iferror(D11/J11,"") | J11: =SUMIF('ADV - GG'!A:A,A11,'ADV - GG'!H:H)+SUMIF('ADV - FB'!A:A,$A11,'ADV - FB'!I:I) -> 0 | K11: =SUMIF('ADV - GA4'!A:A,A11,'ADV - GA4'!C:C) -> 7 | L11: =IFERROR(E11/J11,"") | M11: =$M$2/$B$2 -> 0 | N11: =$N$2/$B$2 -> 0 | O11: =iferror(Planejador!$I$14,"") | P11: =Planejador!$I$5 | Q11: =Planejador!$I$7 | R11: =Planejador!$I$11 -> #DIV/0! | S11: =$S$2/$B$2 -> 0 | T11: =Planejador!$I$6
A12: 46032 | B12: =TEXT(A12,"dddd") -> sábado | D12: =SUMIF('ADV - GG'!A:A,A12,'ADV - GG'!C:C)+SUMIF('ADV - FB'!A:A,$A12,'ADV - FB'!E:E) -> 29.7 | F12: =IFERROR(E12/D12,"") -> 0 | G12: =IFERROR(D12/K12,"") -> 29.7 | H12: =iferror(J12/K12,"") -> 0 | I12: =iferror(D12/J12,"") | J12: =SUMIF('ADV - GG'!A:A,A12,'ADV - GG'!H:H)+SUMIF('ADV - FB'!A:A,$A12,'ADV - FB'!I:I) -> 0 | K12: =SUMIF('ADV - GA4'!A:A,A12,'ADV - GA4'!C:C) -> 1 | L12: =IFERROR(E12/J12,"") | M12: =$M$2/$B$2 -> 0 | N12: =$N$2/$B$2 -> 0 | O12: =iferror(Planejador!$I$14,"") | P12: =Planejador!$I$5 | Q12: =Planejador!$I$7 | R12: =Planejador!$I$11 -> #DIV/0! | S12: =$S$2/$B$2 -> 0 | T12: =Planejador!$I$6
A13: 46033 | B13: =TEXT(A13,"dddd") -> domingo | D13: =SUMIF('ADV - GG'!A:A,A13,'ADV - GG'!C:C)+SUMIF('ADV - FB'!A:A,$A13,'ADV - FB'!E:E) -> 39.73 | F13: =IFERROR(E13/D13,"") -> 0 | G13: =IFERROR(D13/K13,"") -> 5.6757143 | H13: =iferror(J13/K13,"") -> 0 | I13: =iferror(D13/J13,"") | J13: =SUMIF('ADV - GG'!A:A,A13,'ADV - GG'!H:H)+SUMIF('ADV - FB'!A:A,$A13,'ADV - FB'!I:I) -> 0 | K13: =SUMIF('ADV - GA4'!A:A,A13,'ADV - GA4'!C:C) -> 7 | L13: =IFERROR(E13/J13,"") | M13: =$M$2/$B$2 -> 0 | N13: =$N$2/$B$2 -> 0 | O13: =iferror(Planejador!$I$14,"") | P13: =Planejador!$I$5 | Q13: =Planejador!$I$7 | R13: =Planejador!$I$11 -> #DIV/0! | S13: =$S$2/$B$2 -> 0 | T13: =Planejador!$I$6
A14: 46034 | B14: =TEXT(A14,"dddd") -> segunda-feira | D14: =SUMIF('ADV - GG'!A:A,A14,'ADV - GG'!C:C)+SUMIF('ADV - FB'!A:A,$A14,'ADV - FB'!E:E) -> 53.64 | F14: =IFERROR(E14/D14,"") -> 0 | G14: =IFERROR(D14/K14,"") -> 4.8763636 | H14: =iferror(J14/K14,"") -> 0 | I14: =iferror(D14/J14,"") | J14: =SUMIF('ADV - GG'!A:A,A14,'ADV - GG'!H:H)+SUMIF('ADV - FB'!A:A,$A14,'ADV - FB'!I:I) -> 0 | K14: =SUMIF('ADV - GA4'!A:A,A14,'ADV - GA4'!C:C) -> 11 | L14: =IFERROR(E14/J14,"") | M14: =$M$2/$B$2 -> 0 | N14: =$N$2/$B$2 -> 0 | O14: =iferror(Planejador!$I$14,"") | P14: =Planejador!$I$5 | Q14: =Planejador!$I$7 | R14: =Planejador!$I$11 -> #DIV/0! | S14: =$S$2/$B$2 -> 0 | T14: =Planejador!$I$6
... A33: 46053 | B33: =TEXT(A33,"dddd") -> sábado | D33: =SUMIF('ADV - GG'!A:A,A33,'ADV - GG'!C:C)+SUMIF('ADV - FB'!A:A,$A33,'ADV - FB'!E:E) -> 71.29 | F33: =IFERROR(E33/D33,"") -> 0 | G33: =IFERROR(D33/K33,"") -> 71.29 | H33: =iferror(J33/K33,"") -> 0 | I33: =iferror(D33/J33,"") | J33: =SUMIF('ADV - GG'!A:A,A33,'ADV - GG'!H:H)+SUMIF('ADV - FB'!A:A,$A33,'ADV - FB'!I:I) -> 0 | K33: =SUMIF('ADV - GA4'!A:A,A33,'ADV - GA4'!C:C) -> 1 | L33: =IFERROR(E33/J33,"") | M33: =$M$2/$B$2 -> 0 | N33: =$N$2/$B$2 -> 0 | O33: =iferror(Planejador!$I$14,"") | P33: =Planejador!$I$5 | Q33: =Planejador!$I$7 | R33: =Planejador!$I$11 -> #DIV/0! | S33: =$S$2/$B$2 -> 0 | T33: =Planejador!$I$6
A34: FEVEREIRO | B34: =COUNTA(A35:A63) -> 29 | D34: =IFERROR(SUM(D35:D63),"") -> 1640.2 | E34: =iferror(SUM(E35:E63),"") -> 0 | F34: =iferror(E34/D34,"") -> 0 | G34: =iferror(D34/K34,"") -> 5.1741325 | H34: =iferror(J34/K34,"") -> 0.14511041 | I34: =iferror(D34/J34,"") -> 35.656522 | J34: =iferror(SUM(J35:J63),"") -> 46 | K34: =IFERROR(SUM(K35:K63),"") -> 317 | L34: =iferror(E34/J34,"") -> 0 | M34: =Planejador!$I$27 | N34: =IFERROR(Planejador!$I$36,"") | O34: =IFERROR(Planejador!$I$37,"") | P34: =Planejador!$I$28 | Q34: =Planejador!$I$30 | R34: =iferror(Planejador!$I$34,"") | S34: =iferror(Planejador!$I$33,"") | T34: =iferror(Planejador!$I$29,"")
A35: 46054 | B35: =TEXT(A35,"dddd") -> domingo | D35: =SUMIF('ADV - GG'!A:A,A35,'ADV - GG'!C:C)+SUMIF('ADV - FB'!A:A,$A35,'ADV - FB'!E:E) -> 89.37 | F35: =IFERROR(E35/D35,"") -> 0 | G35: =IFERROR(D35/K33,"") -> 89.37 | H35: =iferror(J35/K35,"") -> 0 | I35: =iferror(D35/J35,"") | J35: =SUMIF('ADV - GG'!A:A,A35,'ADV - GG'!H:H)+SUMIF('ADV - FB'!A:A,$A35,'ADV - FB'!I:I) -> 0 | K35: =SUMIF('ADV - GA4'!A:A,A35,'ADV - GA4'!C:C) -> 129 | L35: =IFERROR(E35/J35,"") | M35: =$M$34/$B$34 -> 0 | N35: =$N$34/$B$34 -> 0 | O35: =IFERROR(Planejador!$I$37,"") | P35: =Planejador!$I$28 | Q35: =Planejador!$I$30 | R35: =iferror(Planejador!$I$34,"") | S35: =$S$34/$B$34 -> 0 | T35: =iferror(Planejador!$I$29,"")
A36: 46055 | B36: =TEXT(A36,"dddd") -> segunda-feira | D36: =SUMIF('ADV - GG'!A:A,A36,'ADV - GG'!C:C)+SUMIF('ADV - FB'!A:A,$A36,'ADV - FB'!E:E) -> 39.12 | F36: =IFERROR(E36/D36,"") -> 0 | G36: =IFERROR(D36/K34,"") -> 0.12340694 | H36: =iferror(J36/K36,"") -> 0 | I36: =iferror(D36/J36,"") | J36: =SUMIF('ADV - GG'!A:A,A36,'ADV - GG'!H:H)+SUMIF('ADV - FB'!A:A,$A36,'ADV - FB'!I:I) -> 0 | K36: =SUMIF('ADV - GA4'!A:A,A36,'ADV - GA4'!C:C) -> 47 | L36: =IFERROR(E36/J36,"") | M36: =$M$34/$B$34 -> 0 | N36: =$N$34/$B$34 -> 0 | O36: =IFERROR(Planejador!$I$37,"") | P36: =Planejador!$I$28 | Q36: =Planejador!$I$30 | R36: =iferror(Planejador!$I$34,"") | S36: =$S$34/$B$34 -> 0 | T36: =iferror(Planejador!$I$29,"")
A37: 46056 | B37: =TEXT(A37,"dddd") -> terça-feira | D37: =SUMIF('ADV - GG'!A:A,A37,'ADV - GG'!C:C)+SUMIF('ADV - FB'!A:A,$A37,'ADV - FB'!E:E) -> 122.42 | F37: =IFERROR(E37/D37,"") -> 0 | G37: =IFERROR(D37/K35,"") -> 0.94899225 | H37: =iferror(J37/K37,"") -> 0 | I37: =iferror(D37/J37,"") | J37: =SUMIF('ADV - GG'!A:A,A37,'ADV - GG'!H:H)+SUMIF('ADV - FB'!A:A,$A37,'ADV - FB'!I:I) -> 0 | K37: =SUMIF('ADV - GA4'!A:A,A37,'ADV - GA4'!C:C) -> 19 | L37: =IFERROR(E37/J37,"") | M37: =$M$34/$B$34 -> 0 | N37: =$N$34/$B$34 -> 0 | O37: =IFERROR(Planejador!$I$37,"") | P37: =Planejador!$I$28 | Q37: =Planejador!$I$30 | R37: =iferror(Planejador!$I$34,"") | S37: =$S$34/$B$34 -> 0 | T37: =iferror(Planejador!$I$29,"")
A38: 46057 | B38: =TEXT(A38,"dddd") -> quarta-feira | D38: =SUMIF('ADV - GG'!A:A,A38,'ADV - GG'!C:C)+SUMIF('ADV - FB'!A:A,$A38,'ADV - FB'!E:E) -> 80.8 | F38: =IFERROR(E38/D38,"") -> 0 | G38: =IFERROR(D38/K36,"") -> 1.7191489 | H38: =iferror(J38/K38,"") -> 0 | I38: =iferror(D38/J38,"") | J38: =SUMIF('ADV - GG'!A:A,A38,'ADV - GG'!H:H)+SUMIF('ADV - FB'!A:A,$A38,'ADV - FB'!I:I) -> 0 | K38: =SUMIF('ADV - GA4'!A:A,A38,'ADV - GA4'!C:C) -> 25 | L38: =IFERROR(E38/J38,"") | M38: =$M$34/$B$34 -> 0 | N38: =$N$34/$B$34 -> 0 | O38: =IFERROR(Planejador!$I$37,"") | P38: =Planejador!$I$28 | Q38: =Planejador!$I$30 | R38: =iferror(Planejador!$I$34,"") | S38: =$S$34/$B$34 -> 0 | T38: =iferror(Planejador!$I$29,"")
A39: 46058 | B39: =TEXT(A39,"dddd") -> quinta-feira | D39: =SUMIF('ADV - GG'!A:A,A39,'ADV - GG'!C:C)+SUMIF('ADV - FB'!A:A,$A39,'ADV - FB'!E:E) -> 78.11 | F39: =IFERROR(E39/D39,"") -> 0 | G39: =IFERROR(D39/K37,"") -> 4.1110526 | H39: =iferror(J39/K39,"") -> 0.08 | I39: =iferror(D39/J39,"") -> 39.055 | J39: =SUMIF('ADV - GG'!A:A,A39,'ADV - GG'!H:H)+SUMIF('ADV - FB'!A:A,$A39,'ADV - FB'!I:I) -> 2 | K39: =SUMIF('ADV - GA4'!A:A,A39,'ADV - GA4'!C:C) -> 25 | L39: =IFERROR(E39/J39,"") -> 0 | M39: =$M$34/$B$34 -> 0 | N39: =$N$34/$B$34 -> 0 | O39: =IFERROR(Planejador!$I$37,"") | P39: =Planejador!$I$28 | Q39: =Planejador!$I$30 | R39: =iferror(Planejador!$I$34,"") | S39: =$S$34/$B$34 -> 0 | T39: =iferror(Planejador!$I$29,"")
A40: 46059 | B40: =TEXT(A40,"dddd") -> sexta-feira | D40: =SUMIF('ADV - GG'!A:A,A40,'ADV - GG'!C:C)+SUMIF('ADV - FB'!A:A,$A40,'ADV - FB'!E:E) -> 101.89 | F40: =IFERROR(E40/D40,"") -> 0 | G40: =IFERROR(D40/K38,"") -> 4.0756 | H40: =iferror(J40/K40,"") -> 0.5 | I40: =iferror(D40/J40,"") -> 101.89 | J40: =SUMIF('ADV - GG'!A:A,A40,'ADV - GG'!H:H)+SUMIF('ADV - FB'!A:A,$A40,'ADV - FB'!I:I) -> 1 | K40: =SUMIF('ADV - GA4'!A:A,A40,'ADV - GA4'!C:C) -> 2 | L40: =IFERROR(E40/J40,"") -> 0 | M40: =$M$34/$B$34 -> 0 | N40: =$N$34/$B$34 -> 0 | O40: =IFERROR(Planejador!$I$37,"") | P40: =Planejador!$I$28 | Q40: =Planejador!$I$30 | R40: =iferror(Planejador!$I$34,"") | S40: =$S$34/$B$34 -> 0 | T40: =iferror(Planejador!$I$29,"")
A41: 46060 | B41: =TEXT(A41,"dddd") -> sábado | D41: =SUMIF('ADV - GG'!A:A,A41,'ADV - GG'!C:C)+SUMIF('ADV - FB'!A:A,$A41,'ADV - FB'!E:E) -> 12.11 | F41: =IFERROR(E41/D41,"") -> 0 | G41: =IFERROR(D41/K39,"") -> 0.4844 | H41: =iferror(J41/K41,"") -> 0 | I41: =iferror(D41/J41,"") | J41: =SUMIF('ADV - GG'!A:A,A41,'ADV - GG'!H:H)+SUMIF('ADV - FB'!A:A,$A41,'ADV - FB'!I:I) -> 0 | K41: =SUMIF('ADV - GA4'!A:A,A41,'ADV - GA4'!C:C) -> 8 | L41: =IFERROR(E41/J41,"") | M41: =$M$34/$B$34 -> 0 | N41: =$N$34/$B$34 -> 0 | O41: =IFERROR(Planejador!$I$37,"") | P41: =Planejador!$I$28 | Q41: =Planejador!$I$30 | R41: =iferror(Planejador!$I$34,"") | S41: =$S$34/$B$34 -> 0 | T41: =iferror(Planejador!$I$29,"")
A42: 46061 | B42: =TEXT(A42,"dddd") -> domingo | D42: =SUMIF('ADV - GG'!A:A,A42,'ADV - GG'!C:C)+SUMIF('ADV - FB'!A:A,$A42,'ADV - FB'!E:E) -> 0 | F42: =IFERROR(E42/D42,"") | G42: =IFERROR(D42/K40,"") -> 0 | H42: =iferror(J42/K42,"") -> 0 | I42: =iferror(D42/J42,"") | J42: =SUMIF('ADV - GG'!A:A,A42,'ADV - GG'!H:H)+SUMIF('ADV - FB'!A:A,$A42,'ADV - FB'!I:I) -> 0 | K42: =SUMIF('ADV - GA4'!A:A,A42,'ADV - GA4'!C:C) -> 4 | L42: =IFERROR(E42/J42,"") | M42: =$M$34/$B$34 -> 0 | N42: =$N$34/$B$34 -> 0 | O42: =IFERROR(Planejador!$I$37,"") | P42: =Planejador!$I$28 | Q42: =Planejador!$I$30 | R42: =iferror(Planejador!$I$34,"") | S42: =$S$34/$B$34 -> 0 | T42: =iferror(Planejador!$I$29,"")
A43: 46062 | B43: =TEXT(A43,"dddd") -> segunda-feira | D43: =SUMIF('ADV - GG'!A:A,A43,'ADV - GG'!C:C)+SUMIF('ADV - FB'!A:A,$A43,'ADV - FB'!E:E) -> 125.59 | F43: =IFERROR(E43/D43,"") -> 0 | G43: =IFERROR(D43/K41,"") -> 15.69875 | H43: =iferror(J43/K43,"") -> 2 | I43: =iferror(D43/J43,"") -> 31.3975 | J43: =SUMIF('ADV - GG'!A:A,A43,'ADV - GG'!H:H)+SUMIF('ADV - FB'!A:A,$A43,'ADV - FB'!I:I) -> 4 | K43: =SUMIF('ADV - GA4'!A:A,A43,'ADV - GA4'!C:C) -> 2 | L43: =IFERROR(E43/J43,"") -> 0 | M43: =$M$34/$B$34 -> 0 | N43: =$N$34/$B$34 -> 0 | O43: =IFERROR(Planejador!$I$37,"") | P43: =Planejador!$I$28 | Q43: =Planejador!$I$30 | R43: =iferror(Planejador!$I$34,"") | S43: =$S$34/$B$34 -> 0 | T43: =iferror(Planejador!$I$29,"")
A44: 46063 | B44: =TEXT(A44,"dddd") -> terça-feira | D44: =SUMIF('ADV - GG'!A:A,A44,'ADV - GG'!C:C)+SUMIF('ADV - FB'!A:A,$A44,'ADV - FB'!E:E) -> 108.07 | F44: =IFERROR(E44/D44,"") -> 0 | G44: =IFERROR(D44/K42,"") -> 27.0175 | H44: =iferror(J44/K44,"") -> 0.5 | I44: =iferror(D44/J44,"") -> 54.035 | J44: =SUMIF('ADV - GG'!A:A,A44,'ADV - GG'!H:H)+SUMIF('ADV - FB'!A:A,$A44,'ADV - FB'!I:I) -> 2 | K44: =SUMIF('ADV - GA4'!A:A,A44,'ADV - GA4'!C:C) -> 4 | L44: =IFERROR(E44/J44,"") -> 0 | M44: =$M$34/$B$34 -> 0 | N44: =$N$34/$B$34 -> 0 | O44: =IFERROR(Planejador!$I$37,"") | P44: =Planejador!$I$28 | Q44: =Planejador!$I$30 | R44: =iferror(Planejador!$I$34,"") | S44: =$S$34/$B$34 -> 0 | T44: =iferror(Planejador!$I$29,"")
A45: 46064 | B45: =TEXT(A45,"dddd") -> quarta-feira | D45: =SUMIF('ADV - GG'!A:A,A45,'ADV - GG'!C:C)+SUMIF('ADV - FB'!A:A,$A45,'ADV - FB'!E:E) -> 105.34 | F45: =IFERROR(E45/D45,"") -> 0 | G45: =IFERROR(D45/K43,"") -> 52.67 | H45: =iferror(J45/K45,"") -> 1.4 | I45: =iferror(D45/J45,"") -> 15.048571 | J45: =SUMIF('ADV - GG'!A:A,A45,'ADV - GG'!H:H)+SUMIF('ADV - FB'!A:A,$A45,'ADV - FB'!I:I) -> 7 | K45: =SUMIF('ADV - GA4'!A:A,A45,'ADV - GA4'!C:C) -> 5 | L45: =IFERROR(E45/J45,"") -> 0 | M45: =$M$34/$B$34 -> 0 | N45: =$N$34/$B$34 -> 0 | O45: =IFERROR(Planejador!$I$37,"") | P45: =Planejador!$I$28 | Q45: =Planejador!$I$30 | R45: =iferror(Planejador!$I$34,"") | S45: =$S$34/$B$34 -> 0 | T45: =iferror(Planejador!$I$29,"")
A46: 46065 | B46: =TEXT(A46,"dddd") -> quinta-feira | D46: =SUMIF('ADV - GG'!A:A,A46,'ADV - GG'!C:C)+SUMIF('ADV - FB'!A:A,$A46,'ADV - FB'!E:E) -> 56.33 | F46: =IFERROR(E46/D46,"") -> 0 | G46: =IFERROR(D46/K44,"") -> 14.0825 | H46: =iferror(J46/K46,"") -> 0.5 | I46: =iferror(D46/J46,"") -> 56.33 | J46: =SUMIF('ADV - GG'!A:A,A46,'ADV - GG'!H:H)+SUMIF('ADV - FB'!A:A,$A46,'ADV - FB'!I:I) -> 1 | K46: =SUMIF('ADV - GA4'!A:A,A46,'ADV - GA4'!C:C) -> 2 | L46: =IFERROR(E46/J46,"") -> 0 | M46: =$M$34/$B$34 -> 0 | N46: =$N$34/$B$34 -> 0 | O46: =IFERROR(Planejador!$I$37,"") | P46: =Planejador!$I$28 | Q46: =Planejador!$I$30 | R46: =iferror(Planejador!$I$34,"") | S46: =$S$34/$B$34 -> 0 | T46: =iferror(Planejador!$I$29,"")
... A62: 46081 | B62: =TEXT(A62,"dddd") -> sábado | D62: =SUMIF('ADV - GG'!A:A,A62,'ADV - GG'!C:C)+SUMIF('ADV - FB'!A:A,$A62,'ADV - FB'!E:E) -> 35.17 | F62: =IFERROR(E62/D62,"") -> 0 | G62: =IFERROR(D62/K60,"") -> 3.9077778 | H62: =iferror(J62/K62,"") -> 1 | I62: =iferror(D62/J62,"") -> 17.585 | J62: =SUMIF('ADV - GG'!A:A,A62,'ADV - GG'!H:H)+SUMIF('ADV - FB'!A:A,$A62,'ADV - FB'!I:I) -> 2 | K62: =SUMIF('ADV - GA4'!A:A,A62,'ADV - GA4'!C:C) -> 2 | L62: =IFERROR(E62/J62,"") -> 0 | M62: =$M$34/$B$34 -> 0 | N62: =$N$34/$B$34 -> 0 | O62: =IFERROR(Planejador!$I$37,"") | P62: =Planejador!$I$28 | Q62: =Planejador!$I$30 | R62: =iferror(Planejador!$I$34,"") | S62: =$S$34/$B$34 -> 0 | T62: =iferror(Planejador!$I$29,"")
A63: 29/02/2026 | B63: =TEXT(A63,"dddd") -> 29/02/2026 | D63: =SUMIF('ADV - GG'!A:A,A63,'ADV - GG'!C:C)+SUMIF('ADV - FB'!A:A,$A63,'ADV - FB'!E:E) -> 0 | F63: =IFERROR(E63/D63,"") | G63: =IFERROR(D63/K61,"") -> 0 | H63: =iferror(J63/K63,"") | I63: =iferror(D63/J63,"") | J63: =SUMIF('ADV - GG'!A:A,A63,'ADV - GG'!H:H)+SUMIF('ADV - FB'!A:A,$A63,'ADV - FB'!I:I) -> 0 | K63: =SUMIF('ADV - GA4'!A:A,A63,'ADV - GA4'!C:C) -> 0 | L63: =IFERROR(E63/J63,"") | M63: =$M$34/$B$34 -> 0 | N63: =$N$34/$B$34 -> 0 | O63: =IFERROR(Planejador!$I$37,"") | P63: =Planejador!$I$28 | Q63: =Planejador!$I$30 | R63: =iferror(Planejador!$I$34,"") | S63: =$S$34/$B$34 -> 0 | T63: =iferror(Planejador!$I$29,"")
A64: MARÇO | B64: 31 | D64: =IFERROR(SUM(D65:D95),"") -> 1935.08 | E64: =iferror(SUM(E65:E95),"") -> 0 | F64: =iferror(E64/D64,"") -> 0 | G64: =iferror(D64/K64,"") -> 15.117812 | H64: =iferror(J64/K64,"") -> 0.4921875 | I64: =iferror(D64/J64,"") -> 30.715556 | J64: =iferror(SUM(J65:J95),"") -> 63 | K64: =IFERROR(SUM(K65:K95),"") -> 128 | L64: =iferror(E64/J64,"") -> 0 | M64: =Planejador!$I$50 | N64: =IFERROR(Planejador!$I$59,"") | O64: =IFERROR(Planejador!$I$60,"") | P64: =Planejador!$I$51 | Q64: =Planejador!$I$53 | R64: =iferror(Planejador!$I$57,"") | S64: =iferror(Planejador!$I$56,"") | T64: =iferror(Planejador!$I$52,"")
A65: 46082 | B65: =TEXT(A65,"dddd") -> domingo | D65: =SUMIF('ADV - GG'!A:A,A65,'ADV - GG'!C:C)+SUMIF('ADV - FB'!A:A,$A65,'ADV - FB'!E:E) -> 51.15 | F65: =IFERROR(E65/D65,"") -> 0 | G65: =IFERROR(D65/K65,"") -> 51.15 | H65: =iferror(J65/K65,"") -> 3 | I65: =iferror(D65/J65,"") -> 17.05 | J65: =SUMIF('ADV - GG'!A:A,A65,'ADV - GG'!H:H)+SUMIF('ADV - FB'!A:A,$A65,'ADV - FB'!I:I) -> 3 | K65: =SUMIF('ADV - GA4'!A:A,A65,'ADV - GA4'!C:C) -> 1 | L65: =IFERROR(E65/J65,"") -> 0 | M65: =$M$64/$B$64 -> 0 | N65: =$N$64/$B$64 -> 0 | O65: =IFERROR(Planejador!$I$60,"") | P65: =Planejador!$I$51 | Q65: =Planejador!$I$53 | R65: =iferror(Planejador!$I$57,"") | S65: =$S$64/$B$64 -> 0 | T65: =Planejador!$I$52
A66: 46083 | B66: =TEXT(A66,"dddd") -> segunda-feira | D66: =SUMIF('ADV - GG'!A:A,A66,'ADV - GG'!C:C)+SUMIF('ADV - FB'!A:A,$A66,'ADV - FB'!E:E) -> 66.59 | F66: =IFERROR(E66/D66,"") -> 0 | G66: =IFERROR(D66/K66,"") -> 16.6475 | H66: =iferror(J66/K66,"") -> 0.5 | I66: =iferror(D66/J66,"") -> 33.295 | J66: =SUMIF('ADV - GG'!A:A,A66,'ADV - GG'!H:H)+SUMIF('ADV - FB'!A:A,$A66,'ADV - FB'!I:I) -> 2 | K66: =SUMIF('ADV - GA4'!A:A,A66,'ADV - GA4'!C:C) -> 4 | L66: =IFERROR(E66/J66,"") -> 0 | M66: =$M$64/$B$64 -> 0 | N66: =$N$64/$B$64 -> 0 | O66: =IFERROR(Planejador!$I$60,"") | P66: =Planejador!$I$51 | Q66: =Planejador!$I$53 | R66: =iferror(Planejador!$I$57,"") | S66: =$S$64/$B$64 -> 0 | T66: =Planejador!$I$52
A67: 46084 | B67: =TEXT(A67,"dddd") -> terça-feira | D67: =SUMIF('ADV - GG'!A:A,A67,'ADV - GG'!C:C)+SUMIF('ADV - FB'!A:A,$A67,'ADV - FB'!E:E) -> 61.98 | F67: =IFERROR(E67/D67,"") -> 0 | G67: =IFERROR(D67/K67,"") -> 30.99 | H67: =iferror(J67/K67,"") -> 1 | I67: =iferror(D67/J67,"") -> 30.99 | J67: =SUMIF('ADV - GG'!A:A,A67,'ADV - GG'!H:H)+SUMIF('ADV - FB'!A:A,$A67,'ADV - FB'!I:I) -> 2 | K67: =SUMIF('ADV - GA4'!A:A,A67,'ADV - GA4'!C:C) -> 2 | L67: =IFERROR(E67/J67,"") -> 0 | M67: =$M$64/$B$64 -> 0 | N67: =$N$64/$B$64 -> 0 | O67: =IFERROR(Planejador!$I$60,"") | P67: =Planejador!$I$51 | Q67: =Planejador!$I$53 | R67: =iferror(Planejador!$I$57,"") | S67: =$S$64/$B$64 -> 0 | T67: =Planejador!$I$52
A68: 46085 | B68: =TEXT(A68,"dddd") -> quarta-feira | D68: =SUMIF('ADV - GG'!A:A,A68,'ADV - GG'!C:C)+SUMIF('ADV - FB'!A:A,$A68,'ADV - FB'!E:E) -> 55.45 | F68: =IFERROR(E68/D68,"") -> 0 | G68: =IFERROR(D68/K68,"") -> 13.8625 | H68: =iferror(J68/K68,"") -> 0.25 | I68: =iferror(D68/J68,"") -> 55.45 | J68: =SUMIF('ADV - GG'!A:A,A68,'ADV - GG'!H:H)+SUMIF('ADV - FB'!A:A,$A68,'ADV - FB'!I:I) -> 1 | K68: =SUMIF('ADV - GA4'!A:A,A68,'ADV - GA4'!C:C) -> 4 | L68: =IFERROR(E68/J68,"") -> 0 | M68: =$M$64/$B$64 -> 0 | N68: =$N$64/$B$64 -> 0 | O68: =IFERROR(Planejador!$I$60,"") | P68: =Planejador!$I$51 | Q68: =Planejador!$I$53 | R68: =iferror(Planejador!$I$57,"") | S68: =$S$64/$B$64 -> 0 | T68: =Planejador!$I$52
A69: 46086 | B69: =TEXT(A69,"dddd") -> quinta-feira | D69: =SUMIF('ADV - GG'!A:A,A69,'ADV - GG'!C:C)+SUMIF('ADV - FB'!A:A,$A69,'ADV - FB'!E:E) -> 69.46 | F69: =IFERROR(E69/D69,"") -> 0 | G69: =IFERROR(D69/K69,"") -> 23.153333 | H69: =iferror(J69/K69,"") -> 1 | I69: =iferror(D69/J69,"") -> 23.153333 | J69: =SUMIF('ADV - GG'!A:A,A69,'ADV - GG'!H:H)+SUMIF('ADV - FB'!A:A,$A69,'ADV - FB'!I:I) -> 3 | K69: =SUMIF('ADV - GA4'!A:A,A69,'ADV - GA4'!C:C) -> 3 | L69: =IFERROR(E69/J69,"") -> 0 | M69: =$M$64/$B$64 -> 0 | N69: =$N$64/$B$64 -> 0 | O69: =IFERROR(Planejador!$I$60,"") | P69: =Planejador!$I$51 | Q69: =Planejador!$I$53 | R69: =iferror(Planejador!$I$57,"") | S69: =$S$64/$B$64 -> 0 | T69: =Planejador!$I$52
A70: 46087 | B70: =TEXT(A70,"dddd") -> sexta-feira | D70: =SUMIF('ADV - GG'!A:A,A70,'ADV - GG'!C:C)+SUMIF('ADV - FB'!A:A,$A70,'ADV - FB'!E:E) -> 70.74 | F70: =IFERROR(E70/D70,"") -> 0 | G70: =IFERROR(D70/K70,"") -> 14.148 | H70: =iferror(J70/K70,"") -> 1 | I70: =iferror(D70/J70,"") -> 14.148 | J70: =SUMIF('ADV - GG'!A:A,A70,'ADV - GG'!H:H)+SUMIF('ADV - FB'!A:A,$A70,'ADV - FB'!I:I) -> 5 | K70: =SUMIF('ADV - GA4'!A:A,A70,'ADV - GA4'!C:C) -> 5 | L70: =IFERROR(E70/J70,"") -> 0 | M70: =$M$64/$B$64 -> 0 | N70: =$N$64/$B$64 -> 0 | O70: =IFERROR(Planejador!$I$60,"") | P70: =Planejador!$I$51 | Q70: =Planejador!$I$53 | R70: =iferror(Planejador!$I$57,"") | S70: =$S$64/$B$64 -> 0 | T70: =Planejador!$I$52
A71: 46088 | B71: =TEXT(A71,"dddd") -> sábado | D71: =SUMIF('ADV - GG'!A:A,A71,'ADV - GG'!C:C)+SUMIF('ADV - FB'!A:A,$A71,'ADV - FB'!E:E) -> 66.94 | F71: =IFERROR(E71/D71,"") -> 0 | G71: =IFERROR(D71/K71,"") -> 66.94 | H71: =iferror(J71/K71,"") -> 1 | I71: =iferror(D71/J71,"") -> 66.94 | J71: =SUMIF('ADV - GG'!A:A,A71,'ADV - GG'!H:H)+SUMIF('ADV - FB'!A:A,$A71,'ADV - FB'!I:I) -> 1 | K71: =SUMIF('ADV - GA4'!A:A,A71,'ADV - GA4'!C:C) -> 1 | L71: =IFERROR(E71/J71,"") -> 0 | M71: =$M$64/$B$64 -> 0 | N71: =$N$64/$B$64 -> 0 | O71: =IFERROR(Planejador!$I$60,"") | P71: =Planejador!$I$51 | Q71: =Planejador!$I$53 | R71: =iferror(Planejador!$I$57,"") | S71: =$S$64/$B$64 -> 0 | T71: =Planejador!$I$52
A72: 46089 | B72: =TEXT(A72,"dddd") -> domingo | D72: =SUMIF('ADV - GG'!A:A,A72,'ADV - GG'!C:C)+SUMIF('ADV - FB'!A:A,$A72,'ADV - FB'!E:E) -> 81.19 | F72: =IFERROR(E72/D72,"") -> 0 | G72: =IFERROR(D72/K72,"") -> 27.063333 | H72: =iferror(J72/K72,"") -> 0.33333333 | I72: =iferror(D72/J72,"") -> 81.19 | J72: =SUMIF('ADV - GG'!A:A,A72,'ADV - GG'!H:H)+SUMIF('ADV - FB'!A:A,$A72,'ADV - FB'!I:I) -> 1 | K72: =SUMIF('ADV - GA4'!A:A,A72,'ADV - GA4'!C:C) -> 3 | L72: =IFERROR(E72/J72,"") -> 0 | M72: =$M$64/$B$64 -> 0 | N72: =$N$64/$B$64 -> 0 | O72: =IFERROR(Planejador!$I$60,"") | P72: =Planejador!$I$51 | Q72: =Planejador!$I$53 | R72: =iferror(Planejador!$I$57,"") | S72: =$S$64/$B$64 -> 0 | T72: =Planejador!$I$52
A73: 46090 | B73: =TEXT(A73,"dddd") -> segunda-feira | D73: =SUMIF('ADV - GG'!A:A,A73,'ADV - GG'!C:C)+SUMIF('ADV - FB'!A:A,$A73,'ADV - FB'!E:E) -> 81.01 | F73: =IFERROR(E73/D73,"") -> 0 | G73: =IFERROR(D73/K73,"") -> 20.2525 | H73: =iferror(J73/K73,"") -> 0 | I73: =iferror(D73/J73,"") | J73: =SUMIF('ADV - GG'!A:A,A73,'ADV - GG'!H:H)+SUMIF('ADV - FB'!A:A,$A73,'ADV - FB'!I:I) -> 0 | K73: =SUMIF('ADV - GA4'!A:A,A73,'ADV - GA4'!C:C) -> 4 | L73: =IFERROR(E73/J73,"") | M73: =$M$64/$B$64 -> 0 | N73: =$N$64/$B$64 -> 0 | O73: =IFERROR(Planejador!$I$60,"") | P73: =Planejador!$I$51 | Q73: =Planejador!$I$53 | R73: =iferror(Planejador!$I$57,"") | S73: =$S$64/$B$64 -> 0 | T73: =Planejador!$I$52
A74: 46091 | B74: =TEXT(A74,"dddd") -> terça-feira | D74: =SUMIF('ADV - GG'!A:A,A74,'ADV - GG'!C:C)+SUMIF('ADV - FB'!A:A,$A74,'ADV - FB'!E:E) -> 71.25 | F74: =IFERROR(E74/D74,"") -> 0 | G74: =IFERROR(D74/K74,"") -> 17.8125 | H74: =iferror(J74/K74,"") -> 0.75 | I74: =iferror(D74/J74,"") -> 23.75 | J74: =SUMIF('ADV - GG'!A:A,A74,'ADV - GG'!H:H)+SUMIF('ADV - FB'!A:A,$A74,'ADV - FB'!I:I) -> 3 | K74: =SUMIF('ADV - GA4'!A:A,A74,'ADV - GA4'!C:C) -> 4 | L74: =IFERROR(E74/J74,"") -> 0 | M74: =$M$64/$B$64 -> 0 | N74: =$N$64/$B$64 -> 0 | O74: =IFERROR(Planejador!$I$60,"") | P74: =Planejador!$I$51 | Q74: =Planejador!$I$53 | R74: =iferror(Planejador!$I$57,"") | S74: =$S$64/$B$64 -> 0 | T74: =Planejador!$I$52
A75: 46092 | B75: =TEXT(A75,"dddd") -> quarta-feira | D75: =SUMIF('ADV - GG'!A:A,A75,'ADV - GG'!C:C)+SUMIF('ADV - FB'!A:A,$A75,'ADV - FB'!E:E) -> 51.8 | F75: =IFERROR(E75/D75,"") -> 0 | G75: =IFERROR(D75/K75,"") -> 12.95 | H75: =iferror(J75/K75,"") -> 0 | I75: =iferror(D75/J75,"") | J75: =SUMIF('ADV - GG'!A:A,A75,'ADV - GG'!H:H)+SUMIF('ADV - FB'!A:A,$A75,'ADV - FB'!I:I) -> 0 | K75: =SUMIF('ADV - GA4'!A:A,A75,'ADV - GA4'!C:C) -> 4 | L75: =IFERROR(E75/J75,"") | M75: =$M$64/$B$64 -> 0 | N75: =$N$64/$B$64 -> 0 | O75: =IFERROR(Planejador!$I$60,"") | P75: =Planejador!$I$51 | Q75: =Planejador!$I$53 | R75: =iferror(Planejador!$I$57,"") | S75: =$S$64/$B$64 -> 0 | T75: =Planejador!$I$52
A76: 46093 | B76: =TEXT(A76,"dddd") -> quinta-feira | D76: =SUMIF('ADV - GG'!A:A,A76,'ADV - GG'!C:C)+SUMIF('ADV - FB'!A:A,$A76,'ADV - FB'!E:E) -> 86.42 | F76: =IFERROR(E76/D76,"") -> 0 | G76: =IFERROR(D76/K76,"") -> 21.605 | H76: =iferror(J76/K76,"") -> 1 | I76: =iferror(D76/J76,"") -> 21.605 | J76: =SUMIF('ADV - GG'!A:A,A76,'ADV - GG'!H:H)+SUMIF('ADV - FB'!A:A,$A76,'ADV - FB'!I:I) -> 4 | K76: =SUMIF('ADV - GA4'!A:A,A76,'ADV - GA4'!C:C) -> 4 | L76: =IFERROR(E76/J76,"") -> 0 | M76: =$M$64/$B$64 -> 0 | N76: =$N$64/$B$64 -> 0 | O76: =IFERROR(Planejador!$I$60,"") | P76: =Planejador!$I$51 | Q76: =Planejador!$I$53 | R76: =iferror(Planejador!$I$57,"") | S76: =$S$64/$B$64 -> 0 | T76: =Planejador!$I$52
... A95: 46112 | B95: =TEXT(A95,"dddd") -> terça-feira | D95: =SUMIF('ADV - GG'!A:A,A95,'ADV - GG'!C:C)+SUMIF('ADV - FB'!A:A,$A95,'ADV - FB'!E:E) -> 0 | F95: =IFERROR(E95/D95,"") | G95: =IFERROR(D95/K95,"") -> 0 | H95: =iferror(J95/K95,"") -> 0 | I95: =iferror(D95/J95,"") | J95: =SUMIF('ADV - GG'!A:A,A95,'ADV - GG'!H:H)+SUMIF('ADV - FB'!A:A,$A95,'ADV - FB'!I:I) -> 0 | K95: =SUMIF('ADV - GA4'!A:A,A95,'ADV - GA4'!C:C) -> 4 | L95: =IFERROR(E95/J95,"") | M95: =$M$64/$B$64 -> 0 | N95: =$N$64/$B$64 -> 0 | O95: =IFERROR(Planejador!$I$60,"") | P95: =Planejador!$I$51 | Q95: =Planejador!$I$53 | R95: =iferror(Planejador!$I$57,"") | S95: =$S$64/$B$64 -> 0 | T95: =Planejador!$I$52
A96: ABRIL | B96: 30 | D96: =IFERROR(SUM(D97:D126),"") -> 1365.72 | E96: =iferror(SUM(E97:E126),"") -> 4557.7 | F96: =iferror(E96/D96,"") -> 3.3372141 | G96: =iferror(D96/K96,"") -> 15.345169 | H96: =iferror(J96/K96,"") -> 0.39325843 | I96: =iferror(D96/J96,"") -> 39.020571 | J96: =iferror(SUM(J97:J126),"") -> 35 | K96: =IFERROR(SUM(K97:K126),"") -> 89 | L96: =iferror(E96/J96,"") -> 130.22 | M96: =Planejador!$I$73 | N96: =IFERROR(Planejador!$I$82,"") | O96: =IFERROR(Planejador!$I$83,"") | P96: =Planejador!$I$74 | Q96: =Planejador!$I$76 | R96: =iferror(Planejador!$I$80,"") | S96: =iferror(Planejador!$I$79,"") | T96: =iferror(Planejador!$I$75,"")
A97: 46113 | B97: =TEXT(A97,"dddd") -> quarta-feira | D97: =SUMIF('ADV - GG'!A:A,A97,'ADV - GG'!C:C)+SUMIF('ADV - FB'!A:A,$A97,'ADV - FB'!E:E) -> 93.96 | E97: 492.7 | F97: =IFERROR(E97/D97,"") -> 5.2437207 | G97: =IFERROR(D97/K97,"") -> 46.98 | H97: =iferror(J97/K97,"") -> 1.5 | I97: =iferror(D97/J97,"") -> 31.32 | J97: =SUMIF('ADV - GG'!A:A,A97,'ADV - GG'!H:H)+SUMIF('ADV - FB'!A:A,$A97,'ADV - FB'!I:I) -> 3 | K97: =SUMIF('ADV - GA4'!A:A,A97,'ADV - GA4'!C:C) -> 2 | L97: =IFERROR(E97/J97,"") -> 164.23333 | M97: =$M$96/$B$96 -> 0 | N97: =$N$96/$B$96 -> 0 | O97: =IFERROR(Planejador!$I$83,"") | P97: =Planejador!$I$74 | Q97: =Planejador!$I$76 | R97: =Planejador!$I$80 -> #DIV/0! | S97: =$S$96/$B$96 -> 0 | T97: =Planejador!$I$75
A98: 46114 | B98: =TEXT(A98,"dddd") -> quinta-feira | D98: =SUMIF('ADV - GG'!A:A,A98,'ADV - GG'!C:C)+SUMIF('ADV - FB'!A:A,$A98,'ADV - FB'!E:E) -> 112.41 | E98: 89.5 | F98: =IFERROR(E98/D98,"") -> 0.79619251 | G98: =IFERROR(D98/K98,"") -> 10.219091 | H98: =iferror(J98/K98,"") -> 0.090909091 | I98: =iferror(D98/J98,"") -> 112.41 | J98: =SUMIF('ADV - GG'!A:A,A98,'ADV - GG'!H:H)+SUMIF('ADV - FB'!A:A,$A98,'ADV - FB'!I:I) -> 1 | K98: =SUMIF('ADV - GA4'!A:A,A98,'ADV - GA4'!C:C) -> 11 | L98: =IFERROR(E98/J98,"") -> 89.5 | M98: =$M$96/$B$96 -> 0 | N98: =$N$96/$B$96 -> 0 | O98: =IFERROR(Planejador!$I$83,"") | P98: =Planejador!$I$74 | Q98: =Planejador!$I$76 | R98: =Planejador!$I$80 -> #DIV/0! | S98: =$S$96/$B$96 -> 0 | T98: =Planejador!$I$75
A99: 46115 | B99: =TEXT(A99,"dddd") -> sexta-feira | D99: =SUMIF('ADV - GG'!A:A,A99,'ADV - GG'!C:C)+SUMIF('ADV - FB'!A:A,$A99,'ADV - FB'!E:E) -> 110.71 | E99: 298.2 | F99: =IFERROR(E99/D99,"") -> 2.6935236 | G99: =IFERROR(D99/K99,"") -> 3.9539286 | H99: =iferror(J99/K99,"") -> 0.071428571 | I99: =iferror(D99/J99,"") -> 55.355 | J99: =SUMIF('ADV - GG'!A:A,A99,'ADV - GG'!H:H)+SUMIF('ADV - FB'!A:A,$A99,'ADV - FB'!I:I) -> 2 | K99: =SUMIF('ADV - GA4'!A:A,A99,'ADV - GA4'!C:C) -> 28 | L99: =IFERROR(E99/J99,"") -> 149.1 | M99: =$M$96/$B$96 -> 0 | N99: =$N$96/$B$96 -> 0 | O99: =IFERROR(Planejador!$I$83,"") | P99: =Planejador!$I$74 | Q99: =Planejador!$I$76 | R99: =Planejador!$I$80 -> #DIV/0! | S99: =$S$96/$B$96 -> 0 | T99: =Planejador!$I$75
A100: 46116 | B100: =TEXT(A100,"dddd") -> sábado | D100: =SUMIF('ADV - GG'!A:A,A100,'ADV - GG'!C:C)+SUMIF('ADV - FB'!A:A,$A100,'ADV - FB'!E:E) -> 110.27 | E100: 322.2 | F100: =IFERROR(E100/D100,"") -> 2.9219189 | G100: =IFERROR(D100/K100,"") -> 36.756667 | H100: =iferror(J100/K100,"") -> 1 | I100: =iferror(D100/J100,"") -> 36.756667 | J100: =SUMIF('ADV - GG'!A:A,A100,'ADV - GG'!H:H)+SUMIF('ADV - FB'!A:A,$A100,'ADV - FB'!I:I) -> 3 | K100: =SUMIF('ADV - GA4'!A:A,A100,'ADV - GA4'!C:C) -> 3 | L100: =IFERROR(E100/J100,"") -> 107.4 | M100: =$M$96/$B$96 -> 0 | N100: =$N$96/$B$96 -> 0 | O100: =IFERROR(Planejador!$I$83,"") | P100: =Planejador!$I$74 | Q100: =Planejador!$I$76 | R100: =Planejador!$I$80 -> #DIV/0! | S100: =$S$96/$B$96 -> 0 | T100: =Planejador!$I$75
A101: 46117 | B101: =TEXT(A101,"dddd") -> domingo | D101: =SUMIF('ADV - GG'!A:A,A101,'ADV - GG'!C:C)+SUMIF('ADV - FB'!A:A,$A101,'ADV - FB'!E:E) -> 72.54 | E101: 89.5 | F101: =IFERROR(E101/D101,"") -> 1.233802 | G101: =IFERROR(D101/K101,"") -> 24.18 | H101: =iferror(J101/K101,"") -> 0.33333333 | I101: =iferror(D101/J101,"") -> 72.54 | J101: =SUMIF('ADV - GG'!A:A,A101,'ADV - GG'!H:H)+SUMIF('ADV - FB'!A:A,$A101,'ADV - FB'!I:I) -> 1 | K101: =SUMIF('ADV - GA4'!A:A,A101,'ADV - GA4'!C:C) -> 3 | L101: =IFERROR(E101/J101,"") -> 89.5 | M101: =$M$96/$B$96 -> 0 | N101: =$N$96/$B$96 -> 0 | O101: =IFERROR(Planejador!$I$83,"") | P101: =Planejador!$I$74 | Q101: =Planejador!$I$76 | R101: =Planejador!$I$80 -> #DIV/0! | S101: =$S$96/$B$96 -> 0 | T101: =Planejador!$I$75
A102: 46118 | B102: =TEXT(A102,"dddd") -> segunda-feira | D102: =SUMIF('ADV - GG'!A:A,A102,'ADV - GG'!C:C)+SUMIF('ADV - FB'!A:A,$A102,'ADV - FB'!E:E) -> 72.29 | E102: 392.8 | F102: =IFERROR(E102/D102,"") -> 5.4336699 | G102: =IFERROR(D102/K102,"") -> 8.0322222 | H102: =iferror(J102/K102,"") -> 0.44444444 | I102: =iferror(D102/J102,"") -> 18.0725 | J102: =SUMIF('ADV - GG'!A:A,A102,'ADV - GG'!H:H)+SUMIF('ADV - FB'!A:A,$A102,'ADV - FB'!I:I) -> 4 | K102: =SUMIF('ADV - GA4'!A:A,A102,'ADV - GA4'!C:C) -> 9 | L102: =IFERROR(E102/J102,"") -> 98.2 | M102: =$M$96/$B$96 -> 0 | N102: =$N$96/$B$96 -> 0 | O102: =IFERROR(Planejador!$I$83,"") | P102: =Planejador!$I$74 | Q102: =Planejador!$I$76 | R102: =Planejador!$I$80 -> #DIV/0! | S102: =$S$96/$B$96 -> 0 | T102: =Planejador!$I$75
A103: 46119 | B103: =TEXT(A103,"dddd") -> terça-feira | D103: =SUMIF('ADV - GG'!A:A,A103,'ADV - GG'!C:C)+SUMIF('ADV - FB'!A:A,$A103,'ADV - FB'!E:E) -> 63.01 | E103: 107.4 | F103: =IFERROR(E103/D103,"") -> 1.7044914 | G103: =IFERROR(D103/K103,"") -> 31.505 | H103: =iferror(J103/K103,"") -> 0.5 | I103: =iferror(D103/J103,"") -> 63.01 | J103: =SUMIF('ADV - GG'!A:A,A103,'ADV - GG'!H:H)+SUMIF('ADV - FB'!A:A,$A103,'ADV - FB'!I:I) -> 1 | K103: =SUMIF('ADV - GA4'!A:A,A103,'ADV - GA4'!C:C) -> 2 | L103: =IFERROR(E103/J103,"") -> 107.4 | M103: =$M$96/$B$96 -> 0 | N103: =$N$96/$B$96 -> 0 | O103: =IFERROR(Planejador!$I$83,"") | P103: =Planejador!$I$74 | Q103: =Planejador!$I$76 | R103: =Planejador!$I$80 -> #DIV/0! | S103: =$S$96/$B$96 -> 0 | T103: =Planejador!$I$75
A104: 46120 | B104: =TEXT(A104,"dddd") -> quarta-feira | D104: =SUMIF('ADV - GG'!A:A,A104,'ADV - GG'!C:C)+SUMIF('ADV - FB'!A:A,$A104,'ADV - FB'!E:E) -> 70.65 | E104: 190.8 | F104: =IFERROR(E104/D104,"") -> 2.7006369 | G104: =IFERROR(D104/K104,"") -> 23.55 | H104: =iferror(J104/K104,"") -> 0.33333333 | I104: =iferror(D104/J104,"") -> 70.65 | J104: =SUMIF('ADV - GG'!A:A,A104,'ADV - GG'!H:H)+SUMIF('ADV - FB'!A:A,$A104,'ADV - FB'!I:I) -> 1 | K104: =SUMIF('ADV - GA4'!A:A,A104,'ADV - GA4'!C:C) -> 3 | L104: =IFERROR(E104/J104,"") -> 190.8 | M104: =$M$96/$B$96 -> 0 | N104: =$N$96/$B$96 -> 0 | O104: =IFERROR(Planejador!$I$83,"") | P104: =Planejador!$I$74 | Q104: =Planejador!$I$76 | R104: =Planejador!$I$80 -> #DIV/0! | S104: =$S$96/$B$96 -> 0 | T104: =Planejador!$I$75
A105: 46121 | B105: =TEXT(A105,"dddd") -> quinta-feira | D105: =SUMIF('ADV - GG'!A:A,A105,'ADV - GG'!C:C)+SUMIF('ADV - FB'!A:A,$A105,'ADV - FB'!E:E) -> 61.25 | E105: 262.4 | F105: =IFERROR(E105/D105,"") -> 4.2840816 | G105: =IFERROR(D105/K105,"") -> 61.25 | H105: =iferror(J105/K105,"") -> 2 | I105: =iferror(D105/J105,"") -> 30.625 | J105: =SUMIF('ADV - GG'!A:A,A105,'ADV - GG'!H:H)+SUMIF('ADV - FB'!A:A,$A105,'ADV - FB'!I:I) -> 2 | K105: =SUMIF('ADV - GA4'!A:A,A105,'ADV - GA4'!C:C) -> 1 | L105: =IFERROR(E105/J105,"") -> 131.2 | M105: =$M$96/$B$96 -> 0 | N105: =$N$96/$B$96 -> 0 | O105: =IFERROR(Planejador!$I$83,"") | P105: =Planejador!$I$74 | Q105: =Planejador!$I$76 | R105: =Planejador!$I$80 -> #DIV/0! | S105: =$S$96/$B$96 -> 0 | T105: =Planejador!$I$75
A106: 46122 | B106: =TEXT(A106,"dddd") -> sexta-feira | D106: =SUMIF('ADV - GG'!A:A,A106,'ADV - GG'!C:C)+SUMIF('ADV - FB'!A:A,$A106,'ADV - FB'!E:E) -> 65.07 | E106: 606.8 | F106: =IFERROR(E106/D106,"") -> 9.3253419 | G106: =IFERROR(D106/K106,"") -> 65.07 | H106: =iferror(J106/K106,"") -> 3 | I106: =iferror(D106/J106,"") -> 21.69 | J106: =SUMIF('ADV - GG'!A:A,A106,'ADV - GG'!H:H)+SUMIF('ADV - FB'!A:A,$A106,'ADV - FB'!I:I) -> 3 | K106: =SUMIF('ADV - GA4'!A:A,A106,'ADV - GA4'!C:C) -> 1 | L106: =IFERROR(E106/J106,"") -> 202.26667 | M106: =$M$96/$B$96 -> 0 | N106: =$N$96/$B$96 -> 0 | O106: =IFERROR(Planejador!$I$83,"") | P106: =Planejador!$I$74 | Q106: =Planejador!$I$76 | R106: =Planejador!$I$80 -> #DIV/0! | S106: =$S$96/$B$96 -> 0 | T106: =Planejador!$I$75
A107: 46123 | B107: =TEXT(A107,"dddd") -> sábado | D107: =SUMIF('ADV - GG'!A:A,A107,'ADV - GG'!C:C)+SUMIF('ADV - FB'!A:A,$A107,'ADV - FB'!E:E) -> 60.45 | E107: 572.4 | F107: =IFERROR(E107/D107,"") -> 9.4689826 | G107: =IFERROR(D107/K107,"") -> 60.45 | H107: =iferror(J107/K107,"") -> 3 | I107: =iferror(D107/J107,"") -> 20.15 | J107: =SUMIF('ADV - GG'!A:A,A107,'ADV - GG'!H:H)+SUMIF('ADV - FB'!A:A,$A107,'ADV - FB'!I:I) -> 3 | K107: =SUMIF('ADV - GA4'!A:A,A107,'ADV - GA4'!C:C) -> 1 | L107: =IFERROR(E107/J107,"") -> 190.8 | M107: =$M$96/$B$96 -> 0 | N107: =$N$96/$B$96 -> 0 | O107: =IFERROR(Planejador!$I$83,"") | P107: =Planejador!$I$74 | Q107: =Planejador!$I$76 | R107: =Planejador!$I$80 -> #DIV/0! | S107: =$S$96/$B$96 -> 0 | T107: =Planejador!$I$75
A108: 46124 | B108: =TEXT(A108,"dddd") -> domingo | D108: =SUMIF('ADV - GG'!A:A,A108,'ADV - GG'!C:C)+SUMIF('ADV - FB'!A:A,$A108,'ADV - FB'!E:E) -> 9.23 | E108: 0 | F108: =IFERROR(E108/D108,"") -> 0 | G108: =IFERROR(D108/K108,"") -> 1.846 | H108: =iferror(J108/K108,"") -> 0 | I108: =iferror(D108/J108,"") | J108: =SUMIF('ADV - GG'!A:A,A108,'ADV - GG'!H:H)+SUMIF('ADV - FB'!A:A,$A108,'ADV - FB'!I:I) -> 0 | K108: =SUMIF('ADV - GA4'!A:A,A108,'ADV - GA4'!C:C) -> 5 | L108: =IFERROR(E108/J108,"") | M108: =$M$96/$B$96 -> 0 | N108: =$N$96/$B$96 -> 0 | O108: =IFERROR(Planejador!$I$83,"") | P108: =Planejador!$I$74 | Q108: =Planejador!$I$76 | R108: =Planejador!$I$80 -> #DIV/0! | S108: =$S$96/$B$96 -> 0 | T108: =Planejador!$I$75
... A112: 46128 | B112: =TEXT(A112,"dddd") -> quinta-feira | D112: =SUMIF('ADV - GG'!A:A,A112,'ADV - GG'!C:C)+SUMIF('ADV - FB'!A:A,$A112,'ADV - FB'!E:E) -> 73.14 | E112: 513 | F112: =IFERROR(E112/D112,"") -> 7.0139459 | G112: =IFERROR(D112/K112,"") -> 10.448571 | H112: =iferror(J112/K112,"") -> 0.57142857 | I112: =iferror(D112/J112,"") -> 18.285 | J112: =SUMIF('ADV - GG'!A:A,A112,'ADV - GG'!H:H)+SUMIF('ADV - FB'!A:A,$A112,'ADV - FB'!I:I) -> 4 | K112: =SUMIF('ADV - GA4'!A:A,A112,'ADV - GA4'!C:C) -> 7 | L112: =IFERROR(E112/J112,"") -> 128.25 | M112: =$M$96/$B$96 -> 0 | N112: =$N$96/$B$96 -> 0 | O112: =IFERROR(Planejador!$I$83,"") | P112: =Planejador!$I$74 | Q112: =Planejador!$I$76 | R112: =Planejador!$I$80 -> #DIV/0! | S112: =$S$96/$B$96 -> 0 | T112: =Planejador!$I$75
A113: 46129 | B113: =TEXT(A113,"dddd") -> sexta-feira | D113: =SUMIF('ADV - GG'!A:A,A113,'ADV - GG'!C:C)+SUMIF('ADV - FB'!A:A,$A113,'ADV - FB'!E:E) -> 64.63 | F113: =IFERROR(E113/D113,"") -> 0 | G113: =IFERROR(D113/K113,"") -> 64.63 | H113: =iferror(J113/K113,"") -> 1 | I113: =iferror(D113/J113,"") -> 64.63 | J113: =SUMIF('ADV - GG'!A:A,A113,'ADV - GG'!H:H)+SUMIF('ADV - FB'!A:A,$A113,'ADV - FB'!I:I) -> 1 | K113: =SUMIF('ADV - GA4'!A:A,A113,'ADV - GA4'!C:C) -> 1 | L113: =IFERROR(E113/J113,"") -> 0 | M113: =$M$96/$B$96 -> 0 | N113: =$N$96/$B$96 -> 0 | O113: =IFERROR(Planejador!$I$83,"") | P113: =Planejador!$I$74 | Q113: =Planejador!$I$76 | R113: =Planejador!$I$80 -> #DIV/0! | S113: =$S$96/$B$96 -> 0 | T113: =Planejador!$I$75
A114: 46130 | B114: =TEXT(A114,"dddd") -> sábado | D114: =SUMIF('ADV - GG'!A:A,A114,'ADV - GG'!C:C)+SUMIF('ADV - FB'!A:A,$A114,'ADV - FB'!E:E) -> 65.67 | F114: =IFERROR(E114/D114,"") -> 0 | G114: =IFERROR(D114/K114,"") | H114: =iferror(J114/K114,"") | I114: =iferror(D114/J114,"") -> 65.67 | J114: =SUMIF('ADV - GG'!A:A,A114,'ADV - GG'!H:H)+SUMIF('ADV - FB'!A:A,$A114,'ADV - FB'!I:I) -> 1 | K114: =SUMIF('ADV - GA4'!A:A,A114,'ADV - GA4'!C:C) -> 0 | L114: =IFERROR(E114/J114,"") -> 0 | M114: =$M$96/$B$96 -> 0 | N114: =$N$96/$B$96 -> 0 | O114: =IFERROR(Planejador!$I$83,"") | P114: =Planejador!$I$74 | Q114: =Planejador!$I$76 | R114: =Planejador!$I$80 -> #DIV/0! | S114: =$S$96/$B$96 -> 0 | T114: =Planejador!$I$75
A115: 46131 | B115: =TEXT(A115,"dddd") -> domingo | D115: =SUMIF('ADV - GG'!A:A,A115,'ADV - GG'!C:C)+SUMIF('ADV - FB'!A:A,$A115,'ADV - FB'!E:E) -> 49.5 | F115: =IFERROR(E115/D115,"") -> 0 | G115: =IFERROR(D115/K115,"") | H115: =iferror(J115/K115,"") | I115: =iferror(D115/J115,"") | J115: =SUMIF('ADV - GG'!A:A,A115,'ADV - GG'!H:H)+SUMIF('ADV - FB'!A:A,$A115,'ADV - FB'!I:I) -> 0 | K115: =SUMIF('ADV - GA4'!A:A,A115,'ADV - GA4'!C:C) -> 0 | L115: =IFERROR(E115/J115,"") | M115: =$M$96/$B$96 -> 0 | N115: =$N$96/$B$96 -> 0 | O115: =IFERROR(Planejador!$I$83,"") | P115: =Planejador!$I$74 | Q115: =Planejador!$I$76 | R115: =Planejador!$I$80 -> #DIV/0! | S115: =$S$96/$B$96 -> 0 | T115: =Planejador!$I$75
A116: 46132 | B116: =TEXT(A116,"dddd") -> segunda-feira | D116: =SUMIF('ADV - GG'!A:A,A116,'ADV - GG'!C:C)+SUMIF('ADV - FB'!A:A,$A116,'ADV - FB'!E:E) -> 67.73 | F116: =IFERROR(E116/D116,"") -> 0 | G116: =IFERROR(D116/K116,"") | H116: =iferror(J116/K116,"") | I116: =iferror(D116/J116,"") | J116: =SUMIF('ADV - GG'!A:A,A116,'ADV - GG'!H:H)+SUMIF('ADV - FB'!A:A,$A116,'ADV - FB'!I:I) -> 0 | K116: =SUMIF('ADV - GA4'!A:A,A116,'ADV - GA4'!C:C) -> 0 | L116: =IFERROR(E116/J116,"") | M116: =$M$96/$B$96 -> 0 | N116: =$N$96/$B$96 -> 0 | O116: =IFERROR(Planejador!$I$83,"") | P116: =Planejador!$I$74 | Q116: =Planejador!$I$76 | R116: =Planejador!$I$80 -> #DIV/0! | S116: =$S$96/$B$96 -> 0 | T116: =Planejador!$I$75
A117: 46133 | B117: =TEXT(A117,"dddd") -> terça-feira | D117: =SUMIF('ADV - GG'!A:A,A117,'ADV - GG'!C:C)+SUMIF('ADV - FB'!A:A,$A117,'ADV - FB'!E:E) -> 0.85 | F117: =IFERROR(E117/D117,"") -> 0 | G117: =IFERROR(D117/K117,"") | H117: =iferror(J117/K117,"") | I117: =iferror(D117/J117,"") | J117: =SUMIF('ADV - GG'!A:A,A117,'ADV - GG'!H:H)+SUMIF('ADV - FB'!A:A,$A117,'ADV - FB'!I:I) -> 0 | K117: =SUMIF('ADV - GA4'!A:A,A117,'ADV - GA4'!C:C) -> 0 | L117: =IFERROR(E117/J117,"") | M117: =$M$96/$B$96 -> 0 | N117: =$N$96/$B$96 -> 0 | O117: =IFERROR(Planejador!$I$83,"") | P117: =Planejador!$I$74 | Q117: =Planejador!$I$76 | R117: =Planejador!$I$80 -> #DIV/0! | S117: =$S$96/$B$96 -> 0 | T117: =Planejador!$I$75
A118: 46134 | B118: =TEXT(A118,"dddd") -> quarta-feira | D118: =SUMIF('ADV - GG'!A:A,A118,'ADV - GG'!C:C)+SUMIF('ADV - FB'!A:A,$A118,'ADV - FB'!E:E) -> 0 | F118: =IFERROR(E118/D118,"") | G118: =IFERROR(D118/K118,"") | H118: =iferror(J118/K118,"") | I118: =iferror(D118/J118,"") | J118: =SUMIF('ADV - GG'!A:A,A118,'ADV - GG'!H:H)+SUMIF('ADV - FB'!A:A,$A118,'ADV - FB'!I:I) -> 0 | K118: =SUMIF('ADV - GA4'!A:A,A118,'ADV - GA4'!C:C) -> 0 | L118: =IFERROR(E118/J118,"") | M118: =$M$96/$B$96 -> 0 | N118: =$N$96/$B$96 -> 0 | O118: =IFERROR(Planejador!$I$83,"") | P118: =Planejador!$I$74 | Q118: =Planejador!$I$76 | R118: =Planejador!$I$80 -> #DIV/0! | S118: =$S$96/$B$96 -> 0 | T118: =Planejador!$I$75
A119: 46135 | B119: =TEXT(A119,"dddd") -> quinta-feira | D119: =SUMIF('ADV - GG'!A:A,A119,'ADV - GG'!C:C)+SUMIF('ADV - FB'!A:A,$A119,'ADV - FB'!E:E) -> 0 | F119: =IFERROR(E119/D119,"") | G119: =IFERROR(D119/K119,"") | H119: =iferror(J119/K119,"") | I119: =iferror(D119/J119,"") | J119: =SUMIF('ADV - GG'!A:A,A119,'ADV - GG'!H:H)+SUMIF('ADV - FB'!A:A,$A119,'ADV - FB'!I:I) -> 0 | K119: =SUMIF('ADV - GA4'!A:A,A119,'ADV - GA4'!C:C) -> 0 | L119: =IFERROR(E119/J119,"") | M119: =$M$96/$B$96 -> 0 | N119: =$N$96/$B$96 -> 0 | O119: =IFERROR(Planejador!$I$83,"") | P119: =Planejador!$I$74 | Q119: =Planejador!$I$76 | R119: =Planejador!$I$80 -> #DIV/0! | S119: =$S$96/$B$96 -> 0 | T119: =Planejador!$I$75
A120: 46136 | B120: =TEXT(A120,"dddd") -> sexta-feira | D120: =SUMIF('ADV - GG'!A:A,A120,'ADV - GG'!C:C)+SUMIF('ADV - FB'!A:A,$A120,'ADV - FB'!E:E) -> 0 | F120: =IFERROR(E120/D120,"") | G120: =IFERROR(D120/K120,"") | H120: =iferror(J120/K120,"") | I120: =iferror(D120/J120,"") | J120: =SUMIF('ADV - GG'!A:A,A120,'ADV - GG'!H:H)+SUMIF('ADV - FB'!A:A,$A120,'ADV - FB'!I:I) -> 0 | K120: =SUMIF('ADV - GA4'!A:A,A120,'ADV - GA4'!C:C) -> 0 | L120: =IFERROR(E120/J120,"") | M120: =$M$96/$B$96 -> 0 | N120: =$N$96/$B$96 -> 0 | O120: =IFERROR(Planejador!$I$83,"") | P120: =Planejador!$I$74 | Q120: =Planejador!$I$76 | R120: =Planejador!$I$80 -> #DIV/0! | S120: =$S$96/$B$96 -> 0 | T120: =Planejador!$I$75
A121: 46137 | B121: =TEXT(A121,"dddd") -> sábado | D121: =SUMIF('ADV - GG'!A:A,A121,'ADV - GG'!C:C)+SUMIF('ADV - FB'!A:A,$A121,'ADV - FB'!E:E) -> 0 | F121: =IFERROR(E121/D121,"") | G121: =IFERROR(D121/K121,"") | H121: =iferror(J121/K121,"") | I121: =iferror(D121/J121,"") | J121: =SUMIF('ADV - GG'!A:A,A121,'ADV - GG'!H:H)+SUMIF('ADV - FB'!A:A,$A121,'ADV - FB'!I:I) -> 0 | K121: =SUMIF('ADV - GA4'!A:A,A121,'ADV - GA4'!C:C) -> 0 | L121: =IFERROR(E121/J121,"") | M121: =$M$96/$B$96 -> 0 | N121: =$N$96/$B$96 -> 0 | O121: =IFERROR(Planejador!$I$83,"") | P121: =Planejador!$I$74 | Q121: =Planejador!$I$76 | R121: =Planejador!$I$80 -> #DIV/0! | S121: =$S$96/$B$96 -> 0 | T121: =Planejador!$I$75
A122: 46138 | B122: =TEXT(A122,"dddd") -> domingo | D122: =SUMIF('ADV - GG'!A:A,A122,'ADV - GG'!C:C)+SUMIF('ADV - FB'!A:A,$A122,'ADV - FB'!E:E) -> 0 | F122: =IFERROR(E122/D122,"") | G122: =IFERROR(D122/K122,"") | H122: =iferror(J122/K122,"") | I122: =iferror(D122/J122,"") | J122: =SUMIF('ADV - GG'!A:A,A122,'ADV - GG'!H:H)+SUMIF('ADV - FB'!A:A,$A122,'ADV - FB'!I:I) -> 0 | K122: =SUMIF('ADV - GA4'!A:A,A122,'ADV - GA4'!C:C) -> 0 | L122: =IFERROR(E122/J122,"") | M122: =$M$96/$B$96 -> 0 | N122: =$N$96/$B$96 -> 0 | O122: =IFERROR(Planejador!$I$83,"") | P122: =Planejador!$I$74 | Q122: =Planejador!$I$76 | R122: =Planejador!$I$80 -> #DIV/0! | S122: =$S$96/$B$96 -> 0 | T122: =Planejador!$I$75
A123: 46139 | B123: =TEXT(A123,"dddd") -> segunda-feira | D123: =SUMIF('ADV - GG'!A:A,A123,'ADV - GG'!C:C)+SUMIF('ADV - FB'!A:A,$A123,'ADV - FB'!E:E) -> 0 | F123: =IFERROR(E123/D123,"") | G123: =IFERROR(D123/K123,"") | H123: =iferror(J123/K123,"") | I123: =iferror(D123/J123,"") | J123: =SUMIF('ADV - GG'!A:A,A123,'ADV - GG'!H:H)+SUMIF('ADV - FB'!A:A,$A123,'ADV - FB'!I:I) -> 0 | K123: =SUMIF('ADV - GA4'!A:A,A123,'ADV - GA4'!C:C) -> 0 | L123: =IFERROR(E123/J123,"") | M123: =$M$96/$B$96 -> 0 | N123: =$N$96/$B$96 -> 0 | O123: =IFERROR(Planejador!$I$83,"") | P123: =Planejador!$I$74 | Q123: =Planejador!$I$76 | R123: =Planejador!$I$80 -> #DIV/0! | S123: =$S$96/$B$96 -> 0 | T123: =Planejador!$I$75
A124: 46140 | B124: =TEXT(A124,"dddd") -> terça-feira | D124: =SUMIF('ADV - GG'!A:A,A124,'ADV - GG'!C:C)+SUMIF('ADV - FB'!A:A,$A124,'ADV - FB'!E:E) -> 0 | F124: =IFERROR(E124/D124,"") | G124: =IFERROR(D124/K124,"") | H124: =iferror(J124/K124,"") | I124: =iferror(D124/J124,"") | J124: =SUMIF('ADV - GG'!A:A,A124,'ADV - GG'!H:H)+SUMIF('ADV - FB'!A:A,$A124,'ADV - FB'!I:I) -> 0 | K124: =SUMIF('ADV - GA4'!A:A,A124,'ADV - GA4'!C:C) -> 0 | L124: =IFERROR(E124/J124,"") | M124: =$M$96/$B$96 -> 0 | N124: =$N$96/$B$96 -> 0 | O124: =IFERROR(Planejador!$I$83,"") | P124: =Planejador!$I$74 | Q124: =Planejador!$I$76 | R124: =Planejador!$I$80 -> #DIV/0! | S124: =$S$96/$B$96 -> 0 | T124: =Planejador!$I$75
... A126: 46142 | B126: =TEXT(A126,"dddd") -> quinta-feira | D126: =SUMIF('ADV - GG'!A:A,A126,'ADV - GG'!C:C)+SUMIF('ADV - FB'!A:A,$A126,'ADV - FB'!E:E) -> 0 | F126: =IFERROR(E126/D126,"") | G126: =IFERROR(D126/K126,"") | H126: =iferror(J126/K126,"") | I126: =iferror(D126/J126,"") | J126: =SUMIF('ADV - GG'!A:A,A126,'ADV - GG'!H:H)+SUMIF('ADV - FB'!A:A,$A126,'ADV - FB'!I:I) -> 0 | K126: =SUMIF('ADV - GA4'!A:A,A126,'ADV - GA4'!C:C) -> 0 | L126: =IFERROR(E126/J126,"") | M126: =$M$96/$B$96 -> 0 | N126: =$N$96/$B$96 -> 0 | O126: =IFERROR(Planejador!$I$83,"") | P126: =Planejador!$I$74 | Q126: =Planejador!$I$76 | R126: =Planejador!$I$80 -> #DIV/0! | S126: =$S$96/$B$96 -> 0 | T126: =Planejador!$I$75
A127: MAIO | B127: 31 | D127: =IFERROR(SUM(D128:D158),"") -> 0 | E127: =iferror(SUM(E128:E158),"") -> 0 | F127: =iferror(E127/D127,"") | G127: =iferror(D127/K127,"") | H127: =iferror(J127/K127,"") | I127: =iferror(D127/J127,"") | J127: =iferror(SUM(J128:J158),"") -> 0 | K127: =IFERROR(SUM(K128:K158),"") -> 0 | L127: =iferror(E127/J127,"") | M127: =Planejador!$I$96 | N127: =IFERROR(Planejador!$I$105,"") | O127: =IFERROR(Planejador!$I$106,"") | P127: =Planejador!$I$97 | Q127: =Planejador!$I$99 | R127: =iferror(Planejador!$I$103,"") | S127: =iferror(Planejador!$I$102,"") | T127: =iferror(Planejador!$I$98,"")
A128: 46143 | B128: =TEXT(A128,"dddd") -> sexta-feira | D128: =SUMIF('ADV - GG'!A:A,A128,'ADV - GG'!C:C)+SUMIF('ADV - FB'!A:A,$A128,'ADV - FB'!E:E) -> 0 | F128: =IFERROR(E128/D128,"") | G128: =IFERROR(D128/K128,"") | H128: =iferror(J128/K128,"") | I128: =iferror(D128/J128,"") | J128: =SUMIF('ADV - GG'!A:A,A128,'ADV - GG'!H:H)+SUMIF('ADV - FB'!A:A,$A128,'ADV - FB'!I:I) -> 0 | K128: =SUMIF('ADV - GA4'!A:A,A128,'ADV - GA4'!C:C) -> 0 | L128: =IFERROR(E128/J128,"") | M128: =$M$96/$B$96 -> 0 | N128: =$N$127/$B$127 -> 0 | O128: =IFERROR(Planejador!$I$106,"") | P128: =Planejador!$I$97 | Q128: =Planejador!$I$99 | R128: =iferror(Planejador!$I$103,"") | S128: =$S$127/$B$127 -> 0 | T128: =Planejador!$I$98
A129: 46144 | B129: =TEXT(A129,"dddd") -> sábado | D129: =SUMIF('ADV - GG'!A:A,A129,'ADV - GG'!C:C)+SUMIF('ADV - FB'!A:A,$A129,'ADV - FB'!E:E) -> 0 | F129: =IFERROR(E129/D129,"") | G129: =IFERROR(D129/K129,"") | H129: =iferror(J129/K129,"") | I129: =iferror(D129/J129,"") | J129: =SUMIF('ADV - GG'!A:A,A129,'ADV - GG'!H:H)+SUMIF('ADV - FB'!A:A,$A129,'ADV - FB'!I:I) -> 0 | K129: =SUMIF('ADV - GA4'!A:A,A129,'ADV - GA4'!C:C) -> 0 | L129: =IFERROR(E129/J129,"") | M129: =$M$96/$B$96 -> 0 | N129: =$N$127/$B$127 -> 0 | O129: =IFERROR(Planejador!$I$106,"") | P129: =Planejador!$I$97 | Q129: =Planejador!$I$99 | R129: =iferror(Planejador!$I$103,"") | S129: =$S$127/$B$127 -> 0 | T129: =Planejador!$I$98
A130: 46145 | B130: =TEXT(A130,"dddd") -> domingo | D130: =SUMIF('ADV - GG'!A:A,A130,'ADV - GG'!C:C)+SUMIF('ADV - FB'!A:A,$A130,'ADV - FB'!E:E) -> 0 | F130: =IFERROR(E130/D130,"") | G130: =IFERROR(D130/K130,"") | H130: =iferror(J130/K130,"") | I130: =iferror(D130/J130,"") | J130: =SUMIF('ADV - GG'!A:A,A130,'ADV - GG'!H:H)+SUMIF('ADV - FB'!A:A,$A130,'ADV - FB'!I:I) -> 0 | K130: =SUMIF('ADV - GA4'!A:A,A130,'ADV - GA4'!C:C) -> 0 | L130: =IFERROR(E130/J130,"") | M130: =$M$96/$B$96 -> 0 | N130: =$N$127/$B$127 -> 0 | O130: =IFERROR(Planejador!$I$106,"") | P130: =Planejador!$I$97 | Q130: =Planejador!$I$99 | R130: =iferror(Planejador!$I$103,"") | S130: =$S$127/$B$127 -> 0 | T130: =Planejador!$I$98
A131: 46146 | B131: =TEXT(A131,"dddd") -> segunda-feira | D131: =SUMIF('ADV - GG'!A:A,A131,'ADV - GG'!C:C)+SUMIF('ADV - FB'!A:A,$A131,'ADV - FB'!E:E) -> 0 | F131: =IFERROR(E131/D131,"") | G131: =IFERROR(D131/K131,"") | H131: =iferror(J131/K131,"") | I131: =iferror(D131/J131,"") | J131: =SUMIF('ADV - GG'!A:A,A131,'ADV - GG'!H:H)+SUMIF('ADV - FB'!A:A,$A131,'ADV - FB'!I:I) -> 0 | K131: =SUMIF('ADV - GA4'!A:A,A131,'ADV - GA4'!C:C) -> 0 | L131: =IFERROR(E131/J131,"") | M131: =$M$96/$B$96 -> 0 | N131: =$N$127/$B$127 -> 0 | O131: =IFERROR(Planejador!$I$106,"") | P131: =Planejador!$I$97 | Q131: =Planejador!$I$99 | R131: =iferror(Planejador!$I$103,"") | S131: =$S$127/$B$127 -> 0 | T131: =Planejador!$I$98
A132: 46147 | B132: =TEXT(A132,"dddd") -> terça-feira | D132: =SUMIF('ADV - GG'!A:A,A132,'ADV - GG'!C:C)+SUMIF('ADV - FB'!A:A,$A132,'ADV - FB'!E:E) -> 0 | F132: =IFERROR(E132/D132,"") | G132: =IFERROR(D132/K132,"") | H132: =iferror(J132/K132,"") | I132: =iferror(D132/J132,"") | J132: =SUMIF('ADV - GG'!A:A,A132,'ADV - GG'!H:H)+SUMIF('ADV - FB'!A:A,$A132,'ADV - FB'!I:I) -> 0 | K132: =SUMIF('ADV - GA4'!A:A,A132,'ADV - GA4'!C:C) -> 0 | L132: =IFERROR(E132/J132,"") | M132: =$M$96/$B$96 -> 0 | N132: =$N$127/$B$127 -> 0 | O132: =IFERROR(Planejador!$I$106,"") | P132: =Planejador!$I$97 | Q132: =Planejador!$I$99 | R132: =iferror(Planejador!$I$103,"") | S132: =$S$127/$B$127 -> 0 | T132: =Planejador!$I$98
A133: 46148 | B133: =TEXT(A133,"dddd") -> quarta-feira | D133: =SUMIF('ADV - GG'!A:A,A133,'ADV - GG'!C:C)+SUMIF('ADV - FB'!A:A,$A133,'ADV - FB'!E:E) -> 0 | F133: =IFERROR(E133/D133,"") | G133: =IFERROR(D133/K133,"") | H133: =iferror(J133/K133,"") | I133: =iferror(D133/J133,"") | J133: =SUMIF('ADV - GG'!A:A,A133,'ADV - GG'!H:H)+SUMIF('ADV - FB'!A:A,$A133,'ADV - FB'!I:I) -> 0 | K133: =SUMIF('ADV - GA4'!A:A,A133,'ADV - GA4'!C:C) -> 0 | L133: =IFERROR(E133/J133,"") | M133: =$M$96/$B$96 -> 0 | N133: =$N$127/$B$127 -> 0 | O133: =IFERROR(Planejador!$I$106,"") | P133: =Planejador!$I$97 | Q133: =Planejador!$I$99 | R133: =iferror(Planejador!$I$103,"") | S133: =$S$127/$B$127 -> 0 | T133: =Planejador!$I$98
A134: 46149 | B134: =TEXT(A134,"dddd") -> quinta-feira | D134: =SUMIF('ADV - GG'!A:A,A134,'ADV - GG'!C:C)+SUMIF('ADV - FB'!A:A,$A134,'ADV - FB'!E:E) -> 0 | F134: =IFERROR(E134/D134,"") | G134: =IFERROR(D134/K134,"") | H134: =iferror(J134/K134,"") | I134: =iferror(D134/J134,"") | J134: =SUMIF('ADV - GG'!A:A,A134,'ADV - GG'!H:H)+SUMIF('ADV - FB'!A:A,$A134,'ADV - FB'!I:I) -> 0 | K134: =SUMIF('ADV - GA4'!A:A,A134,'ADV - GA4'!C:C) -> 0 | L134: =IFERROR(E134/J134,"") | M134: =$M$96/$B$96 -> 0 | N134: =$N$127/$B$127 -> 0 | O134: =IFERROR(Planejador!$I$106,"") | P134: =Planejador!$I$97 | Q134: =Planejador!$I$99 | R134: =iferror(Planejador!$I$103,"") | S134: =$S$127/$B$127 -> 0 | T134: =Planejador!$I$98
A135: 46150 | B135: =TEXT(A135,"dddd") -> sexta-feira | D135: =SUMIF('ADV - GG'!A:A,A135,'ADV - GG'!C:C)+SUMIF('ADV - FB'!A:A,$A135,'ADV - FB'!E:E) -> 0 | F135: =IFERROR(E135/D135,"") | G135: =IFERROR(D135/K135,"") | H135: =iferror(J135/K135,"") | I135: =iferror(D135/J135,"") | J135: =SUMIF('ADV - GG'!A:A,A135,'ADV - GG'!H:H)+SUMIF('ADV - FB'!A:A,$A135,'ADV - FB'!I:I) -> 0 | K135: =SUMIF('ADV - GA4'!A:A,A135,'ADV - GA4'!C:C) -> 0 | L135: =IFERROR(E135/J135,"") | M135: =$M$96/$B$96 -> 0 | N135: =$N$127/$B$127 -> 0 | O135: =IFERROR(Planejador!$I$106,"") | P135: =Planejador!$I$97 | Q135: =Planejador!$I$99 | R135: =iferror(Planejador!$I$103,"") | S135: =$S$127/$B$127 -> 0 | T135: =Planejador!$I$98
A136: 46151 | B136: =TEXT(A136,"dddd") -> sábado | D136: =SUMIF('ADV - GG'!A:A,A136,'ADV - GG'!C:C)+SUMIF('ADV - FB'!A:A,$A136,'ADV - FB'!E:E) -> 0 | F136: =IFERROR(E136/D136,"") | G136: =IFERROR(D136/K136,"") | H136: =iferror(J136/K136,"") | I136: =iferror(D136/J136,"") | J136: =SUMIF('ADV - GG'!A:A,A136,'ADV - GG'!H:H)+SUMIF('ADV - FB'!A:A,$A136,'ADV - FB'!I:I) -> 0 | K136: =SUMIF('ADV - GA4'!A:A,A136,'ADV - GA4'!C:C) -> 0 | L136: =IFERROR(E136/J136,"") | M136: =$M$96/$B$96 -> 0 | N136: =$N$127/$B$127 -> 0 | O136: =IFERROR(Planejador!$I$106,"") | P136: =Planejador!$I$97 | Q136: =Planejador!$I$99 | R136: =iferror(Planejador!$I$103,"") | S136: =$S$127/$B$127 -> 0 | T136: =Planejador!$I$98
A137: 46152 | B137: =TEXT(A137,"dddd") -> domingo | D137: =SUMIF('ADV - GG'!A:A,A137,'ADV - GG'!C:C)+SUMIF('ADV - FB'!A:A,$A137,'ADV - FB'!E:E) -> 0 | F137: =IFERROR(E137/D137,"") | G137: =IFERROR(D137/K137,"") | H137: =iferror(J137/K137,"") | I137: =iferror(D137/J137,"") | J137: =SUMIF('ADV - GG'!A:A,A137,'ADV - GG'!H:H)+SUMIF('ADV - FB'!A:A,$A137,'ADV - FB'!I:I) -> 0 | K137: =SUMIF('ADV - GA4'!A:A,A137,'ADV - GA4'!C:C) -> 0 | L137: =IFERROR(E137/J137,"") | M137: =$M$96/$B$96 -> 0 | N137: =$N$127/$B$127 -> 0 | O137: =IFERROR(Planejador!$I$106,"") | P137: =Planejador!$I$97 | Q137: =Planejador!$I$99 | R137: =iferror(Planejador!$I$103,"") | S137: =$S$127/$B$127 -> 0 | T137: =Planejador!$I$98
A138: 46153 | B138: =TEXT(A138,"dddd") -> segunda-feira | D138: =SUMIF('ADV - GG'!A:A,A138,'ADV - GG'!C:C)+SUMIF('ADV - FB'!A:A,$A138,'ADV - FB'!E:E) -> 0 | F138: =IFERROR(E138/D138,"") | G138: =IFERROR(D138/K138,"") | H138: =iferror(J138/K138,"") | I138: =iferror(D138/J138,"") | J138: =SUMIF('ADV - GG'!A:A,A138,'ADV - GG'!H:H)+SUMIF('ADV - FB'!A:A,$A138,'ADV - FB'!I:I) -> 0 | K138: =SUMIF('ADV - GA4'!A:A,A138,'ADV - GA4'!C:C) -> 0 | L138: =IFERROR(E138/J138,"") | M138: =$M$96/$B$96 -> 0 | N138: =$N$127/$B$127 -> 0 | O138: =IFERROR(Planejador!$I$106,"") | P138: =Planejador!$I$97 | Q138: =Planejador!$I$99 | R138: =iferror(Planejador!$I$103,"") | S138: =$S$127/$B$127 -> 0 | T138: =Planejador!$I$98
A139: 46154 | B139: =TEXT(A139,"dddd") -> terça-feira | D139: =SUMIF('ADV - GG'!A:A,A139,'ADV - GG'!C:C)+SUMIF('ADV - FB'!A:A,$A139,'ADV - FB'!E:E) -> 0 | F139: =IFERROR(E139/D139,"") | G139: =IFERROR(D139/K139,"") | H139: =iferror(J139/K139,"") | I139: =iferror(D139/J139,"") | J139: =SUMIF('ADV - GG'!A:A,A139,'ADV - GG'!H:H)+SUMIF('ADV - FB'!A:A,$A139,'ADV - FB'!I:I) -> 0 | K139: =SUMIF('ADV - GA4'!A:A,A139,'ADV - GA4'!C:C) -> 0 | L139: =IFERROR(E139/J139,"") | M139: =$M$96/$B$96 -> 0 | N139: =$N$127/$B$127 -> 0 | O139: =IFERROR(Planejador!$I$106,"") | P139: =Planejador!$I$97 | Q139: =Planejador!$I$99 | R139: =iferror(Planejador!$I$103,"") | S139: =$S$127/$B$127 -> 0 | T139: =Planejador!$I$98
... A158: 46173 | B158: =TEXT(A158,"dddd") -> domingo | D158: =SUMIF('ADV - GG'!A:A,A158,'ADV - GG'!C:C)+SUMIF('ADV - FB'!A:A,$A158,'ADV - FB'!E:E) -> 0 | F158: =IFERROR(E158/D158,"") | G158: =IFERROR(D158/K158,"") | H158: =iferror(J158/K158,"") | I158: =iferror(D158/J158,"") | J158: =SUMIF('ADV - GG'!A:A,A158,'ADV - GG'!H:H)+SUMIF('ADV - FB'!A:A,$A158,'ADV - FB'!I:I) -> 0 | K158: =SUMIF('ADV - GA4'!A:A,A158,'ADV - GA4'!C:C) -> 0 | L158: =IFERROR(E158/J158,"") | M158: =$M$96/$B$96 -> 0 | N158: =$N$127/$B$127 -> 0 | O158: =IFERROR(Planejador!$I$106,"") | P158: =Planejador!$I$97 | Q158: =Planejador!$I$99 | R158: =iferror(Planejador!$I$103,"") | S158: =$S$127/$B$127 -> 0 | T158: =Planejador!$I$98
A159: JUNHO | B159: 30 | D159: =IFERROR(SUM(D160:D189),"") -> 0 | E159: =IFERROR(SUM(E160:E189),"") -> 0 | F159: =IFERROR(E159/D159,"") | G159: =IFERROR(D159/K159,"") | H159: =IFERROR(J159/K159,"") | I159: =IFERROR(D159/J159,"") | J159: =IFERROR(SUM(J160:J189),"") -> 0 | K159: =IFERROR(SUM(K160:K189),"") -> 0 | L159: =IFERROR(E159/J159,"") | M159: =Planejador!$I$119 | N159: =IFERROR(Planejador!$I$128,"") | O159: =IFERROR(Planejador!$I$129,"") | P159: =Planejador!$I$120 | Q159: =Planejador!$I$122 | R159: =IFERROR(Planejador!$I$126,"") | S159: =IFERROR(Planejador!$I$125,"") | T159: =IFERROR(Planejador!$I$121,"")
A160: 46174 | B160: =TEXT(A160,"dddd") -> segunda-feira | D160: =SUMIF('ADV - GG'!A:A,A160,'ADV - GG'!C:C)+SUMIF('ADV - FB'!A:A,$A160,'ADV - FB'!E:E) -> 0 | F160: =IFERROR(E160/D160,"") | G160: =IFERROR(D160/K160,"") | H160: =iferror(J160/K160,"") | I160: =iferror(D160/J160,"") | J160: =SUMIF('ADV - GG'!A:A,A160,'ADV - GG'!H:H)+SUMIF('ADV - FB'!A:A,$A160,'ADV - FB'!I:I) -> 0 | K160: =SUMIF('ADV - GA4'!A:A,A160,'ADV - GA4'!C:C) -> 0 | L160: =IFERROR(E160/J160,"") | M160: =$M$159/$B$159 -> 0 | N160: =$N$159/$B$159 -> 0 | O160: =Planejador!$I$129 -> #DIV/0! | P160: =Planejador!$I$120 | Q160: =Planejador!$I$122 | R160: =Planejador!$I$126 -> #DIV/0! | S160: =$S$159/$B$159 -> 0 | T160: =Planejador!$I$121
A161: 46175 | B161: =TEXT(A161,"dddd") -> terça-feira | D161: =SUMIF('ADV - GG'!A:A,A161,'ADV - GG'!C:C)+SUMIF('ADV - FB'!A:A,$A161,'ADV - FB'!E:E) -> 0 | F161: =IFERROR(E161/D161,"") | G161: =IFERROR(D161/K161,"") | H161: =iferror(J161/K161,"") | I161: =iferror(D161/J161,"") | J161: =SUMIF('ADV - GG'!A:A,A161,'ADV - GG'!H:H)+SUMIF('ADV - FB'!A:A,$A161,'ADV - FB'!I:I) -> 0 | K161: =SUMIF('ADV - GA4'!A:A,A161,'ADV - GA4'!C:C) -> 0 | L161: =IFERROR(E161/J161,"") | M161: =$M$159/$B$159 -> 0 | N161: =$N$159/$B$159 -> 0 | O161: =Planejador!$I$129 -> #DIV/0! | P161: =Planejador!$I$120 | Q161: =Planejador!$I$122 | R161: =Planejador!$I$126 -> #DIV/0! | S161: =$S$159/$B$159 -> 0 | T161: =Planejador!$I$121
A162: 46176 | B162: =TEXT(A162,"dddd") -> quarta-feira | D162: =SUMIF('ADV - GG'!A:A,A162,'ADV - GG'!C:C)+SUMIF('ADV - FB'!A:A,$A162,'ADV - FB'!E:E) -> 0 | F162: =IFERROR(E162/D162,"") | G162: =IFERROR(D162/K162,"") | H162: =iferror(J162/K162,"") | I162: =iferror(D162/J162,"") | J162: =SUMIF('ADV - GG'!A:A,A162,'ADV - GG'!H:H)+SUMIF('ADV - FB'!A:A,$A162,'ADV - FB'!I:I) -> 0 | K162: =SUMIF('ADV - GA4'!A:A,A162,'ADV - GA4'!C:C) -> 0 | L162: =IFERROR(E162/J162,"") | M162: =$M$159/$B$159 -> 0 | N162: =$N$159/$B$159 -> 0 | O162: =Planejador!$I$129 -> #DIV/0! | P162: =Planejador!$I$120 | Q162: =Planejador!$I$122 | R162: =Planejador!$I$126 -> #DIV/0! | S162: =$S$159/$B$159 -> 0 | T162: =Planejador!$I$121
A163: 46177 | B163: =TEXT(A163,"dddd") -> quinta-feira | D163: =SUMIF('ADV - GG'!A:A,A163,'ADV - GG'!C:C)+SUMIF('ADV - FB'!A:A,$A163,'ADV - FB'!E:E) -> 0 | F163: =IFERROR(E163/D163,"") | G163: =IFERROR(D163/K163,"") | H163: =iferror(J163/K163,"") | I163: =iferror(D163/J163,"") | J163: =SUMIF('ADV - GG'!A:A,A163,'ADV - GG'!H:H)+SUMIF('ADV - FB'!A:A,$A163,'ADV - FB'!I:I) -> 0 | K163: =SUMIF('ADV - GA4'!A:A,A163,'ADV - GA4'!C:C) -> 0 | L163: =IFERROR(E163/J163,"") | M163: =$M$159/$B$159 -> 0 | N163: =$N$159/$B$159 -> 0 | O163: =Planejador!$I$129 -> #DIV/0! | P163: =Planejador!$I$120 | Q163: =Planejador!$I$122 | R163: =Planejador!$I$126 -> #DIV/0! | S163: =$S$159/$B$159 -> 0 | T163: =Planejador!$I$121
A164: 46178 | B164: =TEXT(A164,"dddd") -> sexta-feira | D164: =SUMIF('ADV - GG'!A:A,A164,'ADV - GG'!C:C)+SUMIF('ADV - FB'!A:A,$A164,'ADV - FB'!E:E) -> 0 | F164: =IFERROR(E164/D164,"") | G164: =IFERROR(D164/K164,"") | H164: =iferror(J164/K164,"") | I164: =iferror(D164/J164,"") | J164: =SUMIF('ADV - GG'!A:A,A164,'ADV - GG'!H:H)+SUMIF('ADV - FB'!A:A,$A164,'ADV - FB'!I:I) -> 0 | K164: =SUMIF('ADV - GA4'!A:A,A164,'ADV - GA4'!C:C) -> 0 | L164: =IFERROR(E164/J164,"") | M164: =$M$159/$B$159 -> 0 | N164: =$N$159/$B$159 -> 0 | O164: =Planejador!$I$129 -> #DIV/0! | P164: =Planejador!$I$120 | Q164: =Planejador!$I$122 | R164: =Planejador!$I$126 -> #DIV/0! | S164: =$S$159/$B$159 -> 0 | T164: =Planejador!$I$121
A165: 46179 | B165: =TEXT(A165,"dddd") -> sábado | D165: =SUMIF('ADV - GG'!A:A,A165,'ADV - GG'!C:C)+SUMIF('ADV - FB'!A:A,$A165,'ADV - FB'!E:E) -> 0 | F165: =IFERROR(E165/D165,"") | G165: =IFERROR(D165/K165,"") | H165: =iferror(J165/K165,"") | I165: =iferror(D165/J165,"") | J165: =SUMIF('ADV - GG'!A:A,A165,'ADV - GG'!H:H)+SUMIF('ADV - FB'!A:A,$A165,'ADV - FB'!I:I) -> 0 | K165: =SUMIF('ADV - GA4'!A:A,A165,'ADV - GA4'!C:C) -> 0 | L165: =IFERROR(E165/J165,"") | M165: =$M$159/$B$159 -> 0 | N165: =$N$159/$B$159 -> 0 | O165: =Planejador!$I$129 -> #DIV/0! | P165: =Planejador!$I$120 | Q165: =Planejador!$I$122 | R165: =Planejador!$I$126 -> #DIV/0! | S165: =$S$159/$B$159 -> 0 | T165: =Planejador!$I$121
A166: 46180 | B166: =TEXT(A166,"dddd") -> domingo | D166: =SUMIF('ADV - GG'!A:A,A166,'ADV - GG'!C:C)+SUMIF('ADV - FB'!A:A,$A166,'ADV - FB'!E:E) -> 0 | F166: =IFERROR(E166/D166,"") | G166: =IFERROR(D166/K166,"") | H166: =iferror(J166/K166,"") | I166: =iferror(D166/J166,"") | J166: =SUMIF('ADV - GG'!A:A,A166,'ADV - GG'!H:H)+SUMIF('ADV - FB'!A:A,$A166,'ADV - FB'!I:I) -> 0 | K166: =SUMIF('ADV - GA4'!A:A,A166,'ADV - GA4'!C:C) -> 0 | L166: =IFERROR(E166/J166,"") | M166: =$M$159/$B$159 -> 0 | N166: =$N$159/$B$159 -> 0 | O166: =Planejador!$I$129 -> #DIV/0! | P166: =Planejador!$I$120 | Q166: =Planejador!$I$122 | R166: =Planejador!$I$126 -> #DIV/0! | S166: =$S$159/$B$159 -> 0 | T166: =Planejador!$I$121
A167: 46181 | B167: =TEXT(A167,"dddd") -> segunda-feira | D167: =SUMIF('ADV - GG'!A:A,A167,'ADV - GG'!C:C)+SUMIF('ADV - FB'!A:A,$A167,'ADV - FB'!E:E) -> 0 | F167: =IFERROR(E167/D167,"") | G167: =IFERROR(D167/K167,"") | H167: =iferror(J167/K167,"") | I167: =iferror(D167/J167,"") | J167: =SUMIF('ADV - GG'!A:A,A167,'ADV - GG'!H:H)+SUMIF('ADV - FB'!A:A,$A167,'ADV - FB'!I:I) -> 0 | K167: =SUMIF('ADV - GA4'!A:A,A167,'ADV - GA4'!C:C) -> 0 | L167: =IFERROR(E167/J167,"") | M167: =$M$159/$B$159 -> 0 | N167: =$N$159/$B$159 -> 0 | O167: =Planejador!$I$129 -> #DIV/0! | P167: =Planejador!$I$120 | Q167: =Planejador!$I$122 | R167: =Planejador!$I$126 -> #DIV/0! | S167: =$S$159/$B$159 -> 0 | T167: =Planejador!$I$121
A168: 46182 | B168: =TEXT(A168,"dddd") -> terça-feira | D168: =SUMIF('ADV - GG'!A:A,A168,'ADV - GG'!C:C)+SUMIF('ADV - FB'!A:A,$A168,'ADV - FB'!E:E) -> 0 | F168: =IFERROR(E168/D168,"") | G168: =IFERROR(D168/K168,"") | H168: =iferror(J168/K168,"") | I168: =iferror(D168/J168,"") | J168: =SUMIF('ADV - GG'!A:A,A168,'ADV - GG'!H:H)+SUMIF('ADV - FB'!A:A,$A168,'ADV - FB'!I:I) -> 0 | K168: =SUMIF('ADV - GA4'!A:A,A168,'ADV - GA4'!C:C) -> 0 | L168: =IFERROR(E168/J168,"") | M168: =$M$159/$B$159 -> 0 | N168: =$N$159/$B$159 -> 0 | O168: =Planejador!$I$129 -> #DIV/0! | P168: =Planejador!$I$120 | Q168: =Planejador!$I$122 | R168: =Planejador!$I$126 -> #DIV/0! | S168: =$S$159/$B$159 -> 0 | T168: =Planejador!$I$121
A169: 46183 | B169: =TEXT(A169,"dddd") -> quarta-feira | D169: =SUMIF('ADV - GG'!A:A,A169,'ADV - GG'!C:C)+SUMIF('ADV - FB'!A:A,$A169,'ADV - FB'!E:E) -> 0 | F169: =IFERROR(E169/D169,"") | G169: =IFERROR(D169/K169,"") | H169: =iferror(J169/K169,"") | I169: =iferror(D169/J169,"") | J169: =SUMIF('ADV - GG'!A:A,A169,'ADV - GG'!H:H)+SUMIF('ADV - FB'!A:A,$A169,'ADV - FB'!I:I) -> 0 | K169: =SUMIF('ADV - GA4'!A:A,A169,'ADV - GA4'!C:C) -> 0 | L169: =IFERROR(E169/J169,"") | M169: =$M$159/$B$159 -> 0 | N169: =$N$159/$B$159 -> 0 | O169: =Planejador!$I$129 -> #DIV/0! | P169: =Planejador!$I$120 | Q169: =Planejador!$I$122 | R169: =Planejador!$I$126 -> #DIV/0! | S169: =$S$159/$B$159 -> 0 | T169: =Planejador!$I$121
A170: 46184 | B170: =TEXT(A170,"dddd") -> quinta-feira | D170: =SUMIF('ADV - GG'!A:A,A170,'ADV - GG'!C:C)+SUMIF('ADV - FB'!A:A,$A170,'ADV - FB'!E:E) -> 0 | F170: =IFERROR(E170/D170,"") | G170: =IFERROR(D170/K170,"") | H170: =iferror(J170/K170,"") | I170: =iferror(D170/J170,"") | J170: =SUMIF('ADV - GG'!A:A,A170,'ADV - GG'!H:H)+SUMIF('ADV - FB'!A:A,$A170,'ADV - FB'!I:I) -> 0 | K170: =SUMIF('ADV - GA4'!A:A,A170,'ADV - GA4'!C:C) -> 0 | L170: =IFERROR(E170/J170,"") | M170: =$M$159/$B$159 -> 0 | N170: =$N$159/$B$159 -> 0 | O170: =Planejador!$I$129 -> #DIV/0! | P170: =Planejador!$I$120 | Q170: =Planejador!$I$122 | R170: =Planejador!$I$126 -> #DIV/0! | S170: =$S$159/$B$159 -> 0 | T170: =Planejador!$I$121
A171: 46185 | B171: =TEXT(A171,"dddd") -> sexta-feira | D171: =SUMIF('ADV - GG'!A:A,A171,'ADV - GG'!C:C)+SUMIF('ADV - FB'!A:A,$A171,'ADV - FB'!E:E) -> 0 | F171: =IFERROR(E171/D171,"") | G171: =IFERROR(D171/K171,"") | H171: =iferror(J171/K171,"") | I171: =iferror(D171/J171,"") | J171: =SUMIF('ADV - GG'!A:A,A171,'ADV - GG'!H:H)+SUMIF('ADV - FB'!A:A,$A171,'ADV - FB'!I:I) -> 0 | K171: =SUMIF('ADV - GA4'!A:A,A171,'ADV - GA4'!C:C) -> 0 | L171: =IFERROR(E171/J171,"") | M171: =$M$159/$B$159 -> 0 | N171: =$N$159/$B$159 -> 0 | O171: =Planejador!$I$129 -> #DIV/0! | P171: =Planejador!$I$120 | Q171: =Planejador!$I$122 | R171: =Planejador!$I$126 -> #DIV/0! | S171: =$S$159/$B$159 -> 0 | T171: =Planejador!$I$121
... A189: 46203 | B189: =TEXT(A189,"dddd") -> terça-feira | D189: =SUMIF('ADV - GG'!A:A,A189,'ADV - GG'!C:C)+SUMIF('ADV - FB'!A:A,$A189,'ADV - FB'!E:E) -> 0 | F189: =IFERROR(E189/D189,"") | G189: =IFERROR(D189/K189,"") | H189: =iferror(J189/K189,"") | I189: =iferror(D189/J189,"") | J189: =SUMIF('ADV - GG'!A:A,A189,'ADV - GG'!H:H)+SUMIF('ADV - FB'!A:A,$A189,'ADV - FB'!I:I) -> 0 | K189: =SUMIF('ADV - GA4'!A:A,A189,'ADV - GA4'!C:C) -> 0 | L189: =IFERROR(E189/J189,"") | M189: =$M$159/$B$159 -> 0 | N189: =$N$159/$B$159 -> 0 | O189: =Planejador!$I$129 -> #DIV/0! | P189: =Planejador!$I$120 | Q189: =Planejador!$I$122 | R189: =Planejador!$I$126 -> #DIV/0! | S189: =$S$159/$B$159 -> 0 | T189: =Planejador!$I$121
A190: JULHO | B190: 31 | D190: =IFERROR(SUM(D191:D221),"") -> 0 | E190: =IFERROR(SUM(E191:E221),"") -> 0 | F190: =IFERROR(E190/D190,"") | G190: =IFERROR(D190/K190,"") | H190: =IFERROR(J190/K190,"") | I190: =IFERROR(D190/J190,"") | J190: =IFERROR(SUM(J191:J221),"") -> 0 | K190: =IFERROR(SUM(K191:K221),"") -> 0 | L190: =IFERROR(E190/J190,"") | M190: =Planejador!$I$142 | N190: =IFERROR(Planejador!$I$151,"") | O190: =IFERROR(Planejador!$I$152,"") | P190: =Planejador!$I$143 | Q190: =Planejador!$I$145 | R190: =IFERROR(Planejador!$I$149,"") | S190: =IFERROR(Planejador!$I$148,"") | T190: =IFERROR(Planejador!$I$144,"")
...

Sheet Dados Históricos
A1: CRESCIMENTO MoM | C1: =(C3-B3)/B3*1 -> #DIV/0! | D1: =(D3-C3)/C3*1 -> #DIV/0! | E1: =(E3-D3)/D3*1 -> #DIV/0! | F1: =(F3-E3)/E3*1 -> #DIV/0! | G1: =(G3-F3)/F3*1 -> #DIV/0! | H1: =(H3-G3)/G3*1 -> #DIV/0! | I1: =(I3-H3)/H3*1 -> #DIV/0! | J1: =(J3-I3)/I3*1 -> #DIV/0! | ... M1: =(M3-L3)/L3*1 -> #DIV/0! | O1: MÉTRICAS MÉDIAS
A2: MÉTRICAS / MÊS | B2: JAN | C2: FEV | D2: MAR | E2: ABR | F2: MAI | G2: JUN | H2: JUL | I2: AGO | J2: SET | K2: OUT | L2: NOV | M2: DEZ | O2: Crescimento Médio | P2: =AVERAGE(C1:K1) -> #DIV/0!
A3: Receita Captada | O3: Receita Captada | P3: =AVERAGE(B3:M3) -> #DIV/0!
A4: Receita Faturada | O4: Receita Faturada | P4: =AVERAGE(B4:M4) -> #DIV/0!
A5: % de Aprovação | B5: =IFERROR(B4/B3,"") | C5: =IFERROR(C4/C3,"") | D5: =IFERROR(D4/D3,"") | E5: =IFERROR(E4/E3,"") | F5: =IFERROR(F4/F3,"") | G5: =IFERROR(G4/G3,"") | H5: =IFERROR(H4/H3,"") | I5: =IFERROR(I4/I3,"") | ... M5: =IFERROR(M4/M3,"") | O5: % Aprovação | P5: =AVERAGE(B5:M5) -> #DIV/0!
A6: Receita Captada Midia Paga | O6: Receita Mídia | P6: =AVERAGE(B6:M6) -> #DIV/0!
A7: % Mídia Paga | B7: =IFERROR((B6/B3)*1,"") | C7: =IFERROR((C6/C3)*1,"") | D7: =IFERROR((D6/D3)*1,"") | E7: =IFERROR((E6/E3)*1,"") | F7: =IFERROR((F6/F3)*1,"") | G7: =IFERROR((G6/G3)*1,"") | H7: =IFERROR((H6/H3)*1,"") | I7: =IFERROR((I6/I3)*1,"") | ... M7: =IFERROR((M6/M3)*1,"") | O7: % Mídia Paga | P7: =AVERAGE(B7:J7) -> #DIV/0!
A8: Receita Captada Outros Canais | B8: =IFERROR(B3-B6,"") -> 0 | C8: =IFERROR(C3-C6,"") -> 0 | D8: =IFERROR(D3-D6,"") -> 0 | E8: =IFERROR(E3-E6,"") -> 0 | F8: =IFERROR(F3-F6,"") -> 0 | G8: =IFERROR(G3-G6,"") -> 0 | H8: =IFERROR(H3-H6,"") -> 0 | I8: =IFERROR(I3-I6,"") -> 0 | ... M8: =IFERROR(M3-M6,"") -> 0 | O8: Receita Canais | P8: =AVERAGE(B8:M8) -> 0
A9: % Outros Canais | B9: =IFERROR((B8/B3)*1,"") | C9: =IFERROR((C8/C3)*1,"") | D9: =IFERROR((D8/D3)*1,"") | E9: =IFERROR((E8/E3)*1,"") | F9: =IFERROR((F8/F3)*1,"") | G9: =IFERROR((G8/G3)*1,"") | H9: =IFERROR((H8/H3)*1,"") | I9: =IFERROR((I8/I3)*1,"") | ... M9: =IFERROR((M8/M3)*1,"") | O9: % Outros Canais | P9: =AVERAGE(B9:M9) -> #DIV/0!
A10: Investimento Ads | O10: Investimento | P10: =AVERAGE(B10:M10) -> #DIV/0!
A11: % Aumento / Redução ADS | C11: =(C10-B10)/B10*1 -> #DIV/0! | D11: =(D10-C10)/C10*1 -> #DIV/0! | E11: =(E10-D10)/D10*1 -> #DIV/0! | F11: =(F10-E10)/E10*1 -> #DIV/0! | G11: =(G10-F10)/F10*1 -> #DIV/0! | H11: =(H10-G10)/G10*1 -> #DIV/0! | I11: =(I10-H10)/H10*1 -> #DIV/0! | J11: =(J10-I10)/I10*1 -> #DIV/0! | O11: % Aumento / Redução ADS | P11: =AVERAGE(B11:M11) -> #DIV/0!
A12: Sessões Totais | O12: Sessões Geral | P12: =AVERAGE(B12:M12) -> #DIV/0!
A13: Sessões Midia | O13: Sessões Mídia | P13: =AVERAGE(B13:M13) -> #DIV/0!
A14: CPS Geral | B14: =IFERROR(B10/B12,"") | C14: =IFERROR(C10/C12,"") | D14: =IFERROR(D10/D12,"") | E14: =IFERROR(E10/E12,"") | F14: =IFERROR(F10/F12,"") | G14: =IFERROR(G10/G12,"") | H14: =IFERROR(H10/H12,"") | I14: =IFERROR(I10/I12,"") | ... M14: =IFERROR(M10/M12,"") | O14: CPS Geral | P14: =AVERAGE(B14:M14) -> #DIV/0!
A15: CPS Midia | B15: =IFERROR(B10/B13,"") | C15: =IFERROR(C10/C13,"") | D15: =IFERROR(D10/D13,"") | E15: =IFERROR(E10/E13,"") | F15: =IFERROR(F10/F13,"") | G15: =IFERROR(G10/G13,"") | H15: =IFERROR(H10/H13,"") | I15: =IFERROR(I10/I13,"") | ... M15: =IFERROR(M10/M13,"") | O15: CPS Mídia | P15: =AVERAGE(B15:M15) -> #DIV/0!
A16: Transações Captadas | O16: Pedidos | P16: =AVERAGE(B16:M16) -> #DIV/0!
A17: Ticket Médio | B17: =IFERROR(B3/B16,"") | C17: =IFERROR(C3/C16,"") | D17: =IFERROR(D3/D16,"") | E17: =IFERROR(E3/E16,"") | F17: =IFERROR(F3/F16,"") | G17: =IFERROR(G3/G16,"") | H17: =IFERROR(H3/H16,"") | I17: =IFERROR(I3/I16,"") | ... M17: =IFERROR(M3/M16,"") | O17: Ticket Médio | P17: =AVERAGE(B17:M17) -> #DIV/0!
A18: Taxa de Conversão | B18: =IFERROR(B16/B12,"") | C18: =IFERROR(C16/C12,"") | D18: =IFERROR(D16/D12,"") | E18: =IFERROR(E16/E12,"") | F18: =IFERROR(F16/F12,"") | G18: =IFERROR(G16/G12,"") | H18: =IFERROR(H16/H12,"") | I18: =IFERROR(I16/I12,"") | ... M18: =IFERROR(M16/M12,"") | O18: Taxa de Conversão | P18: =AVERAGE(B18:M18) -> #DIV/0!
A19: ROAS Captado | B19: =IFERROR(B3/B10,"") | C19: =IFERROR(C3/C10,"") | D19: =IFERROR(D3/D10,"") | E19: =IFERROR(E3/E10,"") | F19: =IFERROR(F3/F10,"") | G19: =IFERROR(G3/G10,"") | H19: =IFERROR(H3/H10,"") | I19: =IFERROR(I3/I10,"") | ... M19: =IFERROR(M3/M10,"") | O19: ROAS Captado | P19: =AVERAGE(B19:M19) -> #DIV/0!
A20: % + - ROAS Geral | C20: =(C19/B19)-1 -> #DIV/0! | D20: =(D19/C19)-1 -> #DIV/0! | E20: =(E19/D19)-1 -> #DIV/0! | F20: =(F19/E19)-1 -> #DIV/0! | G20: =(G19/F19)-1 -> #DIV/0! | H20: =(H19/G19)-1 -> #DIV/0! | I20: =(I19/H19)-1 -> #DIV/0! | J20: =(J19/I19)-1 -> #DIV/0! | O20: % + - ROAS Geral | P20: =AVERAGE(B20:M20) -> #DIV/0!
A21: ROAS Faturado | B21: =IFERROR(B4/B10,"") | C21: =IFERROR(C4/C10,"") | D21: =IFERROR(D4/D10,"") | E21: =IFERROR(E4/E10,"") | F21: =IFERROR(F4/F10,"") | G21: =IFERROR(G4/G10,"") | H21: =IFERROR(H4/H10,"") | I21: =IFERROR(I4/I10,"") | ... M21: =IFERROR(M4/M10,"") | O21: ROAS Faturado | P21: =AVERAGE(B21:M21) -> #DIV/0!
A22: ROAS Midia Paga | B22: =IFERROR(B6/B10,"") | C22: =IFERROR(C6/C10,"") | D22: =IFERROR(D6/D10,"") | E22: =IFERROR(E6/E10,"") | F22: =IFERROR(F6/F10,"") | G22: =IFERROR(G6/G10,"") | H22: =IFERROR(H6/H10,"") | I22: =IFERROR(I6/I10,"") | ... M22: =IFERROR(M6/M10,"") | O22: ROAS Mídia | P22: =AVERAGE(B22:M22) -> #DIV/0!
A23: % + - ROAS Midia | C23: =IFERROR((C22/B22)-1,"") | D23: =(D22/C22)-1 -> #DIV/0! | E23: =(E22/D22)-1 -> #DIV/0! | F23: =(F22/E22)-1 -> #DIV/0! | G23: =(G22/F22)-1 -> #DIV/0! | H23: =(H22/G22)-1 -> #DIV/0! | I23: =(I22/H22)-1 -> #DIV/0! | J23: =(J22/I22)-1 -> #DIV/0! | O23: % + - ROAS Midia | P23: =AVERAGE(B23:M23) -> #DIV/0!
A27: CANAIS | B27: JAN | C27: FEV | D27: MAR | E27: ABR | F27: MAI | G27: JUN | H27: JUL | I27: AGO | J27: SET | K27: OUT | L27: NOV | M27: DEZ | O27: TOTAL
A28: (Other) | O28: =SUM(B28:M28) -> 0 | P28: =O28/$O$42 -> #DIV/0!
A29: Direto / none | O29: =SUM(B29:M29) -> 0 | P29: =O29/$O$42 -> #DIV/0!
A30: Facebook cpc | O30: =SUM(B30:M30) -> 0 | P30: =O30/$O$42 -> #DIV/0!
A31: Google cpc | O31: =SUM(B31:M31) -> 0 | P31: =O31/$O$42 -> #DIV/0!
A32: Orgânico | O32: =SUM(B32:M32) -> 0 | P32: =O32/$O$42 -> #DIV/0!
A33: Instagram Perfil | O33: =SUM(B33:M33) -> 0 | P33: =O33/$O$42 -> #DIV/0!
A34: E-mail | O34: =SUM(B34:M34) -> 0 | P34: =O34/$O$42 -> #DIV/0!
A35: IG Shopping | O35: =SUM(B35:M35) -> 0 | P35: =O35/$O$42 -> #DIV/0!
A36: Instagram / FB Referral | O36: =SUM(B36:M36) -> 0 | P36: =O36/$O$42 -> #DIV/0!
A37: Blog | O37: =SUM(B37:M37) -> 0 | P37: =O37/$O$42 -> #DIV/0!
A38: Pinterest / Referral | O38: =SUM(B38:M38) -> 0 | P38: =O38/$O$42 -> #DIV/0!
A39: TikTok | O39: =SUM(B39:M39) -> 0 | P39: =O39/$O$42 -> #DIV/0!
... A41: Youtube referral | O41: =SUM(B41:M41) -> 0 | P41: =O41/$O$42 -> #DIV/0!
A42: Total de receita | B42: =IFERROR(SUM(B28:B41),"") -> 0 | C42: =IFERROR(SUM(C28:C41),"") -> 0 | D42: =IFERROR(SUM(D28:D41),"") -> 0 | E42: =IFERROR(SUM(E28:E41),"") -> 0 | F42: =IFERROR(SUM(F28:F41),"") -> 0 | G42: =IFERROR(SUM(G28:G41),"") -> 0 | H42: =IFERROR(SUM(H28:H41),"") -> 0 | I42: =IFERROR(SUM(I28:I41),"") -> 0 | ... M42: =IFERROR(SUM(M28:M41),"") -> 0 | O42: =SUM(B42:M42) -> 0
A43: Share dos meses | B43: =IFERROR(B42/$O$42,"") | C43: =IFERROR(C42/$O$42,"") | D43: =IFERROR(D42/$O$42,"") | E43: =IFERROR(E42/$O$42,"") | F43: =IFERROR(F42/$O$42,"") | G43: =IFERROR(G42/$O$42,"") | H43: =IFERROR(H42/$O$42,"") | I43: =IFERROR(I42/$O$42,"") | ... M43: =IFERROR(M42/$O$42,"")

Sheet Planejador
B1: JANEIRO
B3: CENÁRIO ATUAL (ÚLTIMO MÊS) | E3: CENÁRIO DESEJADO | H3: CENÁRIO IDEAL | J3: MÉDIA / ANUAL | K3: % ATUAL | L3: % MÁX
B4: Valor Investimento | E4: Faturamento Desejado | H4: Verba Mensal | K4: =(I4-J4)/J4*1 -> #DIV/0! | L4: 0.4
B5: CPS Geral | E5: CPS Atual | F5: =C5 | H5: CPS Ideal | K5: =(I5-J5)/J5*1 -> #DIV/0! | L5: -0.1
B6: Ticket Médio | E6: Ticket Médio | F6: =C6 | H6: Ticket Médio Ideal | K6: =(I6-J6)/J6*1 -> #DIV/0! | L6: 0.1
B7: TX Conversão | E7: Taxa de Conversão Atual | F7: =C7 | H7: Taxa Conversão Ideal | K7: =(I7-J7)/J7*1 -> #DIV/0! | L7: 0.1
B8: % De Aprovação | E8: % De Pagamento Atual | F8: =C8 | H8: Aprovação Pagamento | K8: =(I8-J8)/J8*1 -> #DIV/0! | L8: 0.03
B10: Sessões | C10: =C4/C5 -> #DIV/0! | E10: Visitas Ideais | F10: =F12/F7 -> #DIV/0! | H10: Visitas Ideais | I10: =I4/I5 -> #DIV/0! | K10: CANAL DE VENDA | L10: % | M10: FATURAMENTO | N10: PEDIDOS POR CANAL | Q10: 80/20 PRODUTOS | R10: PRODUTO | S10: % | T10: PEDIDOS POR PRODUTO | U10: TICKET MÉDIO | V10: FATURAMENTO ESPERADO
B11: CPA | C11: =C4/C12 -> #DIV/0! | E11: CPA Ideal | F11: =F15/F12 -> #DIV/0! | H11: CPA Ideal | I11: =I4/I12 -> #DIV/0! | K11: Meta Ads | L11: 0.2 | M11: =I15/100*L11*100 -> #DIV/0! | N11: =M11/I6 -> #DIV/0! | Q11: 80% DAS VENDAS | R11: Produto 1 | S11: 0.25 | T11: =I12*S11 -> #DIV/0! | U11: 100 | V11: =T11*U11 -> #DIV/0!
B12: Pedidos | C12: =C10*C7 -> #DIV/0! | E12: Pedidos Mês Ideal | F12: =F13/F6 -> #DIV/0! | H12: Pedidos Mês Ideal | I12: =I10*I7 -> #DIV/0! | K12: Google Ads | L12: 0.2 | M12: =I15/100*L12*100 -> #DIV/0! | N12: =M12/I6 -> #DIV/0! | R12: Produto 2 | S12: 0.2 | T12: =I12*S12 -> #DIV/0! | U12: 100 | V12: =T12*U12 -> #DIV/0!
B13: Faturamento Captado | C13: =(C10*C7)*C6 -> #DIV/0! | E13: Faturamento Captado | F13: =F4/F8 -> #DIV/0! | H13: Faturamento Bruto | I13: =I10*I7*I6 -> #DIV/0! | K13: Social | L13: 0.3 | M13: =I15/100*L13*100 -> #DIV/0! | N13: =M13/I6 -> #DIV/0! | R13: Produto 3 | S13: 0.2 | T13: =I12*S13 -> #DIV/0! | U13: 100 | V13: =T13*U13 -> #DIV/0!
B14: ROAS Bruto | C14: =C13/C4 -> #DIV/0! | E14: ROAS Bruto | F14: =F13/F15 -> #DIV/0! | H14: ROAS Bruto | I14: =I13/I4 -> #DIV/0! | K14: Organico | L14: 0.15 | M14: =I15/100*L14*100 -> #DIV/0! | N14: =M14/I6 -> #DIV/0! | R14: Produto 4 | S14: 0.15 | T14: =I12*S14 -> #DIV/0! | U14: 100 | V14: =T14*U14 -> #DIV/0!
B15: Faturamento Real | C15: =C13*C8 -> #DIV/0! | E15: Investimento Necessário | F15: =F10*F5 -> #DIV/0! | H15: Faturamento Desejado | I15: =I13*I8 -> #DIV/0! | K15: E-mail | L15: 0.15 | M15: =I15/100*L15*100 -> #DIV/0! | N15: =M15/I6 -> #DIV/0! | Q15: 20% DAS VENDAS | R15: Produto 5 | S15: 0.05 | T15: =I12*S15 -> #DIV/0! | U15: 100 | V15: =T15*U15 -> #DIV/0!
B16: ROAS Real | C16: =C15/C4 -> #DIV/0! | E16: ROAS Desejado | F16: =F4/F15 -> #DIV/0! | H16: ROAS Real | I16: =I15/I4 -> #DIV/0! | L16: =SUM(L11:L15) -> 1 | N16: =SUM(N11:N15) -> #DIV/0! | R16: Produto 6 | S16: 0.05 | T16: =I12*S16 -> #DIV/0! | U16: 100 | V16: =T16*U16 -> #DIV/0!
R17: Produto 7 | S17: 0.05 | T17: =I12*S17 -> #DIV/0! | U17: 100 | V17: =T17*U17 -> #DIV/0!
B18: CENÁRIO DIÁRIO ATUAL | E18: CENÁRIO DIÁRIO DESEJADO | H18: CENÁRIO DIÁRIO IDEAL | K18: Canal | L18: Facebook | M18: Google | N18: Outros | O18: Total | R18: Produto 8 | S18: 0.05 | T18: =I12*S18 -> #DIV/0! | U18: 100 | V18: =T18*U18 -> #DIV/0!
B19: Investimento Diário | C19: =C4/30 -> 0 | E19: Investimento Diário | F19: =F4/30 -> 0 | H19: Investimento Diário | I19: =I4/'Acompanhamento Geral'!B2 -> 0 | K19: % | L19: 0.7 | M19: 0.3 | N19: 0 | O19: =sum(L19:N19) -> 1 | S19: =SUM(S11:S18) -> 1 | T19: =SUM(T11:T18) -> #DIV/0! | V19: =SUM(V11:V18) -> #DIV/0!
B20: Sessões Diárias | C20: =C10/30 -> #DIV/0! | E20: Sessões Diárias | F20: =F10/30 -> #DIV/0! | H20: Sessões Diárias | I20: =I10/'Acompanhamento Geral'!B2 -> #DIV/0! | K20: Verba Mês | L20: =I4*L19 -> 0 | M20: =I4*M19 -> 0 | N20: =I4*N19 -> 0 | O20: =sum(L20:N20) -> 0
B21: Pedidos Diários | C21: =C12/30 -> #DIV/0! | E21: Pedidos Diários | F21: =F12/30 -> #DIV/0! | H21: Pedidos Diários | I21: =I12/'Acompanhamento Geral'!B2 -> #DIV/0! | K21: Verba Dia | L21: =L20/'Acompanhamento Geral'!B2 -> 0 | M21: =M20/'Acompanhamento Geral'!B2 -> 0 | N21: =iferror(N20/'Acompanhamento Geral'!B2,"") -> 0 | O21: =SUM(L21:N21) -> 0
B22: Faturamento Diário | C22: =C13/30 -> #DIV/0! | E22: Faturamento Diário | F22: =F13/30 -> #DIV/0! | H22: Faturamento Diário | I22: =I13/'Acompanhamento Geral'!B2 -> #DIV/0!
B24: FEVEREIRO
B26: CENÁRIO ATUAL (ÚLTIMO MÊS) | E26: CENÁRIO DESEJADO | H26: CENÁRIO IDEAL | J26: MÉDIA / ANUAL | K26: % ATUAL | L26: % MÁX
B27: Valor Investimento | E27: Faturamento Desejado | H27: Verba Mensal | K27: =(I27-J27)/J27*1 -> #DIV/0! | L27: 0.4
B28: CPS Geral | E28: CPS Atual | F28: =C28 | H28: CPS Ideal | K28: =(I28-J28)/J28*1 -> #DIV/0! | L28: -0.1
B29: Ticket Médio | E29: Ticket Médio | F29: =C29 | H29: Ticket Médio Ideal | K29: =(I29-J29)/J29*1 -> #DIV/0! | L29: 0.1
B30: TX Conversão | E30: Taxa de Conversão Atual | F30: =C30 | H30: Taxa Conversão Ideal | K30: =(I30-J30)/J30*1 -> #DIV/0! | L30: 0.1
B31: % De Aprovação | E31: % De Pagamento Atual | F31: =C31 | H31: Aprovação Pagamento | K31: =(I31-J31)/J31*1 -> #DIV/0! | L31: 0.03
B33: Sessões | C33: =C27/C28 -> #DIV/0! | E33: Visitas Ideais | F33: =F35/F30 -> #DIV/0! | H33: Visitas Ideais | I33: =I27/I28 -> #DIV/0! | K33: CANAL DE VENDA | L33: % | M33: FATURAMENTO | N33: PEDIDOS POR CANAL
B34: CPA | C34: =C27/C35 -> #DIV/0! | E34: CPA Ideal | F34: =F38/F35 -> #DIV/0! | H34: CPA Ideal | I34: =I27/I35 -> #DIV/0! | K34: Meta Ads | L34: 0.2 | M34: =I38/100*L34*100 -> #DIV/0! | N34: =M34/I29 -> #DIV/0!
B35: Pedidos | C35: =C33*C30 -> #DIV/0! | E35: Pedidos Mês Ideal | F35: =F36/F29 -> #DIV/0! | H35: Pedidos Mês Ideal | I35: =I33*I30 -> #DIV/0! | K35: Google Ads | L35: 0.2 | M35: =I38/100*L35*100 -> #DIV/0! | N35: =M35/I29 -> #DIV/0!
B36: Faturamento Captado | C36: =(C33*C30)*C29 -> #DIV/0! | E36: Faturamento Captado | F36: =F27/F31 -> #DIV/0! | H36: Faturamento Bruto | I36: =I33*I30*I29 -> #DIV/0! | K36: Social | L36: 0.3 | M36: =I38/100*L36*100 -> #DIV/0! | N36: =M36/I29 -> #DIV/0!
B37: ROAS Bruto | C37: =C36/C27 -> #DIV/0! | E37: ROAS Bruto | F37: =F36/F38 -> #DIV/0! | H37: ROAS Bruto | I37: =I36/I27 -> #DIV/0! | K37: Organico | L37: 0.15 | M37: =I38/100*L37*100 -> #DIV/0! | N37: =M37/I29 -> #DIV/0!
B38: Faturamento Real | C38: =C36*C31 -> #DIV/0! | E38: Investimento Necessário | F38: =F33*F28 -> #DIV/0! | H38: Faturamento Desejado | I38: =I36*I31 -> #DIV/0! | K38: E-mail | L38: 0.15 | M38: =I38/100*L38*100 -> #DIV/0! | N38: =M38/I29 -> #DIV/0!
B39: ROAS Real | C39: =C38/C27 -> #DIV/0! | E39: ROAS Desejado | F39: =F27/F38 -> #DIV/0! | H39: ROAS Real | I39: =I38/I27 -> #DIV/0! | L39: =SUM(L34:L38) -> 1 | N39: =SUM(N34:N38) -> #DIV/0!
B41: CENÁRIO DIÁRIO ATUAL | E41: CENÁRIO DIÁRIO DESEJADO | H41: CENÁRIO DIÁRIO IDEAL | K41: Canal | L41: Facebook | M41: Google | N41: Outros | O41: Total
B42: Investimento Diário | C42: =C27/30 -> 0 | E42: Investimento Diário | F42: =F27/30 -> 0 | H42: Investimento Diário | I42: =I27/'Acompanhamento Geral'!B34 -> 0 | K42: % | L42: 0.7 | M42: 0.3 | N42: 0 | O42: =sum(L42:N42) -> 1
B43: Sessões Diárias | C43: =C33/30 -> #DIV/0! | E43: Sessões Diárias | F43: =F33/30 -> #DIV/0! | H43: Sessões Diárias | I43: =I33/'Acompanhamento Geral'!B34 -> #DIV/0! | K43: Verba Mês | L43: =I27*L42 -> 0 | M43: =I27*M42 -> 0 | N43: =I27*N42 -> 0 | O43: =sum(L43:N43) -> 0
B44: Pedidos Diários | C44: =C35/30 -> #DIV/0! | E44: Pedidos Diários | F44: =F35/30 -> #DIV/0! | H44: Pedidos Diários | I44: =I35/'Acompanhamento Geral'!B34 -> #DIV/0! | K44: Verba Dia | L44: =L43/'Acompanhamento Geral'!B34 -> 0 | M44: =M43/'Acompanhamento Geral'!B34 -> 0 | N44: =iferror(N43/'Acompanhamento Geral'!B34,"") -> 0 | O44: =SUM(L44:N44) -> 0
B45: Faturamento Diário | C45: =C36/30 -> #DIV/0! | E45: Faturamento Diário | F45: =F36/30 -> #DIV/0! | H45: Faturamento Diário | I45: =I36/'Acompanhamento Geral'!B34 -> #DIV/0!
B47: MARÇO
B49: CENÁRIO ATUAL (ÚLTIMO MÊS) | E49: CENÁRIO DESEJADO | H49: CENÁRIO IDEAL | J49: MÉDIA / ANUAL | K49: % ATUAL | L49: % MÁX
B50: Valor Investimento | E50: Faturamento Desejado | H50: Verba Mensal | K50: =(I50-J50)/J50*1 -> #DIV/0! | L50: 0.4
B51: CPS Geral | E51: CPS Atual | F51: =C51 | H51: CPS Ideal | K51: =(I51-J51)/J51*1 -> #DIV/0! | L51: -0.1
B52: Ticket Médio | E52: Ticket Médio | F52: =C52 | H52: Ticket Médio Ideal | K52: =(I52-J52)/J52*1 -> #DIV/0! | L52: 0.1
B53: TX Conversão | E53: Taxa de Conversão Atual | F53: =C53 | H53: Taxa Conversão Ideal | K53: =(I53-J53)/J53*1 -> #DIV/0! | L53: 0.1
B54: % De Aprovação | E54: % De Pagamento Atual | F54: =C54 | H54: Aprovação Pagamento | K54: =(I54-J54)/J54*1 -> #DIV/0! | L54: 0.03
B56: Sessões | C56: =C50/C51 -> #DIV/0! | E56: Visitas Ideais | F56: =F58/F53 -> #DIV/0! | H56: Visitas Ideais | I56: =I50/I51 -> #DIV/0! | K56: CANAL DE VENDA | L56: % | M56: FATURAMENTO | N56: PEDIDOS POR CANAL
B57: CPA | C57: =C50/C58 -> #DIV/0! | E57: CPA Ideal | F57: =F61/F58 -> #DIV/0! | H57: CPA Ideal | I57: =I50/I58 -> #DIV/0! | K57: Meta Ads | L57: 0.2 | M57: =I61/100*L57*100 -> #DIV/0! | N57: =M57/I52 -> #DIV/0!
B58: Pedidos | C58: =C56*C53 -> #DIV/0! | E58: Pedidos Mês Ideal | F58: =F59/F52 -> #DIV/0! | H58: Pedidos Mês Ideal | I58: =I56*I53 -> #DIV/0! | K58: Google Ads | L58: 0.2 | M58: =I61/100*L58*100 -> #DIV/0! | N58: =M58/I52 -> #DIV/0!
B59: Faturamento Captado | C59: =(C56*C53)*C52 -> #DIV/0! | E59: Faturamento Captado | F59: =F50/F54 -> #DIV/0! | H59: Faturamento Bruto | I59: =I56*I53*I52 -> #DIV/0! | K59: Social | L59: 0.3 | M59: =I61/100*L59*100 -> #DIV/0! | N59: =M59/I52 -> #DIV/0!
B60: ROAS Bruto | C60: =C59/C50 -> #DIV/0! | E60: ROAS Bruto | F60: =F59/F61 -> #DIV/0! | H60: ROAS Bruto | I60: =I59/I50 -> #DIV/0! | K60: Organico | L60: 0.15 | M60: =I61/100*L60*100 -> #DIV/0! | N60: =M60/I52 -> #DIV/0!
B61: Faturamento Real | C61: =C59*C54 -> #DIV/0! | E61: Investimento Necessário | F61: =F56*F51 -> #DIV/0! | H61: Faturamento Desejado | I61: =I59*I54 -> #DIV/0! | K61: E-mail | L61: 0.15 | M61: =I61/100*L61*100 -> #DIV/0! | N61: =M61/I52 -> #DIV/0!
B62: ROAS Real | C62: =C61/C50 -> #DIV/0! | E62: ROAS Desejado | F62: =F50/F61 -> #DIV/0! | H62: ROAS Real | I62: =I61/I50 -> #DIV/0! | L62: =SUM(L57:L61) -> 1 | N62: =SUM(N57:N61) -> #DIV/0!
B64: CENÁRIO DIÁRIO ATUAL | E64: CENÁRIO DIÁRIO DESEJADO | H64: CENÁRIO DIÁRIO IDEAL | K64: Canal | L64: Facebook | M64: Google | N64: Outros | O64: Total
B65: Investimento Diário | C65: =C50/30 -> 0 | E65: Investimento Diário | F65: =F50/30 -> 0 | H65: Investimento Diário | I65: =I50/'Acompanhamento Geral'!B64 -> 0 | K65: % | L65: 0.7 | M65: 0.3 | N65: 0 | O65: =sum(L65:N65) -> 1
B66: Sessões Diárias | C66: =C56/30 -> #DIV/0! | E66: Sessões Diárias | F66: =F56/30 -> #DIV/0! | H66: Sessões Diárias | I66: =I56/'Acompanhamento Geral'!B64 -> #DIV/0! | K66: Verba Mês | L66: =I50*L65 -> 0 | M66: =I50*M65 -> 0 | N66: =I50*N65 -> 0 | O66: =sum(L66:N66) -> 0
B67: Pedidos Diários | C67: =C58/30 -> #DIV/0! | E67: Pedidos Diários | F67: =F58/30 -> #DIV/0! | H67: Pedidos Diários | I67: =I58/'Acompanhamento Geral'!B64 -> #DIV/0! | K67: Verba Dia | L67: =L66/'Acompanhamento Geral'!B64 -> 0 | M67: =M66/'Acompanhamento Geral'!B64 -> 0 | N67: =iferror(N66/'Acompanhamento Geral'!B64,"") -> 0 | O67: =SUM(L67:N67) -> 0
B68: Faturamento Diário | C68: =C59/30 -> #DIV/0! | E68: Faturamento Diário | F68: =F59/30 -> #DIV/0! | H68: Faturamento Diário | I68: =I59/'Acompanhamento Geral'!B64 -> #DIV/0!
B70: ABRIL
B72: CENÁRIO ATUAL (ÚLTIMO MÊS) | E72: CENÁRIO DESEJADO | H72: CENÁRIO IDEAL | J72: MÉDIA / ANUAL | K72: % ATUAL | L72: % MÁX
B73: Valor Investimento | E73: Faturamento Desejado | H73: Verba Mensal | K73: =(I73-J73)/J73*1 -> #DIV/0! | L73: 0.4
B74: CPS Geral | E74: CPS Atual | F74: =C74 | H74: CPS Ideal | K74: =(I74-J74)/J74*1 -> #DIV/0! | L74: -0.1
B75: Ticket Médio | E75: Ticket Médio | F75: =C75 | H75: Ticket Médio Ideal | K75: =(I75-J75)/J75*1 -> #DIV/0! | L75: 0.1
B76: TX Conversão | E76: Taxa de Conversão Atual | F76: =C76 | H76: Taxa Conversão Ideal | K76: =(I76-J76)/J76*1 -> #DIV/0! | L76: 0.1
B77: % De Aprovação | E77: % De Pagamento Atual | F77: =C77 | H77: Aprovação Pagamento | K77: =(I77-J77)/J77*1 -> #DIV/0! | L77: 0.03
B79: Sessões | C79: =C73/C74 -> #DIV/0! | E79: Visitas Ideais | F79: =F81/F76 -> #DIV/0! | H79: Visitas Ideais | I79: =I73/I74 -> #DIV/0! | K79: CANAL DE VENDA | L79: % | M79: FATURAMENTO | N79: PEDIDOS POR CANAL
B80: CPA | C80: =C73/C81 -> #DIV/0! | E80: CPA Ideal | F80: =F84/F81 -> #DIV/0! | H80: CPA Ideal | I80: =I73/I81 -> #DIV/0! | K80: Meta Ads | L80: 0.2 | M80: =I84/100*L80*100 -> #DIV/0! | N80: =M80/I75 -> #DIV/0!
B81: Pedidos | C81: =C79*C76 -> #DIV/0! | E81: Pedidos Mês Ideal | F81: =F82/F75 -> #DIV/0! | H81: Pedidos Mês Ideal | I81: =I79*I76 -> #DIV/0! | K81: Google Ads | L81: 0.2 | M81: =I84/100*L81*100 -> #DIV/0! | N81: =M81/I75 -> #DIV/0!
B82: Faturamento Captado | C82: =(C79*C76)*C75 -> #DIV/0! | E82: Faturamento Captado | F82: =F73/F77 -> #DIV/0! | H82: Faturamento Bruto | I82: =I79*I76*I75 -> #DIV/0! | K82: Social | L82: 0.3 | M82: =I84/100*L82*100 -> #DIV/0! | N82: =M82/I75 -> #DIV/0!
B83: ROAS Bruto | C83: =C82/C73 -> #DIV/0! | E83: ROAS Bruto | F83: =F82/F84 -> #DIV/0! | H83: ROAS Bruto | I83: =I82/I73 -> #DIV/0! | K83: Organico | L83: 0.15 | M83: =I84/100*L83*100 -> #DIV/0! | N83: =M83/I75 -> #DIV/0!
B84: Faturamento Real | C84: =C82*C77 -> #DIV/0! | E84: Investimento Necessário | F84: =F79*F74 -> #DIV/0! | H84: Faturamento Desejado | I84: =I82*I77 -> #DIV/0! | K84: E-mail | L84: 0.15 | M84: =I84/100*L84*100 -> #DIV/0! | N84: =M84/I75 -> #DIV/0!
B85: ROAS Real | C85: =C84/C73 -> #DIV/0! | E85: ROAS Desejado | F85: =F73/F84 -> #DIV/0! | H85: ROAS Real | I85: =I84/I73 -> #DIV/0! | L85: =SUM(L80:L84) -> 1 | N85: =SUM(N80:N84) -> #DIV/0!
B87: CENÁRIO DIÁRIO ATUAL | E87: CENÁRIO DIÁRIO DESEJADO | H87: CENÁRIO DIÁRIO IDEAL | K87: Canal | L87: Facebook | M87: Google | N87: Outros | O87: Total
B88: Investimento Diário | C88: =C73/30 -> 0 | E88: Investimento Diário | F88: =F73/30 -> 0 | H88: Investimento Diário | I88: =I73/'Acompanhamento Geral'!B96 -> 0 | K88: % | L88: 0.7 | M88: 0.3 | N88: 0 | O88: =sum(L88:N88) -> 1
B89: Sessões Diárias | C89: =C79/30 -> #DIV/0! | E89: Sessões Diárias | F89: =F79/30 -> #DIV/0! | H89: Sessões Diárias | I89: =I79/'Acompanhamento Geral'!B96 -> #DIV/0! | K89: Verba Mês | L89: =I73*L88 -> 0 | M89: =I73*M88 -> 0 | N89: =I73*N88 -> 0 | O89: =sum(L89:N89) -> 0
B90: Pedidos Diários | C90: =C81/30 -> #DIV/0! | E90: Pedidos Diários | F90: =F81/30 -> #DIV/0! | H90: Pedidos Diários | I90: =I81/'Acompanhamento Geral'!B96 -> #DIV/0! | K90: Verba Dia | L90: =L89/'Acompanhamento Geral'!B96 -> 0 | M90: =M89/'Acompanhamento Geral'!B96 -> 0 | N90: =iferror(N89/'Acompanhamento Geral'!B96,"") -> 0 | O90: =SUM(L90:N90) -> 0
B91: Faturamento Diário | C91: =C82/30 -> #DIV/0! | E91: Faturamento Diário | F91: =F82/30 -> #DIV/0! | H91: Faturamento Diário | I91: =I82/'Acompanhamento Geral'!B96 -> #DIV/0!
B93: MAIO
B95: CENÁRIO ATUAL (ÚLTIMO MÊS) | E95: CENÁRIO DESEJADO | H95: CENÁRIO IDEAL | J95: MÉDIA / ANUAL | K95: % ATUAL | L95: % MÁX
B96: Valor Investimento | E96: Faturamento Desejado | H96: Verba Mensal | K96: =(I96-J96)/J96*1 -> #DIV/0! | L96: 0.4
B97: CPS Geral | E97: CPS Atual | F97: =C97 | H97: CPS Ideal | K97: =(I97-J97)/J97*1 -> #DIV/0! | L97: -0.1
B98: Ticket Médio | E98: Ticket Médio | F98: =C98 | H98: Ticket Médio Ideal | K98: =(I98-J98)/J98*1 -> #DIV/0! | L98: 0.1
B99: TX Conversão | E99: Taxa de Conversão Atual | F99: =C99 | H99: Taxa Conversão Ideal | K99: =(I99-J99)/J99*1 -> #DIV/0! | L99: 0.1
B100: % De Aprovação | E100: % De Pagamento Atual | F100: =C100 | H100: Aprovação Pagamento | K100: =(I100-J100)/J100*1 -> #DIV/0! | L100: 0.03
B102: Sessões | C102: =C96/C97 -> #DIV/0! | E102: Visitas Ideais | F102: =F104/F99 -> #DIV/0! | H102: Visitas Ideais | I102: =I96/I97 -> #DIV/0! | K102: CANAL DE VENDA | L102: % | M102: FATURAMENTO | N102: PEDIDOS POR CANAL
B103: CPA | C103: =C96/C104 -> #DIV/0! | E103: CPA Ideal | F103: =F107/F104 -> #DIV/0! | H103: CPA Ideal | I103: =I96/I104 -> #DIV/0! | K103: Meta Ads | L103: 0.2 | M103: =I107/100*L103*100 -> #DIV/0! | N103: =M103/I98 -> #DIV/0!
B104: Pedidos | C104: =C102*C99 -> #DIV/0! | E104: Pedidos Mês Ideal | F104: =F105/F98 -> #DIV/0! | H104: Pedidos Mês Ideal | I104: =I102*I99 -> #DIV/0! | K104: Google Ads | L104: 0.2 | M104: =I107/100*L104*100 -> #DIV/0! | N104: =M104/I98 -> #DIV/0!
B105: Faturamento Captado | C105: =(C102*C99)*C98 -> #DIV/0! | E105: Faturamento Captado | F105: =F96/F100 -> #DIV/0! | H105: Faturamento Bruto | I105: =I102*I99*I98 -> #DIV/0! | K105: Social | L105: 0.3 | M105: =I107/100*L105*100 -> #DIV/0! | N105: =M105/I98 -> #DIV/0!
B106: ROAS Bruto | C106: =C105/C96 -> #DIV/0! | E106: ROAS Bruto | F106: =F105/F107 -> #DIV/0! | H106: ROAS Bruto | I106: =I105/I96 -> #DIV/0! | K106: Organico | L106: 0.15 | M106: =I107/100*L106*100 -> #DIV/0! | N106: =M106/I98 -> #DIV/0!
B107: Faturamento Real | C107: =C105*C100 -> #DIV/0! | E107: Investimento Necessário | F107: =F102*F97 -> #DIV/0! | H107: Faturamento Desejado | I107: =I105*I100 -> #DIV/0! | K107: E-mail | L107: 0.15 | M107: =I107/100*L107*100 -> #DIV/0! | N107: =M107/I98 -> #DIV/0!
B108: ROAS Real | C108: =C107/C96 -> #DIV/0! | E108: ROAS Desejado | F108: =F96/F107 -> #DIV/0! | H108: ROAS Real | I108: =I107/I96 -> #DIV/0! | L108: =SUM(L103:L107) -> 1 | N108: =SUM(N103:N107) -> #DIV/0!
B110: CENÁRIO DIÁRIO ATUAL | E110: CENÁRIO DIÁRIO DESEJADO | H110: CENÁRIO DIÁRIO IDEAL | K110: Canal | L110: Facebook | M110: Google | N110: Outros | O110: Total
B111: Investimento Diário | C111: =C96/30 -> 0 | E111: Investimento Diário | F111: =F96/30 -> 0 | H111: Investimento Diário | I111: =I96/'Acompanhamento Geral'!B127 -> 0 | K111: % | L111: 0.7 | M111: 0.3 | N111: 0 | O111: =sum(L111:N111) -> 1
B112: Sessões Diárias | C112: =C102/30 -> #DIV/0! | E112: Sessões Diárias | F112: =F102/30 -> #DIV/0! | H112: Sessões Diárias | I112: =I102/'Acompanhamento Geral'!B127 -> #DIV/0! | K112: Verba Mês | L112: =I96*L111 -> 0 | M112: =I96*M111 -> 0 | N112: =I96*N111 -> 0 | O112: =sum(L112:N112) -> 0
B113: Pedidos Diários | C113: =C104/30 -> #DIV/0! | E113: Pedidos Diários | F113: =F104/30 -> #DIV/0! | H113: Pedidos Diários | I113: =I104/'Acompanhamento Geral'!B127 -> #DIV/0! | K113: Verba Dia | L113: =L112/'Acompanhamento Geral'!B127 -> 0 | M113: =M112/'Acompanhamento Geral'!B127 -> 0 | N113: =iferror(N112/'Acompanhamento Geral'!B127,"") -> 0 | O113: =SUM(L113:N113) -> 0
B114: Faturamento Diário | C114: =C105/30 -> #DIV/0! | E114: Faturamento Diário | F114: =F105/30 -> #DIV/0! | H114: Faturamento Diário | I114: =I105/'Acompanhamento Geral'!B127 -> #DIV/0!
B116: JUNHO
B118: CENÁRIO ATUAL (ÚLTIMO MÊS) | E118: CENÁRIO DESEJADO | H118: CENÁRIO IDEAL | J118: MÉDIA / ANUAL | K118: % ATUAL | L118: % MÁX
B119: Valor Investimento | E119: Faturamento Desejado | H119: Verba Mensal | K119: =(I119-J119)/J119*1 -> #DIV/0! | L119: 0.4
B120: CPS Geral | E120: CPS Atual | F120: =C120 | H120: CPS Ideal | K120: =(I120-J120)/J120*1 -> #DIV/0! | L120: -0.1
...

Sheet Projeção Rápida
D1: PROJEÇÃO RÁPIDA
B3: Investimento | D3: CPS | F3: Canal | G3: Facebook | H3: Google | I3: Outros
B4: 10000 | D4: 0.3 | F4: % | G4: 0.7 | H4: 0.4 | I4: 0
F5: Verba Mês | G5: =G4*$B$4 -> 7000 | H5: =H4*$B$4 -> 4000 | I5: =I4*$B$4 -> 0
B6: Ticket Médio | D6: Taxa de Conversão | F6: Verba Dia | G6: =ROUNDUP((B4*G4)/30,0) -> 234 | H6: =ROUNDUP((B4*H4)/30,0) -> 134 | I6: =ROUNDUP((B4*I4)/30,0) -> 0 | J6: =SUM(G6:I6) -> 368
B7: 150 | D7: 0.015
B9: MER | D9: VISITAS
B10: =B16/B4 -> 7.5 | D10: =B4/D4 -> 33333.333
B12: CPA | D12: N. PEDIDOS / MÊS
B13: =B4/D13 -> 20 | D13: =D10*D7 -> 500
B15: FATURAMENTO
B16: =D13*B7 -> 75000
B18: ANTES DE ENTRAR NO SITE | D18: DEPOIS DE ENTRAR NO SITE
B19: MELHORIAS PARA CPC | D19: MELHORIAS PARA TX
B20: CRIATIVO | D20: NAVEGABILIDADE
B21: COPY | D21: CONTEÚDO
B22: PÚBLICO | D22: OFERTA
B23: OFERTA | D23: FRETE
B24: CAMPANHAS DE CPC BAIXO | D24: CHECKOUT
B25: PRODUTO | D25: CREDIBILIDADE E PROVA SOCIAL
B26: QUALIDADE DA PÁGINA
B28: BENCHMARK MERCADO | D28: BENCHMARK MERCADO
B29: CPS | D29: TAXA DE CONVERSÃO
B30: 0.35 | D30: 0.005
B31: 0.6 | D31: 0.01
B32: 0.9 | D32: 0.015

Sheet DRE Performance
B3: Preencer dados (Atual) | E3: Não Preencer dados | I3: Não Preencer dados
B4: Preencher | E4: DRE | H4: 0.25 | I4: ROAS/Budget | J4: =C12 -> 5000 | K4: =J4*(1+$H$4) -> 6250 | L4: =K4*(1+$H$4) -> 7812.5 | M4: =L4*(1+$H$4) -> 9765.625 | N4: =M4*(1+$H$4) -> 12207.031 | O4: =N4*(1+$H$4) -> 15258.789 | P4: =O4*(1+$H$4) -> 19073.486 | Q4: =P4*(1+$H$4) -> 23841.858 | R4: =Q4*(1+$H$4) -> 29802.322 | S4: =R4*(1+$H$4) -> 37252.903
B5: Receita Mensal (R$) | C5: 10000 | E5: Ticket Médio | F5: =C5/C6 -> 100 | I5: 1 | J5: =($J$4*I5)-(($J$4*I5)*(SUM($G$6:$G$10)))-$J$4 -> -3500 | K5: =($K$4*I5)-(($K$4*I5)*(SUM($G$6:$G$10)))-$K$4 -> -4375 | L5: =($L$4*I5)-(($L$4*I5)*(SUM($G$6:$G$10)))-$L$4 -> -5468.75 | M5: =($M$4*I5)-(($M$4*I5)*(SUM($G$6:$G$10)))-$M$4 -> -6835.9375 | N5: =($N$4*I5)-(($N$4*I5)*(SUM($G$6:$G$10)))-$N$4 -> -8544.9219 | O5: =($O$4*I5)-(($O$4*I5)*(SUM($G$6:$G$10)))-$O$4 -> -10681.152 | P5: =($P$4*I5)-(($P$4*I5)*(SUM($G$6:$G$10)))-$P$4 -> -13351.44 | Q5: =($Q$4*I5)-(($Q$4*I5)*(SUM($G$6:$G$10)))-$Q$4 -> -16689.301 | R5: =($R$4*I5)-(($R$4*I5)*(SUM($G$6:$G$10)))-$R$4 -> -20861.626 | S5: =($S$4*I5)-(($S$4*I5)*(SUM($G$6:$G$10)))-$S$4 -> -26077.032
B6: Número de pedidos | C6: 100 | E6: (-) Gateway de pagamento | F6: =C8*F5 -> 7 | G6: =F6/$F$5 -> 0.07 | I6: 1.5 | J6: =($J$4*I6)-(($J$4*I6)*(SUM($G$6:$G$10)))-$J$4 -> -2750 | K6: =($K$4*I6)-(($K$4*I6)*(SUM($G$6:$G$10)))-$K$4 -> -3437.5 | L6: =($L$4*I6)-(($L$4*I6)*(SUM($G$6:$G$10)))-$L$4 -> -4296.875 | M6: =($M$4*I6)-(($M$4*I6)*(SUM($G$6:$G$10)))-$M$4 -> -5371.0938 | N6: =($N$4*I6)-(($N$4*I6)*(SUM($G$6:$G$10)))-$N$4 -> -6713.8672 | O6: =($O$4*I6)-(($O$4*I6)*(SUM($G$6:$G$10)))-$O$4 -> -8392.334 | P6: =($P$4*I6)-(($P$4*I6)*(SUM($G$6:$G$10)))-$P$4 -> -10490.417 | Q6: =($Q$4*I6)-(($Q$4*I6)*(SUM($G$6:$G$10)))-$Q$4 -> -13113.022 | R6: =($R$4*I6)-(($R$4*I6)*(SUM($G$6:$G$10)))-$R$4 -> -16391.277 | S6: =($S$4*I6)-(($S$4*I6)*(SUM($G$6:$G$10)))-$S$4 -> -20489.097
B7: Número de devoluções | C7: 0 | E7: (-) Devoluções | F7: =(C7/C6)*F5 -> 0 | G7: =F7/$F$5 -> 0 | I7: 2 | J7: =($J$4*I7)-(($J$4*I7)*(SUM($G$6:$G$10)))-$J$4 -> -2000 | K7: =($K$4*I7)-(($K$4*I7)*(SUM($G$6:$G$10)))-$K$4 -> -2500 | L7: =($L$4*I7)-(($L$4*I7)*(SUM($G$6:$G$10)))-$L$4 -> -3125 | M7: =($M$4*I7)-(($M$4*I7)*(SUM($G$6:$G$10)))-$M$4 -> -3906.25 | N7: =($N$4*I7)-(($N$4*I7)*(SUM($G$6:$G$10)))-$N$4 -> -4882.8125 | O7: =($O$4*I7)-(($O$4*I7)*(SUM($G$6:$G$10)))-$O$4 -> -6103.5156 | P7: =($P$4*I7)-(($P$4*I7)*(SUM($G$6:$G$10)))-$P$4 -> -7629.3945 | Q7: =($Q$4*I7)-(($Q$4*I7)*(SUM($G$6:$G$10)))-$Q$4 -> -9536.7432 | R7: =($R$4*I7)-(($R$4*I7)*(SUM($G$6:$G$10)))-$R$4 -> -11920.929 | S7: =($S$4*I7)-(($S$4*I7)*(SUM($G$6:$G$10)))-$S$4 -> -14901.161
B8: Taxa Gateway & Checkout (%) | C8: 0.07 | E8: (-) Impostos sob receita | F8: =F5*C9 -> 8 | G8: =F8/$F$5 -> 0.08 | I8: 2.5 | J8: =($J$4*I8)-(($J$4*I8)*(SUM($G$6:$G$10)))-$J$4 -> -1250 | K8: =($K$4*I8)-(($K$4*I8)*(SUM($G$6:$G$10)))-$K$4 -> -1562.5 | L8: =($L$4*I8)-(($L$4*I8)*(SUM($G$6:$G$10)))-$L$4 -> -1953.125 | M8: =($M$4*I8)-(($M$4*I8)*(SUM($G$6:$G$10)))-$M$4 -> -2441.4062 | N8: =($N$4*I8)-(($N$4*I8)*(SUM($G$6:$G$10)))-$N$4 -> -3051.7578 | O8: =($O$4*I8)-(($O$4*I8)*(SUM($G$6:$G$10)))-$O$4 -> -3814.6973 | P8: =($P$4*I8)-(($P$4*I8)*(SUM($G$6:$G$10)))-$P$4 -> -4768.3716 | Q8: =($Q$4*I8)-(($Q$4*I8)*(SUM($G$6:$G$10)))-$Q$4 -> -5960.4645 | R8: =($R$4*I8)-(($R$4*I8)*(SUM($G$6:$G$10)))-$R$4 -> -7450.5806 | S8: =($S$4*I8)-(($S$4*I8)*(SUM($G$6:$G$10)))-$S$4 -> -9313.2257
B9: Impostos sob receita (%) | C9: 0.08 | E9: (-) CMV | F9: =(1/C11)*F5 -> 40 | G9: =F9/$F$5 -> 0.4 | I9: 3 | J9: =($J$4*I9)-(($J$4*I9)*(SUM($G$6:$G$10)))-$J$4 -> -500 | K9: =($K$4*I9)-(($K$4*I9)*(SUM($G$6:$G$10)))-$K$4 -> -625 | L9: =($L$4*I9)-(($L$4*I9)*(SUM($G$6:$G$10)))-$L$4 -> -781.25 | M9: =($M$4*I9)-(($M$4*I9)*(SUM($G$6:$G$10)))-$M$4 -> -976.5625 | N9: =($N$4*I9)-(($N$4*I9)*(SUM($G$6:$G$10)))-$N$4 -> -1220.7031 | O9: =($O$4*I9)-(($O$4*I9)*(SUM($G$6:$G$10)))-$O$4 -> -1525.8789 | P9: =($P$4*I9)-(($P$4*I9)*(SUM($G$6:$G$10)))-$P$4 -> -1907.3486 | Q9: =($Q$4*I9)-(($Q$4*I9)*(SUM($G$6:$G$10)))-$Q$4 -> -2384.1858 | R9: =($R$4*I9)-(($R$4*I9)*(SUM($G$6:$G$10)))-$R$4 -> -2980.2322 | S9: =($S$4*I9)-(($S$4*I9)*(SUM($G$6:$G$10)))-$S$4 -> -3725.2903
B10: Valor gasto Frete mensal (R$) | C10: 1500 | E10: (-) Frete | F10: =C10/C6 -> 15 | G10: =F10/$F$5 -> 0.15 | I10: 3.5 | J10: =($J$4*I10)-(($J$4*I10)*(SUM($G$6:$G$10)))-$J$4 -> 250 | K10: =($K$4*I10)-(($K$4*I10)*(SUM($G$6:$G$10)))-$K$4 -> 312.5 | L10: =($L$4*I10)-(($L$4*I10)*(SUM($G$6:$G$10)))-$L$4 -> 390.625 | M10: =($M$4*I10)-(($M$4*I10)*(SUM($G$6:$G$10)))-$M$4 -> 488.28125 | N10: =($N$4*I10)-(($N$4*I10)*(SUM($G$6:$G$10)))-$N$4 -> 610.35156 | O10: =($O$4*I10)-(($O$4*I10)*(SUM($G$6:$G$10)))-$O$4 -> 762.93945 | P10: =($P$4*I10)-(($P$4*I10)*(SUM($G$6:$G$10)))-$P$4 -> 953.67432 | Q10: =($Q$4*I10)-(($Q$4*I10)*(SUM($G$6:$G$10)))-$Q$4 -> 1192.0929 | R10: =($R$4*I10)-(($R$4*I10)*(SUM($G$6:$G$10)))-$R$4 -> 1490.1161 | S10: =($S$4*I10)-(($S$4*I10)*(SUM($G$6:$G$10)))-$S$4 -> 1862.6451
B11: Markup | C11: 2.5 | E11: (=) Margem bruta | F11: =F5-F6-F7-F8-F9-F10 -> 30 | G11: =F11/$F$5 -> 0.3 | I11: 4 | J11: =($J$4*I11)-(($J$4*I11)*(SUM($G$6:$G$10)))-$J$4 -> 1000 | K11: =($K$4*I11)-(($K$4*I11)*(SUM($G$6:$G$10)))-$K$4 -> 1250 | L11: =($L$4*I11)-(($L$4*I11)*(SUM($G$6:$G$10)))-$L$4 -> 1562.5 | M11: =($M$4*I11)-(($M$4*I11)*(SUM($G$6:$G$10)))-$M$4 -> 1953.125 | N11: =($N$4*I11)-(($N$4*I11)*(SUM($G$6:$G$10)))-$N$4 -> 2441.4062 | O11: =($O$4*I11)-(($O$4*I11)*(SUM($G$6:$G$10)))-$O$4 -> 3051.7578 | P11: =($P$4*I11)-(($P$4*I11)*(SUM($G$6:$G$10)))-$P$4 -> 3814.6973 | Q11: =($Q$4*I11)-(($Q$4*I11)*(SUM($G$6:$G$10)))-$Q$4 -> 4768.3716 | R11: =($R$4*I11)-(($R$4*I11)*(SUM($G$6:$G$10)))-$R$4 -> 5960.4645 | S11: =($S$4*I11)-(($S$4*I11)*(SUM($G$6:$G$10)))-$S$4 -> 7450.5806
B12: Budget Anúncios (R$) | C12: 5000 | E12: (-) CPA | F12: =(C12/C6) -> 50 | G12: =F12/F5 -> 0.5 | I12: 4.5 | J12: =($J$4*I12)-(($J$4*I12)*(SUM($G$6:$G$10)))-$J$4 -> 1750 | K12: =($K$4*I12)-(($K$4*I12)*(SUM($G$6:$G$10)))-$K$4 -> 2187.5 | L12: =($L$4*I12)-(($L$4*I12)*(SUM($G$6:$G$10)))-$L$4 -> 2734.375 | M12: =($M$4*I12)-(($M$4*I12)*(SUM($G$6:$G$10)))-$M$4 -> 3417.9688 | N12: =($N$4*I12)-(($N$4*I12)*(SUM($G$6:$G$10)))-$N$4 -> 4272.4609 | O12: =($O$4*I12)-(($O$4*I12)*(SUM($G$6:$G$10)))-$O$4 -> 5340.5762 | P12: =($P$4*I12)-(($P$4*I12)*(SUM($G$6:$G$10)))-$P$4 -> 6675.7202 | Q12: =($Q$4*I12)-(($Q$4*I12)*(SUM($G$6:$G$10)))-$Q$4 -> 8344.6503 | R12: =($R$4*I12)-(($R$4*I12)*(SUM($G$6:$G$10)))-$R$4 -> 10430.813 | S12: =($S$4*I12)-(($S$4*I12)*(SUM($G$6:$G$10)))-$S$4 -> 13038.516
E13: (=) Margem de Contribuição | F13: =F11-F12 -> -20 | G13: =F13/F5 -> -0.2 | I13: 5 | J13: =($J$4*I13)-(($J$4*I13)*(SUM($G$6:$G$10)))-$J$4 -> 2500 | K13: =($K$4*I13)-(($K$4*I13)*(SUM($G$6:$G$10)))-$K$4 -> 3125 | L13: =($L$4*I13)-(($L$4*I13)*(SUM($G$6:$G$10)))-$L$4 -> 3906.25 | M13: =($M$4*I13)-(($M$4*I13)*(SUM($G$6:$G$10)))-$M$4 -> 4882.8125 | N13: =($N$4*I13)-(($N$4*I13)*(SUM($G$6:$G$10)))-$N$4 -> 6103.5156 | O13: =($O$4*I13)-(($O$4*I13)*(SUM($G$6:$G$10)))-$O$4 -> 7629.3945 | P13: =($P$4*I13)-(($P$4*I13)*(SUM($G$6:$G$10)))-$P$4 -> 9536.7432 | Q13: =($Q$4*I13)-(($Q$4*I13)*(SUM($G$6:$G$10)))-$Q$4 -> 11920.929 | R13: =($R$4*I13)-(($R$4*I13)*(SUM($G$6:$G$10)))-$R$4 -> 14901.161 | S13: =($S$4*I13)-(($S$4*I13)*(SUM($G$6:$G$10)))-$S$4 -> 18626.451
I14: 5.5 | J14: =($J$4*I14)-(($J$4*I14)*(SUM($G$6:$G$10)))-$J$4 -> 3250 | K14: =($K$4*I14)-(($K$4*I14)*(SUM($G$6:$G$10)))-$K$4 -> 4062.5 | L14: =($L$4*I14)-(($L$4*I14)*(SUM($G$6:$G$10)))-$L$4 -> 5078.125 | M14: =($M$4*I14)-(($M$4*I14)*(SUM($G$6:$G$10)))-$M$4 -> 6347.6562 | N14: =($N$4*I14)-(($N$4*I14)*(SUM($G$6:$G$10)))-$N$4 -> 7934.5703 | O14: =($O$4*I14)-(($O$4*I14)*(SUM($G$6:$G$10)))-$O$4 -> 9918.2129 | P14: =($P$4*I14)-(($P$4*I14)*(SUM($G$6:$G$10)))-$P$4 -> 12397.766 | Q14: =($Q$4*I14)-(($Q$4*I14)*(SUM($G$6:$G$10)))-$Q$4 -> 15497.208 | R14: =($R$4*I14)-(($R$4*I14)*(SUM($G$6:$G$10)))-$R$4 -> 19371.51 | S14: =($S$4*I14)-(($S$4*I14)*(SUM($G$6:$G$10)))-$S$4 -> 24214.387
B15: Preencer dados (Planejamento) | E15: (=) Margem Contribuição | F15: =F13/F5 -> -0.2 | I15: 6 | J15: =($J$4*I15)-(($J$4*I15)*(SUM($G$6:$G$10)))-$J$4 -> 4000 | K15: =($K$4*I15)-(($K$4*I15)*(SUM($G$6:$G$10)))-$K$4 -> 5000 | L15: =($L$4*I15)-(($L$4*I15)*(SUM($G$6:$G$10)))-$L$4 -> 6250 | M15: =($M$4*I15)-(($M$4*I15)*(SUM($G$6:$G$10)))-$M$4 -> 7812.5 | N15: =($N$4*I15)-(($N$4*I15)*(SUM($G$6:$G$10)))-$N$4 -> 9765.625 | O15: =($O$4*I15)-(($O$4*I15)*(SUM($G$6:$G$10)))-$O$4 -> 12207.031 | P15: =($P$4*I15)-(($P$4*I15)*(SUM($G$6:$G$10)))-$P$4 -> 15258.789 | Q15: =($Q$4*I15)-(($Q$4*I15)*(SUM($G$6:$G$10)))-$Q$4 -> 19073.486 | R15: =($R$4*I15)-(($R$4*I15)*(SUM($G$6:$G$10)))-$R$4 -> 23841.858 | S15: =($S$4*I15)-(($S$4*I15)*(SUM($G$6:$G$10)))-$S$4 -> 29802.322
B16: Preencher | E16: (=) ROAs Realizado | F16: =C5/C12 -> 2 | I16: 6.5 | J16: =($J$4*I16)-(($J$4*I16)*(SUM($G$6:$G$10)))-$J$4 -> 4750 | K16: =($K$4*I16)-(($K$4*I16)*(SUM($G$6:$G$10)))-$K$4 -> 5937.5 | L16: =($L$4*I16)-(($L$4*I16)*(SUM($G$6:$G$10)))-$L$4 -> 7421.875 | M16: =($M$4*I16)-(($M$4*I16)*(SUM($G$6:$G$10)))-$M$4 -> 9277.3438 | N16: =($N$4*I16)-(($N$4*I16)*(SUM($G$6:$G$10)))-$N$4 -> 11596.68 | O16: =($O$4*I16)-(($O$4*I16)*(SUM($G$6:$G$10)))-$O$4 -> 14495.85 | P16: =($P$4*I16)-(($P$4*I16)*(SUM($G$6:$G$10)))-$P$4 -> 18119.812 | Q16: =($Q$4*I16)-(($Q$4*I16)*(SUM($G$6:$G$10)))-$Q$4 -> 22649.765 | R16: =($R$4*I16)-(($R$4*I16)*(SUM($G$6:$G$10)))-$R$4 -> 28312.206 | S16: =($S$4*I16)-(($S$4*I16)*(SUM($G$6:$G$10)))-$S$4 -> 35390.258
B17: Receita Mensal (R$) | E17: (=) Lucro Bruto | F17: =C5*F15 -> -2000 | I17: 7 | J17: =($J$4*I17)-(($J$4*I17)*(SUM($G$6:$G$10)))-$J$4 -> 5500 | K17: =($K$4*I17)-(($K$4*I17)*(SUM($G$6:$G$10)))-$K$4 -> 6875 | L17: =($L$4*I17)-(($L$4*I17)*(SUM($G$6:$G$10)))-$L$4 -> 8593.75 | M17: =($M$4*I17)-(($M$4*I17)*(SUM($G$6:$G$10)))-$M$4 -> 10742.188 | N17: =($N$4*I17)-(($N$4*I17)*(SUM($G$6:$G$10)))-$N$4 -> 13427.734 | O17: =($O$4*I17)-(($O$4*I17)*(SUM($G$6:$G$10)))-$O$4 -> 16784.668 | P17: =($P$4*I17)-(($P$4*I17)*(SUM($G$6:$G$10)))-$P$4 -> 20980.835 | Q17: =($Q$4*I17)-(($Q$4*I17)*(SUM($G$6:$G$10)))-$Q$4 -> 26226.044 | R17: =($R$4*I17)-(($R$4*I17)*(SUM($G$6:$G$10)))-$R$4 -> 32782.555 | S17: =($S$4*I17)-(($S$4*I17)*(SUM($G$6:$G$10)))-$S$4 -> 40978.193
B18: Número de pedidos | E18: Breakeven Roas | F18: =1/G11 -> 3.3333333 | I18: 7.5 | J18: =($J$4*I18)-(($J$4*I18)*(SUM($G$6:$G$10)))-$J$4 -> 6250 | K18: =($K$4*I18)-(($K$4*I18)*(SUM($G$6:$G$10)))-$K$4 -> 7812.5 | L18: =($L$4*I18)-(($L$4*I18)*(SUM($G$6:$G$10)))-$L$4 -> 9765.625 | M18: =($M$4*I18)-(($M$4*I18)*(SUM($G$6:$G$10)))-$M$4 -> 12207.031 | N18: =($N$4*I18)-(($N$4*I18)*(SUM($G$6:$G$10)))-$N$4 -> 15258.789 | O18: =($O$4*I18)-(($O$4*I18)*(SUM($G$6:$G$10)))-$O$4 -> 19073.486 | P18: =($P$4*I18)-(($P$4*I18)*(SUM($G$6:$G$10)))-$P$4 -> 23841.858 | Q18: =($Q$4*I18)-(($Q$4*I18)*(SUM($G$6:$G$10)))-$Q$4 -> 29802.322 | R18: =($R$4*I18)-(($R$4*I18)*(SUM($G$6:$G$10)))-$R$4 -> 37252.903 | S18: =($S$4*I18)-(($S$4*I18)*(SUM($G$6:$G$10)))-$S$4 -> 46566.129
B19: Número de devoluções | I19: 8 | J19: =($J$4*I19)-(($J$4*I19)*(SUM($G$6:$G$10)))-$J$4 -> 7000 | K19: =($K$4*I19)-(($K$4*I19)*(SUM($G$6:$G$10)))-$K$4 -> 8750 | L19: =($L$4*I19)-(($L$4*I19)*(SUM($G$6:$G$10)))-$L$4 -> 10937.5 | M19: =($M$4*I19)-(($M$4*I19)*(SUM($G$6:$G$10)))-$M$4 -> 13671.875 | N19: =($N$4*I19)-(($N$4*I19)*(SUM($G$6:$G$10)))-$N$4 -> 17089.844 | O19: =($O$4*I19)-(($O$4*I19)*(SUM($G$6:$G$10)))-$O$4 -> 21362.305 | P19: =($P$4*I19)-(($P$4*I19)*(SUM($G$6:$G$10)))-$P$4 -> 26702.881 | Q19: =($Q$4*I19)-(($Q$4*I19)*(SUM($G$6:$G$10)))-$Q$4 -> 33378.601 | R19: =($R$4*I19)-(($R$4*I19)*(SUM($G$6:$G$10)))-$R$4 -> 41723.251 | S19: =($S$4*I19)-(($S$4*I19)*(SUM($G$6:$G$10)))-$S$4 -> 52154.064
B20: Taxa Gateway & Checkout (%) | E20: ROAS | F20: Margem Contrib. | I20: 8.5 | J20: =($J$4*I20)-(($J$4*I20)*(SUM($G$6:$G$10)))-$J$4 -> 7750 | K20: =($K$4*I20)-(($K$4*I20)*(SUM($G$6:$G$10)))-$K$4 -> 9687.5 | L20: =($L$4*I20)-(($L$4*I20)*(SUM($G$6:$G$10)))-$L$4 -> 12109.375 | M20: =($M$4*I20)-(($M$4*I20)*(SUM($G$6:$G$10)))-$M$4 -> 15136.719 | N20: =($N$4*I20)-(($N$4*I20)*(SUM($G$6:$G$10)))-$N$4 -> 18920.898 | O20: =($O$4*I20)-(($O$4*I20)*(SUM($G$6:$G$10)))-$O$4 -> 23651.123 | P20: =($P$4*I20)-(($P$4*I20)*(SUM($G$6:$G$10)))-$P$4 -> 29563.904 | Q20: =($Q$4*I20)-(($Q$4*I20)*(SUM($G$6:$G$10)))-$Q$4 -> 36954.88 | R20: =($R$4*I20)-(($R$4*I20)*(SUM($G$6:$G$10)))-$R$4 -> 46193.6 | S20: =($S$4*I20)-(($S$4*I20)*(SUM($G$6:$G$10)))-$S$4 -> 57742
B21: Impostos sob receita (%) | E21: 1 | F21: =($F$5-$F$6-$F$7-$F$8-$F$9-$F$10-($F$5/E21))/$F$5 -> -0.7 | I21: 9 | J21: =($J$4*I21)-(($J$4*I21)*(SUM($G$6:$G$10)))-$J$4 -> 8500 | K21: =($K$4*I21)-(($K$4*I21)*(SUM($G$6:$G$10)))-$K$4 -> 10625 | L21: =($L$4*I21)-(($L$4*I21)*(SUM($G$6:$G$10)))-$L$4 -> 13281.25 | M21: =($M$4*I21)-(($M$4*I21)*(SUM($G$6:$G$10)))-$M$4 -> 16601.562 | N21: =($N$4*I21)-(($N$4*I21)*(SUM($G$6:$G$10)))-$N$4 -> 20751.953 | O21: =($O$4*I21)-(($O$4*I21)*(SUM($G$6:$G$10)))-$O$4 -> 25939.941 | P21: =($P$4*I21)-(($P$4*I21)*(SUM($G$6:$G$10)))-$P$4 -> 32424.927 | Q21: =($Q$4*I21)-(($Q$4*I21)*(SUM($G$6:$G$10)))-$Q$4 -> 40531.158 | R21: =($R$4*I21)-(($R$4*I21)*(SUM($G$6:$G$10)))-$R$4 -> 50663.948 | S21: =($S$4*I21)-(($S$4*I21)*(SUM($G$6:$G$10)))-$S$4 -> 63329.935
B22: Valor gasto Frete mensal (R$) | E22: 2 | F22: =($F$5-$F$6-$F$7-$F$8-$F$9-$F$10-($F$5/E22))/$F$5 -> -0.2 | I22: 9.5 | J22: =($J$4*I22)-(($J$4*I22)*(SUM($G$6:$G$10)))-$J$4 -> 9250 | K22: =($K$4*I22)-(($K$4*I22)*(SUM($G$6:$G$10)))-$K$4 -> 11562.5 | L22: =($L$4*I22)-(($L$4*I22)*(SUM($G$6:$G$10)))-$L$4 -> 14453.125 | M22: =($M$4*I22)-(($M$4*I22)*(SUM($G$6:$G$10)))-$M$4 -> 18066.406 | N22: =($N$4*I22)-(($N$4*I22)*(SUM($G$6:$G$10)))-$N$4 -> 22583.008 | O22: =($O$4*I22)-(($O$4*I22)*(SUM($G$6:$G$10)))-$O$4 -> 28228.76 | P22: =($P$4*I22)-(($P$4*I22)*(SUM($G$6:$G$10)))-$P$4 -> 35285.95 | Q22: =($Q$4*I22)-(($Q$4*I22)*(SUM($G$6:$G$10)))-$Q$4 -> 44107.437 | R22: =($R$4*I22)-(($R$4*I22)*(SUM($G$6:$G$10)))-$R$4 -> 55134.296 | S22: =($S$4*I22)-(($S$4*I22)*(SUM($G$6:$G$10)))-$S$4 -> 68917.871
B23: Markup | E23: 3 | F23: =($F$5-$F$6-$F$7-$F$8-$F$9-$F$10-($F$5/E23))/$F$5 -> -0.033333333 | I23: 10 | J23: =($J$4*I23)-(($J$4*I23)*(SUM($G$6:$G$10)))-$J$4 -> 10000 | K23: =($K$4*I23)-(($K$4*I23)*(SUM($G$6:$G$10)))-$K$4 -> 12500 | L23: =($L$4*I23)-(($L$4*I23)*(SUM($G$6:$G$10)))-$L$4 -> 15625 | M23: =($M$4*I23)-(($M$4*I23)*(SUM($G$6:$G$10)))-$M$4 -> 19531.25 | N23: =($N$4*I23)-(($N$4*I23)*(SUM($G$6:$G$10)))-$N$4 -> 24414.062 | O23: =($O$4*I23)-(($O$4*I23)*(SUM($G$6:$G$10)))-$O$4 -> 30517.578 | P23: =($P$4*I23)-(($P$4*I23)*(SUM($G$6:$G$10)))-$P$4 -> 38146.973 | Q23: =($Q$4*I23)-(($Q$4*I23)*(SUM($G$6:$G$10)))-$Q$4 -> 47683.716 | R23: =($R$4*I23)-(($R$4*I23)*(SUM($G$6:$G$10)))-$R$4 -> 59604.645 | S23: =($S$4*I23)-(($S$4*I23)*(SUM($G$6:$G$10)))-$S$4 -> 74505.806
B24: Budget Anúncios (R$) | E24: 4 | F24: =($F$5-$F$6-$F$7-$F$8-$F$9-$F$10-($F$5/E24))/$F$5 -> 0.05 | I24: 10.5 | J24: =($J$4*I24)-(($J$4*I24)*(SUM($G$6:$G$10)))-$J$4 -> 10750 | K24: =($K$4*I24)-(($K$4*I24)*(SUM($G$6:$G$10)))-$K$4 -> 13437.5 | L24: =($L$4*I24)-(($L$4*I24)*(SUM($G$6:$G$10)))-$L$4 -> 16796.875 | M24: =($M$4*I24)-(($M$4*I24)*(SUM($G$6:$G$10)))-$M$4 -> 20996.094 | N24: =($N$4*I24)-(($N$4*I24)*(SUM($G$6:$G$10)))-$N$4 -> 26245.117 | O24: =($O$4*I24)-(($O$4*I24)*(SUM($G$6:$G$10)))-$O$4 -> 32806.396 | P24: =($P$4*I24)-(($P$4*I24)*(SUM($G$6:$G$10)))-$P$4 -> 41007.996 | Q24: =($Q$4*I24)-(($Q$4*I24)*(SUM($G$6:$G$10)))-$Q$4 -> 51259.995 | R24: =($R$4*I24)-(($R$4*I24)*(SUM($G$6:$G$10)))-$R$4 -> 64074.993 | S24: =($S$4*I24)-(($S$4*I24)*(SUM($G$6:$G$10)))-$S$4 -> 80093.741
E25: 5 | F25: =($F$5-$F$6-$F$7-$F$8-$F$9-$F$10-($F$5/E25))/$F$5 -> 0.1 | I25: 11 | J25: =($J$4*I25)-(($J$4*I25)*(SUM($G$6:$G$10)))-$J$4 -> 11500 | K25: =($K$4*I25)-(($K$4*I25)*(SUM($G$6:$G$10)))-$K$4 -> 14375 | L25: =($L$4*I25)-(($L$4*I25)*(SUM($G$6:$G$10)))-$L$4 -> 17968.75 | M25: =($M$4*I25)-(($M$4*I25)*(SUM($G$6:$G$10)))-$M$4 -> 22460.938 | N25: =($N$4*I25)-(($N$4*I25)*(SUM($G$6:$G$10)))-$N$4 -> 28076.172 | O25: =($O$4*I25)-(($O$4*I25)*(SUM($G$6:$G$10)))-$O$4 -> 35095.215 | P25: =($P$4*I25)-(($P$4*I25)*(SUM($G$6:$G$10)))-$P$4 -> 43869.019 | Q25: =($Q$4*I25)-(($Q$4*I25)*(SUM($G$6:$G$10)))-$Q$4 -> 54836.273 | R25: =($R$4*I25)-(($R$4*I25)*(SUM($G$6:$G$10)))-$R$4 -> 68545.341 | S25: =($S$4*I25)-(($S$4*I25)*(SUM($G$6:$G$10)))-$S$4 -> 85681.677
E26: 6 | F26: =($F$5-$F$6-$F$7-$F$8-$F$9-$F$10-($F$5/E26))/$F$5 -> 0.13333333 | I26: 11.5 | J26: =($J$4*I26)-(($J$4*I26)*(SUM($G$6:$G$10)))-$J$4 -> 12250 | K26: =($K$4*I26)-(($K$4*I26)*(SUM($G$6:$G$10)))-$K$4 -> 15312.5 | L26: =($L$4*I26)-(($L$4*I26)*(SUM($G$6:$G$10)))-$L$4 -> 19140.625 | M26: =($M$4*I26)-(($M$4*I26)*(SUM($G$6:$G$10)))-$M$4 -> 23925.781 | N26: =($N$4*I26)-(($N$4*I26)*(SUM($G$6:$G$10)))-$N$4 -> 29907.227 | O26: =($O$4*I26)-(($O$4*I26)*(SUM($G$6:$G$10)))-$O$4 -> 37384.033 | P26: =($P$4*I26)-(($P$4*I26)*(SUM($G$6:$G$10)))-$P$4 -> 46730.041 | Q26: =($Q$4*I26)-(($Q$4*I26)*(SUM($G$6:$G$10)))-$Q$4 -> 58412.552 | R26: =($R$4*I26)-(($R$4*I26)*(SUM($G$6:$G$10)))-$R$4 -> 73015.69 | S26: =($S$4*I26)-(($S$4*I26)*(SUM($G$6:$G$10)))-$S$4 -> 91269.612
E27: 7 | F27: =($F$5-$F$6-$F$7-$F$8-$F$9-$F$10-($F$5/E27))/$F$5 -> 0.15714286 | I27: 12 | J27: =($J$4*I27)-(($J$4*I27)*(SUM($G$6:$G$10)))-$J$4 -> 13000 | K27: =($K$4*I27)-(($K$4*I27)*(SUM($G$6:$G$10)))-$K$4 -> 16250 | L27: =($L$4*I27)-(($L$4*I27)*(SUM($G$6:$G$10)))-$L$4 -> 20312.5 | M27: =($M$4*I27)-(($M$4*I27)*(SUM($G$6:$G$10)))-$M$4 -> 25390.625 | N27: =($N$4*I27)-(($N$4*I27)*(SUM($G$6:$G$10)))-$N$4 -> 31738.281 | O27: =($O$4*I27)-(($O$4*I27)*(SUM($G$6:$G$10)))-$O$4 -> 39672.852 | P27: =($P$4*I27)-(($P$4*I27)*(SUM($G$6:$G$10)))-$P$4 -> 49591.064 | Q27: =($Q$4*I27)-(($Q$4*I27)*(SUM($G$6:$G$10)))-$Q$4 -> 61988.831 | R27: =($R$4*I27)-(($R$4*I27)*(SUM($G$6:$G$10)))-$R$4 -> 77486.038 | S27: =($S$4*I27)-(($S$4*I27)*(SUM($G$6:$G$10)))-$S$4 -> 96857.548
E28: 8 | F28: =($F$5-$F$6-$F$7-$F$8-$F$9-$F$10-($F$5/E28))/$F$5 -> 0.175
E29: 9 | F29: =($F$5-$F$6-$F$7-$F$8-$F$9-$F$10-($F$5/E29))/$F$5 -> 0.18888889 | I29: Recorrêcia Atual | J29: 0.4
E30: 10 | F30: =($F$5-$F$6-$F$7-$F$8-$F$9-$F$10-($F$5/E30))/$F$5 -> 0.2 | I30: Recompra 90D | J30: 0.2
E31: 11 | F31: =($F$5-$F$6-$F$7-$F$8-$F$9-$F$10-($F$5/E31))/$F$5 -> 0.20909091 | I31: Investimento | J31: Receita | K31: Lucro 1° Mês | L31: Rec. Novos | M31: N° N.Clien. | N31: Lucro LTV 90D | O31: Total 90D
E32: 12 | F32: =($F$5-$F$6-$F$7-$F$8-$F$9-$F$10-($F$5/E32))/$F$5 -> 0.21666667 | I32: =J4 -> 5000 | J32: =C5 -> 10000 | K32: =F17 -> -2000 | L32: =J32*(1-J29) -> 6000 | M32: =L32/$F$5 -> 60 | N32: =(M32*$F$5*$J$30)*(1-(SUM($G$6:$G$10))) -> 360 | O32: =N32+K32 -> -1640
E33: 13 | F33: =($F$5-$F$6-$F$7-$F$8-$F$9-$F$10-($F$5/E33))/$F$5 -> 0.22307692 | H33: =-(1-I33/I32) -> 0.5625 | I33: =J4*(L4/J4) -> 7812.5 | J33: =I33*I19 -> 62500 | K33: 18083 | L33: =J33*(1-(J29*0.8)) -> 42500 | M33: =L33/$F$5 -> 425 | N33: =(M33*$F$5*$J$30)*(1-(SUM($G$6:$G$10))) -> 2550 | O33: =N33+K33 -> 20633 | P33: =(O33/O32)-1 -> -13.581098
H34: =-(1-I34/I32) -> 1.4414062 | I34: =L4*(N4/L4) -> 12207.031 | J34: =I34*I16 -> 79345.703 | K34: 18803 | L34: =J33*(1-(J29*0.7)) -> 45000 | M34: =L34/$F$5 -> 450 | N34: =(M34*$F$5*$J$30)*(1-(SUM($G$6:$G$10))) -> 2700 | O34: =N34+K34 -> 21503 | P34: =(O34/O32)-1 -> -14.111585
H35: =-(1-I35/I32) -> 2.8146973 | I35: =N4*(N4/L4) -> 19073.486 | J35: =I35*I14 -> 104904.17 | K35: 19520 | L35: =J35*(1-(J29*0.6)) -> 79727.173 | M35: =L35/$F$5 -> 797.27173 | N35: =(M35*$F$5*$J$30)*(1-(SUM($G$6:$G$10))) -> 4783.6304 | O35: =N35+K35 -> 24303.63 | P35: =(O35/O32)-1 -> -15.819287
H36: =-(1-I36/I32) -> 4.9604645 | I36: =P4*(P4/N4) -> 29802.322 | J36: =I36*I14 -> 163912.77 | K36: 22795.841 | L36: =J36*(1-(J29*0.5)) -> 131130.22 | M36: =L36/$F$5 -> 1311.3022 | N36: =(M36*$F$5*$J$30)*(1-(SUM($G$6:$G$10))) -> 7867.8131 | O36: =N36+K36 -> 30663.654 | P36: =(O36/O32)-1 -> -19.69735
H37: =-(1-I37/I32) -> 6.4505806 | I37: =S4 -> 37252.903 | J37: =I37*I12 -> 167638.06 | K37: 18865 | L37: =J37*(1-(J29*0.4)) -> 140815.97 | M37: =L37/$F$5 -> 1408.1597 | N37: =(M37*$F$5*$J$30)*(1-(SUM($G$6:$G$10))) -> 8448.9584 | O37: =N37+K37 -> 27313.958 | P37: =(O37/O32)-1 -> -17.654853

Sheet Calendário 2025
C1: CALENDÁRIO 2026
B3: OUTUBRO | J3: NOVEMBRO | R3: DEZEMBRO | Z3: DATAS COMEMORATIVAS
B4: Seg | C4: Ter | D4: Qua | E4: Qui | F4: Sex | G4: Sáb | H4: Dom | J4: Seg | K4: Ter | L4: Qua | M4: Qui | N4: Sex | O4: Sáb | P4: Dom | R4: Seg | S4: Ter | T4: Qua | U4: Qui | V4: Sex | W4: Sáb | X4: Dom | Z4: 45245 | AA4: Dia da proclamação da Republica
O5: 1 | P5: 2 | R5: 1 | S5: 2 | T5: 3 | U5: 4 | V5: 5 | W5: 6 | X5: 7 | Z5: 45252 | AA5: Black Friday
J6: 3 | K6: 4 | L6: 5 | M6: 6 | N6: 7 | O6: 8 | P6: 9 | R6: 8 | S6: 9 | T6: 10 | U6: 11 | V6: 12 | W6: 13 | X6: 14 | Z6: 45255 | AA6: Cyber Monday
J7: 10 | K7: 11 | L7: 12 | M7: 13 | N7: 14 | O7: 15 | P7: 16 | R7: 15 | S7: 16 | T7: 17 | U7: 18 | V7: 19 | W7: 20 | X7: 21 | Z7: 45285 | AA7: Natal
J8: 17 | K8: 18 | L8: 19 | M8: 20 | N8: 21 | O8: 22 | P8: 23 | R8: 22 | S8: 23 | T8: 24 | U8: 25 | V8: 26 | W8: 27 | X8: 28 | Z8: 45291 | AA8: Ano novo
J9: 24 | K9: 25 | L9: 26 | M9: 27 | N9: 28 | O9: 29 | P9: 30 | R9: 29 | S9: 30 | T9: 31

Sheet Calendário Fevereiro
B1: FEVEREIRO 2026
B3: SEGUNDA-FEIRA | C3: TERÇA-FEIRA | D3: QUARTA-FEIRA | E3: QUINTA-FEIRA | F3: SEXTA-FEIRA | G3: SÁBADO | H3: DOMINGO | J3: LEGENDA:
E4: 1 | F4: 2 | G4: 3 | H4: 4 | J4: Feriados
J5: Datas de nicho
B6: 5 | C6: 6 | D6: 7 | E6: 8 | F6: 9 | G6: 10 | H6: 11 | J6: Datas Importantes
J7: Essenciais no E-commerce
B8: 12 | C8: 13 | D8: 14 | E8: 15 | F8: 16 | G8: 17 | H8: 18 | J8: Aquecimento
B9: Carnaval | C9: Carnaval
B10: 19 | C10: 20 | D10: 21 | E10: 22 | F10: 23 | G10: 24 | H10: 25
B11: Dia do Esportista
B12: 26 | C12: 27 | D12: 28 | E12: 29
B15: OBSERVAÇÕES:

Sheet Calendário Março
B1: MARÇO 2026
B3: SEGUNDA-FEIRA | C3: TERÇA-FEIRA | D3: QUARTA-FEIRA | E3: QUINTA-FEIRA | F3: SEXTA-FEIRA | G3: SÁBADO | H3: DOMINGO | J3: LEGENDA:
F4: 1 | G4: 2 | H4: 3 | J4: Feriados
J5: Datas de nicho
B6: 4 | C6: 5 | D6: 6 | E6: 7 | F6: 8 | G6: 9 | H6: 10 | J6: Datas Importantes
F7: Dia da Mulher | J7: Essenciais no E-commerce
B8: 11 | C8: 12 | D8: 13 | E8: 14 | F8: 15 | G8: 16 | H8: 17 | J8: Aquecimento
F9: Dia do Consumidor
B10: 18 | C10: 19 | D10: 20 | E10: 21 | F10: 22 | G10: 23 | H10: 24
D11: Início do Outono
B12: 25 | C12: 26 | D12: 27 | E12: 28 | F12: 29 | G12: 30 | H12: 31
H13: Páscoa
B15: OBSERVAÇÕES:

Sheet Calendário Abril
B1: ABRIL 2026
B3: SEGUNDA-FEIRA | C3: TERÇA-FEIRA | D3: QUARTA-FEIRA | E3: QUINTA-FEIRA | F3: SEXTA-FEIRA | G3: SÁBADO | H3: DOMINGO | J3: LEGENDA:
B4: 1 | C4: 2 | D4: 3 | E4: 4 | F4: 5 | G4: 6 | H4: 7 | J4: Feriados
B5: Dia da Mentira | H5: Dia Mundial da Saúde | J5: Datas de nicho
B6: 8 | C6: 9 | D6: 10 | E6: 11 | F6: 12 | G6: 13 | H6: 14 | J6: Datas Importantes
G7: Dia do Beijo | H7: Dia do Café | J7: Essenciais no E-commerce
B8: 15 | C8: 16 | D8: 17 | E8: 18 | F8: 19 | G8: 20 | H8: 21 | J8: Aquecimento
B10: 22 | C10: 23 | D10: 24 | E10: 25 | F10: 26 | G10: 27 | H10: 28
B11: Dia Mundial da Terra
B12: 29 | C12: 30
B15: OBSERVAÇÕES:

Sheet Calendário Maio
B1: MAIO 2026
B3: SEGUNDA-FEIRA | C3: TERÇA-FEIRA | D3: QUARTA-FEIRA | E3: QUINTA-FEIRA | F3: SEXTA-FEIRA | G3: SÁBADO | H3: DOMINGO | J3: LEGENDA:
D4: 1 | E4: 2 | F4: 3 | G4: 4 | H4: 5 | J4: Feriados
D5: Dia do Trabalho | J5: Datas de nicho
B6: 6 | C6: 7 | D6: 8 | E6: 9 | F6: 10 | G6: 11 | H6: 12 | J6: Datas Importantes
H7: Dia das Mães | J7: Essenciais no E-commerce
B8: 13 | C8: 14 | D8: 15 | E8: 16 | F8: 17 | G8: 18 | H8: 19 | J8: Aquecimento
B10: 20 | C10: 21 | D10: 22 | E10: 23 | F10: 24 | G10: 25 | H10: 26
D11: Dia do Abraço | G11: Dia do Orgulho Nerd
B12: 27 | C12: 28 | D12: 29 | E12: 30 | F12: 31
B15: OBSERVAÇÕES:

Sheet Calendário Junho
B1: JUNHO 2026
B3: SEGUNDA-FEIRA | C3: TERÇA-FEIRA | D3: QUARTA-FEIRA | E3: QUINTA-FEIRA | F3: SEXTA-FEIRA | G3: SÁBADO | H3: DOMINGO | J3: LEGENDA:
G4: 1 | H4: 2 | J4: Feriados
J5: Datas de nicho
B6: 3 | C6: 4 | D6: 5 | E6: 6 | F6: 7 | G6: 8 | H6: 9 | J6: Datas Importantes
J7: Essenciais no E-commerce
B8: 10 | C8: 11 | D8: 12 | E8: 13 | F8: 14 | G8: 15 | H8: 16 | J8: Aquecimento
D9: Dia dos Namorados
B10: 17 | C10: 18 | E10: 20 | F10: 21 | G10: 22 | H10: 23
E11: Início do Inverno
B12: 24 | C12: 25 | D12: 26 | E12: 27 | F12: 28 | G12: 29 | H12: 30
F13: Dia do Orgulho LGBTQIA+
B15: OBSERVAÇÕES:

Sheet Calendário Julho
B1: JULHO 2026
B3: SEGUNDA-FEIRA | C3: TERÇA-FEIRA | D3: QUARTA-FEIRA | E3: QUINTA-FEIRA | F3: SEXTA-FEIRA | G3: SÁBADO | H3: DOMINGO | J3: LEGENDA:
B4: 1 | C4: 2 | D4: 3 | E4: 4 | F4: 5 | G4: 6 | H4: 7 | J4: Feriados
H5: Dia do Chocolate | J5: Datas de nicho
B6: 8 | C6: 9 | D6: 10 | E6: 11 | F6: 12 | G6: 13 | H6: 14 | J6: Datas Importantes
G7: Dia do Rock | J7: Essenciais no E-commerce
B8: 15 | C8: 16 | D8: 17 | E8: 18 | F8: 19 | G8: 20 | H8: 21 | J8: Aquecimento
B9: Dia do Homem
B10: 22 | C10: 23 | D10: 24 | E10: 25 | F10: 26 | G10: 27 | H10: 28
F11: Dia dos Avós
B12: 29 | C12: 30 | D12: 31
C13: Dia da Amizade
B15: OBSERVAÇÕES:

Sheet Ação por Métricas
B1: CTR | C1: CPS | D1: SESSÕES | E1: TAXA DE CONVERSÃO | F1: TICKET MÉDIO | G1: FATURAMENTO
B2: Analisar melhores Períodos de CTR | C2: Analisar melhores Períodos de CPS | D2: Analisar melhores Períodos de Sessões | E2: Analisar melhores Períodos de Taxa de Conversão | F2: Analisar melhores Períodos de Ticket Médio | G2: Analisar melhores Períodos de Faturamento
B3: Teste A/B de Criativos | C3: Analisar melhores Períodos de CPM | D3: Iniciar em Canais com mais Chance de Crescimento | E3: Velocidade do Site | F3: Frete Fixo acima de TM 10%+ | G3: Campanha de Frete Grátis
B4: Teste A/B de Copy | C4: Velocidade do Site | D4: Ampliar Aquisição em Canais com menor Representatividade | E4: Mapear Objeções | F4: Kit e Combo | G4: Ação com Desconto Especial
B5: Teste A/B de Públicos | C5: Revisar LP ( Contexto e Estrutura ) | D5: Velocidade | E5: Mapear Motivações | F5: Brindes | G5: LiveShop
B6: Otimizar Chamada 3 Primeiros Segundos | C6: Entender a Relação de Maior CTR x Menor CPS | D6: SEO | E6: Analisar Gatilhos e Incentivos | F6: Order Bump | G6: Recuperação de Pagamento
B7: Usar Vídeos DSB | C7: Decentralizar Mídia | D7: Régua de Relacionamento | E7: Revisar Oferta | F7: Cupom Progressivo | G7: Forma de Pagamento
B8: Segmentar Audiências | C8: Comentários no Anúncio | D8: Influencer | E8: Direcionar para Canais com mais Taxa de Conversão | F8: Frete Grátis acima de TM 15% | G8: Cupom de Madrugada
B9: Trocar CTA | C9: Oferta Agressiva no Criativo | D9: Aumento de Verba | E9: Ajustar Canais com Menor Taxa de Conversão | F9: Compre Junto | G9: Focar em Recompra
B10: Produtos Curva A | C10: Públicos Amplos | D10: Cross Public | E10: Intensificar entrega de Produtos com maior Taxa de Conversão | F10: Produtos Relacionados | G10: E-Mail Marketing
B11: Posicionamento de ADS | C11: Criativo x Persona | D11: Criativo Virais | E11: Otimizar Frete | F11: Upsell | G11: Indique e Ganhe

Sheet ADV - FB
A1: Data | B1: Campanha | C1: Conjunto de Anuncio | D1: Anuncio | E1: Valor investido | F1: Visualização de Página | G1: Impressões | H1: Cliques (All) | I1: Compras | J1: Valor de Compras | K1: Ad Prefix
A2: 46133 | B2: Tp-vendas-abo-05.02 | C2: UGC-04-Interesses-12.03 | D2: UGC-hook2 | E2: 0.55 | F2: 1 | G2: 21 | H2: 3
A3: 46133 | B3: Tp-vendas-abo-05.02 | C3: UGC-02-Interesses-09.02 | D3: UGC-hook2 | E3: 0.3 | G3: 24 | H3: 0
A4: 46132 | B4: Tp-vendas-abo-05.02 | C4: UGC-04-Interesses-12.03 | D4: UGC-hook2 | E4: 32.78 | F4: 13 | G4: 814 | H4: 25
A5: 46132 | B5: Tp-vendas-abo-05.02 | C5: UGC-02-Interesses-09.02 | D5: UGC-hook2 | E5: 34.95 | F5: 14 | G5: 1055 | H5: 30
A6: 46131 | B6: Tp-vendas-abo-05.02 | C6: UGC-04-Interesses-12.03 | D6: UGC-hook2 | E6: 23.33 | F6: 7 | G6: 656 | H6: 20
A7: 46131 | B7: Tp-vendas-abo-05.02 | C7: UGC-02-Interesses-09.02 | D7: UGC-hook2 | E7: 24.45 | F7: 3 | G7: 709 | H7: 16
A8: 46131 | B8: Tp-vendas-abo-05.02 | C8: UGC-02-Interesses-09.02 | D8: UGC-Hook3 | E8: 1.72 | F8: 1 | G8: 70 | H8: 2
A9: 46130 | B9: Tp-vendas-abo-05.02 | C9: UGC-04-Interesses-12.03 | D9: UGC-hook2 | E9: 29.89 | F9: 18 | G9: 885 | H9: 34
A10: 46130 | B10: Tp-vendas-abo-05.02 | C10: UGC-04-Interesses-12.03 | D10: UGC-Hook3 | E10: 1.1 | F10: 1 | G10: 10 | H10: 1
A11: 46130 | B11: Tp-vendas-abo-05.02 | C11: UGC-02-Interesses-09.02 | D11: UGC-hook2 | E11: 34.68 | F11: 13 | G11: 1017 | H11: 39 | I11: 1 | J11: 107.4
A12: 46129 | B12: Tp-vendas-abo-05.02 | C12: UGC-04-Interesses-12.03 | D12: UGC-hook2 | E12: 31.11 | F12: 11 | G12: 811 | H12: 30
A13: 46129 | B13: Tp-vendas-abo-05.02 | C13: UGC-02-Interesses-09.02 | D13: UGC-hook2 | E13: 30.96 | F13: 13 | G13: 902 | H13: 28 | I13: 1 | J13: 107.4
A14: 46129 | B14: Tp-vendas-abo-05.02 | C14: UGC-02-Interesses-09.02 | D14: UGC-Hook3 | E14: 2.56 | F14: 5 | G14: 103 | H14: 3
A15: 46128 | B15: Tp-vendas-abo-05.02 | C15: UGC-04-Interesses-12.03 | D15: UGC-hook2 | E15: 34.4 | F15: 10 | G15: 950 | H15: 33
A16: 46128 | B16: Tp-vendas-abo-05.02 | C16: UGC-04-Interesses-12.03 | D16: UGC-Hook3 | E16: 0.44 | G16: 26 | H16: 0
A17: 46128 | B17: Tp-vendas-abo-05.02 | C17: UGC-02-Interesses-09.02 | D17: UGC-hook2 | E17: 37.98 | F17: 16 | G17: 1081 | H17: 39 | I17: 4 | J17: 513
A18: 46128 | B18: Tp-vendas-abo-05.02 | C18: UGC-02-Interesses-09.02 | D18: UGC-Hook3 | E18: 0.32 | G18: 17 | H18: 0
A19: 46127 | B19: Tp-vendas-abo-05.02 | C19: UGC-04-Interesses-12.03 | D19: UGC-hook2 | E19: 38.28 | F19: 10 | G19: 1029 | H19: 43 | I19: 2 | J19: 214.8
A20: 46127 | B20: Tp-vendas-abo-05.02 | C20: UGC-04-Interesses-12.03 | D20: UGC-Hook3 | E20: 0.02 | G20: 4 | H20: 0
A21: 46127 | B21: Tp-vendas-abo-05.02 | C21: UGC-02-Interesses-09.02 | D21: UGC-hook2 | E21: 42.6 | F21: 13 | G21: 1255 | H21: 34 | I21: 3 | J21: 405.6
A22: 46127 | B22: Tp-vendas-abo-05.02 | C22: UGC-02-Interesses-09.02 | D22: UGC-Hook3 | E22: 0.45 | G22: 11 | H22: 0
A23: 46126 | B23: Tp-vendas-abo-05.02 | C23: UGC-04-Interesses-12.03 | D23: UGC-hook2 | E23: 29.62 | F23: 6 | G23: 881 | H23: 23
A24: 46126 | B24: Tp-vendas-abo-05.02 | C24: UGC-04-Interesses-12.03 | D24: UGC-Hook3 | E24: 0.02 | G24: 1 | H24: 0
A25: 46126 | B25: Tp-vendas-abo-05.02 | C25: UGC-02-Interesses-09.02 | D25: UGC-hook2 | E25: 28.3 | F25: 7 | G25: 880 | H25: 23
A26: 46126 | B26: Tp-vendas-abo-05.02 | C26: UGC-02-Interesses-09.02 | D26: UGC-Hook3 | E26: 3.07 | G26: 109 | H26: 4
A27: 46124 | B27: Tp-vendas-abo-05.02 | C27: UGC-04-Interesses-12.03 | D27: UGC-hook2 | E27: 4.65 | F27: 5 | G27: 144 | H27: 8
A28: 46124 | B28: Tp-vendas-abo-05.02 | C28: UGC-02-Interesses-09.02 | D28: UGC-hook2 | E28: 4.58 | F28: 2 | G28: 133 | H28: 4
A29: 46123 | B29: Tp-vendas-abo-05.02 | C29: UGC-04-Interesses-12.03 | D29: UGC-hook2 | E29: 31.57 | F29: 16 | G29: 980 | H29: 31 | I29: 3 | J29: 572.4
A30: 46123 | B30: Tp-vendas-abo-05.02 | C30: UGC-04-Interesses-12.03 | D30: UGC-Hook3 | E30: 0.25 | G30: 13 | H30: 0
A31: 46123 | B31: Tp-vendas-abo-05.02 | C31: UGC-02-Interesses-09.02 | D31: UGC-hook2 | E31: 28.62 | F31: 14 | G31: 730 | H31: 26
A32: 46123 | B32: Tp-vendas-abo-05.02 | C32: UGC-02-Interesses-09.02 | D32: UGC-Hook3 | E32: 0.01 | G32: 1 | H32: 0
A33: 46122 | B33: Tp-vendas-abo-05.02 | C33: UGC-04-Interesses-12.03 | D33: UGC-hook2 | E33: 34.79 | F33: 22 | G33: 893 | H33: 46
A34: 46122 | B34: Tp-vendas-abo-05.02 | C34: UGC-04-Interesses-12.03 | D34: UGC-Hook3 | E34: 2.91 | F34: 1 | G34: 71 | H34: 2
A35: 46122 | B35: Tp-vendas-abo-05.02 | C35: UGC-02-Interesses-09.02 | D35: UGC-hook2 | E35: 25.62 | F35: 7 | G35: 597 | H35: 29 | I35: 3 | J35: 606.8
A36: 46122 | B36: Tp-vendas-abo-05.02 | C36: UGC-02-Interesses-09.02 | D36: UGC-Hook3 | E36: 1.75 | F36: 1 | G36: 72 | H36: 2
A37: 46121 | B37: Tp-vendas-abo-05.02 | C37: UGC-04-Interesses-12.03 | D37: UGC-hook2 | E37: 31.21 | F37: 16 | G37: 876 | H37: 44
A38: 46121 | B38: Tp-vendas-abo-05.02 | C38: UGC-04-Interesses-12.03 | D38: UGC-Hook3 | E38: 5.72 | F38: 1 | G38: 178 | H38: 4
A39: 46121 | B39: Tp-vendas-abo-05.02 | C39: UGC-02-Interesses-09.02 | D39: UGC-hook2 | E39: 12.03 | F39: 6 | G39: 283 | H39: 17 | I39: 1 | J39: 71.6
A40: 46121 | B40: Tp-vendas-abo-05.02 | C40: UGC-02-Interesses-09.02 | D40: UGC-Hook3 | E40: 12.29 | F40: 3 | G40: 379 | H40: 9 | I40: 1 | J40: 190.8
A41: 46120 | B41: Tp-vendas-abo-05.02 | C41: UGC-04-Interesses-12.03 | D41: UGC-hook2 | E41: 33.86 | F41: 9 | G41: 883 | H41: 24 | I41: 1 | J41: 190.8
A42: 46120 | B42: Tp-vendas-abo-05.02 | C42: UGC-04-Interesses-12.03 | D42: UGC-Hook3 | E42: 8.54 | G42: 236 | H42: 4
A43: 46120 | B43: Tp-vendas-abo-05.02 | C43: UGC-02-Interesses-09.02 | D43: UGC-hook2 | E43: 13.13 | F43: 2 | G43: 370 | H43: 11
A44: 46120 | B44: Tp-vendas-abo-05.02 | C44: UGC-02-Interesses-09.02 | D44: UGC-Hook3 | E44: 15.12 | F44: 1 | G44: 434 | H44: 6
A45: 46119 | B45: Tp-vendas-abo-05.02 | C45: UGC-04-Interesses-12.03 | D45: UGC-hook2 | E45: 30.04 | F45: 7 | G45: 894 | H45: 28 | I45: 1 | J45: 107.4
A46: 46119 | B46: Tp-vendas-abo-05.02 | C46: UGC-04-Interesses-12.03 | D46: UGC-Hook3 | E46: 9.61 | F46: 4 | G46: 257 | H46: 9
A47: 46119 | B47: Tp-vendas-abo-05.02 | C47: UGC-02-Interesses-09.02 | D47: UGC-hook2 | E47: 9.01 | F47: 1 | G47: 216 | H47: 5
A48: 46119 | B48: Tp-vendas-abo-05.02 | C48: UGC-02-Interesses-09.02 | D48: UGC-Hook3 | E48: 14.35 | F48: 4 | G48: 478 | H48: 6
A49: 46118 | B49: Tp-vendas-abo-05.02 | C49: UGC-04-Interesses-12.03 | D49: UGC-hook2 | E49: 37.76 | F49: 10 | G49: 864 | H49: 34 | I49: 2 | J49: 179
A50: 46118 | B50: Tp-vendas-abo-05.02 | C50: UGC-04-Interesses-12.03 | D50: UGC-Hook3 | E50: 7.6 | F50: 1 | G50: 157 | H50: 4
A51: 46118 | B51: Tp-vendas-abo-05.02 | C51: UGC-02-Interesses-09.02 | D51: UGC-hook2 | E51: 11.73 | F51: 3 | G51: 311 | H51: 7 | I51: 1 | J51: 107.4
A52: 46118 | B52: Tp-vendas-abo-05.02 | C52: UGC-02-Interesses-09.02 | D52: UGC-Hook3 | E52: 15.2 | F52: 3 | G52: 433 | H52: 13 | I52: 1 | J52: 107.4
A53: 46117 | B53: Tp-vendas-abo-05.02 | C53: UGC-04-Interesses-12.03 | D53: UGC-hook2 | E53: 35.02 | F53: 9 | G53: 1062 | H53: 32
A54: 46117 | B54: Tp-vendas-abo-05.02 | C54: UGC-04-Interesses-12.03 | D54: UGC-Hook3 | E54: 9.3 | G54: 193 | H54: 3
A55: 46117 | B55: Tp-vendas-abo-05.02 | C55: UGC-02-Interesses-09.02 | D55: UGC-hook2 | E55: 16.97 | F55: 12 | G55: 444 | H55: 15 | I55: 1 | J55: 89.5
A56: 46117 | B56: Tp-vendas-abo-05.02 | C56: UGC-02-Interesses-09.02 | D56: UGC-Hook3 | E56: 11.25 | F56: 6 | G56: 317 | H56: 11
A57: 46116 | B57: Tp-vendas-abo-05.02 | C57: UGC-04-Interesses-12.03 | D57: UGC-hook2 | E57: 61.57 | F57: 20 | G57: 1525 | H57: 71 | I57: 3 | J57: 322.2
A58: 46116 | B58: Tp-vendas-abo-05.02 | C58: UGC-04-Interesses-12.03 | D58: UGC-Hook3 | E58: 6.2 | F58: 1 | G58: 141 | H58: 1
A59: 46116 | B59: Tp-vendas-abo-05.02 | C59: UGC-02-Interesses-09.02 | D59: UGC-hook2 | E59: 9.38 | F59: 3 | G59: 259 | H59: 14
A60: 46116 | B60: Tp-vendas-abo-05.02 | C60: UGC-02-Interesses-09.02 | D60: UGC-Hook3 | E60: 33.12 | F60: 7 | G60: 877 | H60: 10
A61: 46115 | B61: Tp-vendas-abo-05.02 | C61: UGC-04-Interesses-12.03 | D61: UGC-hook2 | E61: 58.67 | F61: 25 | G61: 1637 | H61: 58 | I61: 2 | J61: 298.2
A62: 46115 | B62: Tp-vendas-abo-05.02 | C62: UGC-04-Interesses-12.03 | D62: UGC-Hook3 | E62: 9.38 | G62: 210 | H62: 0
A63: 46115 | B63: Tp-vendas-abo-05.02 | C63: UGC-02-Interesses-09.02 | D63: UGC-hook2 | E63: 14.1 | F63: 7 | G63: 291 | H63: 13
A64: 46115 | B64: Tp-vendas-abo-05.02 | C64: UGC-02-Interesses-09.02 | D64: UGC-Hook3 | E64: 28.56 | F64: 10 | G64: 974 | H64: 28
A65: 46114 | B65: Tp-vendas-abo-05.02 | C65: UGC-04-Interesses-12.03 | D65: UGC-hook2 | E65: 40.11 | F65: 6 | G65: 1005 | H65: 28
A66: 46114 | B66: Tp-vendas-abo-05.02 | C66: UGC-04-Interesses-12.03 | D66: UGC-Hook3 | E66: 29.42 | F66: 8 | G66: 1120 | H66: 26
A67: 46114 | B67: Tp-vendas-abo-05.02 | C67: UGC-02-Interesses-09.02 | D67: UGC-hook2 | E67: 13.95 | F67: 6 | G67: 331 | H67: 14
A68: 46114 | B68: Tp-vendas-abo-05.02 | C68: UGC-02-Interesses-09.02 | D68: UGC-Hook3 | E68: 28.93 | F68: 6 | G68: 850 | H68: 22 | I68: 1 | J68: 89.5
A69: 46113 | B69: Tp-vendas-abo-05.02 | C69: UGC-04-Interesses-12.03 | D69: UGC-hook2 | E69: 42.7 | F69: 11 | G69: 1134 | H69: 37
A70: 46113 | B70: Tp-vendas-abo-05.02 | C70: UGC-04-Interesses-12.03 | D70: UGC-Hook3 | E70: 16.35 | F70: 9 | G70: 718 | H70: 17
A71: 46113 | B71: Tp-vendas-abo-05.02 | C71: UGC-02-Interesses-09.02 | D71: UGC-hook2 | E71: 0 | G71: 0 | H71: 0 | I71: 1 | J71: 107.4
A72: 46113 | B72: Tp-vendas-abo-05.02 | C72: UGC-02-Interesses-09.02 | D72: UGC-Hook3 | E72: 34.91 | F72: 13 | G72: 1260 | H72: 25 | I72: 2 | J72: 385.3
A73: 46112 | B73: Tp-vendas-abo-05.02 | C73: UGC-04-Interesses-12.03 | D73: UGC-hook2 | E73: 0 | G73: 0 | H73: 0
A74: 46111 | B74: Tp-vendas-abo-05.02 | C74: UGC-04-Interesses-12.03 | D74: UGC-hook2 | E74: 0 | G74: 0 | H74: 0
A75: 46109 | B75: Tp-vendas-abo-05.02 | C75: UGC-04-Interesses-12.03 | D75: UGC-hook2 | E75: 9.18 | F75: 3 | G75: 184 | H75: 7
A76: 46109 | B76: Tp-vendas-abo-05.02 | C76: UGC-04-Interesses-12.03 | D76: UGC-Hook3 | E76: 0.01 | F76: 1 | G76: 3 | H76: 1
A77: 46109 | B77: Tp-vendas-abo-05.02 | C77: UGC-02-Interesses-09.02 | D77: UGC-hook2 | E77: 4.94 | F77: 3 | G77: 71 | H77: 3
A78: 46108 | B78: Tp-vendas-abo-05.02 | C78: UGC-04-Interesses-12.03 | D78: UGC-hook2 | E78: 38.29 | F78: 10 | G78: 1018 | H78: 25 | I78: 2 | J78: 179
A79: 46108 | B79: Tp-vendas-abo-05.02 | C79: UGC-04-Interesses-12.03 | D79: UGC-Hook3 | E79: 1.16 | G79: 20 | H79: 0
A80: 46108 | B80: Tp-vendas-abo-05.02 | C80: UGC-02-Interesses-09.02 | D80: UGC-hook2 | E80: 10.72 | F80: 2 | G80: 164 | H80: 6
A81: 46108 | B81: Tp-vendas-abo-05.02 | C81: UGC-02-Interesses-09.02 | D81: UGC-Hook3 | E81: 12.16 | F81: 3 | G81: 352 | H81: 6
A82: 46107 | B82: Tp-vendas-abo-05.02 | C82: UGC-04-Interesses-12.03 | D82: UGC-hook2 | E82: 42.7 | F82: 18 | G82: 1064 | H82: 47 | I82: 2 | J82: 322.2
A83: 46107 | B83: Tp-vendas-abo-05.02 | C83: UGC-04-Interesses-12.03 | D83: UGC-Hook3 | E83: 1.44 | G83: 35 | H83: 0
A84: 46107 | B84: Tp-vendas-abo-05.02 | C84: UGC-02-Interesses-09.02 | D84: UGC-hook2 | E84: 6.23 | F84: 1 | G84: 108 | H84: 2
A85: 46107 | B85: Tp-vendas-abo-05.02 | C85: UGC-02-Interesses-09.02 | D85: UGC-Hook3 | E85: 15.91 | F85: 7 | G85: 468 | H85: 16 | I85: 1 | J85: 190.8
A86: 46106 | B86: Tp-vendas-abo-05.02 | C86: UGC-04-Interesses-12.03 | D86: UGC-hook2 | E86: 38.45 | F86: 15 | G86: 1027 | H86: 33 | I86: 3 | J86: 375.9
A87: 46106 | B87: Tp-vendas-abo-05.02 | C87: UGC-04-Interesses-12.03 | D87: UGC-Hook3 | E87: 0.63 | F87: 3 | G87: 15 | H87: 2
A88: 46106 | B88: Tp-vendas-abo-05.02 | C88: UGC-02-Interesses-09.02 | D88: UGC-hook2 | E88: 0.08 | G88: 4 | H88: 0
A89: 46106 | B89: Tp-vendas-abo-05.02 | C89: UGC-02-Interesses-09.02 | D89: UGC-Hook3 | E89: 27.61 | F89: 8 | G89: 741 | H89: 18
A90: 46105 | B90: Tp-vendas-abo-05.02 | C90: UGC-04-Interesses-12.03 | D90: UGC-hook2 | E90: 31.61 | F90: 6 | G90: 956 | H90: 32
A91: 46105 | B91: Tp-vendas-abo-05.02 | C91: UGC-04-Interesses-12.03 | D91: UGC-Hook3 | E91: 1.59 | G91: 41 | H91: 1 | I91: 1 | J91: 107.4
A92: 46105 | B92: Tp-vendas-abo-05.02 | C92: UGC-02-Interesses-09.02 | D92: UGC-hook2 | E92: 0.07 | G92: 1 | H92: 0
A93: 46105 | B93: Tp-vendas-abo-05.02 | C93: UGC-02-Interesses-09.02 | D93: UGC-Hook3 | E93: 41.43 | F93: 13 | G93: 1071 | H93: 32 | I93: 1 | J93: 277.9
A94: 46104 | B94: Tp-vendas-abo-05.02 | C94: UGC-04-Interesses-12.03 | D94: UGC-hook2 | E94: 22.61 | F94: 10 | G94: 658 | H94: 32 | I94: 1 | J94: 107.4
A95: 46104 | B95: Tp-vendas-abo-05.02 | C95: UGC-02-Interesses-09.02 | D95: UGC-hook2 | E95: 2.98 | G95: 86 | H95: 5
A96: 46104 | B96: Tp-vendas-abo-05.02 | C96: UGC-02-Interesses-09.02 | D96: UGC-Hook3 | E96: 28.77 | F96: 4 | G96: 994 | H96: 24
A97: 46103 | B97: Tp-vendas-abo-05.02 | C97: UGC-04-Interesses-12.03 | D97: UGC-hook2 | E97: 25 | F97: 7 | G97: 682 | H97: 22
A98: 46103 | B98: Tp-vendas-abo-05.02 | C98: UGC-04-Interesses-12.03 | D98: UGC-Hook3 | E98: 1.59 | G98: 51 | H98: 0 | I98: 1 | J98: 107.4
A99: 46103 | B99: Tp-vendas-abo-05.02 | C99: UGC-02-Interesses-09.02 | D99: UGC-Hook3 | E99: 43.64 | F99: 12 | G99: 1175 | H99: 34
A100: 46102 | B100: Tp-vendas-abo-05.02 | C100: UGC-04-Interesses-12.03 | D100: UGC-hook2 | E100: 20.8 | F100: 8 | G100: 503 | H100: 18
...

Sheet ADV - GG
A1: Data | B1: Campanha | C1: Valor Investido | D1: Impressões | E1: Cliques | F1: DATA | G1: CAMPANHA | H1: CONVERSÕES | I1: ALL. CONV VALUE

Sheet ADV - GA4
A1: Data | B1: Usuarios | C1: Sessões
A2: 46129 | B2: 1 | C2: 1
A3: 46128 | B3: 7 | C3: 7
A4: 46127 | B4: 6 | C4: 6
A5: 46126 | B5: 2 | C5: 2
A6: 46125 | B6: 4 | C6: 4
A7: 46124 | B7: 5 | C7: 5
A8: 46123 | B8: 1 | C8: 1
A9: 46122 | B9: 1 | C9: 1
A10: 46121 | B10: 1 | C10: 1
A11: 46120 | B11: 3 | C11: 3
A12: 46119 | B12: 2 | C12: 2
A13: 46118 | B13: 8 | C13: 9
... A169: 45957 | B169: 14 | C169: 15

Sheet Calendário Agosto
B1: AGOSTO 2026
B3: SEGUNDA-FEIRA | C3: TERÇA-FEIRA | D3: QUARTA-FEIRA | E3: QUINTA-FEIRA | F3: SEXTA-FEIRA | G3: SÁBADO | H3: DOMINGO | J3: LEGENDA:
E4: 1 | F4: 2 | G4: 3 | H4: 4 | J4: Feriados
J5: Datas de nicho
B6: 5 | C6: 6 | D6: 7 | E6: 8 | F6: 9 | G6: 10 | H6: 11 | J6: Datas Importantes
H7: Dia dos Pais | J7: Essenciais no E-commerce
B8: 12 | C8: 13 | D8: 14 | E8: 15 | F8: 16 | G8: 17 | H8: 18 | J8: Aquecimento
E9: Dia do Homem
B10: 19 | C10: 20 | D10: 21 | E10: 22 | F10: 23 | G10: 24 | H10: 25
B12: 26 | C12: 27 | D12: 28 | E12: 29 | F12: 30 | G12: 31
B15: OBSERVAÇÕES:

Sheet Calendário Setembro
B1: SETEMBRO 2026
B3: SEGUNDA-FEIRA | C3: TERÇA-FEIRA | D3: QUARTA-FEIRA | E3: QUINTA-FEIRA | F3: SEXTA-FEIRA | G3: SÁBADO | H3: DOMINGO | J3: LEGENDA:
H4: 1 | J4: Feriados
J5: Datas de nicho
B6: 2 | C6: 3 | D6: 4 | E6: 5 | F6: 6 | G6: 7 | H6: 8 | J6: Datas Importantes
G7: Independência do Brasil | J7: Essenciais no E-commerce
B8: 9 | C8: 10 | D8: 11 | E8: 12 | F8: 13 | G8: 14 | H8: 15 | J8: Aquecimento
H9: Dia do Cliente
B10: 16 | C10: 17 | D10: 18 | E10: 19 | F10: 20 | G10: 21 | H10: 22
H11: Dia Mundial Sem Carro
B12: 23 | C12: 24 | D12: 25 | E12: 26 | F12: 27 | G12: 28 | H12: 29
B14: 30
B17: OBSERVAÇÕES:

Sheet Calendário Outubro
B1: OUTUBRO 2026
B3: SEGUNDA-FEIRA | C3: TERÇA-FEIRA | D3: QUARTA-FEIRA | E3: QUINTA-FEIRA | F3: SEXTA-FEIRA | G3: SÁBADO | H3: DOMINGO | J3: LEGENDA:
C4: 1 | D4: 2 | E4: 3 | F4: 4 | G4: 5 | H4: 6 | J4: Feriados
J5: Datas de nicho
B6: 7 | C6: 8 | D6: 9 | E6: 10 | F6: 11 | G6: 12 | H6: 13 | J6: Datas Importantes
G7: Dia das Crianças | J7: Essenciais no E-commerce
B8: 14 | C8: 15 | D8: 16 | E8: 17 | F8: 18 | G8: 19 | H8: 20 | J8: Aquecimento
B10: 21 | C10: 22 | D10: 23 | E10: 24 | F10: 25 | G10: 26 | H10: 27
B12: 28 | C12: 29 | D12: 30 | E12: 31
E13: Dia das Bruxas
B15: OBSERVAÇÕES:

Sheet Calendário Novembro
B1: NOVEMBRO 2026
B3: SEGUNDA-FEIRA | C3: TERÇA-FEIRA | D3: QUARTA-FEIRA | E3: QUINTA-FEIRA | F3: SEXTA-FEIRA | G3: SÁBADO | H3: DOMINGO | J3: LEGENDA:
F4: 1 | G4: 2 | H4: 3 | J4: Feriados
J5: Datas de nicho
B6: 4 | C6: 5 | D6: 6 | E6: 7 | F6: 8 | G6: 9 | H6: 10 | J6: Datas Importantes
J7: Essenciais no E-commerce
B8: 11 | C8: 12 | D8: 13 | E8: 14 | F8: 15 | G8: 16 | H8: 17 | J8: Aquecimento
B10: 18 | C10: 19 | D10: 20 | E10: 21 | F10: 22 | G10: 23 | H10: 24
F11: Black Friday
B12: 25 | C12: 26 | D12: 27 | E12: 28 | F12: 29 | G12: 30
B13: Cyber Monday
B15: OBSERVAÇÕES:

Sheet Calendário Dezembro
B1: DEZEMBRO 2026
B3: SEGUNDA-FEIRA | C3: TERÇA-FEIRA | D3: QUARTA-FEIRA | E3: QUINTA-FEIRA | F3: SEXTA-FEIRA | G3: SÁBADO | H3: DOMINGO | J3: LEGENDA:
H4: 1 | J4: Feriados
J5: Datas de nicho
B6: 2 | C6: 3 | D6: 4 | E6: 5 | F6: 6 | G6: 7 | H6: 8 | J6: Datas Importantes
J7: Essenciais no E-commerce
B8: 9 | C8: 10 | D8: 11 | E8: 12 | F8: 13 | G8: 14 | H8: 15 | J8: Aquecimento
B10: 16 | C10: 17 | D10: 18 | E10: 19 | F10: 20 | G10: 21 | H10: 22
B12: 23 | C12: 24 | D12: 25 | E12: 26 | F12: 27 | G12: 28 | H12: 29
D13: Natal
B14: 30 | C14: 31
C15: Ano Novo
B17: OBSERVAÇÕES:
