Workbook
Name zsupermetrics_forceRefresh: #REF!
Name zsupermetrics_refreshAllSilent: #REF!
Name zsupermetrics_refreshAll: #REF!

Sheet Acompanhamento Geral
A1: DATA | B1: DIA | C1: AÇÃO DO DIA | D1: VALOR INVESTIDO | E1: LEADS | F1: CPL | G1: LEADS QUALIFICADOS | H1: VENDAS | I1: VALOR DE VENDA | J1: SESSÕES | K1: CPS | L1: TAXA DE CONVERSÃO P/ LEAD | M1: META INVESTIMENTO | N1: META LEADS | O1: CPL META | P1: CPS META | Q1: META SESSÕES | R1: META TAXA DE CONVERSÃO P/LEAD
A2: JANEIRO | B2: 31 | D2: =IFERROR(SUM(D3:D33),"") -> 2003.14 | E2: =iferror(SUM(E3:E33),"") -> 382 | F2: =IFERROR(D2/E2,"") -> 5.243822 | G2: =iferror(SUM(G3:G33),"") -> 0 | H2: =iferror(SUM(H3:H33),"") -> 0 | I2: =iferror(SUM(I3:I33),"") -> 0 | J2: =IFERROR(SUM(J3:J33),"") -> 0 | K2: =iferror(D2/J2,"") | L2: =iferror(E2/J2,"") | M2: =iferror(Planejador!$I$4,"") | N2: =iferror(Planejador!$I$11,"") | O2: =iferror(Planejador!$I$13,"") | P2: =iferror(Planejador!$I$5,"") | Q2: =iferror(Planejador!$I$10,"") | R2: =Iferror(Planejador!$I$7,"")
A3: 46023 | B3: quinta-feira | D3: =SUMIF('ADV - GG'!A:A,A3,'ADV - GG'!C:C)+SUMIF('ADV - FB'!A:A,$A3,'ADV - FB'!E:E) -> 82.16 | E3: =SUMIF('ADV - GG'!A:A,A3,'ADV - GG'!H:H)+SUMIF('ADV - FB'!A:A,$A3,'ADV - FB'!I:I)+SUMIF('ADV - FB'!A:A,$A3,'ADV - FB'!J:J)+SUMIF('ADV - FB'!A:A,$A3,'ADV - FB'!K:K) -> 14 | F3: =IFERROR(D3/E3,"") -> 5.8685714 | J3: =SUMIF('ADV - GA4'!A:A,A3,'ADV - GA4'!C:C) -> 0 | K3: =IFERROR(D3/J3,"") | L3: =iferror(E3/J3,"") | M3: =iferror($M$2/$B$2,"") -> 0 | N3: =iferror($N$2/$B$2,"") -> 0 | O3: =iferror(Planejador!$I$13,"") | P3: =Planejador!$I$5 | Q3: =iferror($Q$2/$B$2,"") -> 0 | R3: =Planejador!$I$7
A4: 46024 | B4: sexta-feira | D4: =SUMIF('ADV - GG'!A:A,A4,'ADV - GG'!C:C)+SUMIF('ADV - FB'!A:A,$A4,'ADV - FB'!E:E) -> 83.78 | E4: =SUMIF('ADV - GG'!A:A,A4,'ADV - GG'!H:H)+SUMIF('ADV - FB'!A:A,$A4,'ADV - FB'!I:I)+SUMIF('ADV - FB'!A:A,$A4,'ADV - FB'!J:J)+SUMIF('ADV - FB'!A:A,$A4,'ADV - FB'!K:K) -> 20 | F4: =IFERROR(D4/E4,"") -> 4.189 | J4: =SUMIF('ADV - GA4'!A:A,A4,'ADV - GA4'!C:C) -> 0 | K4: =IFERROR(D4/J4,"") | L4: =iferror(E4/J4,"") | M4: =iferror($M$2/$B$2,"") -> 0 | N4: =iferror($N$2/$B$2,"") -> 0 | O4: =iferror(Planejador!$I$13,"") | P4: =Planejador!$I$5 | Q4: =iferror($Q$2/$B$2,"") -> 0 | R4: =Planejador!$I$7
A5: 46025 | B5: sábado | D5: =SUMIF('ADV - GG'!A:A,A5,'ADV - GG'!C:C)+SUMIF('ADV - FB'!A:A,$A5,'ADV - FB'!E:E) -> 78.33 | E5: =SUMIF('ADV - GG'!A:A,A5,'ADV - GG'!H:H)+SUMIF('ADV - FB'!A:A,$A5,'ADV - FB'!I:I)+SUMIF('ADV - FB'!A:A,$A5,'ADV - FB'!J:J)+SUMIF('ADV - FB'!A:A,$A5,'ADV - FB'!K:K) -> 20 | F5: =IFERROR(D5/E5,"") -> 3.9165 | J5: =SUMIF('ADV - GA4'!A:A,A5,'ADV - GA4'!C:C) -> 0 | K5: =IFERROR(D5/J5,"") | L5: =iferror(E5/J5,"") | M5: =iferror($M$2/$B$2,"") -> 0 | N5: =iferror($N$2/$B$2,"") -> 0 | O5: =iferror(Planejador!$I$13,"") | P5: =Planejador!$I$5 | Q5: =iferror($Q$2/$B$2,"") -> 0 | R5: =Planejador!$I$7
A6: 46026 | B6: domingo | D6: =SUMIF('ADV - GG'!A:A,A6,'ADV - GG'!C:C)+SUMIF('ADV - FB'!A:A,$A6,'ADV - FB'!E:E) -> 85.09 | E6: =SUMIF('ADV - GG'!A:A,A6,'ADV - GG'!H:H)+SUMIF('ADV - FB'!A:A,$A6,'ADV - FB'!I:I)+SUMIF('ADV - FB'!A:A,$A6,'ADV - FB'!J:J)+SUMIF('ADV - FB'!A:A,$A6,'ADV - FB'!K:K) -> 19 | F6: =IFERROR(D6/E6,"") -> 4.4784211 | J6: =SUMIF('ADV - GA4'!A:A,A6,'ADV - GA4'!C:C) -> 0 | K6: =IFERROR(D6/J6,"") | L6: =iferror(E6/J6,"") | M6: =iferror($M$2/$B$2,"") -> 0 | N6: =iferror($N$2/$B$2,"") -> 0 | O6: =iferror(Planejador!$I$13,"") | P6: =Planejador!$I$5 | Q6: =iferror($Q$2/$B$2,"") -> 0 | R6: =Planejador!$I$7
A7: 46027 | B7: segunda-feira | D7: =SUMIF('ADV - GG'!A:A,A7,'ADV - GG'!C:C)+SUMIF('ADV - FB'!A:A,$A7,'ADV - FB'!E:E) -> 76.3 | E7: =SUMIF('ADV - GG'!A:A,A7,'ADV - GG'!H:H)+SUMIF('ADV - FB'!A:A,$A7,'ADV - FB'!I:I)+SUMIF('ADV - FB'!A:A,$A7,'ADV - FB'!J:J)+SUMIF('ADV - FB'!A:A,$A7,'ADV - FB'!K:K) -> 11 | F7: =IFERROR(D7/E7,"") -> 6.9363636 | J7: =SUMIF('ADV - GA4'!A:A,A7,'ADV - GA4'!C:C) -> 0 | K7: =IFERROR(D7/J7,"") | L7: =iferror(E7/J7,"") | M7: =iferror($M$2/$B$2,"") -> 0 | N7: =iferror($N$2/$B$2,"") -> 0 | O7: =iferror(Planejador!$I$13,"") | P7: =Planejador!$I$5 | Q7: =iferror($Q$2/$B$2,"") -> 0 | R7: =Planejador!$I$7
A8: 46028 | B8: terça-feira | D8: =SUMIF('ADV - GG'!A:A,A8,'ADV - GG'!C:C)+SUMIF('ADV - FB'!A:A,$A8,'ADV - FB'!E:E) -> 81.59 | E8: =SUMIF('ADV - GG'!A:A,A8,'ADV - GG'!H:H)+SUMIF('ADV - FB'!A:A,$A8,'ADV - FB'!I:I)+SUMIF('ADV - FB'!A:A,$A8,'ADV - FB'!J:J)+SUMIF('ADV - FB'!A:A,$A8,'ADV - FB'!K:K) -> 19 | F8: =IFERROR(D8/E8,"") -> 4.2942105 | J8: =SUMIF('ADV - GA4'!A:A,A8,'ADV - GA4'!C:C) -> 0 | K8: =IFERROR(D8/J8,"") | L8: =iferror(E8/J8,"") | M8: =iferror($M$2/$B$2,"") -> 0 | N8: =iferror($N$2/$B$2,"") -> 0 | O8: =iferror(Planejador!$I$13,"") | P8: =Planejador!$I$5 | Q8: =iferror($Q$2/$B$2,"") -> 0 | R8: =Planejador!$I$7
A9: 46029 | B9: quarta-feira | D9: =SUMIF('ADV - GG'!A:A,A9,'ADV - GG'!C:C)+SUMIF('ADV - FB'!A:A,$A9,'ADV - FB'!E:E) -> 79.41 | E9: =SUMIF('ADV - GG'!A:A,A9,'ADV - GG'!H:H)+SUMIF('ADV - FB'!A:A,$A9,'ADV - FB'!I:I)+SUMIF('ADV - FB'!A:A,$A9,'ADV - FB'!J:J)+SUMIF('ADV - FB'!A:A,$A9,'ADV - FB'!K:K) -> 13 | F9: =IFERROR(D9/E9,"") -> 6.1084615 | J9: =SUMIF('ADV - GA4'!A:A,A9,'ADV - GA4'!C:C) -> 0 | K9: =IFERROR(D9/J9,"") | L9: =iferror(E9/J9,"") | M9: =iferror($M$2/$B$2,"") -> 0 | N9: =iferror($N$2/$B$2,"") -> 0 | O9: =iferror(Planejador!$I$13,"") | P9: =Planejador!$I$5 | Q9: =iferror($Q$2/$B$2,"") -> 0 | R9: =Planejador!$I$7
A10: 46030 | B10: quinta-feira | D10: =SUMIF('ADV - GG'!A:A,A10,'ADV - GG'!C:C)+SUMIF('ADV - FB'!A:A,$A10,'ADV - FB'!E:E) -> 83.06 | E10: =SUMIF('ADV - GG'!A:A,A10,'ADV - GG'!H:H)+SUMIF('ADV - FB'!A:A,$A10,'ADV - FB'!I:I)+SUMIF('ADV - FB'!A:A,$A10,'ADV - FB'!J:J)+SUMIF('ADV - FB'!A:A,$A10,'ADV - FB'!K:K) -> 8 | F10: =IFERROR(D10/E10,"") -> 10.3825 | J10: =SUMIF('ADV - GA4'!A:A,A10,'ADV - GA4'!C:C) -> 0 | K10: =IFERROR(D10/J10,"") | L10: =iferror(E10/J10,"") | M10: =iferror($M$2/$B$2,"") -> 0 | N10: =iferror($N$2/$B$2,"") -> 0 | O10: =iferror(Planejador!$I$13,"") | P10: =Planejador!$I$5 | Q10: =iferror($Q$2/$B$2,"") -> 0 | R10: =Planejador!$I$7
A11: 46031 | B11: sexta-feira | D11: =SUMIF('ADV - GG'!A:A,A11,'ADV - GG'!C:C)+SUMIF('ADV - FB'!A:A,$A11,'ADV - FB'!E:E) -> 77.34 | E11: =SUMIF('ADV - GG'!A:A,A11,'ADV - GG'!H:H)+SUMIF('ADV - FB'!A:A,$A11,'ADV - FB'!I:I)+SUMIF('ADV - FB'!A:A,$A11,'ADV - FB'!J:J)+SUMIF('ADV - FB'!A:A,$A11,'ADV - FB'!K:K) -> 14 | F11: =IFERROR(D11/E11,"") -> 5.5242857 | J11: =SUMIF('ADV - GA4'!A:A,A11,'ADV - GA4'!C:C) -> 0 | K11: =IFERROR(D11/J11,"") | L11: =iferror(E11/J11,"") | M11: =iferror($M$2/$B$2,"") -> 0 | N11: =iferror($N$2/$B$2,"") -> 0 | O11: =iferror(Planejador!$I$13,"") | P11: =Planejador!$I$5 | Q11: =iferror($Q$2/$B$2,"") -> 0 | R11: =Planejador!$I$7
A12: 46032 | B12: sábado | D12: =SUMIF('ADV - GG'!A:A,A12,'ADV - GG'!C:C)+SUMIF('ADV - FB'!A:A,$A12,'ADV - FB'!E:E) -> 75.27 | E12: =SUMIF('ADV - GG'!A:A,A12,'ADV - GG'!H:H)+SUMIF('ADV - FB'!A:A,$A12,'ADV - FB'!I:I)+SUMIF('ADV - FB'!A:A,$A12,'ADV - FB'!J:J)+SUMIF('ADV - FB'!A:A,$A12,'ADV - FB'!K:K) -> 11 | F12: =IFERROR(D12/E12,"") -> 6.8427273 | J12: =SUMIF('ADV - GA4'!A:A,A12,'ADV - GA4'!C:C) -> 0 | K12: =IFERROR(D12/J12,"") | L12: =iferror(E12/J12,"") | M12: =iferror($M$2/$B$2,"") -> 0 | N12: =iferror($N$2/$B$2,"") -> 0 | O12: =iferror(Planejador!$I$13,"") | P12: =Planejador!$I$5 | Q12: =iferror($Q$2/$B$2,"") -> 0 | R12: =Planejador!$I$7
A13: 46033 | B13: domingo | D13: =SUMIF('ADV - GG'!A:A,A13,'ADV - GG'!C:C)+SUMIF('ADV - FB'!A:A,$A13,'ADV - FB'!E:E) -> 78.85 | E13: =SUMIF('ADV - GG'!A:A,A13,'ADV - GG'!H:H)+SUMIF('ADV - FB'!A:A,$A13,'ADV - FB'!I:I)+SUMIF('ADV - FB'!A:A,$A13,'ADV - FB'!J:J)+SUMIF('ADV - FB'!A:A,$A13,'ADV - FB'!K:K) -> 19 | F13: =IFERROR(D13/E13,"") -> 4.15 | J13: =SUMIF('ADV - GA4'!A:A,A13,'ADV - GA4'!C:C) -> 0 | K13: =IFERROR(D13/J13,"") | L13: =iferror(E13/J13,"") | M13: =iferror($M$2/$B$2,"") -> 0 | N13: =iferror($N$2/$B$2,"") -> 0 | O13: =iferror(Planejador!$I$13,"") | P13: =Planejador!$I$5 | Q13: =iferror($Q$2/$B$2,"") -> 0 | R13: =Planejador!$I$7
A14: 46034 | B14: segunda-feira | D14: =SUMIF('ADV - GG'!A:A,A14,'ADV - GG'!C:C)+SUMIF('ADV - FB'!A:A,$A14,'ADV - FB'!E:E) -> 72.4 | E14: =SUMIF('ADV - GG'!A:A,A14,'ADV - GG'!H:H)+SUMIF('ADV - FB'!A:A,$A14,'ADV - FB'!I:I)+SUMIF('ADV - FB'!A:A,$A14,'ADV - FB'!J:J)+SUMIF('ADV - FB'!A:A,$A14,'ADV - FB'!K:K) -> 9 | F14: =IFERROR(D14/E14,"") -> 8.0444444 | J14: =SUMIF('ADV - GA4'!A:A,A14,'ADV - GA4'!C:C) -> 0 | K14: =IFERROR(D14/J14,"") | L14: =iferror(E14/J14,"") | M14: =iferror($M$2/$B$2,"") -> 0 | N14: =iferror($N$2/$B$2,"") -> 0 | O14: =iferror(Planejador!$I$13,"") | P14: =Planejador!$I$5 | Q14: =iferror($Q$2/$B$2,"") -> 0 | R14: =Planejador!$I$7
... A33: 46053 | B33: sábado | D33: =SUMIF('ADV - GG'!A:A,A33,'ADV - GG'!C:C)+SUMIF('ADV - FB'!A:A,$A33,'ADV - FB'!E:E) -> 53.55 | E33: =SUMIF('ADV - GG'!A:A,A33,'ADV - GG'!H:H)+SUMIF('ADV - FB'!A:A,$A33,'ADV - FB'!I:I)+SUMIF('ADV - FB'!A:A,$A33,'ADV - FB'!J:J)+SUMIF('ADV - FB'!A:A,$A33,'ADV - FB'!K:K) -> 3 | F33: =IFERROR(D33/E33,"") -> 17.85 | J33: =SUMIF('ADV - GA4'!A:A,A33,'ADV - GA4'!C:C) -> 0 | K33: =IFERROR(D33/J33,"") | L33: =iferror(E33/J33,"") | M33: =iferror($M$2/$B$2,"") -> 0 | N33: =iferror($N$2/$B$2,"") -> 0 | O33: =iferror(Planejador!$I$13,"") | P33: =Planejador!$I$5 | Q33: =iferror($Q$2/$B$2,"") -> 0 | R33: =Planejador!$I$7
A34: FEVEREIRO | B34: =COUNTA(A35:A62) -> 28 | D34: =IFERROR(SUM(D35:D62),"") -> 1840.12 | E34: =iferror(SUM(E35:E62),"") -> 250 | F34: =IFERROR(D34/E34,"") -> 7.36048 | G34: =iferror(SUM(G35:G62),"") -> 0 | H34: =iferror(SUM(H35:H62),"") -> 0 | I34: =iferror(SUM(I35:I62),"") -> 0 | J34: =IFERROR(SUM(J35:J62),"") -> 0 | K34: =iferror(D34/J34,"") | L34: =iferror(E34/J34,"") | M34: =iferror(Planejador!$I$27,"") | N34: =iferror(Planejador!$I$34,"") | O34: =iferror(Planejador!$I$36,"") | P34: =iferror(Planejador!$I$28,"") | Q34: =iferror(Planejador!$I$33,"") | R34: =Iferror(Planejador!$I$30,"")
A35: 46054 | B35: =TEXT(A35,"dddd") -> domingo | D35: =SUMIF('ADV - GG'!A:A,A35,'ADV - GG'!C:C)+SUMIF('ADV - FB'!A:A,$A35,'ADV - FB'!E:E) -> 60.4 | E35: =SUMIF('ADV - GG'!A:A,A35,'ADV - GG'!H:H)+SUMIF('ADV - FB'!A:A,$A35,'ADV - FB'!I:I)+SUMIF('ADV - FB'!A:A,$A35,'ADV - FB'!J:J)+SUMIF('ADV - FB'!A:A,$A35,'ADV - FB'!K:K) -> 6 | F35: =IFERROR(D35/E35,"") -> 10.066667 | J35: =SUMIF('ADV - GA4'!A:A,A35,'ADV - GA4'!C:C) -> 0 | K35: =IFERROR(D35/J35,"") | L35: =iferror(E35/J35,"") | M35: =$M$34/$B$34 -> 0 | N35: =iferror($N$34/$B$34,"") -> 0 | O35: =iferror(Planejador!$I$36,"") | P35: =Planejador!$I$28 | Q35: =iferror($Q$34/$B$34,"") -> 0 | R35: =Planejador!$I$30
A36: 46055 | B36: =TEXT(A36,"dddd") -> segunda-feira | D36: =SUMIF('ADV - GG'!A:A,A36,'ADV - GG'!C:C)+SUMIF('ADV - FB'!A:A,$A36,'ADV - FB'!E:E) -> 58.38 | E36: =SUMIF('ADV - GG'!A:A,A36,'ADV - GG'!H:H)+SUMIF('ADV - FB'!A:A,$A36,'ADV - FB'!I:I)+SUMIF('ADV - FB'!A:A,$A36,'ADV - FB'!J:J)+SUMIF('ADV - FB'!A:A,$A36,'ADV - FB'!K:K) -> 9 | F36: =IFERROR(D36/E36,"") -> 6.4866667 | J36: =SUMIF('ADV - GA4'!A:A,A36,'ADV - GA4'!C:C) -> 0 | K36: =IFERROR(D36/J36,"") | L36: =iferror(E36/J36,"") | M36: =$M$34/$B$34 -> 0 | N36: =iferror($N$34/$B$34,"") -> 0 | O36: =iferror(Planejador!$I$36,"") | P36: =Planejador!$I$28 | Q36: =iferror($Q$34/$B$34,"") -> 0 | R36: =Planejador!$I$30
A37: 46056 | B37: =TEXT(A37,"dddd") -> terça-feira | D37: =SUMIF('ADV - GG'!A:A,A37,'ADV - GG'!C:C)+SUMIF('ADV - FB'!A:A,$A37,'ADV - FB'!E:E) -> 59.4 | E37: =SUMIF('ADV - GG'!A:A,A37,'ADV - GG'!H:H)+SUMIF('ADV - FB'!A:A,$A37,'ADV - FB'!I:I)+SUMIF('ADV - FB'!A:A,$A37,'ADV - FB'!J:J)+SUMIF('ADV - FB'!A:A,$A37,'ADV - FB'!K:K) -> 13 | F37: =IFERROR(D37/E37,"") -> 4.5692308 | J37: =SUMIF('ADV - GA4'!A:A,A37,'ADV - GA4'!C:C) -> 0 | K37: =IFERROR(D37/J37,"") | L37: =iferror(E37/J37,"") | M37: =$M$34/$B$34 -> 0 | N37: =iferror($N$34/$B$34,"") -> 0 | O37: =iferror(Planejador!$I$36,"") | P37: =Planejador!$I$28 | Q37: =iferror($Q$34/$B$34,"") -> 0 | R37: =Planejador!$I$30
A38: 46057 | B38: =TEXT(A38,"dddd") -> quarta-feira | D38: =SUMIF('ADV - GG'!A:A,A38,'ADV - GG'!C:C)+SUMIF('ADV - FB'!A:A,$A38,'ADV - FB'!E:E) -> 50.03 | E38: =SUMIF('ADV - GG'!A:A,A38,'ADV - GG'!H:H)+SUMIF('ADV - FB'!A:A,$A38,'ADV - FB'!I:I)+SUMIF('ADV - FB'!A:A,$A38,'ADV - FB'!J:J)+SUMIF('ADV - FB'!A:A,$A38,'ADV - FB'!K:K) -> 6 | F38: =IFERROR(D38/E38,"") -> 8.3383333 | J38: =SUMIF('ADV - GA4'!A:A,A38,'ADV - GA4'!C:C) -> 0 | K38: =IFERROR(D38/J38,"") | L38: =iferror(E38/J38,"") | M38: =$M$34/$B$34 -> 0 | N38: =iferror($N$34/$B$34,"") -> 0 | O38: =iferror(Planejador!$I$36,"") | P38: =Planejador!$I$28 | Q38: =iferror($Q$34/$B$34,"") -> 0 | R38: =Planejador!$I$30
A39: 46058 | B39: =TEXT(A39,"dddd") -> quinta-feira | D39: =SUMIF('ADV - GG'!A:A,A39,'ADV - GG'!C:C)+SUMIF('ADV - FB'!A:A,$A39,'ADV - FB'!E:E) -> 49.87 | E39: =SUMIF('ADV - GG'!A:A,A39,'ADV - GG'!H:H)+SUMIF('ADV - FB'!A:A,$A39,'ADV - FB'!I:I)+SUMIF('ADV - FB'!A:A,$A39,'ADV - FB'!J:J)+SUMIF('ADV - FB'!A:A,$A39,'ADV - FB'!K:K) -> 6 | F39: =IFERROR(D39/E39,"") -> 8.3116667 | J39: =SUMIF('ADV - GA4'!A:A,A39,'ADV - GA4'!C:C) -> 0 | K39: =IFERROR(D39/J39,"") | L39: =iferror(E39/J39,"") | M39: =$M$34/$B$34 -> 0 | N39: =iferror($N$34/$B$34,"") -> 0 | O39: =iferror(Planejador!$I$36,"") | P39: =Planejador!$I$28 | Q39: =iferror($Q$34/$B$34,"") -> 0 | R39: =Planejador!$I$30
A40: 46059 | B40: =TEXT(A40,"dddd") -> sexta-feira | D40: =SUMIF('ADV - GG'!A:A,A40,'ADV - GG'!C:C)+SUMIF('ADV - FB'!A:A,$A40,'ADV - FB'!E:E) -> 48.67 | E40: =SUMIF('ADV - GG'!A:A,A40,'ADV - GG'!H:H)+SUMIF('ADV - FB'!A:A,$A40,'ADV - FB'!I:I)+SUMIF('ADV - FB'!A:A,$A40,'ADV - FB'!J:J)+SUMIF('ADV - FB'!A:A,$A40,'ADV - FB'!K:K) -> 5 | F40: =IFERROR(D40/E40,"") -> 9.734 | J40: =SUMIF('ADV - GA4'!A:A,A40,'ADV - GA4'!C:C) -> 0 | K40: =IFERROR(D40/J40,"") | L40: =iferror(E40/J40,"") | M40: =$M$34/$B$34 -> 0 | N40: =iferror($N$34/$B$34,"") -> 0 | O40: =iferror(Planejador!$I$36,"") | P40: =Planejador!$I$28 | Q40: =iferror($Q$34/$B$34,"") -> 0 | R40: =Planejador!$I$30
A41: 46060 | B41: =TEXT(A41,"dddd") -> sábado | D41: =SUMIF('ADV - GG'!A:A,A41,'ADV - GG'!C:C)+SUMIF('ADV - FB'!A:A,$A41,'ADV - FB'!E:E) -> 49.12 | E41: =SUMIF('ADV - GG'!A:A,A41,'ADV - GG'!H:H)+SUMIF('ADV - FB'!A:A,$A41,'ADV - FB'!I:I)+SUMIF('ADV - FB'!A:A,$A41,'ADV - FB'!J:J)+SUMIF('ADV - FB'!A:A,$A41,'ADV - FB'!K:K) -> 6 | F41: =IFERROR(D41/E41,"") -> 8.1866667 | J41: =SUMIF('ADV - GA4'!A:A,A41,'ADV - GA4'!C:C) -> 0 | K41: =IFERROR(D41/J41,"") | L41: =iferror(E41/J41,"") | M41: =$M$34/$B$34 -> 0 | N41: =iferror($N$34/$B$34,"") -> 0 | O41: =iferror(Planejador!$I$36,"") | P41: =Planejador!$I$28 | Q41: =iferror($Q$34/$B$34,"") -> 0 | R41: =Planejador!$I$30
A42: 46061 | B42: =TEXT(A42,"dddd") -> domingo | D42: =SUMIF('ADV - GG'!A:A,A42,'ADV - GG'!C:C)+SUMIF('ADV - FB'!A:A,$A42,'ADV - FB'!E:E) -> 51.47 | E42: =SUMIF('ADV - GG'!A:A,A42,'ADV - GG'!H:H)+SUMIF('ADV - FB'!A:A,$A42,'ADV - FB'!I:I)+SUMIF('ADV - FB'!A:A,$A42,'ADV - FB'!J:J)+SUMIF('ADV - FB'!A:A,$A42,'ADV - FB'!K:K) -> 7 | F42: =IFERROR(D42/E42,"") -> 7.3528571 | J42: =SUMIF('ADV - GA4'!A:A,A42,'ADV - GA4'!C:C) -> 0 | K42: =IFERROR(D42/J42,"") | L42: =iferror(E42/J42,"") | M42: =$M$34/$B$34 -> 0 | N42: =iferror($N$34/$B$34,"") -> 0 | O42: =iferror(Planejador!$I$36,"") | P42: =Planejador!$I$28 | Q42: =iferror($Q$34/$B$34,"") -> 0 | R42: =Planejador!$I$30
A43: 46062 | B43: =TEXT(A43,"dddd") -> segunda-feira | D43: =SUMIF('ADV - GG'!A:A,A43,'ADV - GG'!C:C)+SUMIF('ADV - FB'!A:A,$A43,'ADV - FB'!E:E) -> 60.67 | E43: =SUMIF('ADV - GG'!A:A,A43,'ADV - GG'!H:H)+SUMIF('ADV - FB'!A:A,$A43,'ADV - FB'!I:I)+SUMIF('ADV - FB'!A:A,$A43,'ADV - FB'!J:J)+SUMIF('ADV - FB'!A:A,$A43,'ADV - FB'!K:K) -> 8 | F43: =IFERROR(D43/E43,"") -> 7.58375 | J43: =SUMIF('ADV - GA4'!A:A,A43,'ADV - GA4'!C:C) -> 0 | K43: =IFERROR(D43/J43,"") | L43: =iferror(E43/J43,"") | M43: =$M$34/$B$34 -> 0 | N43: =iferror($N$34/$B$34,"") -> 0 | O43: =iferror(Planejador!$I$36,"") | P43: =Planejador!$I$28 | Q43: =iferror($Q$34/$B$34,"") -> 0 | R43: =Planejador!$I$30
A44: 46063 | B44: =TEXT(A44,"dddd") -> terça-feira | D44: =SUMIF('ADV - GG'!A:A,A44,'ADV - GG'!C:C)+SUMIF('ADV - FB'!A:A,$A44,'ADV - FB'!E:E) -> 59.41 | E44: =SUMIF('ADV - GG'!A:A,A44,'ADV - GG'!H:H)+SUMIF('ADV - FB'!A:A,$A44,'ADV - FB'!I:I)+SUMIF('ADV - FB'!A:A,$A44,'ADV - FB'!J:J)+SUMIF('ADV - FB'!A:A,$A44,'ADV - FB'!K:K) -> 7 | F44: =IFERROR(D44/E44,"") -> 8.4871429 | J44: =SUMIF('ADV - GA4'!A:A,A44,'ADV - GA4'!C:C) -> 0 | K44: =IFERROR(D44/J44,"") | L44: =iferror(E44/J44,"") | M44: =$M$34/$B$34 -> 0 | N44: =iferror($N$34/$B$34,"") -> 0 | O44: =iferror(Planejador!$I$36,"") | P44: =Planejador!$I$28 | Q44: =iferror($Q$34/$B$34,"") -> 0 | R44: =Planejador!$I$30
A45: 46064 | B45: =TEXT(A45,"dddd") -> quarta-feira | D45: =SUMIF('ADV - GG'!A:A,A45,'ADV - GG'!C:C)+SUMIF('ADV - FB'!A:A,$A45,'ADV - FB'!E:E) -> 56.86 | E45: =SUMIF('ADV - GG'!A:A,A45,'ADV - GG'!H:H)+SUMIF('ADV - FB'!A:A,$A45,'ADV - FB'!I:I)+SUMIF('ADV - FB'!A:A,$A45,'ADV - FB'!J:J)+SUMIF('ADV - FB'!A:A,$A45,'ADV - FB'!K:K) -> 9 | F45: =IFERROR(D45/E45,"") -> 6.3177778 | J45: =SUMIF('ADV - GA4'!A:A,A45,'ADV - GA4'!C:C) -> 0 | K45: =IFERROR(D45/J45,"") | L45: =iferror(E45/J45,"") | M45: =$M$34/$B$34 -> 0 | N45: =iferror($N$34/$B$34,"") -> 0 | O45: =iferror(Planejador!$I$36,"") | P45: =Planejador!$I$28 | Q45: =iferror($Q$34/$B$34,"") -> 0 | R45: =Planejador!$I$30
A46: 46065 | B46: =TEXT(A46,"dddd") -> quinta-feira | D46: =SUMIF('ADV - GG'!A:A,A46,'ADV - GG'!C:C)+SUMIF('ADV - FB'!A:A,$A46,'ADV - FB'!E:E) -> 57.92 | E46: =SUMIF('ADV - GG'!A:A,A46,'ADV - GG'!H:H)+SUMIF('ADV - FB'!A:A,$A46,'ADV - FB'!I:I)+SUMIF('ADV - FB'!A:A,$A46,'ADV - FB'!J:J)+SUMIF('ADV - FB'!A:A,$A46,'ADV - FB'!K:K) -> 7 | F46: =IFERROR(D46/E46,"") -> 8.2742857 | J46: =SUMIF('ADV - GA4'!A:A,A46,'ADV - GA4'!C:C) -> 0 | K46: =IFERROR(D46/J46,"") | L46: =iferror(E46/J46,"") | M46: =$M$34/$B$34 -> 0 | N46: =iferror($N$34/$B$34,"") -> 0 | O46: =iferror(Planejador!$I$36,"") | P46: =Planejador!$I$28 | Q46: =iferror($Q$34/$B$34,"") -> 0 | R46: =Planejador!$I$30
... A62: 46081 | B62: =TEXT(A62,"dddd") -> sábado | D62: =SUMIF('ADV - GG'!A:A,A62,'ADV - GG'!C:C)+SUMIF('ADV - FB'!A:A,$A62,'ADV - FB'!E:E) -> 71.89 | E62: =SUMIF('ADV - GG'!A:A,A62,'ADV - GG'!H:H)+SUMIF('ADV - FB'!A:A,$A62,'ADV - FB'!I:I)+SUMIF('ADV - FB'!A:A,$A62,'ADV - FB'!J:J)+SUMIF('ADV - FB'!A:A,$A62,'ADV - FB'!K:K) -> 10 | F62: =IFERROR(D62/E62,"") -> 7.189 | J62: =SUMIF('ADV - GA4'!A:A,A62,'ADV - GA4'!C:C) -> 0 | K62: =IFERROR(D62/J62,"") | L62: =iferror(E62/J62,"") | M62: =$M$34/$B$34 -> 0 | N62: =iferror($N$34/$B$34,"") -> 0 | O62: =iferror(Planejador!$I$36,"") | P62: =Planejador!$I$28 | Q62: =iferror($Q$34/$B$34,"") -> 0 | R62: =Planejador!$I$30
A63: MARÇO | B63: 31 | D63: =IFERROR(SUM(D64:D94),"") -> 2070.09 | E63: =iferror(SUM(E64:E94),"") -> 214 | F63: =IFERROR(D63/E63,"") -> 9.6733178 | G63: =iferror(SUM(G64:G94),"") -> 0 | H63: =iferror(SUM(H64:H94),"") -> 0 | I63: =iferror(SUM(I64:I94),"") -> 0 | J63: =IFERROR(SUM(J64:J94),"") -> 0 | K63: =iferror(D63/J63,"") | L63: =iferror(E63/J63,"") | M63: =Planejador!$I$50 | N63: =iferror(Planejador!$I$57,"") | O63: =iferror(Planejador!$I$59,"") | P63: =iferror(Planejador!$I$51,"") | Q63: =iferror(Planejador!$I$56,"") | R63: =Iferror(Planejador!$I$53,"")
A64: 46082 | B64: =TEXT(A64,"dddd") -> domingo | D64: =SUMIF('ADV - GG'!A:A,A64,'ADV - GG'!C:C)+SUMIF('ADV - FB'!A:A,$A64,'ADV - FB'!E:E) -> 81.72 | E64: =SUMIF('ADV - GG'!A:A,A64,'ADV - GG'!H:H)+SUMIF('ADV - FB'!A:A,$A64,'ADV - FB'!I:I)+SUMIF('ADV - FB'!A:A,$A64,'ADV - FB'!J:J)+SUMIF('ADV - FB'!A:A,$A64,'ADV - FB'!K:K) -> 16 | F64: =IFERROR(D64/E64,"") -> 5.1075 | J64: =SUMIF('ADV - GA4'!A:A,A64,'ADV - GA4'!C:C) -> 0 | K64: =IFERROR(D64/J64,"") | L64: =iferror(E64/J64,"") | M64: =$M$63/$B$63 -> 0 | N64: =iferror($N$63/$B$63,"") -> 0 | O64: =iferror(Planejador!$I$59,"") | P64: =Planejador!$I$51 | Q64: =$Q$63/$B$63 -> 0 | R64: =Planejador!$I$53
A65: 46083 | B65: =TEXT(A65,"dddd") -> segunda-feira | D65: =SUMIF('ADV - GG'!A:A,A65,'ADV - GG'!C:C)+SUMIF('ADV - FB'!A:A,$A65,'ADV - FB'!E:E) -> 78.19 | E65: =SUMIF('ADV - GG'!A:A,A65,'ADV - GG'!H:H)+SUMIF('ADV - FB'!A:A,$A65,'ADV - FB'!I:I)+SUMIF('ADV - FB'!A:A,$A65,'ADV - FB'!J:J)+SUMIF('ADV - FB'!A:A,$A65,'ADV - FB'!K:K) -> 10 | F65: =IFERROR(D65/E65,"") -> 7.819 | J65: =SUMIF('ADV - GA4'!A:A,A65,'ADV - GA4'!C:C) -> 0 | K65: =IFERROR(D65/J65,"") | L65: =iferror(E65/J65,"") | M65: =$M$63/$B$63 -> 0 | N65: =iferror($N$63/$B$63,"") -> 0 | O65: =iferror(Planejador!$I$59,"") | P65: =Planejador!$I$51 | Q65: =$Q$63/$B$63 -> 0 | R65: =Planejador!$I$53
A66: 46084 | B66: =TEXT(A66,"dddd") -> terça-feira | D66: =SUMIF('ADV - GG'!A:A,A66,'ADV - GG'!C:C)+SUMIF('ADV - FB'!A:A,$A66,'ADV - FB'!E:E) -> 81.84 | E66: =SUMIF('ADV - GG'!A:A,A66,'ADV - GG'!H:H)+SUMIF('ADV - FB'!A:A,$A66,'ADV - FB'!I:I)+SUMIF('ADV - FB'!A:A,$A66,'ADV - FB'!J:J)+SUMIF('ADV - FB'!A:A,$A66,'ADV - FB'!K:K) -> 11 | F66: =IFERROR(D66/E66,"") -> 7.44 | J66: =SUMIF('ADV - GA4'!A:A,A66,'ADV - GA4'!C:C) -> 0 | K66: =IFERROR(D66/J66,"") | L66: =iferror(E66/J66,"") | M66: =$M$63/$B$63 -> 0 | N66: =iferror($N$63/$B$63,"") -> 0 | O66: =iferror(Planejador!$I$59,"") | P66: =Planejador!$I$51 | Q66: =$Q$63/$B$63 -> 0 | R66: =Planejador!$I$53
A67: 46085 | B67: =TEXT(A67,"dddd") -> quarta-feira | D67: =SUMIF('ADV - GG'!A:A,A67,'ADV - GG'!C:C)+SUMIF('ADV - FB'!A:A,$A67,'ADV - FB'!E:E) -> 72.64 | E67: =SUMIF('ADV - GG'!A:A,A67,'ADV - GG'!H:H)+SUMIF('ADV - FB'!A:A,$A67,'ADV - FB'!I:I)+SUMIF('ADV - FB'!A:A,$A67,'ADV - FB'!J:J)+SUMIF('ADV - FB'!A:A,$A67,'ADV - FB'!K:K) -> 5 | F67: =IFERROR(D67/E67,"") -> 14.528 | J67: =SUMIF('ADV - GA4'!A:A,A67,'ADV - GA4'!C:C) -> 0 | K67: =IFERROR(D67/J67,"") | L67: =iferror(E67/J67,"") | M67: =$M$63/$B$63 -> 0 | N67: =iferror($N$63/$B$63,"") -> 0 | O67: =iferror(Planejador!$I$59,"") | P67: =Planejador!$I$51 | Q67: =$Q$63/$B$63 -> 0 | R67: =Planejador!$I$53
A68: 46086 | B68: =TEXT(A68,"dddd") -> quinta-feira | D68: =SUMIF('ADV - GG'!A:A,A68,'ADV - GG'!C:C)+SUMIF('ADV - FB'!A:A,$A68,'ADV - FB'!E:E) -> 64.31 | E68: =SUMIF('ADV - GG'!A:A,A68,'ADV - GG'!H:H)+SUMIF('ADV - FB'!A:A,$A68,'ADV - FB'!I:I)+SUMIF('ADV - FB'!A:A,$A68,'ADV - FB'!J:J)+SUMIF('ADV - FB'!A:A,$A68,'ADV - FB'!K:K) -> 6 | F68: =IFERROR(D68/E68,"") -> 10.718333 | J68: =SUMIF('ADV - GA4'!A:A,A68,'ADV - GA4'!C:C) -> 0 | K68: =IFERROR(D68/J68,"") | L68: =iferror(E68/J68,"") | M68: =$M$63/$B$63 -> 0 | N68: =iferror($N$63/$B$63,"") -> 0 | O68: =iferror(Planejador!$I$59,"") | P68: =Planejador!$I$51 | Q68: =$Q$63/$B$63 -> 0 | R68: =Planejador!$I$53
A69: 46087 | B69: =TEXT(A69,"dddd") -> sexta-feira | D69: =SUMIF('ADV - GG'!A:A,A69,'ADV - GG'!C:C)+SUMIF('ADV - FB'!A:A,$A69,'ADV - FB'!E:E) -> 66.75 | E69: =SUMIF('ADV - GG'!A:A,A69,'ADV - GG'!H:H)+SUMIF('ADV - FB'!A:A,$A69,'ADV - FB'!I:I)+SUMIF('ADV - FB'!A:A,$A69,'ADV - FB'!J:J)+SUMIF('ADV - FB'!A:A,$A69,'ADV - FB'!K:K) -> 5 | F69: =IFERROR(D69/E69,"") -> 13.35 | J69: =SUMIF('ADV - GA4'!A:A,A69,'ADV - GA4'!C:C) -> 0 | K69: =IFERROR(D69/J69,"") | L69: =iferror(E69/J69,"") | M69: =$M$63/$B$63 -> 0 | N69: =iferror($N$63/$B$63,"") -> 0 | O69: =iferror(Planejador!$I$59,"") | P69: =Planejador!$I$51 | Q69: =$Q$63/$B$63 -> 0 | R69: =Planejador!$I$53
A70: 46088 | B70: =TEXT(A70,"dddd") -> sábado | D70: =SUMIF('ADV - GG'!A:A,A70,'ADV - GG'!C:C)+SUMIF('ADV - FB'!A:A,$A70,'ADV - FB'!E:E) -> 58.69 | E70: =SUMIF('ADV - GG'!A:A,A70,'ADV - GG'!H:H)+SUMIF('ADV - FB'!A:A,$A70,'ADV - FB'!I:I)+SUMIF('ADV - FB'!A:A,$A70,'ADV - FB'!J:J)+SUMIF('ADV - FB'!A:A,$A70,'ADV - FB'!K:K) -> 10 | F70: =IFERROR(D70/E70,"") -> 5.869 | J70: =SUMIF('ADV - GA4'!A:A,A70,'ADV - GA4'!C:C) -> 0 | K70: =IFERROR(D70/J70,"") | L70: =iferror(E70/J70,"") | M70: =$M$63/$B$63 -> 0 | N70: =iferror($N$63/$B$63,"") -> 0 | O70: =iferror(Planejador!$I$59,"") | P70: =Planejador!$I$51 | Q70: =$Q$63/$B$63 -> 0 | R70: =Planejador!$I$53
A71: 46089 | B71: =TEXT(A71,"dddd") -> domingo | D71: =SUMIF('ADV - GG'!A:A,A71,'ADV - GG'!C:C)+SUMIF('ADV - FB'!A:A,$A71,'ADV - FB'!E:E) -> 68.48 | E71: =SUMIF('ADV - GG'!A:A,A71,'ADV - GG'!H:H)+SUMIF('ADV - FB'!A:A,$A71,'ADV - FB'!I:I)+SUMIF('ADV - FB'!A:A,$A71,'ADV - FB'!J:J)+SUMIF('ADV - FB'!A:A,$A71,'ADV - FB'!K:K) -> 8 | F71: =IFERROR(D71/E71,"") -> 8.56 | J71: =SUMIF('ADV - GA4'!A:A,A71,'ADV - GA4'!C:C) -> 0 | K71: =IFERROR(D71/J71,"") | L71: =iferror(E71/J71,"") | M71: =$M$63/$B$63 -> 0 | N71: =iferror($N$63/$B$63,"") -> 0 | O71: =iferror(Planejador!$I$59,"") | P71: =Planejador!$I$51 | Q71: =$Q$63/$B$63 -> 0 | R71: =Planejador!$I$53
A72: 46090 | B72: =TEXT(A72,"dddd") -> segunda-feira | D72: =SUMIF('ADV - GG'!A:A,A72,'ADV - GG'!C:C)+SUMIF('ADV - FB'!A:A,$A72,'ADV - FB'!E:E) -> 69.44 | E72: =SUMIF('ADV - GG'!A:A,A72,'ADV - GG'!H:H)+SUMIF('ADV - FB'!A:A,$A72,'ADV - FB'!I:I)+SUMIF('ADV - FB'!A:A,$A72,'ADV - FB'!J:J)+SUMIF('ADV - FB'!A:A,$A72,'ADV - FB'!K:K) -> 8 | F72: =IFERROR(D72/E72,"") -> 8.68 | J72: =SUMIF('ADV - GA4'!A:A,A72,'ADV - GA4'!C:C) -> 0 | K72: =IFERROR(D72/J72,"") | L72: =iferror(E72/J72,"") | M72: =$M$63/$B$63 -> 0 | N72: =iferror($N$63/$B$63,"") -> 0 | O72: =iferror(Planejador!$I$59,"") | P72: =Planejador!$I$51 | Q72: =$Q$63/$B$63 -> 0 | R72: =Planejador!$I$53
A73: 46091 | B73: =TEXT(A73,"dddd") -> terça-feira | D73: =SUMIF('ADV - GG'!A:A,A73,'ADV - GG'!C:C)+SUMIF('ADV - FB'!A:A,$A73,'ADV - FB'!E:E) -> 68.2 | E73: =SUMIF('ADV - GG'!A:A,A73,'ADV - GG'!H:H)+SUMIF('ADV - FB'!A:A,$A73,'ADV - FB'!I:I)+SUMIF('ADV - FB'!A:A,$A73,'ADV - FB'!J:J)+SUMIF('ADV - FB'!A:A,$A73,'ADV - FB'!K:K) -> 9 | F73: =IFERROR(D73/E73,"") -> 7.5777778 | J73: =SUMIF('ADV - GA4'!A:A,A73,'ADV - GA4'!C:C) -> 0 | K73: =IFERROR(D73/J73,"") | L73: =iferror(E73/J73,"") | M73: =$M$63/$B$63 -> 0 | N73: =iferror($N$63/$B$63,"") -> 0 | O73: =iferror(Planejador!$I$59,"") | P73: =Planejador!$I$51 | Q73: =$Q$63/$B$63 -> 0 | R73: =Planejador!$I$53
A74: 46092 | B74: =TEXT(A74,"dddd") -> quarta-feira | D74: =SUMIF('ADV - GG'!A:A,A74,'ADV - GG'!C:C)+SUMIF('ADV - FB'!A:A,$A74,'ADV - FB'!E:E) -> 64.87 | E74: =SUMIF('ADV - GG'!A:A,A74,'ADV - GG'!H:H)+SUMIF('ADV - FB'!A:A,$A74,'ADV - FB'!I:I)+SUMIF('ADV - FB'!A:A,$A74,'ADV - FB'!J:J)+SUMIF('ADV - FB'!A:A,$A74,'ADV - FB'!K:K) -> 4 | F74: =IFERROR(D74/E74,"") -> 16.2175 | J74: =SUMIF('ADV - GA4'!A:A,A74,'ADV - GA4'!C:C) -> 0 | K74: =IFERROR(D74/J74,"") | L74: =iferror(E74/J74,"") | M74: =$M$63/$B$63 -> 0 | N74: =iferror($N$63/$B$63,"") -> 0 | O74: =iferror(Planejador!$I$59,"") | P74: =Planejador!$I$51 | Q74: =$Q$63/$B$63 -> 0 | R74: =Planejador!$I$53
A75: 46093 | B75: =TEXT(A75,"dddd") -> quinta-feira | D75: =SUMIF('ADV - GG'!A:A,A75,'ADV - GG'!C:C)+SUMIF('ADV - FB'!A:A,$A75,'ADV - FB'!E:E) -> 60.55 | E75: =SUMIF('ADV - GG'!A:A,A75,'ADV - GG'!H:H)+SUMIF('ADV - FB'!A:A,$A75,'ADV - FB'!I:I)+SUMIF('ADV - FB'!A:A,$A75,'ADV - FB'!J:J)+SUMIF('ADV - FB'!A:A,$A75,'ADV - FB'!K:K) -> 5 | F75: =IFERROR(D75/E75,"") -> 12.11 | J75: =SUMIF('ADV - GA4'!A:A,A75,'ADV - GA4'!C:C) -> 0 | K75: =IFERROR(D75/J75,"") | L75: =iferror(E75/J75,"") | M75: =$M$63/$B$63 -> 0 | N75: =iferror($N$63/$B$63,"") -> 0 | O75: =iferror(Planejador!$I$59,"") | P75: =Planejador!$I$51 | Q75: =$Q$63/$B$63 -> 0 | R75: =Planejador!$I$53
... A94: 46112 | B94: =TEXT(A94,"dddd") -> terça-feira | D94: =SUMIF('ADV - GG'!A:A,A94,'ADV - GG'!C:C)+SUMIF('ADV - FB'!A:A,$A94,'ADV - FB'!E:E) -> 66.7 | E94: =SUMIF('ADV - GG'!A:A,A94,'ADV - GG'!H:H)+SUMIF('ADV - FB'!A:A,$A94,'ADV - FB'!I:I)+SUMIF('ADV - FB'!A:A,$A94,'ADV - FB'!J:J)+SUMIF('ADV - FB'!A:A,$A94,'ADV - FB'!K:K) -> 3 | F94: =IFERROR(D94/E94,"") -> 22.233333 | J94: =SUMIF('ADV - GA4'!A:A,A94,'ADV - GA4'!C:C) -> 0 | K94: =IFERROR(D94/J94,"") | L94: =iferror(E94/J94,"") | M94: =$M$63/$B$63 -> 0 | N94: =iferror($N$63/$B$63,"") -> 0 | O94: =iferror(Planejador!$I$59,"") | P94: =Planejador!$I$51 | Q94: =$Q$63/$B$63 -> 0 | R94: =Planejador!$I$53
A95: ABRIL | B95: 30 | D95: =IFERROR(SUM(D96:D125),"") -> 1288.4 | E95: =iferror(SUM(E96:E125),"") -> 89 | F95: =IFERROR(D95/E95,"") -> 14.476404 | G95: =iferror(SUM(G96:G125),"") -> 0 | H95: =iferror(SUM(H96:H125),"") -> 0 | I95: =iferror(SUM(I96:I125),"") -> 0 | J95: =IFERROR(SUM(J96:J125),"") -> 0 | K95: =iferror(D95/J95,"") | L95: =iferror(E95/J95,"") | M95: =Planejador!$I$73 | N95: =iferror(Planejador!$I$80,"") | O95: =iferror(Planejador!$I$82,"") | P95: =iferror(Planejador!$I$74,"") | Q95: =iferror(Planejador!$I$79,"") | R95: =Iferror(Planejador!$I$76,"")
A96: 46113 | B96: =TEXT(A96,"dddd") -> quarta-feira | D96: =SUMIF('ADV - GG'!A:A,A96,'ADV - GG'!C:C)+SUMIF('ADV - FB'!A:A,$A96,'ADV - FB'!E:E) -> 67.19 | E96: =SUMIF('ADV - GG'!A:A,A96,'ADV - GG'!H:H)+SUMIF('ADV - FB'!A:A,$A96,'ADV - FB'!I:I)+SUMIF('ADV - FB'!A:A,$A96,'ADV - FB'!J:J)+SUMIF('ADV - FB'!A:A,$A96,'ADV - FB'!K:K) -> 7 | F96: =IFERROR(D96/E96,"") -> 9.5985714 | J96: =SUMIF('ADV - GA4'!A:A,A96,'ADV - GA4'!C:C) -> 0 | K96: =IFERROR(D96/J96,"") | L96: =iferror(E96/J96,"") | M96: =$M$95/$B$95 -> 0 | N96: =iferror($N$95/$B$95,"") -> 0 | O96: =iferror(Planejador!$I$82,"") | P96: =Planejador!$I$74 | Q96: =$Q$95/$B$95 -> 0 | R96: =Planejador!$I$76
A97: 46114 | B97: =TEXT(A97,"dddd") -> quinta-feira | D97: =SUMIF('ADV - GG'!A:A,A97,'ADV - GG'!C:C)+SUMIF('ADV - FB'!A:A,$A97,'ADV - FB'!E:E) -> 62.51 | E97: =SUMIF('ADV - GG'!A:A,A97,'ADV - GG'!H:H)+SUMIF('ADV - FB'!A:A,$A97,'ADV - FB'!I:I)+SUMIF('ADV - FB'!A:A,$A97,'ADV - FB'!J:J)+SUMIF('ADV - FB'!A:A,$A97,'ADV - FB'!K:K) -> 4 | F97: =IFERROR(D97/E97,"") -> 15.6275 | J97: =SUMIF('ADV - GA4'!A:A,A97,'ADV - GA4'!C:C) -> 0 | K97: =IFERROR(D97/J97,"") | L97: =iferror(E97/J97,"") | M97: =$M$95/$B$95 -> 0 | N97: =iferror($N$95/$B$95,"") -> 0 | O97: =iferror(Planejador!$I$82,"") | P97: =Planejador!$I$74 | Q97: =$Q$95/$B$95 -> 0 | R97: =Planejador!$I$76
A98: 46115 | B98: =TEXT(A98,"dddd") -> sexta-feira | D98: =SUMIF('ADV - GG'!A:A,A98,'ADV - GG'!C:C)+SUMIF('ADV - FB'!A:A,$A98,'ADV - FB'!E:E) -> 61.76 | E98: =SUMIF('ADV - GG'!A:A,A98,'ADV - GG'!H:H)+SUMIF('ADV - FB'!A:A,$A98,'ADV - FB'!I:I)+SUMIF('ADV - FB'!A:A,$A98,'ADV - FB'!J:J)+SUMIF('ADV - FB'!A:A,$A98,'ADV - FB'!K:K) -> 6 | F98: =IFERROR(D98/E98,"") -> 10.293333 | J98: =SUMIF('ADV - GA4'!A:A,A98,'ADV - GA4'!C:C) -> 0 | K98: =IFERROR(D98/J98,"") | L98: =iferror(E98/J98,"") | M98: =$M$95/$B$95 -> 0 | N98: =iferror($N$95/$B$95,"") -> 0 | O98: =iferror(Planejador!$I$82,"") | P98: =Planejador!$I$74 | Q98: =$Q$95/$B$95 -> 0 | R98: =Planejador!$I$76
A99: 46116 | B99: =TEXT(A99,"dddd") -> sábado | D99: =SUMIF('ADV - GG'!A:A,A99,'ADV - GG'!C:C)+SUMIF('ADV - FB'!A:A,$A99,'ADV - FB'!E:E) -> 56 | E99: =SUMIF('ADV - GG'!A:A,A99,'ADV - GG'!H:H)+SUMIF('ADV - FB'!A:A,$A99,'ADV - FB'!I:I)+SUMIF('ADV - FB'!A:A,$A99,'ADV - FB'!J:J)+SUMIF('ADV - FB'!A:A,$A99,'ADV - FB'!K:K) -> 5 | F99: =IFERROR(D99/E99,"") -> 11.2 | J99: =SUMIF('ADV - GA4'!A:A,A99,'ADV - GA4'!C:C) -> 0 | K99: =IFERROR(D99/J99,"") | L99: =iferror(E99/J99,"") | M99: =$M$95/$B$95 -> 0 | N99: =iferror($N$95/$B$95,"") -> 0 | O99: =iferror(Planejador!$I$82,"") | P99: =Planejador!$I$74 | Q99: =$Q$95/$B$95 -> 0 | R99: =Planejador!$I$76
A100: 46117 | B100: =TEXT(A100,"dddd") -> domingo | D100: =SUMIF('ADV - GG'!A:A,A100,'ADV - GG'!C:C)+SUMIF('ADV - FB'!A:A,$A100,'ADV - FB'!E:E) -> 66.97 | E100: =SUMIF('ADV - GG'!A:A,A100,'ADV - GG'!H:H)+SUMIF('ADV - FB'!A:A,$A100,'ADV - FB'!I:I)+SUMIF('ADV - FB'!A:A,$A100,'ADV - FB'!J:J)+SUMIF('ADV - FB'!A:A,$A100,'ADV - FB'!K:K) -> 9 | F100: =IFERROR(D100/E100,"") -> 7.4411111 | J100: =SUMIF('ADV - GA4'!A:A,A100,'ADV - GA4'!C:C) -> 0 | K100: =IFERROR(D100/J100,"") | L100: =iferror(E100/J100,"") | M100: =$M$95/$B$95 -> 0 | N100: =iferror($N$95/$B$95,"") -> 0 | O100: =iferror(Planejador!$I$82,"") | P100: =Planejador!$I$74 | Q100: =$Q$95/$B$95 -> 0 | R100: =Planejador!$I$76
A101: 46118 | B101: =TEXT(A101,"dddd") -> segunda-feira | D101: =SUMIF('ADV - GG'!A:A,A101,'ADV - GG'!C:C)+SUMIF('ADV - FB'!A:A,$A101,'ADV - FB'!E:E) -> 66.63 | E101: =SUMIF('ADV - GG'!A:A,A101,'ADV - GG'!H:H)+SUMIF('ADV - FB'!A:A,$A101,'ADV - FB'!I:I)+SUMIF('ADV - FB'!A:A,$A101,'ADV - FB'!J:J)+SUMIF('ADV - FB'!A:A,$A101,'ADV - FB'!K:K) -> 12 | F101: =IFERROR(D101/E101,"") -> 5.5525 | J101: =SUMIF('ADV - GA4'!A:A,A101,'ADV - GA4'!C:C) -> 0 | K101: =IFERROR(D101/J101,"") | L101: =iferror(E101/J101,"") | M101: =$M$95/$B$95 -> 0 | N101: =iferror($N$95/$B$95,"") -> 0 | O101: =iferror(Planejador!$I$82,"") | P101: =Planejador!$I$74 | Q101: =$Q$95/$B$95 -> 0 | R101: =Planejador!$I$76
A102: 46119 | B102: =TEXT(A102,"dddd") -> terça-feira | D102: =SUMIF('ADV - GG'!A:A,A102,'ADV - GG'!C:C)+SUMIF('ADV - FB'!A:A,$A102,'ADV - FB'!E:E) -> 62.74 | E102: =SUMIF('ADV - GG'!A:A,A102,'ADV - GG'!H:H)+SUMIF('ADV - FB'!A:A,$A102,'ADV - FB'!I:I)+SUMIF('ADV - FB'!A:A,$A102,'ADV - FB'!J:J)+SUMIF('ADV - FB'!A:A,$A102,'ADV - FB'!K:K) -> 5 | F102: =IFERROR(D102/E102,"") -> 12.548 | J102: =SUMIF('ADV - GA4'!A:A,A102,'ADV - GA4'!C:C) -> 0 | K102: =IFERROR(D102/J102,"") | L102: =iferror(E102/J102,"") | M102: =$M$95/$B$95 -> 0 | N102: =iferror($N$95/$B$95,"") -> 0 | O102: =iferror(Planejador!$I$82,"") | P102: =Planejador!$I$74 | Q102: =$Q$95/$B$95 -> 0 | R102: =Planejador!$I$76
A103: 46120 | B103: =TEXT(A103,"dddd") -> quarta-feira | D103: =SUMIF('ADV - GG'!A:A,A103,'ADV - GG'!C:C)+SUMIF('ADV - FB'!A:A,$A103,'ADV - FB'!E:E) -> 64.34 | E103: =SUMIF('ADV - GG'!A:A,A103,'ADV - GG'!H:H)+SUMIF('ADV - FB'!A:A,$A103,'ADV - FB'!I:I)+SUMIF('ADV - FB'!A:A,$A103,'ADV - FB'!J:J)+SUMIF('ADV - FB'!A:A,$A103,'ADV - FB'!K:K) -> 6 | F103: =IFERROR(D103/E103,"") -> 10.723333 | J103: =SUMIF('ADV - GA4'!A:A,A103,'ADV - GA4'!C:C) -> 0 | K103: =IFERROR(D103/J103,"") | L103: =iferror(E103/J103,"") | M103: =$M$95/$B$95 -> 0 | N103: =iferror($N$95/$B$95,"") -> 0 | O103: =iferror(Planejador!$I$82,"") | P103: =Planejador!$I$74 | Q103: =$Q$95/$B$95 -> 0 | R103: =Planejador!$I$76
A104: 46121 | B104: =TEXT(A104,"dddd") -> quinta-feira | D104: =SUMIF('ADV - GG'!A:A,A104,'ADV - GG'!C:C)+SUMIF('ADV - FB'!A:A,$A104,'ADV - FB'!E:E) -> 64.84 | E104: =SUMIF('ADV - GG'!A:A,A104,'ADV - GG'!H:H)+SUMIF('ADV - FB'!A:A,$A104,'ADV - FB'!I:I)+SUMIF('ADV - FB'!A:A,$A104,'ADV - FB'!J:J)+SUMIF('ADV - FB'!A:A,$A104,'ADV - FB'!K:K) -> 9 | F104: =IFERROR(D104/E104,"") -> 7.2044444 | J104: =SUMIF('ADV - GA4'!A:A,A104,'ADV - GA4'!C:C) -> 0 | K104: =IFERROR(D104/J104,"") | L104: =iferror(E104/J104,"") | M104: =$M$95/$B$95 -> 0 | N104: =iferror($N$95/$B$95,"") -> 0 | O104: =iferror(Planejador!$I$82,"") | P104: =Planejador!$I$74 | Q104: =$Q$95/$B$95 -> 0 | R104: =Planejador!$I$76
A105: 46122 | B105: =TEXT(A105,"dddd") -> sexta-feira | D105: =SUMIF('ADV - GG'!A:A,A105,'ADV - GG'!C:C)+SUMIF('ADV - FB'!A:A,$A105,'ADV - FB'!E:E) -> 63 | E105: =SUMIF('ADV - GG'!A:A,A105,'ADV - GG'!H:H)+SUMIF('ADV - FB'!A:A,$A105,'ADV - FB'!I:I)+SUMIF('ADV - FB'!A:A,$A105,'ADV - FB'!J:J)+SUMIF('ADV - FB'!A:A,$A105,'ADV - FB'!K:K) -> 4 | F105: =IFERROR(D105/E105,"") -> 15.75 | J105: =SUMIF('ADV - GA4'!A:A,A105,'ADV - GA4'!C:C) -> 0 | K105: =IFERROR(D105/J105,"") | L105: =iferror(E105/J105,"") | M105: =$M$95/$B$95 -> 0 | N105: =iferror($N$95/$B$95,"") -> 0 | O105: =iferror(Planejador!$I$82,"") | P105: =Planejador!$I$74 | Q105: =$Q$95/$B$95 -> 0 | R105: =Planejador!$I$76
A106: 46123 | B106: =TEXT(A106,"dddd") -> sábado | D106: =SUMIF('ADV - GG'!A:A,A106,'ADV - GG'!C:C)+SUMIF('ADV - FB'!A:A,$A106,'ADV - FB'!E:E) -> 60.86 | E106: =SUMIF('ADV - GG'!A:A,A106,'ADV - GG'!H:H)+SUMIF('ADV - FB'!A:A,$A106,'ADV - FB'!I:I)+SUMIF('ADV - FB'!A:A,$A106,'ADV - FB'!J:J)+SUMIF('ADV - FB'!A:A,$A106,'ADV - FB'!K:K) -> 2 | F106: =IFERROR(D106/E106,"") -> 30.43 | J106: =SUMIF('ADV - GA4'!A:A,A106,'ADV - GA4'!C:C) -> 0 | K106: =IFERROR(D106/J106,"") | L106: =iferror(E106/J106,"") | M106: =$M$95/$B$95 -> 0 | N106: =iferror($N$95/$B$95,"") -> 0 | O106: =iferror(Planejador!$I$82,"") | P106: =Planejador!$I$74 | Q106: =$Q$95/$B$95 -> 0 | R106: =Planejador!$I$76
A107: 46124 | B107: =TEXT(A107,"dddd") -> domingo | D107: =SUMIF('ADV - GG'!A:A,A107,'ADV - GG'!C:C)+SUMIF('ADV - FB'!A:A,$A107,'ADV - FB'!E:E) -> 60.56 | E107: =SUMIF('ADV - GG'!A:A,A107,'ADV - GG'!H:H)+SUMIF('ADV - FB'!A:A,$A107,'ADV - FB'!I:I)+SUMIF('ADV - FB'!A:A,$A107,'ADV - FB'!J:J)+SUMIF('ADV - FB'!A:A,$A107,'ADV - FB'!K:K) -> 1 | F107: =IFERROR(D107/E107,"") -> 60.56 | J107: =SUMIF('ADV - GA4'!A:A,A107,'ADV - GA4'!C:C) -> 0 | K107: =IFERROR(D107/J107,"") | L107: =iferror(E107/J107,"") | M107: =$M$95/$B$95 -> 0 | N107: =iferror($N$95/$B$95,"") -> 0 | O107: =iferror(Planejador!$I$82,"") | P107: =Planejador!$I$74 | Q107: =$Q$95/$B$95 -> 0 | R107: =Planejador!$I$76
... A125: 46142 | B125: =TEXT(A125,"dddd") -> quinta-feira | D125: =SUMIF('ADV - GG'!A:A,A125,'ADV - GG'!C:C)+SUMIF('ADV - FB'!A:A,$A125,'ADV - FB'!E:E) -> 0 | E125: =SUMIF('ADV - GG'!A:A,A125,'ADV - GG'!H:H)+SUMIF('ADV - FB'!A:A,$A125,'ADV - FB'!I:I)+SUMIF('ADV - FB'!A:A,$A125,'ADV - FB'!J:J)+SUMIF('ADV - FB'!A:A,$A125,'ADV - FB'!K:K) -> 0 | F125: =IFERROR(D125/E125,"") | J125: =SUMIF('ADV - GA4'!A:A,A125,'ADV - GA4'!C:C) -> 0 | K125: =IFERROR(D125/J125,"") | L125: =iferror(E125/J125,"") | M125: =$M$95/$B$95 -> 0 | N125: =iferror($N$95/$B$95,"") -> 0 | O125: =iferror(Planejador!$I$82,"") | P125: =Planejador!$I$74 | Q125: =$Q$95/$B$95 -> 0 | R125: =Planejador!$I$76
A126: MAIO | B126: 31 | D126: =IFERROR(SUM(D127:D157),"") -> 0 | E126: =iferror(SUM(E127:E157),"") -> 0 | F126: =IFERROR(D126/E126,"") | G126: =iferror(SUM(G127:G157),"") -> 0 | H126: =iferror(SUM(H127:H157),"") -> 0 | I126: =iferror(SUM(I127:I157),"") -> 0 | J126: =IFERROR(SUM(J127:J157),"") -> 0 | K126: =iferror(D126/J126,"") | L126: =iferror(E126/J126,"") | M126: =Planejador!$I$96 | N126: =iferror(Planejador!$I$103,"") | O126: =iferror(Planejador!$I$105,"") | P126: =iferror(Planejador!$I$97,"") | Q126: =iferror(Planejador!$I$102,"") | R126: =Iferror(Planejador!$I$99,"")
A127: 46143 | B127: =TEXT(A127,"dddd") -> sexta-feira | D127: =SUMIF('ADV - GG'!A:A,A127,'ADV - GG'!C:C)+SUMIF('ADV - FB'!A:A,$A127,'ADV - FB'!E:E) -> 0 | E127: =SUMIF('ADV - GG'!A:A,A127,'ADV - GG'!H:H)+SUMIF('ADV - FB'!A:A,$A127,'ADV - FB'!I:I)+SUMIF('ADV - FB'!A:A,$A127,'ADV - FB'!J:J)+SUMIF('ADV - FB'!A:A,$A127,'ADV - FB'!K:K) -> 0 | F127: =IFERROR(D127/E127,"") | J127: =SUMIF('ADV - GA4'!A:A,A127,'ADV - GA4'!C:C) -> 0 | K127: =IFERROR(D127/J127,"") | L127: =iferror(E127/J127,"") | M127: =$M$126/$B$126 -> 0 | N127: =iferror($N$126/$B$126,"") -> 0 | O127: =iferror(Planejador!$I$105,"") | P127: =Planejador!$I$97 | Q127: =$Q$126/$B$126 -> 0 | R127: =Planejador!$I$99
A128: 46144 | B128: =TEXT(A128,"dddd") -> sábado | D128: =SUMIF('ADV - GG'!A:A,A128,'ADV - GG'!C:C)+SUMIF('ADV - FB'!A:A,$A128,'ADV - FB'!E:E) -> 0 | E128: =SUMIF('ADV - GG'!A:A,A128,'ADV - GG'!H:H)+SUMIF('ADV - FB'!A:A,$A128,'ADV - FB'!I:I)+SUMIF('ADV - FB'!A:A,$A128,'ADV - FB'!J:J)+SUMIF('ADV - FB'!A:A,$A128,'ADV - FB'!K:K) -> 0 | F128: =IFERROR(D128/E128,"") | J128: =SUMIF('ADV - GA4'!A:A,A128,'ADV - GA4'!C:C) -> 0 | K128: =IFERROR(D128/J128,"") | L128: =iferror(E128/J128,"") | M128: =$M$126/$B$126 -> 0 | N128: =iferror($N$126/$B$126,"") -> 0 | O128: =iferror(Planejador!$I$105,"") | P128: =Planejador!$I$97 | Q128: =$Q$126/$B$126 -> 0 | R128: =Planejador!$I$99
A129: 46145 | B129: =TEXT(A129,"dddd") -> domingo | D129: =SUMIF('ADV - GG'!A:A,A129,'ADV - GG'!C:C)+SUMIF('ADV - FB'!A:A,$A129,'ADV - FB'!E:E) -> 0 | E129: =SUMIF('ADV - GG'!A:A,A129,'ADV - GG'!H:H)+SUMIF('ADV - FB'!A:A,$A129,'ADV - FB'!I:I)+SUMIF('ADV - FB'!A:A,$A129,'ADV - FB'!J:J)+SUMIF('ADV - FB'!A:A,$A129,'ADV - FB'!K:K) -> 0 | F129: =IFERROR(D129/E129,"") | J129: =SUMIF('ADV - GA4'!A:A,A129,'ADV - GA4'!C:C) -> 0 | K129: =IFERROR(D129/J129,"") | L129: =iferror(E129/J129,"") | M129: =$M$126/$B$126 -> 0 | N129: =iferror($N$126/$B$126,"") -> 0 | O129: =iferror(Planejador!$I$105,"") | P129: =Planejador!$I$97 | Q129: =$Q$126/$B$126 -> 0 | R129: =Planejador!$I$99
A130: 46146 | B130: =TEXT(A130,"dddd") -> segunda-feira | D130: =SUMIF('ADV - GG'!A:A,A130,'ADV - GG'!C:C)+SUMIF('ADV - FB'!A:A,$A130,'ADV - FB'!E:E) -> 0 | E130: =SUMIF('ADV - GG'!A:A,A130,'ADV - GG'!H:H)+SUMIF('ADV - FB'!A:A,$A130,'ADV - FB'!I:I)+SUMIF('ADV - FB'!A:A,$A130,'ADV - FB'!J:J)+SUMIF('ADV - FB'!A:A,$A130,'ADV - FB'!K:K) -> 0 | F130: =IFERROR(D130/E130,"") | J130: =SUMIF('ADV - GA4'!A:A,A130,'ADV - GA4'!C:C) -> 0 | K130: =IFERROR(D130/J130,"") | L130: =iferror(E130/J130,"") | M130: =$M$126/$B$126 -> 0 | N130: =iferror($N$126/$B$126,"") -> 0 | O130: =iferror(Planejador!$I$105,"") | P130: =Planejador!$I$97 | Q130: =$Q$126/$B$126 -> 0 | R130: =Planejador!$I$99
A131: 46147 | B131: =TEXT(A131,"dddd") -> terça-feira | D131: =SUMIF('ADV - GG'!A:A,A131,'ADV - GG'!C:C)+SUMIF('ADV - FB'!A:A,$A131,'ADV - FB'!E:E) -> 0 | E131: =SUMIF('ADV - GG'!A:A,A131,'ADV - GG'!H:H)+SUMIF('ADV - FB'!A:A,$A131,'ADV - FB'!I:I)+SUMIF('ADV - FB'!A:A,$A131,'ADV - FB'!J:J)+SUMIF('ADV - FB'!A:A,$A131,'ADV - FB'!K:K) -> 0 | F131: =IFERROR(D131/E131,"") | J131: =SUMIF('ADV - GA4'!A:A,A131,'ADV - GA4'!C:C) -> 0 | K131: =IFERROR(D131/J131,"") | L131: =iferror(E131/J131,"") | M131: =$M$126/$B$126 -> 0 | N131: =iferror($N$126/$B$126,"") -> 0 | O131: =iferror(Planejador!$I$105,"") | P131: =Planejador!$I$97 | Q131: =$Q$126/$B$126 -> 0 | R131: =Planejador!$I$99
A132: 46148 | B132: =TEXT(A132,"dddd") -> quarta-feira | D132: =SUMIF('ADV - GG'!A:A,A132,'ADV - GG'!C:C)+SUMIF('ADV - FB'!A:A,$A132,'ADV - FB'!E:E) -> 0 | E132: =SUMIF('ADV - GG'!A:A,A132,'ADV - GG'!H:H)+SUMIF('ADV - FB'!A:A,$A132,'ADV - FB'!I:I)+SUMIF('ADV - FB'!A:A,$A132,'ADV - FB'!J:J)+SUMIF('ADV - FB'!A:A,$A132,'ADV - FB'!K:K) -> 0 | F132: =IFERROR(D132/E132,"") | J132: =SUMIF('ADV - GA4'!A:A,A132,'ADV - GA4'!C:C) -> 0 | K132: =IFERROR(D132/J132,"") | L132: =iferror(E132/J132,"") | M132: =$M$126/$B$126 -> 0 | N132: =iferror($N$126/$B$126,"") -> 0 | O132: =iferror(Planejador!$I$105,"") | P132: =Planejador!$I$97 | Q132: =$Q$126/$B$126 -> 0 | R132: =Planejador!$I$99
A133: 46149 | B133: =TEXT(A133,"dddd") -> quinta-feira | D133: =SUMIF('ADV - GG'!A:A,A133,'ADV - GG'!C:C)+SUMIF('ADV - FB'!A:A,$A133,'ADV - FB'!E:E) -> 0 | E133: =SUMIF('ADV - GG'!A:A,A133,'ADV - GG'!H:H)+SUMIF('ADV - FB'!A:A,$A133,'ADV - FB'!I:I)+SUMIF('ADV - FB'!A:A,$A133,'ADV - FB'!J:J)+SUMIF('ADV - FB'!A:A,$A133,'ADV - FB'!K:K) -> 0 | F133: =IFERROR(D133/E133,"") | J133: =SUMIF('ADV - GA4'!A:A,A133,'ADV - GA4'!C:C) -> 0 | K133: =IFERROR(D133/J133,"") | L133: =iferror(E133/J133,"") | M133: =$M$126/$B$126 -> 0 | N133: =iferror($N$126/$B$126,"") -> 0 | O133: =iferror(Planejador!$I$105,"") | P133: =Planejador!$I$97 | Q133: =$Q$126/$B$126 -> 0 | R133: =Planejador!$I$99
A134: 46150 | B134: =TEXT(A134,"dddd") -> sexta-feira | D134: =SUMIF('ADV - GG'!A:A,A134,'ADV - GG'!C:C)+SUMIF('ADV - FB'!A:A,$A134,'ADV - FB'!E:E) -> 0 | E134: =SUMIF('ADV - GG'!A:A,A134,'ADV - GG'!H:H)+SUMIF('ADV - FB'!A:A,$A134,'ADV - FB'!I:I)+SUMIF('ADV - FB'!A:A,$A134,'ADV - FB'!J:J)+SUMIF('ADV - FB'!A:A,$A134,'ADV - FB'!K:K) -> 0 | F134: =IFERROR(D134/E134,"") | J134: =SUMIF('ADV - GA4'!A:A,A134,'ADV - GA4'!C:C) -> 0 | K134: =IFERROR(D134/J134,"") | L134: =iferror(E134/J134,"") | M134: =$M$126/$B$126 -> 0 | N134: =iferror($N$126/$B$126,"") -> 0 | O134: =iferror(Planejador!$I$105,"") | P134: =Planejador!$I$97 | Q134: =$Q$126/$B$126 -> 0 | R134: =Planejador!$I$99
A135: 46151 | B135: =TEXT(A135,"dddd") -> sábado | D135: =SUMIF('ADV - GG'!A:A,A135,'ADV - GG'!C:C)+SUMIF('ADV - FB'!A:A,$A135,'ADV - FB'!E:E) -> 0 | E135: =SUMIF('ADV - GG'!A:A,A135,'ADV - GG'!H:H)+SUMIF('ADV - FB'!A:A,$A135,'ADV - FB'!I:I)+SUMIF('ADV - FB'!A:A,$A135,'ADV - FB'!J:J)+SUMIF('ADV - FB'!A:A,$A135,'ADV - FB'!K:K) -> 0 | F135: =IFERROR(D135/E135,"") | J135: =SUMIF('ADV - GA4'!A:A,A135,'ADV - GA4'!C:C) -> 0 | K135: =IFERROR(D135/J135,"") | L135: =iferror(E135/J135,"") | M135: =$M$126/$B$126 -> 0 | N135: =iferror($N$126/$B$126,"") -> 0 | O135: =iferror(Planejador!$I$105,"") | P135: =Planejador!$I$97 | Q135: =$Q$126/$B$126 -> 0 | R135: =Planejador!$I$99
A136: 46152 | B136: =TEXT(A136,"dddd") -> domingo | D136: =SUMIF('ADV - GG'!A:A,A136,'ADV - GG'!C:C)+SUMIF('ADV - FB'!A:A,$A136,'ADV - FB'!E:E) -> 0 | E136: =SUMIF('ADV - GG'!A:A,A136,'ADV - GG'!H:H)+SUMIF('ADV - FB'!A:A,$A136,'ADV - FB'!I:I)+SUMIF('ADV - FB'!A:A,$A136,'ADV - FB'!J:J)+SUMIF('ADV - FB'!A:A,$A136,'ADV - FB'!K:K) -> 0 | F136: =IFERROR(D136/E136,"") | J136: =SUMIF('ADV - GA4'!A:A,A136,'ADV - GA4'!C:C) -> 0 | K136: =IFERROR(D136/J136,"") | L136: =iferror(E136/J136,"") | M136: =$M$126/$B$126 -> 0 | N136: =iferror($N$126/$B$126,"") -> 0 | O136: =iferror(Planejador!$I$105,"") | P136: =Planejador!$I$97 | Q136: =$Q$126/$B$126 -> 0 | R136: =Planejador!$I$99
A137: 46153 | B137: =TEXT(A137,"dddd") -> segunda-feira | D137: =SUMIF('ADV - GG'!A:A,A137,'ADV - GG'!C:C)+SUMIF('ADV - FB'!A:A,$A137,'ADV - FB'!E:E) -> 0 | E137: =SUMIF('ADV - GG'!A:A,A137,'ADV - GG'!H:H)+SUMIF('ADV - FB'!A:A,$A137,'ADV - FB'!I:I)+SUMIF('ADV - FB'!A:A,$A137,'ADV - FB'!J:J)+SUMIF('ADV - FB'!A:A,$A137,'ADV - FB'!K:K) -> 0 | F137: =IFERROR(D137/E137,"") | J137: =SUMIF('ADV - GA4'!A:A,A137,'ADV - GA4'!C:C) -> 0 | K137: =IFERROR(D137/J137,"") | L137: =iferror(E137/J137,"") | M137: =$M$126/$B$126 -> 0 | N137: =iferror($N$126/$B$126,"") -> 0 | O137: =iferror(Planejador!$I$105,"") | P137: =Planejador!$I$97 | Q137: =$Q$126/$B$126 -> 0 | R137: =Planejador!$I$99
A138: 46154 | B138: =TEXT(A138,"dddd") -> terça-feira | D138: =SUMIF('ADV - GG'!A:A,A138,'ADV - GG'!C:C)+SUMIF('ADV - FB'!A:A,$A138,'ADV - FB'!E:E) -> 0 | E138: =SUMIF('ADV - GG'!A:A,A138,'ADV - GG'!H:H)+SUMIF('ADV - FB'!A:A,$A138,'ADV - FB'!I:I)+SUMIF('ADV - FB'!A:A,$A138,'ADV - FB'!J:J)+SUMIF('ADV - FB'!A:A,$A138,'ADV - FB'!K:K) -> 0 | F138: =IFERROR(D138/E138,"") | J138: =SUMIF('ADV - GA4'!A:A,A138,'ADV - GA4'!C:C) -> 0 | K138: =IFERROR(D138/J138,"") | L138: =iferror(E138/J138,"") | M138: =$M$126/$B$126 -> 0 | N138: =iferror($N$126/$B$126,"") -> 0 | O138: =iferror(Planejador!$I$105,"") | P138: =Planejador!$I$97 | Q138: =$Q$126/$B$126 -> 0 | R138: =Planejador!$I$99
... A157: 46173 | B157: =TEXT(A157,"dddd") -> domingo | D157: =SUMIF('ADV - GG'!A:A,A157,'ADV - GG'!C:C)+SUMIF('ADV - FB'!A:A,$A157,'ADV - FB'!E:E) -> 0 | E157: =SUMIF('ADV - GG'!A:A,A157,'ADV - GG'!H:H)+SUMIF('ADV - FB'!A:A,$A157,'ADV - FB'!I:I)+SUMIF('ADV - FB'!A:A,$A157,'ADV - FB'!J:J)+SUMIF('ADV - FB'!A:A,$A157,'ADV - FB'!K:K) -> 0 | F157: =IFERROR(D157/E157,"") | J157: =SUMIF('ADV - GA4'!A:A,A157,'ADV - GA4'!C:C) -> 0 | K157: =IFERROR(D157/J157,"") | L157: =iferror(E157/J157,"") | M157: =$M$126/$B$126 -> 0 | N157: =iferror($N$126/$B$126,"") -> 0 | O157: =iferror(Planejador!$I$105,"") | P157: =Planejador!$I$97 | Q157: =$Q$126/$B$126 -> 0 | R157: =Planejador!$I$99
A158: JUNHO | B158: 30 | D158: =IFERROR(SUM(D159:D188),"") -> 0 | E158: =iferror(SUM(E159:E188),"") -> 0 | F158: =IFERROR(D158/E158,"") | G158: =iferror(SUM(G159:G188),"") -> 0 | H158: =iferror(SUM(H159:H188),"") -> 0 | I158: =iferror(SUM(I159:I188),"") -> 0 | J158: =IFERROR(SUM(J159:J188),"") -> 0 | K158: =iferror(D158/J158,"") | L158: =iferror(E158/J158,"") | M158: =Planejador!$I$119 | N158: =iferror(Planejador!$I$126,"") | O158: =iferror(Planejador!$I$128,"") | P158: =iferror(Planejador!$I$120,"") | Q158: =iferror(Planejador!$I$125,"") | R158: =Iferror(Planejador!$I$122,"")
A159: 46174 | B159: =TEXT(A159,"dddd") -> segunda-feira | D159: =SUMIF('ADV - GG'!A:A,A159,'ADV - GG'!C:C)+SUMIF('ADV - FB'!A:A,$A159,'ADV - FB'!E:E) -> 0 | E159: =SUMIF('ADV - GG'!A:A,A159,'ADV - GG'!H:H)+SUMIF('ADV - FB'!A:A,$A159,'ADV - FB'!I:I)+SUMIF('ADV - FB'!A:A,$A159,'ADV - FB'!J:J)+SUMIF('ADV - FB'!A:A,$A159,'ADV - FB'!K:K) -> 0 | F159: =IFERROR(D159/E159,"") | J159: =SUMIF('ADV - GA4'!A:A,A159,'ADV - GA4'!C:C) -> 0 | K159: =IFERROR(D159/J159,"") | L159: =iferror(E159/J159,"") | M159: =$M$158/$B$158 -> 0 | N159: =iferror($N$158/$B$158,"") -> 0 | O159: =iferror(Planejador!$I$128,"") | P159: =Planejador!$I$120 | Q159: =$Q$158/$B$158 -> 0 | R159: =Planejador!$I$122
A160: 46175 | B160: =TEXT(A160,"dddd") -> terça-feira | D160: =SUMIF('ADV - GG'!A:A,A160,'ADV - GG'!C:C)+SUMIF('ADV - FB'!A:A,$A160,'ADV - FB'!E:E) -> 0 | E160: =SUMIF('ADV - GG'!A:A,A160,'ADV - GG'!H:H)+SUMIF('ADV - FB'!A:A,$A160,'ADV - FB'!I:I)+SUMIF('ADV - FB'!A:A,$A160,'ADV - FB'!J:J)+SUMIF('ADV - FB'!A:A,$A160,'ADV - FB'!K:K) -> 0 | F160: =IFERROR(D160/E160,"") | J160: =SUMIF('ADV - GA4'!A:A,A160,'ADV - GA4'!C:C) -> 0 | K160: =IFERROR(D160/J160,"") | L160: =iferror(E160/J160,"") | M160: =$M$158/$B$158 -> 0 | N160: =iferror($N$158/$B$158,"") -> 0 | O160: =iferror(Planejador!$I$128,"") | P160: =Planejador!$I$120 | Q160: =$Q$158/$B$158 -> 0 | R160: =Planejador!$I$122
A161: 46176 | B161: =TEXT(A161,"dddd") -> quarta-feira | D161: =SUMIF('ADV - GG'!A:A,A161,'ADV - GG'!C:C)+SUMIF('ADV - FB'!A:A,$A161,'ADV - FB'!E:E) -> 0 | E161: =SUMIF('ADV - GG'!A:A,A161,'ADV - GG'!H:H)+SUMIF('ADV - FB'!A:A,$A161,'ADV - FB'!I:I)+SUMIF('ADV - FB'!A:A,$A161,'ADV - FB'!J:J)+SUMIF('ADV - FB'!A:A,$A161,'ADV - FB'!K:K) -> 0 | F161: =IFERROR(D161/E161,"") | J161: =SUMIF('ADV - GA4'!A:A,A161,'ADV - GA4'!C:C) -> 0 | K161: =IFERROR(D161/J161,"") | L161: =iferror(E161/J161,"") | M161: =$M$158/$B$158 -> 0 | N161: =iferror($N$158/$B$158,"") -> 0 | O161: =iferror(Planejador!$I$128,"") | P161: =Planejador!$I$120 | Q161: =$Q$158/$B$158 -> 0 | R161: =Planejador!$I$122
A162: 46177 | B162: =TEXT(A162,"dddd") -> quinta-feira | D162: =SUMIF('ADV - GG'!A:A,A162,'ADV - GG'!C:C)+SUMIF('ADV - FB'!A:A,$A162,'ADV - FB'!E:E) -> 0 | E162: =SUMIF('ADV - GG'!A:A,A162,'ADV - GG'!H:H)+SUMIF('ADV - FB'!A:A,$A162,'ADV - FB'!I:I)+SUMIF('ADV - FB'!A:A,$A162,'ADV - FB'!J:J)+SUMIF('ADV - FB'!A:A,$A162,'ADV - FB'!K:K) -> 0 | F162: =IFERROR(D162/E162,"") | J162: =SUMIF('ADV - GA4'!A:A,A162,'ADV - GA4'!C:C) -> 0 | K162: =IFERROR(D162/J162,"") | L162: =iferror(E162/J162,"") | M162: =$M$158/$B$158 -> 0 | N162: =iferror($N$158/$B$158,"") -> 0 | O162: =iferror(Planejador!$I$128,"") | P162: =Planejador!$I$120 | Q162: =$Q$158/$B$158 -> 0 | R162: =Planejador!$I$122
A163: 46178 | B163: =TEXT(A163,"dddd") -> sexta-feira | D163: =SUMIF('ADV - GG'!A:A,A163,'ADV - GG'!C:C)+SUMIF('ADV - FB'!A:A,$A163,'ADV - FB'!E:E) -> 0 | E163: =SUMIF('ADV - GG'!A:A,A163,'ADV - GG'!H:H)+SUMIF('ADV - FB'!A:A,$A163,'ADV - FB'!I:I)+SUMIF('ADV - FB'!A:A,$A163,'ADV - FB'!J:J)+SUMIF('ADV - FB'!A:A,$A163,'ADV - FB'!K:K) -> 0 | F163: =IFERROR(D163/E163,"") | J163: =SUMIF('ADV - GA4'!A:A,A163,'ADV - GA4'!C:C) -> 0 | K163: =IFERROR(D163/J163,"") | L163: =iferror(E163/J163,"") | M163: =$M$158/$B$158 -> 0 | N163: =iferror($N$158/$B$158,"") -> 0 | O163: =iferror(Planejador!$I$128,"") | P163: =Planejador!$I$120 | Q163: =$Q$158/$B$158 -> 0 | R163: =Planejador!$I$122
A164: 46179 | B164: =TEXT(A164,"dddd") -> sábado | D164: =SUMIF('ADV - GG'!A:A,A164,'ADV - GG'!C:C)+SUMIF('ADV - FB'!A:A,$A164,'ADV - FB'!E:E) -> 0 | E164: =SUMIF('ADV - GG'!A:A,A164,'ADV - GG'!H:H)+SUMIF('ADV - FB'!A:A,$A164,'ADV - FB'!I:I)+SUMIF('ADV - FB'!A:A,$A164,'ADV - FB'!J:J)+SUMIF('ADV - FB'!A:A,$A164,'ADV - FB'!K:K) -> 0 | F164: =IFERROR(D164/E164,"") | J164: =SUMIF('ADV - GA4'!A:A,A164,'ADV - GA4'!C:C) -> 0 | K164: =IFERROR(D164/J164,"") | L164: =iferror(E164/J164,"") | M164: =$M$158/$B$158 -> 0 | N164: =iferror($N$158/$B$158,"") -> 0 | O164: =iferror(Planejador!$I$128,"") | P164: =Planejador!$I$120 | Q164: =$Q$158/$B$158 -> 0 | R164: =Planejador!$I$122
A165: 46180 | B165: =TEXT(A165,"dddd") -> domingo | D165: =SUMIF('ADV - GG'!A:A,A165,'ADV - GG'!C:C)+SUMIF('ADV - FB'!A:A,$A165,'ADV - FB'!E:E) -> 0 | E165: =SUMIF('ADV - GG'!A:A,A165,'ADV - GG'!H:H)+SUMIF('ADV - FB'!A:A,$A165,'ADV - FB'!I:I)+SUMIF('ADV - FB'!A:A,$A165,'ADV - FB'!J:J)+SUMIF('ADV - FB'!A:A,$A165,'ADV - FB'!K:K) -> 0 | F165: =IFERROR(D165/E165,"") | J165: =SUMIF('ADV - GA4'!A:A,A165,'ADV - GA4'!C:C) -> 0 | K165: =IFERROR(D165/J165,"") | L165: =iferror(E165/J165,"") | M165: =$M$158/$B$158 -> 0 | N165: =iferror($N$158/$B$158,"") -> 0 | O165: =iferror(Planejador!$I$128,"") | P165: =Planejador!$I$120 | Q165: =$Q$158/$B$158 -> 0 | R165: =Planejador!$I$122
A166: 46181 | B166: =TEXT(A166,"dddd") -> segunda-feira | D166: =SUMIF('ADV - GG'!A:A,A166,'ADV - GG'!C:C)+SUMIF('ADV - FB'!A:A,$A166,'ADV - FB'!E:E) -> 0 | E166: =SUMIF('ADV - GG'!A:A,A166,'ADV - GG'!H:H)+SUMIF('ADV - FB'!A:A,$A166,'ADV - FB'!I:I)+SUMIF('ADV - FB'!A:A,$A166,'ADV - FB'!J:J)+SUMIF('ADV - FB'!A:A,$A166,'ADV - FB'!K:K) -> 0 | F166: =IFERROR(D166/E166,"") | J166: =SUMIF('ADV - GA4'!A:A,A166,'ADV - GA4'!C:C) -> 0 | K166: =IFERROR(D166/J166,"") | L166: =iferror(E166/J166,"") | M166: =$M$158/$B$158 -> 0 | N166: =iferror($N$158/$B$158,"") -> 0 | O166: =iferror(Planejador!$I$128,"") | P166: =Planejador!$I$120 | Q166: =$Q$158/$B$158 -> 0 | R166: =Planejador!$I$122
A167: 46182 | B167: =TEXT(A167,"dddd") -> terça-feira | D167: =SUMIF('ADV - GG'!A:A,A167,'ADV - GG'!C:C)+SUMIF('ADV - FB'!A:A,$A167,'ADV - FB'!E:E) -> 0 | E167: =SUMIF('ADV - GG'!A:A,A167,'ADV - GG'!H:H)+SUMIF('ADV - FB'!A:A,$A167,'ADV - FB'!I:I)+SUMIF('ADV - FB'!A:A,$A167,'ADV - FB'!J:J)+SUMIF('ADV - FB'!A:A,$A167,'ADV - FB'!K:K) -> 0 | F167: =IFERROR(D167/E167,"") | J167: =SUMIF('ADV - GA4'!A:A,A167,'ADV - GA4'!C:C) -> 0 | K167: =IFERROR(D167/J167,"") | L167: =iferror(E167/J167,"") | M167: =$M$158/$B$158 -> 0 | N167: =iferror($N$158/$B$158,"") -> 0 | O167: =iferror(Planejador!$I$128,"") | P167: =Planejador!$I$120 | Q167: =$Q$158/$B$158 -> 0 | R167: =Planejador!$I$122
A168: 46183 | B168: =TEXT(A168,"dddd") -> quarta-feira | D168: =SUMIF('ADV - GG'!A:A,A168,'ADV - GG'!C:C)+SUMIF('ADV - FB'!A:A,$A168,'ADV - FB'!E:E) -> 0 | E168: =SUMIF('ADV - GG'!A:A,A168,'ADV - GG'!H:H)+SUMIF('ADV - FB'!A:A,$A168,'ADV - FB'!I:I)+SUMIF('ADV - FB'!A:A,$A168,'ADV - FB'!J:J)+SUMIF('ADV - FB'!A:A,$A168,'ADV - FB'!K:K) -> 0 | F168: =IFERROR(D168/E168,"") | J168: =SUMIF('ADV - GA4'!A:A,A168,'ADV - GA4'!C:C) -> 0 | K168: =IFERROR(D168/J168,"") | L168: =iferror(E168/J168,"") | M168: =$M$158/$B$158 -> 0 | N168: =iferror($N$158/$B$158,"") -> 0 | O168: =iferror(Planejador!$I$128,"") | P168: =Planejador!$I$120 | Q168: =$Q$158/$B$158 -> 0 | R168: =Planejador!$I$122
A169: 46184 | B169: =TEXT(A169,"dddd") -> quinta-feira | D169: =SUMIF('ADV - GG'!A:A,A169,'ADV - GG'!C:C)+SUMIF('ADV - FB'!A:A,$A169,'ADV - FB'!E:E) -> 0 | E169: =SUMIF('ADV - GG'!A:A,A169,'ADV - GG'!H:H)+SUMIF('ADV - FB'!A:A,$A169,'ADV - FB'!I:I)+SUMIF('ADV - FB'!A:A,$A169,'ADV - FB'!J:J)+SUMIF('ADV - FB'!A:A,$A169,'ADV - FB'!K:K) -> 0 | F169: =IFERROR(D169/E169,"") | J169: =SUMIF('ADV - GA4'!A:A,A169,'ADV - GA4'!C:C) -> 0 | K169: =IFERROR(D169/J169,"") | L169: =iferror(E169/J169,"") | M169: =$M$158/$B$158 -> 0 | N169: =iferror($N$158/$B$158,"") -> 0 | O169: =iferror(Planejador!$I$128,"") | P169: =Planejador!$I$120 | Q169: =$Q$158/$B$158 -> 0 | R169: =Planejador!$I$122
A170: 46185 | B170: =TEXT(A170,"dddd") -> sexta-feira | D170: =SUMIF('ADV - GG'!A:A,A170,'ADV - GG'!C:C)+SUMIF('ADV - FB'!A:A,$A170,'ADV - FB'!E:E) -> 0 | E170: =SUMIF('ADV - GG'!A:A,A170,'ADV - GG'!H:H)+SUMIF('ADV - FB'!A:A,$A170,'ADV - FB'!I:I)+SUMIF('ADV - FB'!A:A,$A170,'ADV - FB'!J:J)+SUMIF('ADV - FB'!A:A,$A170,'ADV - FB'!K:K) -> 0 | F170: =IFERROR(D170/E170,"") | J170: =SUMIF('ADV - GA4'!A:A,A170,'ADV - GA4'!C:C) -> 0 | K170: =IFERROR(D170/J170,"") | L170: =iferror(E170/J170,"") | M170: =$M$158/$B$158 -> 0 | N170: =iferror($N$158/$B$158,"") -> 0 | O170: =iferror(Planejador!$I$128,"") | P170: =Planejador!$I$120 | Q170: =$Q$158/$B$158 -> 0 | R170: =Planejador!$I$122
... A188: 46203 | B188: =TEXT(A188,"dddd") -> terça-feira | D188: =SUMIF('ADV - GG'!A:A,A188,'ADV - GG'!C:C)+SUMIF('ADV - FB'!A:A,$A188,'ADV - FB'!E:E) -> 0 | E188: =SUMIF('ADV - GG'!A:A,A188,'ADV - GG'!H:H)+SUMIF('ADV - FB'!A:A,$A188,'ADV - FB'!I:I)+SUMIF('ADV - FB'!A:A,$A188,'ADV - FB'!J:J)+SUMIF('ADV - FB'!A:A,$A188,'ADV - FB'!K:K) -> 0 | F188: =IFERROR(D188/E188,"") | J188: =SUMIF('ADV - GA4'!A:A,A188,'ADV - GA4'!C:C) -> 0 | K188: =IFERROR(D188/J188,"") | L188: =iferror(E188/J188,"") | M188: =$M$158/$B$158 -> 0 | N188: =iferror($N$158/$B$158,"") -> 0 | O188: =iferror(Planejador!$I$128,"") | P188: =Planejador!$I$120 | Q188: =$Q$158/$B$158 -> 0 | R188: =Planejador!$I$122
A189: JULHO | B189: 31 | D189: =IFERROR(SUM(D190:D220),"") -> 0 | E189: =iferror(SUM(E190:E220),"") -> 0 | F189: =IFERROR(D189/E189,"") | G189: =iferror(SUM(G190:G220),"") -> 0 | H189: =iferror(SUM(H190:H220),"") -> 0 | I189: =iferror(SUM(I190:I220),"") -> 0 | J189: =IFERROR(SUM(J190:J220),"") -> 0 | K189: =iferror(D189/J189,"") | L189: =iferror(E189/J189,"") | M189: =Planejador!$I$142 | N189: =iferror(Planejador!$I$149,"") | O189: =iferror(Planejador!$I$151,"") | P189: =iferror(Planejador!$I$143,"") | Q189: =iferror(Planejador!$I$148,"") | R189: =Iferror(Planejador!$I$145,"")
A190: 46204 | B190: =TEXT(A190,"dddd") -> quarta-feira | D190: =SUMIF('ADV - GG'!A:A,A190,'ADV - GG'!C:C)+SUMIF('ADV - FB'!A:A,$A190,'ADV - FB'!E:E) -> 0 | E190: =SUMIF('ADV - GG'!A:A,A190,'ADV - GG'!H:H)+SUMIF('ADV - FB'!A:A,$A190,'ADV - FB'!I:I)+SUMIF('ADV - FB'!A:A,$A190,'ADV - FB'!J:J)+SUMIF('ADV - FB'!A:A,$A190,'ADV - FB'!K:K) -> 0 | F190: =IFERROR(D190/E190,"") | J190: =SUMIF('ADV - GA4'!A:A,A190,'ADV - GA4'!C:C) -> 0 | K190: =IFERROR(D190/J190,"") | L190: =iferror(E190/J190,"") | M190: =$M$189/$B$189 -> 0 | N190: =iferror($N$189/$B$189,"") -> 0 | O190: =iferror(Planejador!$I$151,"") | P190: =Planejador!$I$143 | Q190: =$Q$189/$B$189 -> 0 | R190: =Planejador!$I$145
A191: 46205 | B191: =TEXT(A191,"dddd") -> quinta-feira | D191: =SUMIF('ADV - GG'!A:A,A191,'ADV - GG'!C:C)+SUMIF('ADV - FB'!A:A,$A191,'ADV - FB'!E:E) -> 0 | E191: =SUMIF('ADV - GG'!A:A,A191,'ADV - GG'!H:H)+SUMIF('ADV - FB'!A:A,$A191,'ADV - FB'!I:I)+SUMIF('ADV - FB'!A:A,$A191,'ADV - FB'!J:J)+SUMIF('ADV - FB'!A:A,$A191,'ADV - FB'!K:K) -> 0 | F191: =IFERROR(D191/E191,"") | J191: =SUMIF('ADV - GA4'!A:A,A191,'ADV - GA4'!C:C) -> 0 | K191: =IFERROR(D191/J191,"") | L191: =iferror(E191/J191,"") | M191: =$M$189/$B$189 -> 0 | N191: =iferror($N$189/$B$189,"") -> 0 | O191: =iferror(Planejador!$I$151,"") | P191: =Planejador!$I$143 | Q191: =$Q$189/$B$189 -> 0 | R191: =Planejador!$I$145
A192: 46206 | B192: =TEXT(A192,"dddd") -> sexta-feira | D192: =SUMIF('ADV - GG'!A:A,A192,'ADV - GG'!C:C)+SUMIF('ADV - FB'!A:A,$A192,'ADV - FB'!E:E) -> 0 | E192: =SUMIF('ADV - GG'!A:A,A192,'ADV - GG'!H:H)+SUMIF('ADV - FB'!A:A,$A192,'ADV - FB'!I:I)+SUMIF('ADV - FB'!A:A,$A192,'ADV - FB'!J:J)+SUMIF('ADV - FB'!A:A,$A192,'ADV - FB'!K:K) -> 0 | F192: =IFERROR(D192/E192,"") | J192: =SUMIF('ADV - GA4'!A:A,A192,'ADV - GA4'!C:C) -> 0 | K192: =IFERROR(D192/J192,"") | L192: =iferror(E192/J192,"") | M192: =$M$189/$B$189 -> 0 | N192: =iferror($N$189/$B$189,"") -> 0 | O192: =iferror(Planejador!$I$151,"") | P192: =Planejador!$I$143 | Q192: =$Q$189/$B$189 -> 0 | R192: =Planejador!$I$145
A193: 46207 | B193: =TEXT(A193,"dddd") -> sábado | D193: =SUMIF('ADV - GG'!A:A,A193,'ADV - GG'!C:C)+SUMIF('ADV - FB'!A:A,$A193,'ADV - FB'!E:E) -> 0 | E193: =SUMIF('ADV - GG'!A:A,A193,'ADV - GG'!H:H)+SUMIF('ADV - FB'!A:A,$A193,'ADV - FB'!I:I)+SUMIF('ADV - FB'!A:A,$A193,'ADV - FB'!J:J)+SUMIF('ADV - FB'!A:A,$A193,'ADV - FB'!K:K) -> 0 | F193: =IFERROR(D193/E193,"") | J193: =SUMIF('ADV - GA4'!A:A,A193,'ADV - GA4'!C:C) -> 0 | K193: =IFERROR(D193/J193,"") | L193: =iferror(E193/J193,"") | M193: =$M$189/$B$189 -> 0 | N193: =iferror($N$189/$B$189,"") -> 0 | O193: =iferror(Planejador!$I$151,"") | P193: =Planejador!$I$143 | Q193: =$Q$189/$B$189 -> 0 | R193: =Planejador!$I$145
A194: 46208 | B194: =TEXT(A194,"dddd") -> domingo | D194: =SUMIF('ADV - GG'!A:A,A194,'ADV - GG'!C:C)+SUMIF('ADV - FB'!A:A,$A194,'ADV - FB'!E:E) -> 0 | E194: =SUMIF('ADV - GG'!A:A,A194,'ADV - GG'!H:H)+SUMIF('ADV - FB'!A:A,$A194,'ADV - FB'!I:I)+SUMIF('ADV - FB'!A:A,$A194,'ADV - FB'!J:J)+SUMIF('ADV - FB'!A:A,$A194,'ADV - FB'!K:K) -> 0 | F194: =IFERROR(D194/E194,"") | J194: =SUMIF('ADV - GA4'!A:A,A194,'ADV - GA4'!C:C) -> 0 | K194: =IFERROR(D194/J194,"") | L194: =iferror(E194/J194,"") | M194: =$M$189/$B$189 -> 0 | N194: =iferror($N$189/$B$189,"") -> 0 | O194: =iferror(Planejador!$I$151,"") | P194: =Planejador!$I$143 | Q194: =$Q$189/$B$189 -> 0 | R194: =Planejador!$I$145
A195: 46209 | B195: =TEXT(A195,"dddd") -> segunda-feira | D195: =SUMIF('ADV - GG'!A:A,A195,'ADV - GG'!C:C)+SUMIF('ADV - FB'!A:A,$A195,'ADV - FB'!E:E) -> 0 | E195: =SUMIF('ADV - GG'!A:A,A195,'ADV - GG'!H:H)+SUMIF('ADV - FB'!A:A,$A195,'ADV - FB'!I:I)+SUMIF('ADV - FB'!A:A,$A195,'ADV - FB'!J:J)+SUMIF('ADV - FB'!A:A,$A195,'ADV - FB'!K:K) -> 0 | F195: =IFERROR(D195/E195,"") | J195: =SUMIF('ADV - GA4'!A:A,A195,'ADV - GA4'!C:C) -> 0 | K195: =IFERROR(D195/J195,"") | L195: =iferror(E195/J195,"") | M195: =$M$189/$B$189 -> 0 | N195: =iferror($N$189/$B$189,"") -> 0 | O195: =iferror(Planejador!$I$151,"") | P195: =Planejador!$I$143 | Q195: =$Q$189/$B$189 -> 0 | R195: =Planejador!$I$145
A196: 46210 | B196: =TEXT(A196,"dddd") -> terça-feira | D196: =SUMIF('ADV - GG'!A:A,A196,'ADV - GG'!C:C)+SUMIF('ADV - FB'!A:A,$A196,'ADV - FB'!E:E) -> 0 | E196: =SUMIF('ADV - GG'!A:A,A196,'ADV - GG'!H:H)+SUMIF('ADV - FB'!A:A,$A196,'ADV - FB'!I:I)+SUMIF('ADV - FB'!A:A,$A196,'ADV - FB'!J:J)+SUMIF('ADV - FB'!A:A,$A196,'ADV - FB'!K:K) -> 0 | F196: =IFERROR(D196/E196,"") | J196: =SUMIF('ADV - GA4'!A:A,A196,'ADV - GA4'!C:C) -> 0 | K196: =IFERROR(D196/J196,"") | L196: =iferror(E196/J196,"") | M196: =$M$189/$B$189 -> 0 | N196: =iferror($N$189/$B$189,"") -> 0 | O196: =iferror(Planejador!$I$151,"") | P196: =Planejador!$I$143 | Q196: =$Q$189/$B$189 -> 0 | R196: =Planejador!$I$145
A197: 46211 | B197: =TEXT(A197,"dddd") -> quarta-feira | D197: =SUMIF('ADV - GG'!A:A,A197,'ADV - GG'!C:C)+SUMIF('ADV - FB'!A:A,$A197,'ADV - FB'!E:E) -> 0 | E197: =SUMIF('ADV - GG'!A:A,A197,'ADV - GG'!H:H)+SUMIF('ADV - FB'!A:A,$A197,'ADV - FB'!I:I)+SUMIF('ADV - FB'!A:A,$A197,'ADV - FB'!J:J)+SUMIF('ADV - FB'!A:A,$A197,'ADV - FB'!K:K) -> 0 | F197: =IFERROR(D197/E197,"") | J197: =SUMIF('ADV - GA4'!A:A,A197,'ADV - GA4'!C:C) -> 0 | K197: =IFERROR(D197/J197,"") | L197: =iferror(E197/J197,"") | M197: =$M$189/$B$189 -> 0 | N197: =iferror($N$189/$B$189,"") -> 0 | O197: =iferror(Planejador!$I$151,"") | P197: =Planejador!$I$143 | Q197: =$Q$189/$B$189 -> 0 | R197: =Planejador!$I$145
A198: 46212 | B198: =TEXT(A198,"dddd") -> quinta-feira | D198: =SUMIF('ADV - GG'!A:A,A198,'ADV - GG'!C:C)+SUMIF('ADV - FB'!A:A,$A198,'ADV - FB'!E:E) -> 0 | E198: =SUMIF('ADV - GG'!A:A,A198,'ADV - GG'!H:H)+SUMIF('ADV - FB'!A:A,$A198,'ADV - FB'!I:I)+SUMIF('ADV - FB'!A:A,$A198,'ADV - FB'!J:J)+SUMIF('ADV - FB'!A:A,$A198,'ADV - FB'!K:K) -> 0 | F198: =IFERROR(D198/E198,"") | J198: =SUMIF('ADV - GA4'!A:A,A198,'ADV - GA4'!C:C) -> 0 | K198: =IFERROR(D198/J198,"") | L198: =iferror(E198/J198,"") | M198: =$M$189/$B$189 -> 0 | N198: =iferror($N$189/$B$189,"") -> 0 | O198: =iferror(Planejador!$I$151,"") | P198: =Planejador!$I$143 | Q198: =$Q$189/$B$189 -> 0 | R198: =Planejador!$I$145
A199: 46213 | B199: =TEXT(A199,"dddd") -> sexta-feira | D199: =SUMIF('ADV - GG'!A:A,A199,'ADV - GG'!C:C)+SUMIF('ADV - FB'!A:A,$A199,'ADV - FB'!E:E) -> 0 | E199: =SUMIF('ADV - GG'!A:A,A199,'ADV - GG'!H:H)+SUMIF('ADV - FB'!A:A,$A199,'ADV - FB'!I:I)+SUMIF('ADV - FB'!A:A,$A199,'ADV - FB'!J:J)+SUMIF('ADV - FB'!A:A,$A199,'ADV - FB'!K:K) -> 0 | F199: =IFERROR(D199/E199,"") | J199: =SUMIF('ADV - GA4'!A:A,A199,'ADV - GA4'!C:C) -> 0 | K199: =IFERROR(D199/J199,"") | L199: =iferror(E199/J199,"") | M199: =$M$189/$B$189 -> 0 | N199: =iferror($N$189/$B$189,"") -> 0 | O199: =iferror(Planejador!$I$151,"") | P199: =Planejador!$I$143 | Q199: =$Q$189/$B$189 -> 0 | R199: =Planejador!$I$145
A200: 46214 | B200: =TEXT(A200,"dddd") -> sábado | D200: =SUMIF('ADV - GG'!A:A,A200,'ADV - GG'!C:C)+SUMIF('ADV - FB'!A:A,$A200,'ADV - FB'!E:E) -> 0 | E200: =SUMIF('ADV - GG'!A:A,A200,'ADV - GG'!H:H)+SUMIF('ADV - FB'!A:A,$A200,'ADV - FB'!I:I)+SUMIF('ADV - FB'!A:A,$A200,'ADV - FB'!J:J)+SUMIF('ADV - FB'!A:A,$A200,'ADV - FB'!K:K) -> 0 | F200: =IFERROR(D200/E200,"") | J200: =SUMIF('ADV - GA4'!A:A,A200,'ADV - GA4'!C:C) -> 0 | K200: =IFERROR(D200/J200,"") | L200: =iferror(E200/J200,"") | M200: =$M$189/$B$189 -> 0 | N200: =iferror($N$189/$B$189,"") -> 0 | O200: =iferror(Planejador!$I$151,"") | P200: =Planejador!$I$143 | Q200: =$Q$189/$B$189 -> 0 | R200: =Planejador!$I$145
A201: 46215 | B201: =TEXT(A201,"dddd") -> domingo | D201: =SUMIF('ADV - GG'!A:A,A201,'ADV - GG'!C:C)+SUMIF('ADV - FB'!A:A,$A201,'ADV - FB'!E:E) -> 0 | E201: =SUMIF('ADV - GG'!A:A,A201,'ADV - GG'!H:H)+SUMIF('ADV - FB'!A:A,$A201,'ADV - FB'!I:I)+SUMIF('ADV - FB'!A:A,$A201,'ADV - FB'!J:J)+SUMIF('ADV - FB'!A:A,$A201,'ADV - FB'!K:K) -> 0 | F201: =IFERROR(D201/E201,"") | J201: =SUMIF('ADV - GA4'!A:A,A201,'ADV - GA4'!C:C) -> 0 | K201: =IFERROR(D201/J201,"") | L201: =iferror(E201/J201,"") | M201: =$M$189/$B$189 -> 0 | N201: =iferror($N$189/$B$189,"") -> 0 | O201: =iferror(Planejador!$I$151,"") | P201: =Planejador!$I$143 | Q201: =$Q$189/$B$189 -> 0 | R201: =Planejador!$I$145
... A220: 46234 | B220: =TEXT(A220,"dddd") -> sexta-feira | D220: =SUMIF('ADV - GG'!A:A,A220,'ADV - GG'!C:C)+SUMIF('ADV - FB'!A:A,$A220,'ADV - FB'!E:E) -> 0 | E220: =SUMIF('ADV - GG'!A:A,A220,'ADV - GG'!H:H)+SUMIF('ADV - FB'!A:A,$A220,'ADV - FB'!I:I)+SUMIF('ADV - FB'!A:A,$A220,'ADV - FB'!J:J)+SUMIF('ADV - FB'!A:A,$A220,'ADV - FB'!K:K) -> 0 | F220: =IFERROR(D220/E220,"") | J220: =SUMIF('ADV - GA4'!A:A,A220,'ADV - GA4'!C:C) -> 0 | K220: =IFERROR(D220/J220,"") | L220: =iferror(E220/J220,"") | M220: =$M$189/$B$189 -> 0 | N220: =iferror($N$189/$B$189,"") -> 0 | O220: =iferror(Planejador!$I$151,"") | P220: =Planejador!$I$143 | Q220: =$Q$189/$B$189 -> 0 | R220: =Planejador!$I$145
A221: AGOSTO | B221: 31 | D221: =IFERROR(SUM(D222:D252),"") -> 0 | E221: =iferror(SUM(E222:E252),"") -> 0 | F221: =IFERROR(D221/E221,"") | G221: =iferror(SUM(G222:G252),"") -> 0 | H221: =iferror(SUM(H222:H252),"") -> 0 | I221: =iferror(SUM(I222:I252),"") -> 0 | J221: =IFERROR(SUM(J222:J252),"") -> 0 | K221: =iferror(D221/J221,"") | L221: =iferror(E221/J221,"") | M221: =Planejador!$I$165 | N221: =iferror(Planejador!$I$172,"") | O221: =iferror(Planejador!$I$174,"") | P221: =iferror(Planejador!$I$166,"") | Q221: =iferror(Planejador!$I$171,"") | R221: =Iferror(Planejador!$I$168,"")
...

Sheet Calculadora de Leads
I1: Calculadora de Leads
B2: Preencha os campos abaixo e descubra qual a quantidade de Leads necessarios para atingir seus objetivos comerciais.
M4: Etapa do funil | V4: Quantidade Necessária | Y4: Quantidade Atual | AB4: Taxa
B5: Selecione o seu segmento:
M6: Visitantes Únicos | V6: =IF(AB8=0,0,ROUNDDOWN(V9/AB8,0)) -> 2719 | Y6: =IF(B31="",0,ROUNDDOWN(B31,0)) -> 1000
B7: Telecomunicações
AB8: =VLOOKUP($B$7,'Benchmark de Taxas'!$A$4:$D34,2,FALSE) -> 0.057
B9: Preencha a baixo o valor que pretende vender no Mês | M9: Leads | V9: =IF(AB11=0,0,ROUNDDOWN(V12/AB11,0)) -> 155 | Y9: =ROUNDUP(Y6*AB8,0) -> 57
B11: 30000 | AB11: =VLOOKUP($B$7,'Benchmark de Taxas'!$A$4:$D34,3,FALSE) -> 0.436
M12: Oportunidades | V12: =IF(AB14=0,0,ROUNDDOWN(V15/AB14,0)) -> 68 | Y12: =ROUNDUP(Y9*AB11,0) -> 25
B14: Qual é o seu Ticket médio? Valor medio de cada venda | AB14: =VLOOKUP($B$7,'Benchmark de Taxas'!$A$4:$D34,4,FALSE) -> 0.147
M15: Vendas | V15: =V23 -> 10 | Y15: =ROUNDUP(Y12*AB14,0) -> 4
B16: 3000
B19: Quantos leads seu MELHOR vendedor atende em média por mês? | M19: Sua taxa de Conversão
V20: =IFERROR(IF(V15=0,0,V15/V6),0) -> 0.0036778227 | Y20: =IF(AB6=0,"Preencha todos os campos corretamente para visualizar o resultado.",(IF(Y6=AB6,"_______________PARABÉNS 😊_______________ Sua empresa tem o número de visitantes únicos suficiente para atingir seus objetivos comerciais. Para obter resultados ainda melhores, tente otimizar a média de vendas da sua equipe e avalie aumentar seu investime"&"nto em mídia e/ou otimizar suas campanhas. A equipe da TURBO terá prazer em acompanhar sua jornada de sucesso.",IF(AB6>Y6,"_______________PARABÉNS 😊_______________ Sua empresa tem mais visitantes únicos do que a média do seu setor, o que é um bom sinal. No entanto, é importante lembrar que o número de visitantes não é o único fator que determina o sucesso de uma empresa. Se "&"você não estiver atingindo seus resultados, pode ser necessário investir em treinamentos para sua equipe de vendas ou rever seus processos internos. Além disso, é importante avaliar se o investimento em mídia pode ser otimizado para obter resultados ainda"&" melhores. A equipe da TURBO terá prazer em acompanhar sua jornada de sucesso.","_______________ATENÇÃO ⚠️_______________ Sua empresa não tem um número de visitantes únicos suficiente para atingir suas metas comerciais. Para alcançar seus objetivos, é importante reavaliar seu investimento em mídia e procurar um de nossos especialistas"&" para que possamos juntos traçar uma estratégia realista e eficaz. A equipe da TURBO terá prazer em acompanhar sua jornada de sucesso.")))) -> Preencha todos os campos corretamente para visualizar o resultado.
B21: 50
M22: Número de vendas necessárias
V23: =IF(B16=0,0,ROUNDUP(B11/B16,0)) -> 10
B24: Quantos leads seu PIOR vendedor atende em média por mês?
M25: Número de vendedores necessários
B26: 10 | V26: =IFERROR(ROUNDUP(V12/((B21+B26)/2),0),0) -> 3
M28: Número de leads que cada vendedor precisa atender
B29: Quantos Visitantes únicos você tem em média hoje? | V29: =IFERROR(IF($V$26=0,0,ROUNDUP(V12/$V$26,0)),0) -> 23
B31: 1000 | M31: Número de vendas que cada vendedor precisa realizar
V32: =IFERROR(IF($V$26=0,0,ROUNDUP(V15/$V$26,0)),0) -> 4

Sheet Projeção Rápida
D1: PROJEÇÃO RÁPIDA
B3: Investimento | D3: CPS | G3: Canal | H3: Facebook | I3: Google | J3: Outros
B4: 10000 | D4: 0.1 | G4: % | H4: 0.7 | I4: 0.4 | J4: 0
G5: Verba Mês | H5: =H4*$B$4 -> 7000 | I5: =I4*$B$4 -> 4000 | J5: =J4*$B$4 -> 0
B6: Ticket Médio | D6: Taxa de Conversão Visita -> Lead | G6: Verba Dia | H6: =ROUNDUP((B4*H4)/30,0) -> 234 | I6: =ROUNDUP((B4*I4)/30,0) -> 134 | J6: =ROUNDUP((B4*J4)/30,0) -> 0 | K6: =SUM(H6:J6) -> 368
B7: 100 | D7: 0.5
B9: Taxa de Leads Qualificados | D9: Taxa Conversão Lead para Venda
B10: 0.3 | D10: 0.1
B12: LEADS | D12: LEADS QUALIFICADOS
B13: =(B4/D4)*D7 -> 50000 | D13: =B13*B10 -> 15000
B15: CPL | D15: VENDAS
B16: =B4/B13 -> 0.2 | D16: =B13*D10 -> 5000
B18: FATURAMENTO
B19: =D16*B7 -> 500000
B21: ANTES DE ENTRAR NO SITE | D21: DEPOIS DE ENTRAR NO SITE | F21: BENCHMARK DE TAXAS
B22: MELHORIAS PARA CPC | D22: MELHORIAS PARA TX | F22: Segmento | G22: Leads | H22: Oportunidades | I22: Vendas
B23: CRIATIVO | D23: NAVEGABILIDADE | F23: Agência de Marketing e Publicidade | G23: 0.04 | H23: 0.135 | I23: 0.24
B24: COPY | D24: CONTEÚDO | F24: Consultorias e Treinamentos | G24: 0.045 | H24: 0.123 | I24: 0.379
B25: PÚBLICO | D25: OFERTA | F25: E-commerce | G25: 0.03 | H25: 0.211 | I25: 0.614
B26: OFERTA | D26: FRETE | F26: Educação e Ensino | G26: 0.063 | H26: 0.121 | I26: 0.321
B27: CAMPANHAS DE CPC BAIXO | D27: CHECKOUT | F27: Engenharia e Indústria em Geral | G27: 0.038 | H27: 0.176 | I27: 0.373
B28: PRODUTO | D28: CREDIBILIDADE E PROVA SOCIAL | F28: Eventos | G28: 0.043 | H28: 0.102 | I28: 0.572
B29: QUALIDADE DA PÁGINA | F29: Financeiro, Jurídico e Serviços Relacionados | G29: 0.046 | H29: 0.148 | I29: 0.239
F30: Hardware e Eletrônicos | G30: 0.055 | H30: 0.116 | I30: 0.607
F31: Imobiliárias | G31: 0.029 | H31: 0.131 | I31: 0.383
F32: Mídia e Comunicação | G32: 0.038 | H32: 0.108 | I32: 0.268
F33: ONGs | G33: 0.047 | H33: 0.126 | I33: 0.244
F34: Saúde e Estética | G34: 0.051 | H34: 0.224 | I34: 0.363
F35: Serviços em Geral | G35: 0.041 | H35: 0.227 | I35: 0.358
F36: Serviços em RH e Coaching | G36: 0.05 | H36: 0.162 | I36: 0.209
F37: Software e Cloud | G37: 0.057 | H37: 0.122 | I37: 0.148
F38: Telecomunicações | G38: 0.057 | H38: 0.436 | I38: 0.147
F39: Turismo e Lazer | G39: 0.051 | H39: 0.239 | I39: 0.252
F40: Varejo | G40: 0.026 | H40: 0.217 | I40: 0.169

Sheet Planejador
B1: JANEIRO
B3: CENÁRIO ATUAL (ÚLTIMO MÊS) | E3: CENÁRIO DESEJADO | H3: CENÁRIO IDEAL | J3: MÉDIA / ANUAL | K3: % ATUAL | L3: % MÁX
B4: Valor Investimento | E4: Faturamento Desejado | H4: Verba Mensal | K4: =(I4-J4)/J4*1 -> #DIV/0! | L4: 0.4
B5: CPS Geral | E5: CPS Atual | F5: =C5 | H5: CPS Ideal | K5: =(I5-J5)/J5*1 -> #DIV/0! | L5: -0.1
B6: Ticket Médio | E6: Ticket Médio | F6: =C6 | H6: Ticket Médio Ideal | K6: =(I6-J6)/J6*1 -> #DIV/0! | L6: 0.15
B7: TX Conversão Para Lead | E7: TX Conversão Para Lead | F7: =C7 | H7: TX Conversão Para Lead Ideal | K7: =(I7-J7)/J7*1 -> #DIV/0! | L7: 0.15
B8: % Lead Para Venda | E8: % Lead Para Venda | F8: =C8 | H8: % Lead Para Venda Ideal | K8: =(I8-J8)/J8*1 -> #DIV/0! | L8: 0.1
B10: Sessões | C10: =C4/C5 -> #DIV/0! | E10: Sessões Ideais | F10: =(F12/F7)/F8 -> #DIV/0! | H10: Sessões Ideais | I10: =I4/I5 -> #DIV/0! | K10: CANAL DE VENDA | L10: % | M10: FATURAMENTO | N10: PEDIDOS POR CANAL
B11: Leads | C11: =C10*C7 -> #DIV/0! | E11: Leads Ideais | F11: =F10*F7 -> #DIV/0! | H11: Leads Ideais | I11: =I10*I7 -> #DIV/0! | K11: Meta Ads | L11: 0.2 | M11: =I15/100*L11*100 -> #DIV/0! | N11: =M11/I6 -> #DIV/0!
B12: Vendas | C12: =C11*C8 -> #DIV/0! | E12: Vendas | F12: =F4/F6 -> #DIV/0! | H12: Vendas | I12: =I15/I6 -> #DIV/0! | K12: Google Ads | L12: 0.2 | M12: =I15/100*L12*100 -> #DIV/0! | N12: =M12/I6 -> #DIV/0!
B13: CPL | C13: =C4/C11 -> #DIV/0! | E13: CPL Ideal | F13: =F15/F11 -> #DIV/0! | H13: CPL Ideal | I13: =I4/I11 -> #DIV/0! | K13: Social | L13: 0.3 | M13: =I15/100*L13*100 -> #DIV/0! | N13: =M13/I6 -> #DIV/0!
B14: CPA | C14: =C4/C12 -> #DIV/0! | E14: CPA | F14: =F15/F12 -> #DIV/0! | H14: CPA | I14: =I4/I12 -> #DIV/0! | K14: Organico | L14: 0.15 | M14: =I15/100*L14*100 -> #DIV/0! | N14: =M14/I6 -> #DIV/0!
B15: Faturamento Real | C15: =C12*C6 -> #DIV/0! | E15: Investimento Necessário | F15: =F10*F5 -> #DIV/0! | H15: Faturamento Desejado | I15: =(I10*I7*I8)*I6 -> #DIV/0! | K15: E-mail | L15: 0.15 | M15: =I15/100*L15*100 -> #DIV/0! | N15: =M15/I6 -> #DIV/0!
B16: ROAS | C16: =C15/C4 -> #DIV/0! | E16: ROAS | F16: =F4/F15 -> #DIV/0! | H16: ROAS | I16: =I15/I4 -> #DIV/0! | L16: =SUM(L11:L15) -> 1 | N16: =SUM(N11:N15) -> #DIV/0!
B18: CENÁRIO DIÁRIO ATUAL | E18: CENÁRIO DIÁRIO DESEJADO | H18: CENÁRIO DIÁRIO IDEAL | K18: Canal | L18: Facebook | M18: Google | N18: Outros | O18: Total
B19: Investimento Diário | C19: =C4/30 -> 0 | E19: Investimento Diário | F19: =F4/30 -> 0 | H19: Investimento Diário | I19: =I4/'Acompanhamento Geral'!B2 -> 0 | K19: % | L19: 0.1 | M19: 0.9 | N19: 0 | O19: =sum(L19:N19) -> 1
B20: Sessões Diárias | C20: =C10/30 -> #DIV/0! | E20: Sessões Diárias | F20: =F10/30 -> #DIV/0! | H20: Sessões Diárias | I20: =I10/'Acompanhamento Geral'!B2 -> #DIV/0! | K20: Verba Mês | L20: =I4*L19 -> 0 | M20: =I4*M19 -> 0 | N20: =I4*N19 -> 0 | O20: =sum(L20:N20) -> 0
B21: Pedidos Diários | C21: =C12/30 -> #DIV/0! | E21: Pedidos Diários | F21: =F12/30 -> #DIV/0! | H21: Pedidos Diários | I21: =I12/'Acompanhamento Geral'!B2 -> #DIV/0! | K21: Verba Dia | L21: =L20/'Acompanhamento Geral'!B2 -> 0 | M21: =M20/'Acompanhamento Geral'!B2 -> 0 | N21: =iferror(N20/'Acompanhamento Geral'!B2,"") -> 0 | O21: =SUM(L21:N21) -> 0
B22: Faturamento Diário | C22: =C15/30 -> #DIV/0! | E22: Faturamento Diário | F22: =F4/30 -> 0 | H22: Faturamento Diário | I22: =I15/'Acompanhamento Geral'!B2 -> #DIV/0!
B24: FEVEREIRO
B26: CENÁRIO ATUAL (ÚLTIMO MÊS) | E26: CENÁRIO DESEJADO | H26: CENÁRIO IDEAL | J26: MÉDIA / ANUAL | K26: % ATUAL | L26: % MÁX
B27: Valor Investimento | E27: Faturamento Desejado | H27: Verba Mensal | K27: =(I27-J27)/J27*1 -> #DIV/0! | L27: 0.4
B28: CPS Geral | E28: CPS Atual | F28: =C28 | H28: CPS Ideal | K28: =(I28-J28)/J28*1 -> #DIV/0! | L28: -0.1
B29: Ticket Médio | E29: Ticket Médio | F29: =C29 | H29: Ticket Médio Ideal | K29: =(I29-J29)/J29*1 -> #DIV/0! | L29: 0.15
B30: TX Conversão Para Lead | E30: TX Conversão Para Lead | F30: =C30 | H30: TX Conversão Para Lead Ideal | K30: =(I30-J30)/J30*1 -> #DIV/0! | L30: 0.1
B31: % Lead Para Venda | E31: % Lead Para Venda | F31: =C31 | H31: % Lead Para Venda Ideal | K31: =(I31-J31)/J31*1 -> #DIV/0! | L31: 0.1
B33: Sessões | C33: =C27/C28 -> #DIV/0! | E33: Sessões Ideais | F33: =(F35/F30)/F31 -> #DIV/0! | H33: Sessões Ideais | I33: =I27/I28 -> #DIV/0! | K33: CANAL DE VENDA | L33: % | M33: FATURAMENTO | N33: PEDIDOS POR CANAL
B34: Leads | C34: =C33*C30 -> #DIV/0! | E34: Leads Ideais | F34: =F33*F30 -> #DIV/0! | H34: Leads Ideais | I34: =I33*I30 -> #DIV/0! | K34: Meta Ads | L34: 0.2 | M34: =I38/100*L34*100 -> #DIV/0! | N34: =M34/I29 -> #DIV/0!
B35: Vendas | C35: =C34*C31 -> #DIV/0! | E35: Vendas | F35: =F27/F29 -> #DIV/0! | H35: Vendas | I35: =I38/I29 -> #DIV/0! | K35: Google Ads | L35: 0.2 | M35: =I38/100*L35*100 -> #DIV/0! | N35: =M35/I29 -> #DIV/0!
B36: CPL | C36: =C27/C34 -> #DIV/0! | E36: CPL Ideal | F36: =F38/F34 -> #DIV/0! | H36: CPL Ideal | I36: =I27/I34 -> #DIV/0! | K36: Social | L36: 0.3 | M36: =I38/100*L36*100 -> #DIV/0! | N36: =M36/I29 -> #DIV/0!
B37: CPA | C37: =C27/C35 -> #DIV/0! | E37: CPA | F37: =F38/F35 -> #DIV/0! | H37: CPA | I37: =I27/I35 -> #DIV/0! | K37: Organico | L37: 0.15 | M37: =I38/100*L37*100 -> #DIV/0! | N37: =M37/I29 -> #DIV/0!
B38: Faturamento Real | C38: =C35*C29 -> #DIV/0! | E38: Investimento Necessário | F38: =F33*F28 -> #DIV/0! | H38: Faturamento Desejado | I38: =(I33*I30*I31)*I29 -> #DIV/0! | K38: E-mail | L38: 0.15 | M38: =I38/100*L38*100 -> #DIV/0! | N38: =M38/I29 -> #DIV/0!
B39: ROAS | C39: =C38/C27 -> #DIV/0! | E39: ROAS | F39: =F27/F38 -> #DIV/0! | H39: ROAS | I39: =I38/I27 -> #DIV/0! | L39: =SUM(L34:L38) -> 1 | N39: =SUM(N34:N38) -> #DIV/0!
B41: CENÁRIO DIÁRIO ATUAL | E41: CENÁRIO DIÁRIO DESEJADO | H41: CENÁRIO DIÁRIO IDEAL | K41: Canal | L41: Facebook | M41: Google | N41: Outros | O41: Total
B42: Investimento Diário | C42: =C27/30 -> 0 | E42: Investimento Diário | F42: =F27/30 -> 0 | H42: Investimento Diário | I42: =I27/'Acompanhamento Geral'!B25 -> #VALUE! | K42: % | L42: 0.7 | M42: 0.3 | N42: 0 | O42: =sum(L42:N42) -> 1
B43: Sessões Diárias | C43: =C33/30 -> #DIV/0! | E43: Sessões Diárias | F43: =F33/30 -> #DIV/0! | H43: Sessões Diárias | I43: =I33/'Acompanhamento Geral'!B25 -> #DIV/0! | K43: Verba Mês | L43: =I27*L42 -> 0 | M43: =I27*M42 -> 0 | N43: =I27*N42 -> 0 | O43: =sum(L43:N43) -> 0
B44: Pedidos Diários | C44: =C35/30 -> #DIV/0! | E44: Pedidos Diários | F44: =F35/30 -> #DIV/0! | H44: Pedidos Diários | I44: =I35/'Acompanhamento Geral'!B25 -> #DIV/0! | K44: Verba Dia | L44: =L43/'Acompanhamento Geral'!B25 -> #VALUE! | M44: =M43/'Acompanhamento Geral'!B25 -> #VALUE! | N44: =iferror(N43/'Acompanhamento Geral'!B25,"") | O44: =SUM(L44:N44) -> #VALUE!
B45: Faturamento Diário | C45: =C38/30 -> #DIV/0! | E45: Faturamento Diário | F45: =F27/30 -> 0 | H45: Faturamento Diário | I45: =I38/'Acompanhamento Geral'!B25 -> #DIV/0!
B47: MARÇO
B49: CENÁRIO ATUAL (ÚLTIMO MÊS) | E49: CENÁRIO DESEJADO | H49: CENÁRIO IDEAL | J49: MÉDIA / ANUAL | K49: % ATUAL | L49: % MÁX
B50: Valor Investimento | E50: Faturamento Desejado | H50: Verba Mensal | K50: =(I50-J50)/J50*1 -> #DIV/0! | L50: 0.4
B51: CPS Geral | E51: CPS Atual | F51: =C51 | H51: CPS Ideal | K51: =(I51-J51)/J51*1 -> #DIV/0! | L51: -0.1
B52: Ticket Médio | E52: Ticket Médio | F52: =C52 | H52: Ticket Médio Ideal | K52: =(I52-J52)/J52*1 -> #DIV/0! | L52: 0.15
B53: TX Conversão Para Lead | E53: TX Conversão Para Lead | F53: =C53 | H53: TX Conversão Para Lead Ideal | K53: =(I53-J53)/J53*1 -> #DIV/0! | L53: 0.1
B54: % Lead Para Venda | E54: % Lead Para Venda | F54: =C54 | H54: % Lead Para Venda Ideal | K54: =(I54-J54)/J54*1 -> #DIV/0! | L54: 0.1
B56: Sessões | C56: =C50/C51 -> #DIV/0! | E56: Sessões Ideais | F56: =(F58/F53)/F54 -> #DIV/0! | H56: Sessões Ideais | I56: =I50/I51 -> #DIV/0! | K56: CANAL DE VENDA | L56: % | M56: FATURAMENTO | N56: PEDIDOS POR CANAL
B57: Leads | C57: =C56*C53 -> #DIV/0! | E57: Leads Ideais | F57: =F56*F53 -> #DIV/0! | H57: Leads Ideais | I57: =I56*I53 -> #DIV/0! | K57: Meta Ads | L57: 0.2 | M57: =I61/100*L57*100 -> #DIV/0! | N57: =M57/I52 -> #DIV/0!
B58: Vendas | C58: =C57*C54 -> #DIV/0! | E58: Vendas | F58: =F50/F52 -> #DIV/0! | H58: Vendas | I58: =I61/I52 -> #DIV/0! | K58: Google Ads | L58: 0.2 | M58: =I61/100*L58*100 -> #DIV/0! | N58: =M58/I52 -> #DIV/0!
B59: CPL | C59: =C50/C57 -> #DIV/0! | E59: CPL Ideal | F59: =F61/F57 -> #DIV/0! | H59: CPL Ideal | I59: =I50/I57 -> #DIV/0! | K59: Social | L59: 0.3 | M59: =I61/100*L59*100 -> #DIV/0! | N59: =M59/I52 -> #DIV/0!
B60: CPA | C60: =C50/C58 -> #DIV/0! | E60: CPA | F60: =F61/F58 -> #DIV/0! | H60: CPA | I60: =I50/I58 -> #DIV/0! | K60: Organico | L60: 0.15 | M60: =I61/100*L60*100 -> #DIV/0! | N60: =M60/I52 -> #DIV/0!
B61: Faturamento Real | C61: =C58*C52 -> #DIV/0! | E61: Investimento Necessário | F61: =F56*F51 -> #DIV/0! | H61: Faturamento Desejado | I61: =(I56*I53*I54)*I52 -> #DIV/0! | K61: E-mail | L61: 0.15 | M61: =I61/100*L61*100 -> #DIV/0! | N61: =M61/I52 -> #DIV/0!
B62: ROAS | C62: =C61/C50 -> #DIV/0! | E62: ROAS | F62: =F50/F61 -> #DIV/0! | H62: ROAS | I62: =I61/I50 -> #DIV/0! | L62: =SUM(L57:L61) -> 1 | N62: =SUM(N57:N61) -> #DIV/0!
B64: CENÁRIO DIÁRIO ATUAL | E64: CENÁRIO DIÁRIO DESEJADO | H64: CENÁRIO DIÁRIO IDEAL | K64: Canal | L64: Facebook | M64: Google | N64: Outros | O64: Total
B65: Investimento Diário | C65: =C50/30 -> 0 | E65: Investimento Diário | F65: =F50/30 -> 0 | H65: Investimento Diário | I65: =I50/'Acompanhamento Geral'!B48 -> #VALUE! | K65: % | L65: 0.7 | M65: 0.3 | N65: 0 | O65: =sum(L65:N65) -> 1
B66: Sessões Diárias | C66: =C56/30 -> #DIV/0! | E66: Sessões Diárias | F66: =F56/30 -> #DIV/0! | H66: Sessões Diárias | I66: =I56/'Acompanhamento Geral'!B48 -> #DIV/0! | K66: Verba Mês | L66: =I50*L65 -> 0 | M66: =I50*M65 -> 0 | N66: =I50*N65 -> 0 | O66: =sum(L66:N66) -> 0
B67: Pedidos Diários | C67: =C58/30 -> #DIV/0! | E67: Pedidos Diários | F67: =F58/30 -> #DIV/0! | H67: Pedidos Diários | I67: =I58/'Acompanhamento Geral'!B48 -> #DIV/0! | K67: Verba Dia | L67: =L66/'Acompanhamento Geral'!B48 -> #VALUE! | M67: =M66/'Acompanhamento Geral'!B48 -> #VALUE! | N67: =iferror(N66/'Acompanhamento Geral'!B48,"") | O67: =SUM(L67:N67) -> #VALUE!
B68: Faturamento Diário | C68: =C61/30 -> #DIV/0! | E68: Faturamento Diário | F68: =F50/30 -> 0 | H68: Faturamento Diário | I68: =I61/'Acompanhamento Geral'!B48 -> #DIV/0!
B70: ABRIL
B72: CENÁRIO ATUAL (ÚLTIMO MÊS) | E72: CENÁRIO DESEJADO | H72: CENÁRIO IDEAL | J72: MÉDIA / ANUAL | K72: % ATUAL | L72: % MÁX
B73: Valor Investimento | E73: Faturamento Desejado | H73: Verba Mensal | K73: =(I73-J73)/J73*1 -> #DIV/0! | L73: 0.4
B74: CPS Geral | E74: CPS Atual | F74: =C74 | H74: CPS Ideal | K74: =(I74-J74)/J74*1 -> #DIV/0! | L74: -0.1
B75: Ticket Médio | E75: Ticket Médio | F75: =C75 | H75: Ticket Médio Ideal | K75: =(I75-J75)/J75*1 -> #DIV/0! | L75: 0.15
B76: TX Conversão Para Lead | E76: TX Conversão Para Lead | F76: =C76 | H76: TX Conversão Para Lead Ideal | K76: =(I76-J76)/J76*1 -> #DIV/0! | L76: 0.1
B77: % Lead Para Venda | E77: % Lead Para Venda | F77: =C77 | H77: % Lead Para Venda Ideal | K77: =(I77-J77)/J77*1 -> #DIV/0! | L77: 0.1
B79: Sessões | C79: =C73/C74 -> #DIV/0! | E79: Sessões Ideais | F79: =(F81/F76)/F77 -> #DIV/0! | H79: Sessões Ideais | I79: =I73/I74 -> #DIV/0! | K79: CANAL DE VENDA | L79: % | M79: FATURAMENTO | N79: PEDIDOS POR CANAL
B80: Leads | C80: =C79*C76 -> #DIV/0! | E80: Leads Ideais | F80: =F79*F76 -> #DIV/0! | H80: Leads Ideais | I80: =I79*I76 -> #DIV/0! | K80: Meta Ads | L80: 0.2 | M80: =I84/100*L80*100 -> #DIV/0! | N80: =M80/I75 -> #DIV/0!
B81: Vendas | C81: =C80*C77 -> #DIV/0! | E81: Vendas | F81: =F73/F75 -> #DIV/0! | H81: Vendas | I81: =I84/I75 -> #DIV/0! | K81: Google Ads | L81: 0.2 | M81: =I84/100*L81*100 -> #DIV/0! | N81: =M81/I75 -> #DIV/0!
B82: CPL | C82: =C73/C80 -> #DIV/0! | E82: CPL Ideal | F82: =F84/F80 -> #DIV/0! | H82: CPL Ideal | I82: =I73/I80 -> #DIV/0! | K82: Social | L82: 0.3 | M82: =I84/100*L82*100 -> #DIV/0! | N82: =M82/I75 -> #DIV/0!
B83: CPA | C83: =C73/C81 -> #DIV/0! | E83: CPA | F83: =F84/F81 -> #DIV/0! | H83: CPA | I83: =I73/I81 -> #DIV/0! | K83: Organico | L83: 0.15 | M83: =I84/100*L83*100 -> #DIV/0! | N83: =M83/I75 -> #DIV/0!
B84: Faturamento Real | C84: =C81*C75 -> #DIV/0! | E84: Investimento Necessário | F84: =F79*F74 -> #DIV/0! | H84: Faturamento Desejado | I84: =(I79*I76*I77)*I75 -> #DIV/0! | K84: E-mail | L84: 0.15 | M84: =I84/100*L84*100 -> #DIV/0! | N84: =M84/I75 -> #DIV/0!
B85: ROAS | C85: =C84/C73 -> #DIV/0! | E85: ROAS | F85: =F73/F84 -> #DIV/0! | H85: ROAS | I85: =I84/I73 -> #DIV/0! | L85: =SUM(L80:L84) -> 1 | N85: =SUM(N80:N84) -> #DIV/0!
B87: CENÁRIO DIÁRIO ATUAL | E87: CENÁRIO DIÁRIO DESEJADO | H87: CENÁRIO DIÁRIO IDEAL | K87: Canal | L87: Facebook | M87: Google | N87: Outros | O87: Total
B88: Investimento Diário | C88: =C73/30 -> 0 | E88: Investimento Diário | F88: =F73/30 -> 0 | H88: Investimento Diário | I88: =I73/'Acompanhamento Geral'!B70 -> #VALUE! | K88: % | L88: 0.7 | M88: 0.3 | N88: 0 | O88: =sum(L88:N88) -> 1
B89: Sessões Diárias | C89: =C79/30 -> #DIV/0! | E89: Sessões Diárias | F89: =F79/30 -> #DIV/0! | H89: Sessões Diárias | I89: =I79/'Acompanhamento Geral'!B70 -> #DIV/0! | K89: Verba Mês | L89: =I73*L88 -> 0 | M89: =I73*M88 -> 0 | N89: =I73*N88 -> 0 | O89: =sum(L89:N89) -> 0
B90: Pedidos Diários | C90: =C81/30 -> #DIV/0! | E90: Pedidos Diários | F90: =F81/30 -> #DIV/0! | H90: Pedidos Diários | I90: =I81/'Acompanhamento Geral'!B70 -> #DIV/0! | K90: Verba Dia | L90: =L89/'Acompanhamento Geral'!B70 -> #VALUE! | M90: =M89/'Acompanhamento Geral'!B70 -> #VALUE! | N90: =iferror(N89/'Acompanhamento Geral'!B70,"") | O90: =SUM(L90:N90) -> #VALUE!
B91: Faturamento Diário | C91: =C84/30 -> #DIV/0! | E91: Faturamento Diário | F91: =F73/30 -> 0 | H91: Faturamento Diário | I91: =I84/'Acompanhamento Geral'!B70 -> #DIV/0!
B93: MAIO
B95: CENÁRIO ATUAL (ÚLTIMO MÊS) | E95: CENÁRIO DESEJADO | H95: CENÁRIO IDEAL | J95: MÉDIA / ANUAL | K95: % ATUAL | L95: % MÁX
B96: Valor Investimento | E96: Faturamento Desejado | H96: Verba Mensal | K96: =(I96-J96)/J96*1 -> #DIV/0! | L96: 0.4
B97: CPS Geral | E97: CPS Atual | F97: =C97 | H97: CPS Ideal | K97: =(I97-J97)/J97*1 -> #DIV/0! | L97: -0.1
B98: Ticket Médio | E98: Ticket Médio | F98: =C98 | H98: Ticket Médio Ideal | K98: =(I98-J98)/J98*1 -> #DIV/0! | L98: 0.15
B99: TX Conversão Para Lead | E99: TX Conversão Para Lead | F99: =C99 | H99: TX Conversão Para Lead Ideal | K99: =(I99-J99)/J99*1 -> #DIV/0! | L99: 0.1
B100: % Lead Para Venda | E100: % Lead Para Venda | F100: =C100 | H100: % Lead Para Venda Ideal | K100: =(I100-J100)/J100*1 -> #DIV/0! | L100: 0.1
B102: Sessões | C102: =C96/C97 -> #DIV/0! | E102: Sessões Ideais | F102: =(F104/F99)/F100 -> #DIV/0! | H102: Sessões Ideais | I102: =I96/I97 -> #DIV/0! | K102: CANAL DE VENDA | L102: % | M102: FATURAMENTO | N102: PEDIDOS POR CANAL
B103: Leads | C103: =C102*C99 -> #DIV/0! | E103: Leads Ideais | F103: =F102*F99 -> #DIV/0! | H103: Leads Ideais | I103: =I102*I99 -> #DIV/0! | K103: Meta Ads | L103: 0.2 | M103: =I107/100*L103*100 -> #DIV/0! | N103: =M103/I98 -> #DIV/0!
B104: Vendas | C104: =C103*C100 -> #DIV/0! | E104: Vendas | F104: =F96/F98 -> #DIV/0! | H104: Vendas | I104: =I107/I98 -> #DIV/0! | K104: Google Ads | L104: 0.2 | M104: =I107/100*L104*100 -> #DIV/0! | N104: =M104/I98 -> #DIV/0!
B105: CPL | C105: =C96/C103 -> #DIV/0! | E105: CPL Ideal | F105: =F107/F103 -> #DIV/0! | H105: CPL Ideal | I105: =I96/I103 -> #DIV/0! | K105: Social | L105: 0.3 | M105: =I107/100*L105*100 -> #DIV/0! | N105: =M105/I98 -> #DIV/0!
B106: CPA | C106: =C96/C104 -> #DIV/0! | E106: CPA | F106: =F107/F104 -> #DIV/0! | H106: CPA | I106: =I96/I104 -> #DIV/0! | K106: Organico | L106: 0.15 | M106: =I107/100*L106*100 -> #DIV/0! | N106: =M106/I98 -> #DIV/0!
B107: Faturamento Real | C107: =C104*C98 -> #DIV/0! | E107: Investimento Necessário | F107: =F102*F97 -> #DIV/0! | H107: Faturamento Desejado | I107: =(I102*I99*I100)*I98 -> #DIV/0! | K107: E-mail | L107: 0.15 | M107: =I107/100*L107*100 -> #DIV/0! | N107: =M107/I98 -> #DIV/0!
B108: ROAS | C108: =C107/C96 -> #DIV/0! | E108: ROAS | F108: =F96/F107 -> #DIV/0! | H108: ROAS | I108: =I107/I96 -> #DIV/0! | L108: =SUM(L103:L107) -> 1 | N108: =SUM(N103:N107) -> #DIV/0!
B110: CENÁRIO DIÁRIO ATUAL | E110: CENÁRIO DIÁRIO DESEJADO | H110: CENÁRIO DIÁRIO IDEAL | K110: Canal | L110: Facebook | M110: Google | N110: Outros | O110: Total
B111: Investimento Diário | C111: =C96/30 -> 0 | E111: Investimento Diário | F111: =F96/30 -> 0 | H111: Investimento Diário | I111: =I96/'Acompanhamento Geral'!B93 -> #VALUE! | K111: % | L111: 0.7 | M111: 0.3 | N111: 0 | O111: =sum(L111:N111) -> 1
B112: Sessões Diárias | C112: =C102/30 -> #DIV/0! | E112: Sessões Diárias | F112: =F102/30 -> #DIV/0! | H112: Sessões Diárias | I112: =I102/'Acompanhamento Geral'!B93 -> #DIV/0! | K112: Verba Mês | L112: =I96*L111 -> 0 | M112: =I96*M111 -> 0 | N112: =I96*N111 -> 0 | O112: =sum(L112:N112) -> 0
B113: Pedidos Diários | C113: =C104/30 -> #DIV/0! | E113: Pedidos Diários | F113: =F104/30 -> #DIV/0! | H113: Pedidos Diários | I113: =I104/'Acompanhamento Geral'!B93 -> #DIV/0! | K113: Verba Dia | L113: =L112/'Acompanhamento Geral'!B93 -> #VALUE! | M113: =M112/'Acompanhamento Geral'!B93 -> #VALUE! | N113: =iferror(N112/'Acompanhamento Geral'!B93,"") | O113: =SUM(L113:N113) -> #VALUE!
B114: Faturamento Diário | C114: =C107/30 -> #DIV/0! | E114: Faturamento Diário | F114: =F96/30 -> 0 | H114: Faturamento Diário | I114: =I107/'Acompanhamento Geral'!B93 -> #DIV/0!
B116: JUNHO
B118: CENÁRIO ATUAL (ÚLTIMO MÊS) | E118: CENÁRIO DESEJADO | H118: CENÁRIO IDEAL | J118: MÉDIA / ANUAL | K118: % ATUAL | L118: % MÁX
B119: Valor Investimento | E119: Faturamento Desejado | H119: Verba Mensal | K119: =(I119-J119)/J119*1 -> #DIV/0! | L119: 0.4
B120: CPS Geral | E120: CPS Atual | F120: =C120 | H120: CPS Ideal | K120: =(I120-J120)/J120*1 -> #DIV/0! | L120: -0.1
B121: Ticket Médio | E121: Ticket Médio | F121: =C121 | H121: Ticket Médio Ideal | K121: =(I121-J121)/J121*1 -> #DIV/0! | L121: 0.15
...

Sheet Dados Históricos
A1: CRESCIMENTO MoM | C1: =IFERROR((C3-B3)/B3*1,"") | D1: =iferror((D3-C3)/C3*1,"") | E1: =iferror((E3-D3)/D3*1,"") | F1: =iferror((F3-E3)/E3*1,"") | G1: =iferror((G3-F3)/F3*1,"") | H1: =iferror((H3-G3)/G3*1,"") | I1: =iferror((I3-H3)/H3*1,"") | J1: =iferror((J3-I3)/I3*1,"") | K1: =iferror((K3-J3)/J3*1,"") | ... M1: =iferror((M3-L3)/L3*1,"") | O1: MÉTRICAS MÉDIAS
A2: MÉTRICAS / MÊS | B2: JAN | C2: FEV | D2: MAR | E2: ABR | F2: MAI | G2: JUN | H2: JUL | I2: AGO | J2: SET | K2: OUT | L2: NOV | M2: DEZ | O2: Crescimento Médio | P2: =AVERAGE(C1:M1) -> #DIV/0!
A3: Leads Captados | O3: Leads Captados | P3: =AVERAGE(B3:M3) -> #DIV/0!
A4: Leads Qualificados | O4: Leads Qualificados | P4: =AVERAGE(B4:M4) -> #DIV/0!
A5: % de Qualificados | B5: =IFERROR(B4/B3,"") | C5: =IFERROR(C4/C3,"") | D5: =IFERROR(D4/D3,"") | E5: =IFERROR(E4/E3,"") | F5: =IFERROR(F4/F3,"") | G5: =IFERROR(G4/G3,"") | H5: =IFERROR(H4/H3,"") | I5: =IFERROR(I4/I3,"") | ... M5: =IFERROR(M4/M3,"") | O5: % de Qualificados | P5: =AVERAGE(B5:M5) -> #DIV/0!
A6: Leads Captados Midia Paga | O6: Leads Captados Midia Paga | P6: =AVERAGE(B6:M6) -> #DIV/0!
A7: % Mídia Paga | B7: =IFERROR((B6/B3)*1,"") | C7: =IFERROR((C6/C3)*1,"") | D7: =IFERROR((D6/D3)*1,"") | E7: =IFERROR((E6/E3)*1,"") | F7: =IFERROR((F6/F3)*1,"") | G7: =IFERROR((G6/G3)*1,"") | H7: =IFERROR((H6/H3)*1,"") | I7: =IFERROR((I6/I3)*1,"") | ... M7: =IFERROR((M6/M3)*1,"") | O7: % Mídia Paga | P7: =AVERAGE(B7:J7) -> #DIV/0!
A8: Leads Outros Canais | B8: =IFERROR(B3-B6,"") -> 0 | C8: =IFERROR(C3-C6,"") -> 0 | D8: =IFERROR(D3-D6,"") -> 0 | E8: =IFERROR(E3-E6,"") -> 0 | F8: =IFERROR(F3-F6,"") -> 0 | G8: =IFERROR(G3-G6,"") -> 0 | H8: =IFERROR(H3-H6,"") -> 0 | I8: =IFERROR(I3-I6,"") -> 0 | ... M8: =IFERROR(M3-M6,"") -> 0 | O8: Leads Outros Canais | P8: =AVERAGE(B8:M8) -> 0
A9: % Outros Canais | B9: =IFERROR((B8/B3)*1,"") | C9: =IFERROR((C8/C3)*1,"") | D9: =IFERROR((D8/D3)*1,"") | E9: =IFERROR((E8/E3)*1,"") | F9: =IFERROR((F8/F3)*1,"") | G9: =IFERROR((G8/G3)*1,"") | H9: =IFERROR((H8/H3)*1,"") | I9: =IFERROR((I8/I3)*1,"") | ... M9: =IFERROR((M8/M3)*1,"") | O9: % Outros Canais | P9: =AVERAGE(B9:M9) -> #DIV/0!
A10: Investimento Ads | O10: Investimento Ads | P10: =AVERAGE(B10:M10) -> #DIV/0!
A11: % Aumento / Redução ADS | O11: % Aumento / Redução ADS | P11: =AVERAGE(B11:M11) -> #DIV/0!
A12: Sessões Totais | O12: Sessões Geral | P12: =AVERAGE(B12:M12) -> #DIV/0!
A13: Sessões Midia | O13: Sessões Mídia | P13: =AVERAGE(B13:M13) -> #DIV/0!
A14: CPS Geral | B14: =IFERROR(B10/B12,"") | C14: =IFERROR(C10/C12,"") | D14: =IFERROR(D10/D12,"") | E14: =IFERROR(E10/E12,"") | F14: =IFERROR(F10/F12,"") | G14: =IFERROR(G10/G12,"") | H14: =IFERROR(H10/H12,"") | I14: =IFERROR(I10/I12,"") | ... M14: =IFERROR(M10/M12,"") | O14: CPS Geral | P14: =AVERAGE(B14:M14) -> #DIV/0!
A15: CPS Midia | B15: =IFERROR(B10/B13,"") | C15: =IFERROR(C10/C13,"") | D15: =IFERROR(D10/D13,"") | E15: =IFERROR(E10/E13,"") | F15: =IFERROR(F10/F13,"") | G15: =IFERROR(G10/G13,"") | H15: =IFERROR(H10/H13,"") | I15: =IFERROR(I10/I13,"") | ... M15: =IFERROR(M10/M13,"") | O15: CPS Mídia | P15: =AVERAGE(B15:M15) -> #DIV/0!
A16: Taxa de Conversão Para Lead (%) | B16: =IFERROR(B3/B12,"") | C16: =IFERROR(C3/C12,"") | D16: =IFERROR(D3/D12,"") | E16: =IFERROR(E3/E12,"") | F16: =IFERROR(F3/F12,"") | G16: =IFERROR(G3/G12,"") | H16: =IFERROR(H3/H12,"") | I16: =IFERROR(I3/I12,"") | ... M16: =IFERROR(M3/M12,"") | O16: Taxa de Conversão Para Lead | P16: =AVERAGE(B16:M16) -> #DIV/0!
A17: Taxa de Conversão Para Qualificado (%) | B17: =IFERROR(B4/B12,"") | C17: =IFERROR(C4/C12,"") | D17: =IFERROR(D4/D12,"") | E17: =IFERROR(E4/E12,"") | F17: =IFERROR(F4/F12,"") | G17: =IFERROR(G4/G12,"") | H17: =IFERROR(H4/H12,"") | I17: =IFERROR(I4/I12,"") | ... M17: =IFERROR(M4/M12,"") | O17: Taxa de Conversão Qualificado | P17: =AVERAGE(B17:M17) -> #DIV/0!
A18: CPL Geral | B18: =IFERROR(B10/B3,"") | C18: =IFERROR(C10/C3,"") | D18: =IFERROR(D10/D3,"") | E18: =IFERROR(E10/E3,"") | F18: =IFERROR(F10/F3,"") | G18: =IFERROR(G10/G3,"") | H18: =IFERROR(H10/H3,"") | I18: =IFERROR(I10/I3,"") | ... M18: =IFERROR(M10/M3,"") | O18: CPL Geral | P18: =AVERAGE(B18:M18) -> #DIV/0!
A19: CPL Qualificado | B19: =IFERROR(B10/B4,"") | C19: =IFERROR(C10/C4,"") | D19: =IFERROR(D10/D4,"") | E19: =IFERROR(E10/E4,"") | F19: =IFERROR(F10/F4,"") | G19: =IFERROR(G10/G4,"") | H19: =IFERROR(H10/H4,"") | I19: =IFERROR(I10/I4,"") | ... M19: =IFERROR(M10/M4,"") | O19: CPL Qualificado | P19: =AVERAGE(B19:M19) -> #DIV/0!
A20: Negocios Fechados | O20: Negocios Fechados | P20: =AVERAGE(B20:M20) -> #DIV/0!
A21: CPA (R$) | B21: =iferror(B10/B20,"") | C21: =iferror(C10/C20,"") | D21: =iferror(D10/D20,"") | E21: =iferror(E10/E20,"") | F21: =iferror(F10/F20,"") | G21: =iferror(G10/G20,"") | H21: =iferror(H10/H20,"") | I21: =iferror(I10/I20,"") | ... M21: =iferror(M10/M20,"") | O21: CPA (R$) | P21: =AVERAGE(B21:M21) -> #DIV/0!
A22: Valor de Negocios Fechados | O22: Valor de Negocios Fechados | P22: =AVERAGE(B22:M22) -> #DIV/0!
A23: Ticket Médio | B23: =iferror(B22/B20,"") | C23: =iferror(C22/C20,"") | D23: =iferror(D22/D20,"") | E23: =iferror(E22/E20,"") | F23: =iferror(F22/F20,"") | G23: =iferror(G22/G20,"") | H23: =iferror(H22/H20,"") | I23: =iferror(I22/I20,"") | ... M23: =iferror(M22/M20,"") | O23: Ticket Médio | P23: =AVERAGE(B23:M23) -> #DIV/0!
A24: % Lead Para Venda | B24: =iferror(B20/B3,"") | C24: =iferror(C20/C3,"") | D24: =iferror(D20/D3,"") | E24: =iferror(E20/E3,"") | F24: =iferror(F20/F3,"") | G24: =iferror(G20/G3,"") | H24: =iferror(H20/H3,"") | I24: =iferror(I20/I3,"") | ... M24: =iferror(M20/M3,"") | O24: % Lead Para Venda | P24: =AVERAGE(B24:M24) -> #DIV/0!
A25: ROAS | B25: =iferror(B22/B10,"") | C25: =iferror(C22/C10,"") | D25: =iferror(D22/D10,"") | E25: =iferror(E22/E10,"") | F25: =iferror(F22/F10,"") | G25: =iferror(G22/G10,"") | H25: =iferror(H22/H10,"") | I25: =iferror(I22/I10,"") | ... M25: =iferror(M22/M10,"") | O25: ROAS | P25: =AVERAGE(B25:M25) -> #DIV/0!
A29: CANAIS | B29: JAN | C29: FEV | D29: MAR | E29: ABR | F29: MAI | G29: JUN | H29: JUL | I29: AGO | J29: SET | K29: OUT | L29: NOV | M29: DEZ | O29: TOTAL
A30: (Other) | O30: =SUM(B30:M30) -> 0 | P30: =iferror(O30/$O$44,"")
A31: Direto / none | O31: =SUM(B31:M31) -> 0 | P31: =iferror(O31/$O$44,"")
A32: Facebook cpc | O32: =SUM(B32:M32) -> 0 | P32: =iferror(O32/$O$44,"")
A33: Google cpc | O33: =SUM(B33:M33) -> 0 | P33: =iferror(O33/$O$44,"")
A34: Orgânico | O34: =SUM(B34:M34) -> 0 | P34: =iferror(O34/$O$44,"")
A35: Instagram Perfil | O35: =SUM(B35:M35) -> 0 | P35: =iferror(O35/$O$44,"")
A36: E-mail | O36: =SUM(B36:M36) -> 0 | P36: =iferror(O36/$O$44,"")
A37: IG Shopping | O37: =SUM(B37:M37) -> 0 | P37: =iferror(O37/$O$44,"")
A38: Instagram / FB Referral | O38: =SUM(B38:M38) -> 0 | P38: =iferror(O38/$O$44,"")
A39: Blog | O39: =SUM(B39:M39) -> 0 | P39: =iferror(O39/$O$44,"")
A40: Pinterest / Referral | O40: =SUM(B40:M40) -> 0 | P40: =iferror(O40/$O$44,"")
A41: TikTok | O41: =SUM(B41:M41) -> 0 | P41: =iferror(O41/$O$44,"")
... A43: Youtube referral | O43: =SUM(B43:M43) -> 0 | P43: =iferror(O43/$O$44,"")
A44: Total de Leads | B44: =IFERROR(SUM(B30:B43),"") -> 0 | C44: =IFERROR(SUM(C30:C43),"") -> 0 | D44: =IFERROR(SUM(D30:D43),"") -> 0 | E44: =IFERROR(SUM(E30:E43),"") -> 0 | F44: =IFERROR(SUM(F30:F43),"") -> 0 | G44: =IFERROR(SUM(G30:G43),"") -> 0 | H44: =IFERROR(SUM(H30:H43),"") -> 0 | I44: =IFERROR(SUM(I30:I43),"") -> 0 | ... M44: =IFERROR(SUM(M30:M43),"") -> 0 | O44: =SUM(B44:M44) -> 0
A45: Share dos Meses | B45: =IFERROR(B44/$O$44,"") | C45: =IFERROR(C44/$O$44,"") | D45: =IFERROR(D44/$O$44,"") | E45: =IFERROR(E44/$O$44,"") | F45: =IFERROR(F44/$O$44,"") | G45: =IFERROR(G44/$O$44,"") | H45: =IFERROR(H44/$O$44,"") | I45: =IFERROR(I44/$O$44,"") | ... M45: =IFERROR(M44/$O$44,"")

Sheet Calendário 2024
C1: CALENDÁRIO 2025
B3: JANEIRO | J3: FEVEREIRO | R3: MARÇO | Z3: DATAS COMEMORATIVAS
B4: Seg | C4: Ter | D4: Qua | E4: Qui | F4: Sex | G4: Sáb | H4: Dom | J4: Seg | K4: Ter | L4: Qua | M4: Qui | N4: Sex | O4: Sáb | P4: Dom | R4: Seg | S4: Ter | T4: Qua | U4: Qui | V4: Sex | W4: Sáb | X4: Dom | Z4: 45047 | AA4: Dia do Trabalho
B5: 1 | C5: 2 | D5: 3 | E5: 4 | F5: 5 | G5: 6 | H5: 7 | M5: 1 | N5: 2 | O5: 3 | P5: 4 | V5: 1 | W5: 2 | X5: 3 | Z5: 45058 | AA5: Dia das Mães
B6: 8 | C6: 9 | D6: 10 | E6: 11 | F6: 12 | G6: 13 | H6: 14 | J6: 5 | K6: 6 | L6: 7 | M6: 8 | N6: 9 | O6: 10 | P6: 11 | R6: 4 | S6: 5 | T6: 6 | U6: 7 | V6: 8 | W6: 9 | X6: 10 | Z6: 45068 | AA6: Dia do Abraço
B7: 15 | C7: 16 | D7: 17 | E7: 18 | F7: 19 | G7: 20 | H7: 21 | J7: 12 | K7: 13 | L7: 14 | M7: 15 | N7: 16 | O7: 17 | P7: 18 | R7: 11 | S7: 12 | T7: 13 | U7: 14 | V7: 15 | W7: 16 | X7: 17 | Z7: 45071 | AA7: Dia do Orgulho Nerd
B8: 22 | C8: 23 | D8: 24 | E8: 25 | F8: 26 | G8: 27 | H8: 28 | J8: 19 | K8: 20 | L8: 21 | M8: 22 | N8: 23 | O8: 24 | P8: 25 | R8: 18 | S8: 19 | T8: 20 | U8: 21 | V8: 22 | W8: 23 | X8: 24 | Z8: 45089 | AA8: Dia dos Namorados
B9: 29 | C9: 30 | D9: 31 | J9: 26 | K9: 27 | L9: 28 | M9: 29 | R9: 25 | S9: 26 | T9: 27 | U9: 28 | V9: 29 | W9: 30 | X9: 31 | Z9: 45098 | AA9: Inicio do Inverno
Z10: 45105 | AA10: Dia do Orgulho LGBT
B11: ABRIL | J11: MAIO | R11: JUNHO | Z11: 45120 | AA11: Dia do Rock
B12: Seg | C12: Ter | D12: Qua | E12: Qui | F12: Sex | G12: Sáb | H12: Dom | J12: Seg | K12: Ter | L12: Qua | M12: Qui | N12: Sex | O12: Sáb | P12: Dom | R12: Seg | S12: Ter | T12: Qua | U12: Qui | V12: Sex | W12: Sáb | X12: Dom | Z12: 45122 | AA12: Dia do Homem
B13: 1 | C13: 2 | D13: 3 | E13: 4 | F13: 5 | G13: 6 | H13: 7 | L13: 1 | M13: 2 | N13: 3 | O13: 4 | P13: 5 | W13: 1 | X13: 2 | Z13: 45137 | AA13: Dia dos Amigos
B14: 8 | C14: 9 | D14: 10 | E14: 11 | F14: 12 | G14: 13 | H14: 14 | J14: 6 | K14: 7 | L14: 8 | M14: 9 | N14: 10 | O14: 11 | P14: 12 | R14: 3 | S14: 4 | T14: 5 | U14: 6 | V14: 7 | W14: 8 | X14: 9 | Z14: 45149 | AA14: Dia dos Pais
B15: 15 | C15: 16 | D15: 17 | E15: 18 | F15: 19 | G15: 20 | H15: 21 | J15: 13 | K15: 14 | L15: 15 | M15: 16 | N15: 17 | O15: 18 | P15: 19 | R15: 10 | S15: 11 | T15: 12 | U15: 13 | V15: 14 | W15: 15 | X15: 16 | Z15: 45153 | AA15: Dia dos Solteiros
B16: 22 | C16: 23 | D16: 24 | E16: 25 | F16: 26 | G16: 27 | H16: 28 | J16: 20 | K16: 21 | L16: 22 | M16: 23 | N16: 24 | O16: 25 | P16: 26 | R16: 17 | S16: 18 | T16: 19 | U16: 20 | V16: 21 | W16: 22 | X16: 23 | Z16: 45176 | AA16: Independencia do Brasil
B17: 29 | C17: 30 | J17: 27 | K17: 28 | L17: 29 | M17: 30 | N17: 31 | R17: 24 | S17: 25 | T17: 26 | U17: 27 | V17: 28 | W17: 29 | X17: 30 | Z17: 45184 | AA17: Dia do Cliente
Z18: 45211 | AA18: Dia das Crianças
B19: JULHO | J19: AGOSTO | R19: SETEMBRO | Z19: 45230 | AA19: Halloween
B20: Seg | C20: Ter | D20: Qua | E20: Qui | F20: Sex | G20: Sáb | H20: Dom | J20: Seg | K20: Ter | L20: Qua | M20: Qui | N20: Sex | O20: Sáb | P20: Dom | R20: Seg | S20: Ter | T20: Qua | U20: Qui | V20: Sex | W20: Sáb | X20: Dom | Z20: 45245 | AA20: Dia da proclamação da Republica
B21: 1 | C21: 2 | D21: 3 | E21: 4 | F21: 5 | G21: 6 | H21: 7 | M21: 1 | N21: 2 | O21: 3 | P21: 4 | X21: 1 | Z21: 45252 | AA21: Black Friday
B22: 8 | C22: 9 | D22: 10 | E22: 11 | F22: 12 | G22: 13 | H22: 14 | J22: 5 | K22: 6 | L22: 7 | M22: 8 | N22: 9 | O22: 10 | P22: 11 | R22: 2 | S22: 3 | T22: 4 | U22: 5 | V22: 6 | W22: 7 | X22: 8 | Z22: 45255 | AA22: Cyber Monday
B23: 15 | C23: 16 | D23: 17 | E23: 18 | F23: 19 | G23: 20 | H23: 21 | J23: 12 | K23: 13 | L23: 14 | M23: 15 | N23: 16 | O23: 17 | P23: 18 | R23: 9 | S23: 10 | T23: 11 | U23: 12 | V23: 13 | W23: 14 | X23: 15 | Z23: 45285 | AA23: Natal
B24: 22 | C24: 23 | D24: 24 | E24: 25 | F24: 26 | G24: 27 | H24: 28 | J24: 19 | K24: 20 | L24: 21 | M24: 22 | N24: 23 | O24: 24 | P24: 25 | R24: 16 | S24: 17 | T24: 18 | U24: 19 | V24: 20 | W24: 21 | X24: 22 | Z24: 45291 | AA24: Ano novo
B25: 29 | C25: 30 | D25: 31 | J25: 26 | K25: 27 | L25: 28 | M25: 29 | N25: 20 | O25: 31 | R25: 23 | S25: 24 | T25: 25 | U25: 26 | V25: 27 | W25: 28 | X25: 29
R26: 30
B28: OUTUBRO | J28: NOVEMBRO | R28: DEZEMBRO
B29: Seg | C29: Ter | D29: Qua | E29: Qui | F29: Sex | G29: Sáb | H29: Dom | J29: Seg | K29: Ter | L29: Qua | M29: Qui | N29: Sex | O29: Sáb | P29: Dom | R29: Seg | S29: Ter | T29: Qua | U29: Qui | V29: Sex | W29: Sáb | X29: Dom
C30: 1 | D30: 2 | E30: 3 | F30: 4 | G30: 5 | H30: 6 | N30: 1 | O30: 2 | P30: 3 | X30: 1
B31: 7 | C31: 8 | D31: 9 | E31: 10 | F31: 11 | G31: 12 | H31: 13 | J31: 4 | K31: 5 | L31: 6 | M31: 7 | N31: 8 | O31: 9 | P31: 10 | R31: 2 | S31: 3 | T31: 4 | U31: 5 | V31: 6 | W31: 7 | X31: 8
B32: 14 | C32: 15 | D32: 16 | E32: 17 | F32: 18 | G32: 19 | H32: 20 | J32: 11 | K32: 12 | L32: 13 | M32: 14 | N32: 15 | O32: 16 | P32: 17 | R32: 9 | S32: 10 | T32: 11 | U32: 12 | V32: 13 | W32: 14 | X32: 15
B33: 21 | C33: 22 | D33: 23 | E33: 24 | F33: 25 | G33: 26 | H33: 27 | J33: 18 | K33: 19 | L33: 20 | M33: 21 | N33: 22 | O33: 23 | P33: 24 | R33: 16 | S33: 17 | T33: 18 | U33: 19 | V33: 20 | W33: 21 | X33: 22
B34: 28 | C34: 29 | D34: 30 | E34: 31 | J34: 25 | K34: 26 | L34: 27 | M34: 28 | N34: 29 | O34: 30 | R34: 23 | S34: 24 | T34: 25 | U34: 26 | V34: 27 | W34: 28 | X34: 29
R35: 30 | S35: 31

Sheet Calendário Janeiro
B1: JANEIRO 2025
B3: SEGUNDA-FEIRA | C3: TERÇA-FEIRA | D3: QUARTA-FEIRA | E3: QUINTA-FEIRA | F3: SEXTA-FEIRA | G3: SÁBADO | H3: DOMINGO
B4: 1 | C4: 2 | D4: 3 | E4: 4 | F4: 5 | G4: 6 | H4: 7
B6: 8 | C6: 9 | D6: 10 | E6: 11 | F6: 12 | G6: 13 | H6: 14
B8: 15 | C8: 16 | D8: 17 | E8: 18 | F8: 19 | G8: 20 | H8: 21
B10: 22 | C10: 23 | D10: 24 | E10: 25 | F10: 26 | G10: 27 | H10: 28
B12: 29 | C12: 30 | D12: 31
B15: OBSERVAÇÕES:
B21: LEGENDA:
B22: Feriados
B23: Datas de nicho
B24: Datas Importantes
B25: Essenciais no E-commerce

Sheet E-mail Mkt
A1: Campanha Broadcast | B1: Enviados | C1: Aberturas | D1: % Abertura | E1: Cliques | F1: % Cliques
A2: Nome - data - Segmentação | B2: 61927 | C2: 7226 | D2: =C2/B2 -> 0.11668578 | E2: 605 | F2: =E2/B2 -> 0.0097695674

Sheet Resultado Criativos
A1: ID | B1: Nome Drive | C1: ID Copy | D1: Data Postagem | E1: Info Extra | F1: Nome Final | G1: CUSTO | H1: CTR | I1: CPS | J1: LEADS | K1: CPL
A2: TP01 | F2: =CONCATENATE(A2,," ","-"," ","",B2,""," ","-"," ",C2," ","-"," ",D2) -> TP01 - - - | G2: =SUMIF('ADV - FB'!L:L,$A2,'ADV - FB'!E:E) -> 0 | H2: =IFERROR(SUMIF('ADV - FB'!L:L,$A2,'ADV - FB'!H:H)/(SUMIF('ADV - FB'!L:L,$A2,'ADV - FB'!G:G)),"-") -> - | I2: =IFERROR(SUMIF('ADV - FB'!L:L,$A2,'ADV - FB'!E:E)/(SUMIF('ADV - FB'!L:L,$A2,'ADV - FB'!F:F)),"-") -> - | J2: =SUMIF('ADV - FB'!L:L,$A2,'ADV - FB'!I:I)+SUMIF('ADV - FB'!L:L,$A2,'ADV - FB'!J:J)+SUMIF('ADV - FB'!L:L,$A2,'ADV - FB'!K:K) -> 0 | K2: =IFERROR(G2/J2,"-") -> -
A3: TP02 | F3: =CONCATENATE(A3,," ","-"," ","",B3,""," ","-"," ",C3," ","-"," ",D3) -> TP02 - - - | G3: =SUMIF('ADV - FB'!L:L,$A3,'ADV - FB'!E:E) -> 0 | H3: =IFERROR(SUMIF('ADV - FB'!L:L,$A3,'ADV - FB'!H:H)/(SUMIF('ADV - FB'!L:L,$A3,'ADV - FB'!G:G)),"-") -> - | I3: =IFERROR(SUMIF('ADV - FB'!L:L,$A3,'ADV - FB'!E:E)/(SUMIF('ADV - FB'!L:L,$A3,'ADV - FB'!F:F)),"-") -> - | J3: =SUMIF('ADV - FB'!L:L,$A3,'ADV - FB'!I:I)+SUMIF('ADV - FB'!L:L,$A3,'ADV - FB'!J:J)+SUMIF('ADV - FB'!L:L,$A3,'ADV - FB'!K:K) -> 0 | K3: =IFERROR(G3/J3,"-") -> -
A4: TP03 | F4: =CONCATENATE(A4,," ","-"," ","",B4,""," ","-"," ",C4," ","-"," ",D4) -> TP03 - - - | G4: =SUMIF('ADV - FB'!L:L,$A4,'ADV - FB'!E:E) -> 0 | H4: =IFERROR(SUMIF('ADV - FB'!L:L,$A4,'ADV - FB'!H:H)/(SUMIF('ADV - FB'!L:L,$A4,'ADV - FB'!G:G)),"-") -> - | I4: =IFERROR(SUMIF('ADV - FB'!L:L,$A4,'ADV - FB'!E:E)/(SUMIF('ADV - FB'!L:L,$A4,'ADV - FB'!F:F)),"-") -> - | J4: =SUMIF('ADV - FB'!L:L,$A4,'ADV - FB'!I:I)+SUMIF('ADV - FB'!L:L,$A4,'ADV - FB'!J:J)+SUMIF('ADV - FB'!L:L,$A4,'ADV - FB'!K:K) -> 0 | K4: =IFERROR(G4/J4,"-") -> -
A5: TP04 | F5: =CONCATENATE(A5,," ","-"," ","",B5,""," ","-"," ",C5," ","-"," ",D5) -> TP04 - - - | G5: =SUMIF('ADV - FB'!L:L,$A5,'ADV - FB'!E:E) -> 0 | H5: =IFERROR(SUMIF('ADV - FB'!L:L,$A5,'ADV - FB'!H:H)/(SUMIF('ADV - FB'!L:L,$A5,'ADV - FB'!G:G)),"-") -> - | I5: =IFERROR(SUMIF('ADV - FB'!L:L,$A5,'ADV - FB'!E:E)/(SUMIF('ADV - FB'!L:L,$A5,'ADV - FB'!F:F)),"-") -> - | J5: =SUMIF('ADV - FB'!L:L,$A5,'ADV - FB'!I:I)+SUMIF('ADV - FB'!L:L,$A5,'ADV - FB'!J:J)+SUMIF('ADV - FB'!L:L,$A5,'ADV - FB'!K:K) -> 0 | K5: =IFERROR(G5/J5,"-") -> -
A6: TP05 | F6: =CONCATENATE(A6,," ","-"," ","",B6,""," ","-"," ",C6," ","-"," ",D6) -> TP05 - - - | G6: =SUMIF('ADV - FB'!L:L,$A6,'ADV - FB'!E:E) -> 0 | H6: =IFERROR(SUMIF('ADV - FB'!L:L,$A6,'ADV - FB'!H:H)/(SUMIF('ADV - FB'!L:L,$A6,'ADV - FB'!G:G)),"-") -> - | I6: =IFERROR(SUMIF('ADV - FB'!L:L,$A6,'ADV - FB'!E:E)/(SUMIF('ADV - FB'!L:L,$A6,'ADV - FB'!F:F)),"-") -> - | J6: =SUMIF('ADV - FB'!L:L,$A6,'ADV - FB'!I:I)+SUMIF('ADV - FB'!L:L,$A6,'ADV - FB'!J:J)+SUMIF('ADV - FB'!L:L,$A6,'ADV - FB'!K:K) -> 0 | K6: =IFERROR(G6/J6,"-") -> -
A7: TP06 | F7: =CONCATENATE(A7,," ","-"," ","",B7,""," ","-"," ",C7," ","-"," ",D7) -> TP06 - - - | G7: =SUMIF('ADV - FB'!L:L,$A7,'ADV - FB'!E:E) -> 0 | H7: =IFERROR(SUMIF('ADV - FB'!L:L,$A7,'ADV - FB'!H:H)/(SUMIF('ADV - FB'!L:L,$A7,'ADV - FB'!G:G)),"-") -> - | I7: =IFERROR(SUMIF('ADV - FB'!L:L,$A7,'ADV - FB'!E:E)/(SUMIF('ADV - FB'!L:L,$A7,'ADV - FB'!F:F)),"-") -> - | J7: =SUMIF('ADV - FB'!L:L,$A7,'ADV - FB'!I:I)+SUMIF('ADV - FB'!L:L,$A7,'ADV - FB'!J:J)+SUMIF('ADV - FB'!L:L,$A7,'ADV - FB'!K:K) -> 0 | K7: =IFERROR(G7/J7,"-") -> -
A8: TP07 | F8: =CONCATENATE(A8,," ","-"," ","",B8,""," ","-"," ",C8," ","-"," ",D8) -> TP07 - - - | G8: =SUMIF('ADV - FB'!L:L,$A8,'ADV - FB'!E:E) -> 0 | H8: =IFERROR(SUMIF('ADV - FB'!L:L,$A8,'ADV - FB'!H:H)/(SUMIF('ADV - FB'!L:L,$A8,'ADV - FB'!G:G)),"-") -> - | I8: =IFERROR(SUMIF('ADV - FB'!L:L,$A8,'ADV - FB'!E:E)/(SUMIF('ADV - FB'!L:L,$A8,'ADV - FB'!F:F)),"-") -> - | J8: =SUMIF('ADV - FB'!L:L,$A8,'ADV - FB'!I:I)+SUMIF('ADV - FB'!L:L,$A8,'ADV - FB'!J:J)+SUMIF('ADV - FB'!L:L,$A8,'ADV - FB'!K:K) -> 0 | K8: =IFERROR(G8/J8,"-") -> -
A9: TP08 | F9: =CONCATENATE(A9,," ","-"," ","",B9,""," ","-"," ",C9," ","-"," ",D9) -> TP08 - - - | G9: =SUMIF('ADV - FB'!L:L,$A9,'ADV - FB'!E:E) -> 0 | H9: =IFERROR(SUMIF('ADV - FB'!L:L,$A9,'ADV - FB'!H:H)/(SUMIF('ADV - FB'!L:L,$A9,'ADV - FB'!G:G)),"-") -> - | I9: =IFERROR(SUMIF('ADV - FB'!L:L,$A9,'ADV - FB'!E:E)/(SUMIF('ADV - FB'!L:L,$A9,'ADV - FB'!F:F)),"-") -> - | J9: =SUMIF('ADV - FB'!L:L,$A9,'ADV - FB'!I:I)+SUMIF('ADV - FB'!L:L,$A9,'ADV - FB'!J:J)+SUMIF('ADV - FB'!L:L,$A9,'ADV - FB'!K:K) -> 0 | K9: =IFERROR(G9/J9,"-") -> -
A10: TP09 | F10: =CONCATENATE(A10,," ","-"," ","",B10,""," ","-"," ",C10," ","-"," ",D10) -> TP09 - - - | G10: =SUMIF('ADV - FB'!L:L,$A10,'ADV - FB'!E:E) -> 0 | H10: =IFERROR(SUMIF('ADV - FB'!L:L,$A10,'ADV - FB'!H:H)/(SUMIF('ADV - FB'!L:L,$A10,'ADV - FB'!G:G)),"-") -> - | I10: =IFERROR(SUMIF('ADV - FB'!L:L,$A10,'ADV - FB'!E:E)/(SUMIF('ADV - FB'!L:L,$A10,'ADV - FB'!F:F)),"-") -> - | J10: =SUMIF('ADV - FB'!L:L,$A10,'ADV - FB'!I:I)+SUMIF('ADV - FB'!L:L,$A10,'ADV - FB'!J:J)+SUMIF('ADV - FB'!L:L,$A10,'ADV - FB'!K:K) -> 0 | K10: =IFERROR(G10/J10,"-") -> -
A11: TP10 | F11: =CONCATENATE(A11,," ","-"," ","",B11,""," ","-"," ",C11," ","-"," ",D11) -> TP10 - - - | G11: =SUMIF('ADV - FB'!L:L,$A11,'ADV - FB'!E:E) -> 0 | H11: =IFERROR(SUMIF('ADV - FB'!L:L,$A11,'ADV - FB'!H:H)/(SUMIF('ADV - FB'!L:L,$A11,'ADV - FB'!G:G)),"-") -> - | I11: =IFERROR(SUMIF('ADV - FB'!L:L,$A11,'ADV - FB'!E:E)/(SUMIF('ADV - FB'!L:L,$A11,'ADV - FB'!F:F)),"-") -> - | J11: =SUMIF('ADV - FB'!L:L,$A11,'ADV - FB'!I:I)+SUMIF('ADV - FB'!L:L,$A11,'ADV - FB'!J:J)+SUMIF('ADV - FB'!L:L,$A11,'ADV - FB'!K:K) -> 0 | K11: =IFERROR(G11/J11,"-") -> -
A12: TP11 | F12: =CONCATENATE(A12,," ","-"," ","",B12,""," ","-"," ",C12," ","-"," ",D12) -> TP11 - - - | G12: =SUMIF('ADV - FB'!L:L,$A12,'ADV - FB'!E:E) -> 0 | H12: =IFERROR(SUMIF('ADV - FB'!L:L,$A12,'ADV - FB'!H:H)/(SUMIF('ADV - FB'!L:L,$A12,'ADV - FB'!G:G)),"-") -> - | I12: =IFERROR(SUMIF('ADV - FB'!L:L,$A12,'ADV - FB'!E:E)/(SUMIF('ADV - FB'!L:L,$A12,'ADV - FB'!F:F)),"-") -> - | J12: =SUMIF('ADV - FB'!L:L,$A12,'ADV - FB'!I:I)+SUMIF('ADV - FB'!L:L,$A12,'ADV - FB'!J:J)+SUMIF('ADV - FB'!L:L,$A12,'ADV - FB'!K:K) -> 0 | K12: =IFERROR(G12/J12,"-") -> -
A13: TP12 | F13: =CONCATENATE(A13,," ","-"," ","",B13,""," ","-"," ",C13," ","-"," ",D13) -> TP12 - - - | G13: =SUMIF('ADV - FB'!L:L,$A13,'ADV - FB'!E:E) -> 0 | H13: =IFERROR(SUMIF('ADV - FB'!L:L,$A13,'ADV - FB'!H:H)/(SUMIF('ADV - FB'!L:L,$A13,'ADV - FB'!G:G)),"-") -> - | I13: =IFERROR(SUMIF('ADV - FB'!L:L,$A13,'ADV - FB'!E:E)/(SUMIF('ADV - FB'!L:L,$A13,'ADV - FB'!F:F)),"-") -> - | J13: =SUMIF('ADV - FB'!L:L,$A13,'ADV - FB'!I:I)+SUMIF('ADV - FB'!L:L,$A13,'ADV - FB'!J:J)+SUMIF('ADV - FB'!L:L,$A13,'ADV - FB'!K:K) -> 0 | K13: =IFERROR(G13/J13,"-") -> -
... A998: TP997 | F998: =CONCATENATE(A998,," ","-"," ","",B998,""," ","-"," ",C998," ","-"," ",D998) -> TP997 - - - | G998: =SUMIF('ADV - FB'!L:L,$A998,'ADV - FB'!E:E) -> 0 | H998: =IFERROR(SUMIF('ADV - FB'!L:L,$A998,'ADV - FB'!H:H)/(SUMIF('ADV - FB'!L:L,$A998,'ADV - FB'!G:G)),"-") -> - | I998: =IFERROR(SUMIF('ADV - FB'!L:L,$A998,'ADV - FB'!E:E)/(SUMIF('ADV - FB'!L:L,$A998,'ADV - FB'!F:F)),"-") -> - | J998: =SUMIF('ADV - FB'!L:L,$A998,'ADV - FB'!I:I)+SUMIF('ADV - FB'!L:L,$A998,'ADV - FB'!J:J)+SUMIF('ADV - FB'!L:L,$A998,'ADV - FB'!K:K) -> 0 | K998: =IFERROR(G998/J998,"-") -> -
A999: TP998 | F999: =CONCATENATE(A999,," ","-"," ","",B999,""," ","-"," ",C999," ","-"," ",D999) -> TP998 - - - | G999: =SUMIF('ADV - FB'!L:L,$A999,'ADV - FB'!E:E) -> 0 | H999: =IFERROR(SUMIF('ADV - FB'!L:L,$A999,'ADV - FB'!H:H)/(SUMIF('ADV - FB'!L:L,$A999,'ADV - FB'!G:G)),"-") -> - | I999: =IFERROR(SUMIF('ADV - FB'!L:L,$A999,'ADV - FB'!E:E)/(SUMIF('ADV - FB'!L:L,$A999,'ADV - FB'!F:F)),"-") -> - | J999: =SUMIF('ADV - FB'!L:L,$A999,'ADV - FB'!I:I) -> 0 | K999: =IFERROR(G999/J999,"-") -> -
A1000: TP999 | F1000: =CONCATENATE(A1000,," ","-"," ","",B1000,""," ","-"," ",C1000," ","-"," ",D1000) -> TP999 - - - | G1000: =SUMIF('ADV - FB'!L:L,$A1000,'ADV - FB'!E:E) -> 0 | H1000: =IFERROR(SUMIF('ADV - FB'!L:L,$A1000,'ADV - FB'!H:H)/(SUMIF('ADV - FB'!L:L,$A1000,'ADV - FB'!G:G)),"-") -> - | I1000: =IFERROR(SUMIF('ADV - FB'!L:L,$A1000,'ADV - FB'!E:E)/(SUMIF('ADV - FB'!L:L,$A1000,'ADV - FB'!F:F)),"-") -> - | J1000: =SUMIF('ADV - FB'!L:L,$A1000,'ADV - FB'!I:I) -> 0 | K1000: =IFERROR(G1000/J1000,"-") -> -

Sheet Copy Criativos
A1: ID | B1: Postado | C1: Texto Principal | D1: headline | E1: Descrição | F1: CUSTO | G1: CTR | H1: LEADS | I1: ROAS | J1: VALOR EM COMPRAS | K1: CPA | L1: CPS
A2: adc1 | B2: FALSE | F2: =SUMIF('ADV - FB'!D:D,"*adc1*",'ADV - FB'!E:E) -> 0 | G2: =IFERROR(SUMIF('ADV - FB'!D:D,"*adc1*",'ADV - FB'!H:H)/(SUMIF('ADV - FB'!D:D,"*adc1*",'ADV - FB'!G:G)),"-") -> - | H2: =SUMIF('ADV - FB'!D:D,"*adc1*",'ADV - FB'!I:I)+SUMIF('ADV - FB'!D:D,"*adc1*",'ADV - FB'!J:J) -> 0 | I2: =IFERROR(J2/F2,"-") -> - | J2: =SUMIF('ADV - FB'!D:D,"*adc1*",'ADV - FB'!J:J) -> 0 | K2: =IFERROR(F2/H2,"-") -> - | L2: =IFERROR(SUMIF('ADV - FB'!D:D,"*adc1*",'ADV - FB'!E:E)/(SUMIF('ADV - FB'!D:D,"*adc1*",'ADV - FB'!F:F)),"-") -> -
A3: adc2 | B3: FALSE | F3: =SUMIF('ADV - FB'!D:D,"*adc2*",'ADV - FB'!E:E) -> 0 | G3: =IFERROR(SUMIF('ADV - FB'!D:D,"*adc2*",'ADV - FB'!H:H)/(SUMIF('ADV - FB'!D:D,"*adc2*",'ADV - FB'!G:G)),"-") -> - | H3: =SUMIF('ADV - FB'!D:D,"*adc2*",'ADV - FB'!I:I)+SUMIF('ADV - FB'!D:D,"*adc2*",'ADV - FB'!J:J) -> 0 | I3: =IFERROR(J3/F3,"-") -> - | J3: =SUMIF('ADV - FB'!D:D,"*adc2*",'ADV - FB'!J:J) -> 0 | K3: =IFERROR(F3/H3,"-") -> - | L3: =IFERROR(SUMIF('ADV - FB'!D:D,"*adc2*",'ADV - FB'!E:E)/(SUMIF('ADV - FB'!D:D,"*adc2*",'ADV - FB'!F:F)),"-") -> -
A4: adc3 | B4: FALSE | F4: =SUMIF('ADV - FB'!D:D,"*adc3*",'ADV - FB'!E:E) -> 0 | G4: =IFERROR(SUMIF('ADV - FB'!D:D,"*adc3*",'ADV - FB'!H:H)/(SUMIF('ADV - FB'!D:D,"*adc3*",'ADV - FB'!G:G)),"-") -> - | H4: =SUMIF('ADV - FB'!D:D,"*adc3*",'ADV - FB'!I:I)+SUMIF('ADV - FB'!D:D,"*adc3*",'ADV - FB'!J:J) -> 0 | I4: =IFERROR(J4/F4,"-") -> - | J4: =SUMIF('ADV - FB'!D:D,"*adc3*",'ADV - FB'!J:J) -> 0 | K4: =IFERROR(F4/H4,"-") -> - | L4: =IFERROR(SUMIF('ADV - FB'!D:D,"*adc3*",'ADV - FB'!E:E)/(SUMIF('ADV - FB'!D:D,"*adc3*",'ADV - FB'!F:F)),"-") -> -
A5: adc4 | B5: FALSE | F5: =SUMIF('ADV - FB'!D:D,"*adc4*",'ADV - FB'!E:E) -> 0 | G5: =IFERROR(SUMIF('ADV - FB'!D:D,"*adc4*",'ADV - FB'!H:H)/(SUMIF('ADV - FB'!D:D,"*adc4*",'ADV - FB'!G:G)),"-") -> - | H5: =SUMIF('ADV - FB'!D:D,"*adc4*",'ADV - FB'!I:I)+SUMIF('ADV - FB'!D:D,"*adc4*",'ADV - FB'!J:J) -> 0 | I5: =IFERROR(J5/F5,"-") -> - | J5: =SUMIF('ADV - FB'!D:D,"*adc4*",'ADV - FB'!J:J) -> 0 | K5: =IFERROR(F5/H5,"-") -> - | L5: =IFERROR(SUMIF('ADV - FB'!D:D,"*adc4*",'ADV - FB'!E:E)/(SUMIF('ADV - FB'!D:D,"*adc4*",'ADV - FB'!F:F)),"-") -> -
A6: adc5 | B6: FALSE | F6: =SUMIF('ADV - FB'!D:D,"*adc5*",'ADV - FB'!E:E) -> 0 | G6: =IFERROR(SUMIF('ADV - FB'!D:D,"*adc5*",'ADV - FB'!H:H)/(SUMIF('ADV - FB'!D:D,"*adc5*",'ADV - FB'!G:G)),"-") -> - | H6: =SUMIF('ADV - FB'!D:D,"*adc5*",'ADV - FB'!I:I)+SUMIF('ADV - FB'!D:D,"*adc5*",'ADV - FB'!J:J) -> 0 | I6: =IFERROR(J6/F6,"-") -> - | J6: =SUMIF('ADV - FB'!D:D,"*adc5*",'ADV - FB'!J:J) -> 0 | K6: =IFERROR(F6/H6,"-") -> - | L6: =IFERROR(SUMIF('ADV - FB'!D:D,"*adc5*",'ADV - FB'!E:E)/(SUMIF('ADV - FB'!D:D,"*adc5*",'ADV - FB'!F:F)),"-") -> -
A7: adc6 | B7: FALSE | F7: =SUMIF('ADV - FB'!D:D,"*adc6*",'ADV - FB'!E:E) -> 0 | G7: =IFERROR(SUMIF('ADV - FB'!D:D,"*adc6*",'ADV - FB'!H:H)/(SUMIF('ADV - FB'!D:D,"*adc6*",'ADV - FB'!G:G)),"-") -> - | H7: =SUMIF('ADV - FB'!D:D,"*adc6*",'ADV - FB'!I:I)+SUMIF('ADV - FB'!D:D,"*adc6*",'ADV - FB'!J:J) -> 0 | I7: =IFERROR(J7/F7,"-") -> - | J7: =SUMIF('ADV - FB'!D:D,"*adc6*",'ADV - FB'!J:J) -> 0 | K7: =IFERROR(F7/H7,"-") -> - | L7: =IFERROR(SUMIF('ADV - FB'!D:D,"*adc6*",'ADV - FB'!E:E)/(SUMIF('ADV - FB'!D:D,"*adc6*",'ADV - FB'!F:F)),"-") -> -
A8: adc7 | B8: FALSE | F8: =SUMIF('ADV - FB'!D:D,"*adc7*",'ADV - FB'!E:E) -> 0 | G8: =IFERROR(SUMIF('ADV - FB'!D:D,"*adc7*",'ADV - FB'!H:H)/(SUMIF('ADV - FB'!D:D,"*adc7*",'ADV - FB'!G:G)),"-") -> - | H8: =SUMIF('ADV - FB'!D:D,"*adc7*",'ADV - FB'!I:I)+SUMIF('ADV - FB'!D:D,"*adc7*",'ADV - FB'!J:J) -> 0 | I8: =IFERROR(J8/F8,"-") -> - | J8: =SUMIF('ADV - FB'!D:D,"*adc7*",'ADV - FB'!J:J) -> 0 | K8: =IFERROR(F8/H8,"-") -> - | L8: =IFERROR(SUMIF('ADV - FB'!D:D,"*adc7*",'ADV - FB'!E:E)/(SUMIF('ADV - FB'!D:D,"*adc7*",'ADV - FB'!F:F)),"-") -> -
A9: adc8 | B9: FALSE | F9: =SUMIF('ADV - FB'!D:D,"*adc8*",'ADV - FB'!E:E) -> 0 | G9: =IFERROR(SUMIF('ADV - FB'!D:D,"*adc8*",'ADV - FB'!H:H)/(SUMIF('ADV - FB'!D:D,"*adc8*",'ADV - FB'!G:G)),"-") -> - | H9: =SUMIF('ADV - FB'!D:D,"*adc8*",'ADV - FB'!I:I)+SUMIF('ADV - FB'!D:D,"*adc8*",'ADV - FB'!J:J) -> 0 | I9: =IFERROR(J9/F9,"-") -> - | J9: =SUMIF('ADV - FB'!D:D,"*adc8*",'ADV - FB'!J:J) -> 0 | K9: =IFERROR(F9/H9,"-") -> - | L9: =IFERROR(SUMIF('ADV - FB'!D:D,"*adc8*",'ADV - FB'!E:E)/(SUMIF('ADV - FB'!D:D,"*adc8*",'ADV - FB'!F:F)),"-") -> -
A10: adc9 | B10: FALSE | F10: =SUMIF('ADV - FB'!D:D,"*adc9*",'ADV - FB'!E:E) -> 0 | G10: =IFERROR(SUMIF('ADV - FB'!D:D,"*adc9*",'ADV - FB'!H:H)/(SUMIF('ADV - FB'!D:D,"*adc9*",'ADV - FB'!G:G)),"-") -> - | H10: =SUMIF('ADV - FB'!D:D,"*adc9*",'ADV - FB'!I:I)+SUMIF('ADV - FB'!D:D,"*adc9*",'ADV - FB'!J:J) -> 0 | I10: =IFERROR(J10/F10,"-") -> - | J10: =SUMIF('ADV - FB'!D:D,"*adc9*",'ADV - FB'!J:J) -> 0 | K10: =IFERROR(F10/H10,"-") -> - | L10: =IFERROR(SUMIF('ADV - FB'!D:D,"*adc9*",'ADV - FB'!E:E)/(SUMIF('ADV - FB'!D:D,"*adc9*",'ADV - FB'!F:F)),"-") -> -
A11: adc10 | B11: FALSE | F11: =SUMIF('ADV - FB'!D:D,"*adc10*",'ADV - FB'!E:E) -> 0 | G11: =IFERROR(SUMIF('ADV - FB'!D:D,"*adc10*",'ADV - FB'!H:H)/(SUMIF('ADV - FB'!D:D,"*adc10*",'ADV - FB'!G:G)),"-") -> - | H11: =SUMIF('ADV - FB'!D:D,"*adc10*",'ADV - FB'!I:I)+SUMIF('ADV - FB'!D:D,"*adc10*",'ADV - FB'!J:J) -> 0 | I11: =IFERROR(J11/F11,"-") -> - | J11: =SUMIF('ADV - FB'!D:D,"*adc10*",'ADV - FB'!J:J) -> 0 | K11: =IFERROR(F11/H11,"-") -> - | L11: =IFERROR(SUMIF('ADV - FB'!D:D,"*adc10*",'ADV - FB'!E:E)/(SUMIF('ADV - FB'!D:D,"*adc10*",'ADV - FB'!F:F)),"-") -> -
A12: adc11 | B12: FALSE | F12: =SUMIF('ADV - FB'!D:D,"*adc11*",'ADV - FB'!E:E) -> 0 | G12: =IFERROR(SUMIF('ADV - FB'!D:D,"*adc11*",'ADV - FB'!H:H)/(SUMIF('ADV - FB'!D:D,"*adc11*",'ADV - FB'!G:G)),"-") -> - | H12: =SUMIF('ADV - FB'!D:D,"*adc11*",'ADV - FB'!I:I)+SUMIF('ADV - FB'!D:D,"*adc11*",'ADV - FB'!J:J) -> 0 | I12: =IFERROR(J12/F12,"-") -> - | J12: =SUMIF('ADV - FB'!D:D,"*adc11*",'ADV - FB'!J:J) -> 0 | K12: =IFERROR(F12/H12,"-") -> - | L12: =IFERROR(SUMIF('ADV - FB'!D:D,"*adc11*",'ADV - FB'!E:E)/(SUMIF('ADV - FB'!D:D,"*adc11*",'ADV - FB'!F:F)),"-") -> -
A13: adc12 | B13: FALSE | F13: =SUMIF('ADV - FB'!D:D,"*adc12*",'ADV - FB'!E:E) -> 0 | G13: =IFERROR(SUMIF('ADV - FB'!D:D,"*adc12*",'ADV - FB'!H:H)/(SUMIF('ADV - FB'!D:D,"*adc12*",'ADV - FB'!G:G)),"-") -> - | H13: =SUMIF('ADV - FB'!D:D,"*adc12*",'ADV - FB'!I:I)+SUMIF('ADV - FB'!D:D,"*adc12*",'ADV - FB'!J:J) -> 0 | I13: =IFERROR(J13/F13,"-") -> - | J13: =SUMIF('ADV - FB'!D:D,"*adc12*",'ADV - FB'!J:J) -> 0 | K13: =IFERROR(F13/H13,"-") -> - | L13: =IFERROR(SUMIF('ADV - FB'!D:D,"*adc12*",'ADV - FB'!E:E)/(SUMIF('ADV - FB'!D:D,"*adc12*",'ADV - FB'!F:F)),"-") -> -
A14: adc13 | B14: FALSE | F14: =SUMIF('ADV - FB'!D:D,"*adc13*",'ADV - FB'!E:E) -> 0 | G14: =IFERROR(SUMIF('ADV - FB'!D:D,"*adc13*",'ADV - FB'!H:H)/(SUMIF('ADV - FB'!D:D,"*adc13*",'ADV - FB'!G:G)),"-") -> - | H14: =SUMIF('ADV - FB'!D:D,"*adc13*",'ADV - FB'!I:I)+SUMIF('ADV - FB'!D:D,"*adc13*",'ADV - FB'!J:J) -> 0 | I14: =IFERROR(J14/F14,"-") -> - | J14: =SUMIF('ADV - FB'!D:D,"*adc13*",'ADV - FB'!J:J) -> 0 | K14: =IFERROR(F14/H14,"-") -> - | L14: =IFERROR(SUMIF('ADV - FB'!D:D,"*adc13*",'ADV - FB'!E:E)/(SUMIF('ADV - FB'!D:D,"*adc13*",'ADV - FB'!F:F)),"-") -> -
A15: adc14 | B15: FALSE | F15: =SUMIF('ADV - FB'!D:D,"*adc14*",'ADV - FB'!E:E) -> 0 | G15: =IFERROR(SUMIF('ADV - FB'!D:D,"*adc14*",'ADV - FB'!H:H)/(SUMIF('ADV - FB'!D:D,"*adc14*",'ADV - FB'!G:G)),"-") -> - | H15: =SUMIF('ADV - FB'!D:D,"*adc14*",'ADV - FB'!I:I)+SUMIF('ADV - FB'!D:D,"*adc14*",'ADV - FB'!J:J) -> 0 | I15: =IFERROR(J15/F15,"-") -> - | J15: =SUMIF('ADV - FB'!D:D,"*adc14*",'ADV - FB'!J:J) -> 0 | K15: =IFERROR(F15/H15,"-") -> - | L15: =IFERROR(SUMIF('ADV - FB'!D:D,"*adc14*",'ADV - FB'!E:E)/(SUMIF('ADV - FB'!D:D,"*adc14*",'ADV - FB'!F:F)),"-") -> -
A16: adc15 | B16: FALSE | F16: =SUMIF('ADV - FB'!D:D,"*adc15*",'ADV - FB'!E:E) -> 0 | G16: =IFERROR(SUMIF('ADV - FB'!D:D,"*adc15*",'ADV - FB'!H:H)/(SUMIF('ADV - FB'!D:D,"*adc15*",'ADV - FB'!G:G)),"-") -> - | H16: =SUMIF('ADV - FB'!D:D,"*adc15*",'ADV - FB'!I:I)+SUMIF('ADV - FB'!D:D,"*adc15*",'ADV - FB'!J:J) -> 0 | I16: =IFERROR(J16/F16,"-") -> - | J16: =SUMIF('ADV - FB'!D:D,"*adc15*",'ADV - FB'!J:J) -> 0 | K16: =IFERROR(F16/H16,"-") -> - | L16: =IFERROR(SUMIF('ADV - FB'!D:D,"*adc15*",'ADV - FB'!E:E)/(SUMIF('ADV - FB'!D:D,"*adc15*",'ADV - FB'!F:F)),"-") -> -
A17: adc16 | B17: FALSE | F17: =SUMIF('ADV - FB'!D:D,"*adc16*",'ADV - FB'!E:E) -> 0 | G17: =IFERROR(SUMIF('ADV - FB'!D:D,"*adc16*",'ADV - FB'!H:H)/(SUMIF('ADV - FB'!D:D,"*adc16*",'ADV - FB'!G:G)),"-") -> - | H17: =SUMIF('ADV - FB'!D:D,"*adc16*",'ADV - FB'!I:I)+SUMIF('ADV - FB'!D:D,"*adc16*",'ADV - FB'!J:J) -> 0 | I17: =IFERROR(J17/F17,"-") -> - | J17: =SUMIF('ADV - FB'!D:D,"*adc16*",'ADV - FB'!J:J) -> 0 | K17: =IFERROR(F17/H17,"-") -> - | L17: =IFERROR(SUMIF('ADV - FB'!D:D,"*adc16*",'ADV - FB'!E:E)/(SUMIF('ADV - FB'!D:D,"*adc16*",'ADV - FB'!F:F)),"-") -> -
A18: adc17 | B18: FALSE | F18: =SUMIF('ADV - FB'!D:D,"*adc17*",'ADV - FB'!E:E) -> 0 | G18: =IFERROR(SUMIF('ADV - FB'!D:D,"*adc17*",'ADV - FB'!H:H)/(SUMIF('ADV - FB'!D:D,"*adc17*",'ADV - FB'!G:G)),"-") -> - | H18: =SUMIF('ADV - FB'!D:D,"*adc17*",'ADV - FB'!I:I)+SUMIF('ADV - FB'!D:D,"*adc17*",'ADV - FB'!J:J) -> 0 | I18: =IFERROR(J18/F18,"-") -> - | J18: =SUMIF('ADV - FB'!D:D,"*adc17*",'ADV - FB'!J:J) -> 0 | K18: =IFERROR(F18/H18,"-") -> - | L18: =IFERROR(SUMIF('ADV - FB'!D:D,"*adc17*",'ADV - FB'!E:E)/(SUMIF('ADV - FB'!D:D,"*adc17*",'ADV - FB'!F:F)),"-") -> -
A19: adc18 | B19: FALSE | F19: =SUMIF('ADV - FB'!D:D,"*adc18*",'ADV - FB'!E:E) -> 0 | G19: =IFERROR(SUMIF('ADV - FB'!D:D,"*adc18*",'ADV - FB'!H:H)/(SUMIF('ADV - FB'!D:D,"*adc18*",'ADV - FB'!G:G)),"-") -> - | H19: =SUMIF('ADV - FB'!D:D,"*adc18*",'ADV - FB'!I:I)+SUMIF('ADV - FB'!D:D,"*adc18*",'ADV - FB'!J:J) -> 0 | I19: =IFERROR(J19/F19,"-") -> - | J19: =SUMIF('ADV - FB'!D:D,"*adc18*",'ADV - FB'!J:J) -> 0 | K19: =IFERROR(F19/H19,"-") -> - | L19: =IFERROR(SUMIF('ADV - FB'!D:D,"*adc18*",'ADV - FB'!E:E)/(SUMIF('ADV - FB'!D:D,"*adc18*",'ADV - FB'!F:F)),"-") -> -
A20: adc19 | B20: FALSE | F20: =SUMIF('ADV - FB'!D:D,"*adc19*",'ADV - FB'!E:E) -> 0 | G20: =IFERROR(SUMIF('ADV - FB'!D:D,"*adc19*",'ADV - FB'!H:H)/(SUMIF('ADV - FB'!D:D,"*adc19*",'ADV - FB'!G:G)),"-") -> - | H20: =SUMIF('ADV - FB'!D:D,"*adc19*",'ADV - FB'!I:I)+SUMIF('ADV - FB'!D:D,"*adc19*",'ADV - FB'!J:J) -> 0 | I20: =IFERROR(J20/F20,"-") -> - | J20: =SUMIF('ADV - FB'!D:D,"*adc19*",'ADV - FB'!J:J) -> 0 | K20: =IFERROR(F20/H20,"-") -> - | L20: =IFERROR(SUMIF('ADV - FB'!D:D,"*adc19*",'ADV - FB'!E:E)/(SUMIF('ADV - FB'!D:D,"*adc19*",'ADV - FB'!F:F)),"-") -> -
A21: adc20 | B21: FALSE | F21: =SUMIF('ADV - FB'!D:D,"*adc20*",'ADV - FB'!E:E) -> 0 | G21: =IFERROR(SUMIF('ADV - FB'!D:D,"*adc20*",'ADV - FB'!H:H)/(SUMIF('ADV - FB'!D:D,"*adc20*",'ADV - FB'!G:G)),"-") -> - | H21: =SUMIF('ADV - FB'!D:D,"*adc20*",'ADV - FB'!I:I)+SUMIF('ADV - FB'!D:D,"*adc20*",'ADV - FB'!J:J) -> 0 | I21: =IFERROR(J21/F21,"-") -> - | J21: =SUMIF('ADV - FB'!D:D,"*adc20*",'ADV - FB'!J:J) -> 0 | K21: =IFERROR(F21/H21,"-") -> - | L21: =IFERROR(SUMIF('ADV - FB'!D:D,"*adc20*",'ADV - FB'!E:E)/(SUMIF('ADV - FB'!D:D,"*adc20*",'ADV - FB'!F:F)),"-") -> -
A22: adc21 | B22: FALSE | F22: =SUMIF('ADV - FB'!D:D,"*adc21*",'ADV - FB'!E:E) -> 0 | G22: =IFERROR(SUMIF('ADV - FB'!D:D,"*adc21*",'ADV - FB'!H:H)/(SUMIF('ADV - FB'!D:D,"*adc21*",'ADV - FB'!G:G)),"-") -> - | H22: =SUMIF('ADV - FB'!D:D,"*adc21*",'ADV - FB'!I:I)+SUMIF('ADV - FB'!D:D,"*adc21*",'ADV - FB'!J:J) -> 0 | I22: =IFERROR(J22/F22,"-") -> - | J22: =SUMIF('ADV - FB'!D:D,"*adc21*",'ADV - FB'!J:J) -> 0 | K22: =IFERROR(F22/H22,"-") -> - | L22: =IFERROR(SUMIF('ADV - FB'!D:D,"*adc21*",'ADV - FB'!E:E)/(SUMIF('ADV - FB'!D:D,"*adc21*",'ADV - FB'!F:F)),"-") -> -
A23: adc22 | B23: FALSE | F23: =SUMIF('ADV - FB'!D:D,"*adc22*",'ADV - FB'!E:E) -> 0 | G23: =IFERROR(SUMIF('ADV - FB'!D:D,"*adc22*",'ADV - FB'!H:H)/(SUMIF('ADV - FB'!D:D,"*adc22*",'ADV - FB'!G:G)),"-") -> - | H23: =SUMIF('ADV - FB'!D:D,"*adc22*",'ADV - FB'!I:I)+SUMIF('ADV - FB'!D:D,"*adc22*",'ADV - FB'!J:J) -> 0 | I23: =IFERROR(J23/F23,"-") -> - | J23: =SUMIF('ADV - FB'!D:D,"*adc22*",'ADV - FB'!J:J) -> 0 | K23: =IFERROR(F23/H23,"-") -> - | L23: =IFERROR(SUMIF('ADV - FB'!D:D,"*adc22*",'ADV - FB'!E:E)/(SUMIF('ADV - FB'!D:D,"*adc22*",'ADV - FB'!F:F)),"-") -> -
A24: adc23 | B24: FALSE | F24: =SUMIF('ADV - FB'!D:D,"*adc23*",'ADV - FB'!E:E) -> 0 | G24: =IFERROR(SUMIF('ADV - FB'!D:D,"*adc23*",'ADV - FB'!H:H)/(SUMIF('ADV - FB'!D:D,"*adc23*",'ADV - FB'!G:G)),"-") -> - | H24: =SUMIF('ADV - FB'!D:D,"*adc23*",'ADV - FB'!I:I)+SUMIF('ADV - FB'!D:D,"*adc23*",'ADV - FB'!J:J) -> 0 | I24: =IFERROR(J24/F24,"-") -> - | J24: =SUMIF('ADV - FB'!D:D,"*adc23*",'ADV - FB'!J:J) -> 0 | K24: =IFERROR(F24/H24,"-") -> - | L24: =IFERROR(SUMIF('ADV - FB'!D:D,"*adc23*",'ADV - FB'!E:E)/(SUMIF('ADV - FB'!D:D,"*adc23*",'ADV - FB'!F:F)),"-") -> -
A25: adc24 | B25: FALSE | F25: =SUMIF('ADV - FB'!D:D,"*adc24*",'ADV - FB'!E:E) -> 0 | G25: =IFERROR(SUMIF('ADV - FB'!D:D,"*adc24*",'ADV - FB'!H:H)/(SUMIF('ADV - FB'!D:D,"*adc24*",'ADV - FB'!G:G)),"-") -> - | H25: =SUMIF('ADV - FB'!D:D,"*adc24*",'ADV - FB'!I:I)+SUMIF('ADV - FB'!D:D,"*adc24*",'ADV - FB'!J:J) -> 0 | I25: =IFERROR(J25/F25,"-") -> - | J25: =SUMIF('ADV - FB'!D:D,"*adc24*",'ADV - FB'!J:J) -> 0 | K25: =IFERROR(F25/H25,"-") -> - | L25: =IFERROR(SUMIF('ADV - FB'!D:D,"*adc24*",'ADV - FB'!E:E)/(SUMIF('ADV - FB'!D:D,"*adc24*",'ADV - FB'!F:F)),"-") -> -
A26: adc25 | B26: FALSE | F26: =SUMIF('ADV - FB'!D:D,"*adc25*",'ADV - FB'!E:E) -> 0 | G26: =IFERROR(SUMIF('ADV - FB'!D:D,"*adc25*",'ADV - FB'!H:H)/(SUMIF('ADV - FB'!D:D,"*adc25*",'ADV - FB'!G:G)),"-") -> - | H26: =SUMIF('ADV - FB'!D:D,"*adc25*",'ADV - FB'!I:I)+SUMIF('ADV - FB'!D:D,"*adc25*",'ADV - FB'!J:J) -> 0 | I26: =IFERROR(J26/F26,"-") -> - | J26: =SUMIF('ADV - FB'!D:D,"*adc25*",'ADV - FB'!J:J) -> 0 | K26: =IFERROR(F26/H26,"-") -> - | L26: =IFERROR(SUMIF('ADV - FB'!D:D,"*adc25*",'ADV - FB'!E:E)/(SUMIF('ADV - FB'!D:D,"*adc25*",'ADV - FB'!F:F)),"-") -> -
A27: adc26 | B27: FALSE | F27: =SUMIF('ADV - FB'!D:D,"*adc26*",'ADV - FB'!E:E) -> 0 | G27: =IFERROR(SUMIF('ADV - FB'!D:D,"*adc26*",'ADV - FB'!H:H)/(SUMIF('ADV - FB'!D:D,"*adc26*",'ADV - FB'!G:G)),"-") -> - | H27: =SUMIF('ADV - FB'!D:D,"*adc26*",'ADV - FB'!I:I) -> 0 | I27: =IFERROR(J27/F27,"-") -> - | J27: =SUMIF('ADV - FB'!D:D,"*adc26*",'ADV - FB'!J:J) -> 0 | K27: =IFERROR(F27/H27,"-") -> - | L27: =IFERROR(SUMIF('ADV - FB'!D:D,"*adc26*",'ADV - FB'!E:E)/(SUMIF('ADV - FB'!D:D,"*adc26*",'ADV - FB'!F:F)),"-") -> -
A28: adc27 | B28: FALSE | F28: =SUMIF('ADV - FB'!D:D,"*adc27*",'ADV - FB'!E:E) -> 0 | G28: =IFERROR(SUMIF('ADV - FB'!D:D,"*adc27*",'ADV - FB'!H:H)/(SUMIF('ADV - FB'!D:D,"*adc27*",'ADV - FB'!G:G)),"-") -> - | H28: =SUMIF('ADV - FB'!D:D,"*adc27*",'ADV - FB'!I:I) -> 0 | I28: =IFERROR(J28/F28,"-") -> - | J28: =SUMIF('ADV - FB'!D:D,"*adc27*",'ADV - FB'!J:J) -> 0 | K28: =IFERROR(F28/H28,"-") -> - | L28: =IFERROR(SUMIF('ADV - FB'!D:D,"*adc27*",'ADV - FB'!E:E)/(SUMIF('ADV - FB'!D:D,"*adc27*",'ADV - FB'!F:F)),"-") -> -
A29: adc28 | B29: FALSE | F29: =SUMIF('ADV - FB'!D:D,"*adc28*",'ADV - FB'!E:E) -> 0 | G29: =IFERROR(SUMIF('ADV - FB'!D:D,"*adc28*",'ADV - FB'!H:H)/(SUMIF('ADV - FB'!D:D,"*adc28*",'ADV - FB'!G:G)),"-") -> - | H29: =SUMIF('ADV - FB'!D:D,"*adc28*",'ADV - FB'!I:I) -> 0 | I29: =IFERROR(J29/F29,"-") -> - | J29: =SUMIF('ADV - FB'!D:D,"*adc28*",'ADV - FB'!J:J) -> 0 | K29: =IFERROR(F29/H29,"-") -> - | L29: =IFERROR(SUMIF('ADV - FB'!D:D,"*adc28*",'ADV - FB'!E:E)/(SUMIF('ADV - FB'!D:D,"*adc28*",'ADV - FB'!F:F)),"-") -> -
A30: adc29 | B30: FALSE | F30: =SUMIF('ADV - FB'!D:D,"*adc29*",'ADV - FB'!E:E) -> 0 | G30: =IFERROR(SUMIF('ADV - FB'!D:D,"*adc29*",'ADV - FB'!H:H)/(SUMIF('ADV - FB'!D:D,"*adc29*",'ADV - FB'!G:G)),"-") -> - | H30: =SUMIF('ADV - FB'!D:D,"*adc29*",'ADV - FB'!I:I) -> 0 | I30: =IFERROR(J30/F30,"-") -> - | J30: =SUMIF('ADV - FB'!D:D,"*adc29*",'ADV - FB'!J:J) -> 0 | K30: =IFERROR(F30/H30,"-") -> - | L30: =IFERROR(SUMIF('ADV - FB'!D:D,"*adc29*",'ADV - FB'!E:E)/(SUMIF('ADV - FB'!D:D,"*adc29*",'ADV - FB'!F:F)),"-") -> -
A31: adc30 | B31: FALSE | F31: =SUMIF('ADV - FB'!D:D,"*adc30*",'ADV - FB'!E:E) -> 0 | G31: =IFERROR(SUMIF('ADV - FB'!D:D,"*adc30*",'ADV - FB'!H:H)/(SUMIF('ADV - FB'!D:D,"*adc30*",'ADV - FB'!G:G)),"-") -> - | H31: =SUMIF('ADV - FB'!D:D,"*adc30*",'ADV - FB'!I:I) -> 0 | I31: =IFERROR(J31/F31,"-") -> - | J31: =SUMIF('ADV - FB'!D:D,"*adc30*",'ADV - FB'!J:J) -> 0 | K31: =IFERROR(F31/H31,"-") -> - | L31: =IFERROR(SUMIF('ADV - FB'!D:D,"*adc30*",'ADV - FB'!E:E)/(SUMIF('ADV - FB'!D:D,"*adc30*",'ADV - FB'!F:F)),"-") -> -
A32: adc31 | B32: FALSE | F32: =SUMIF('ADV - FB'!D:D,"*adc31*",'ADV - FB'!E:E) -> 0 | G32: =IFERROR(SUMIF('ADV - FB'!D:D,"*adc31*",'ADV - FB'!H:H)/(SUMIF('ADV - FB'!D:D,"*adc31*",'ADV - FB'!G:G)),"-") -> - | H32: =SUMIF('ADV - FB'!D:D,"*adc31*",'ADV - FB'!I:I) -> 0 | I32: =IFERROR(J32/F32,"-") -> - | J32: =SUMIF('ADV - FB'!D:D,"*adc31*",'ADV - FB'!J:J) -> 0 | K32: =IFERROR(F32/H32,"-") -> - | L32: =IFERROR(SUMIF('ADV - FB'!D:D,"*adc31*",'ADV - FB'!E:E)/(SUMIF('ADV - FB'!D:D,"*adc31*",'ADV - FB'!F:F)),"-") -> -
A33: adc32 | B33: FALSE | F33: =SUMIF('ADV - FB'!D:D,"*adc32*",'ADV - FB'!E:E) -> 0 | G33: =IFERROR(SUMIF('ADV - FB'!D:D,"*adc32*",'ADV - FB'!H:H)/(SUMIF('ADV - FB'!D:D,"*adc32*",'ADV - FB'!G:G)),"-") -> - | H33: =SUMIF('ADV - FB'!D:D,"*adc32*",'ADV - FB'!I:I) -> 0 | I33: =IFERROR(J33/F33,"-") -> - | J33: =SUMIF('ADV - FB'!D:D,"*adc32*",'ADV - FB'!J:J) -> 0 | K33: =IFERROR(F33/H33,"-") -> - | L33: =IFERROR(SUMIF('ADV - FB'!D:D,"*adc32*",'ADV - FB'!E:E)/(SUMIF('ADV - FB'!D:D,"*adc32*",'ADV - FB'!F:F)),"-") -> -
A34: adc33 | B34: FALSE | F34: =SUMIF('ADV - FB'!D:D,"*adc33*",'ADV - FB'!E:E) -> 0 | G34: =IFERROR(SUMIF('ADV - FB'!D:D,"*adc33*",'ADV - FB'!H:H)/(SUMIF('ADV - FB'!D:D,"*adc33*",'ADV - FB'!G:G)),"-") -> - | H34: =SUMIF('ADV - FB'!D:D,"*adc33*",'ADV - FB'!I:I) -> 0 | I34: =IFERROR(J34/F34,"-") -> - | J34: =SUMIF('ADV - FB'!D:D,"*adc33*",'ADV - FB'!J:J) -> 0 | K34: =IFERROR(F34/H34,"-") -> - | L34: =IFERROR(SUMIF('ADV - FB'!D:D,"*adc33*",'ADV - FB'!E:E)/(SUMIF('ADV - FB'!D:D,"*adc33*",'ADV - FB'!F:F)),"-") -> -
A35: adc34 | B35: FALSE | F35: =SUMIF('ADV - FB'!D:D,"*adc34*",'ADV - FB'!E:E) -> 0 | G35: =IFERROR(SUMIF('ADV - FB'!D:D,"*adc34*",'ADV - FB'!H:H)/(SUMIF('ADV - FB'!D:D,"*adc34*",'ADV - FB'!G:G)),"-") -> - | H35: =SUMIF('ADV - FB'!D:D,"*adc34*",'ADV - FB'!I:I) -> 0 | I35: =IFERROR(J35/F35,"-") -> - | J35: =SUMIF('ADV - FB'!D:D,"*adc34*",'ADV - FB'!J:J) -> 0 | K35: =IFERROR(F35/H35,"-") -> - | L35: =IFERROR(SUMIF('ADV - FB'!D:D,"*adc34*",'ADV - FB'!E:E)/(SUMIF('ADV - FB'!D:D,"*adc34*",'ADV - FB'!F:F)),"-") -> -
A36: adc35 | B36: FALSE | F36: =SUMIF('ADV - FB'!D:D,"*adc35*",'ADV - FB'!E:E) -> 0 | G36: =IFERROR(SUMIF('ADV - FB'!D:D,"*adc35*",'ADV - FB'!H:H)/(SUMIF('ADV - FB'!D:D,"*adc35*",'ADV - FB'!G:G)),"-") -> - | H36: =SUMIF('ADV - FB'!D:D,"*adc35*",'ADV - FB'!I:I) -> 0 | I36: =IFERROR(J36/F36,"-") -> - | J36: =SUMIF('ADV - FB'!D:D,"*adc35*",'ADV - FB'!J:J) -> 0 | K36: =IFERROR(F36/H36,"-") -> - | L36: =IFERROR(SUMIF('ADV - FB'!D:D,"*adc35*",'ADV - FB'!E:E)/(SUMIF('ADV - FB'!D:D,"*adc35*",'ADV - FB'!F:F)),"-") -> -
A37: adc36 | B37: FALSE | F37: =SUMIF('ADV - FB'!D:D,"*adc36*",'ADV - FB'!E:E) -> 0 | G37: =IFERROR(SUMIF('ADV - FB'!D:D,"*adc36*",'ADV - FB'!H:H)/(SUMIF('ADV - FB'!D:D,"*adc36*",'ADV - FB'!G:G)),"-") -> - | H37: =SUMIF('ADV - FB'!D:D,"*adc36*",'ADV - FB'!I:I) -> 0 | I37: =IFERROR(J37/F37,"-") -> - | J37: =SUMIF('ADV - FB'!D:D,"*adc36*",'ADV - FB'!J:J) -> 0 | K37: =IFERROR(F37/H37,"-") -> - | L37: =IFERROR(SUMIF('ADV - FB'!D:D,"*adc36*",'ADV - FB'!E:E)/(SUMIF('ADV - FB'!D:D,"*adc36*",'ADV - FB'!F:F)),"-") -> -
A38: adc37 | B38: FALSE | F38: =SUMIF('ADV - FB'!D:D,"*adc37*",'ADV - FB'!E:E) -> 0 | G38: =IFERROR(SUMIF('ADV - FB'!D:D,"*adc37*",'ADV - FB'!H:H)/(SUMIF('ADV - FB'!D:D,"*adc37*",'ADV - FB'!G:G)),"-") -> - | H38: =SUMIF('ADV - FB'!D:D,"*adc37*",'ADV - FB'!I:I) -> 0 | I38: =IFERROR(J38/F38,"-") -> - | J38: =SUMIF('ADV - FB'!D:D,"*adc37*",'ADV - FB'!J:J) -> 0 | K38: =IFERROR(F38/H38,"-") -> - | L38: =IFERROR(SUMIF('ADV - FB'!D:D,"*adc37*",'ADV - FB'!E:E)/(SUMIF('ADV - FB'!D:D,"*adc37*",'ADV - FB'!F:F)),"-") -> -
A39: adc38 | B39: FALSE | F39: =SUMIF('ADV - FB'!D:D,"*adc38*",'ADV - FB'!E:E) -> 0 | G39: =IFERROR(SUMIF('ADV - FB'!D:D,"*adc38*",'ADV - FB'!H:H)/(SUMIF('ADV - FB'!D:D,"*adc38*",'ADV - FB'!G:G)),"-") -> - | H39: =SUMIF('ADV - FB'!D:D,"*adc38*",'ADV - FB'!I:I) -> 0 | I39: =IFERROR(J39/F39,"-") -> - | J39: =SUMIF('ADV - FB'!D:D,"*adc38*",'ADV - FB'!J:J) -> 0 | K39: =IFERROR(F39/H39,"-") -> - | L39: =IFERROR(SUMIF('ADV - FB'!D:D,"*adc38*",'ADV - FB'!E:E)/(SUMIF('ADV - FB'!D:D,"*adc38*",'ADV - FB'!F:F)),"-") -> -
A40: adc39 | B40: FALSE | F40: =SUMIF('ADV - FB'!D:D,"*adc39*",'ADV - FB'!E:E) -> 0 | G40: =IFERROR(SUMIF('ADV - FB'!D:D,"*adc39*",'ADV - FB'!H:H)/(SUMIF('ADV - FB'!D:D,"*adc39*",'ADV - FB'!G:G)),"-") -> - | H40: =SUMIF('ADV - FB'!D:D,"*adc39*",'ADV - FB'!I:I) -> 0 | I40: =IFERROR(J40/F40,"-") -> - | J40: =SUMIF('ADV - FB'!D:D,"*adc39*",'ADV - FB'!J:J) -> 0 | K40: =IFERROR(F40/H40,"-") -> - | L40: =IFERROR(SUMIF('ADV - FB'!D:D,"*adc39*",'ADV - FB'!E:E)/(SUMIF('ADV - FB'!D:D,"*adc39*",'ADV - FB'!F:F)),"-") -> -
A41: adc40 | B41: FALSE | F41: =SUMIF('ADV - FB'!D:D,"*adc40*",'ADV - FB'!E:E) -> 0 | G41: =IFERROR(SUMIF('ADV - FB'!D:D,"*adc40*",'ADV - FB'!H:H)/(SUMIF('ADV - FB'!D:D,"*adc40*",'ADV - FB'!G:G)),"-") -> - | H41: =SUMIF('ADV - FB'!D:D,"*adc40*",'ADV - FB'!I:I) -> 0 | I41: =IFERROR(J41/F41,"-") -> - | J41: =SUMIF('ADV - FB'!D:D,"*adc40*",'ADV - FB'!J:J) -> 0 | K41: =IFERROR(F41/H41,"-") -> - | L41: =IFERROR(SUMIF('ADV - FB'!D:D,"*adc40*",'ADV - FB'!E:E)/(SUMIF('ADV - FB'!D:D,"*adc40*",'ADV - FB'!F:F)),"-") -> -
A42: adc41 | B42: FALSE | F42: =SUMIF('ADV - FB'!D:D,"*adc41*",'ADV - FB'!E:E) -> 0 | G42: =IFERROR(SUMIF('ADV - FB'!D:D,"*adc41*",'ADV - FB'!H:H)/(SUMIF('ADV - FB'!D:D,"*adc41*",'ADV - FB'!G:G)),"-") -> - | H42: =SUMIF('ADV - FB'!D:D,"*adc41*",'ADV - FB'!I:I) -> 0 | I42: =IFERROR(J42/F42,"-") -> - | J42: =SUMIF('ADV - FB'!D:D,"*adc41*",'ADV - FB'!J:J) -> 0 | K42: =IFERROR(F42/H42,"-") -> - | L42: =IFERROR(SUMIF('ADV - FB'!D:D,"*adc41*",'ADV - FB'!E:E)/(SUMIF('ADV - FB'!D:D,"*adc41*",'ADV - FB'!F:F)),"-") -> -
A43: adc42 | B43: FALSE | F43: =SUMIF('ADV - FB'!D:D,"*adc42*",'ADV - FB'!E:E) -> 0 | G43: =IFERROR(SUMIF('ADV - FB'!D:D,"*adc42*",'ADV - FB'!H:H)/(SUMIF('ADV - FB'!D:D,"*adc42*",'ADV - FB'!G:G)),"-") -> - | H43: =SUMIF('ADV - FB'!D:D,"*adc42*",'ADV - FB'!I:I) -> 0 | I43: =IFERROR(J43/F43,"-") -> - | J43: =SUMIF('ADV - FB'!D:D,"*adc42*",'ADV - FB'!J:J) -> 0 | K43: =IFERROR(F43/H43,"-") -> - | L43: =IFERROR(SUMIF('ADV - FB'!D:D,"*adc42*",'ADV - FB'!E:E)/(SUMIF('ADV - FB'!D:D,"*adc42*",'ADV - FB'!F:F)),"-") -> -
A44: adc43 | B44: FALSE | F44: =SUMIF('ADV - FB'!D:D,"*adc43*",'ADV - FB'!E:E) -> 0 | G44: =IFERROR(SUMIF('ADV - FB'!D:D,"*adc43*",'ADV - FB'!H:H)/(SUMIF('ADV - FB'!D:D,"*adc43*",'ADV - FB'!G:G)),"-") -> - | H44: =SUMIF('ADV - FB'!D:D,"*adc43*",'ADV - FB'!I:I) -> 0 | I44: =IFERROR(J44/F44,"-") -> - | J44: =SUMIF('ADV - FB'!D:D,"*adc43*",'ADV - FB'!J:J) -> 0 | K44: =IFERROR(F44/H44,"-") -> - | L44: =IFERROR(SUMIF('ADV - FB'!D:D,"*adc43*",'ADV - FB'!E:E)/(SUMIF('ADV - FB'!D:D,"*adc43*",'ADV - FB'!F:F)),"-") -> -
A45: adc44 | B45: FALSE | F45: =SUMIF('ADV - FB'!D:D,"*adc44*",'ADV - FB'!E:E) -> 0 | G45: =IFERROR(SUMIF('ADV - FB'!D:D,"*adc44*",'ADV - FB'!H:H)/(SUMIF('ADV - FB'!D:D,"*adc44*",'ADV - FB'!G:G)),"-") -> - | H45: =SUMIF('ADV - FB'!D:D,"*adc44*",'ADV - FB'!I:I) -> 0 | I45: =IFERROR(J45/F45,"-") -> - | J45: =SUMIF('ADV - FB'!D:D,"*adc44*",'ADV - FB'!J:J) -> 0 | K45: =IFERROR(F45/H45,"-") -> - | L45: =IFERROR(SUMIF('ADV - FB'!D:D,"*adc44*",'ADV - FB'!E:E)/(SUMIF('ADV - FB'!D:D,"*adc44*",'ADV - FB'!F:F)),"-") -> -
A46: adc45 | B46: FALSE | F46: =SUMIF('ADV - FB'!D:D,"*adc45*",'ADV - FB'!E:E) -> 0 | G46: =IFERROR(SUMIF('ADV - FB'!D:D,"*adc45*",'ADV - FB'!H:H)/(SUMIF('ADV - FB'!D:D,"*adc45*",'ADV - FB'!G:G)),"-") -> - | H46: =SUMIF('ADV - FB'!D:D,"*adc45*",'ADV - FB'!I:I) -> 0 | I46: =IFERROR(J46/F46,"-") -> - | J46: =SUMIF('ADV - FB'!D:D,"*adc45*",'ADV - FB'!J:J) -> 0 | K46: =IFERROR(F46/H46,"-") -> - | L46: =IFERROR(SUMIF('ADV - FB'!D:D,"*adc45*",'ADV - FB'!E:E)/(SUMIF('ADV - FB'!D:D,"*adc45*",'ADV - FB'!F:F)),"-") -> -
A47: adc46 | B47: FALSE | F47: =SUMIF('ADV - FB'!D:D,"*adc46*",'ADV - FB'!E:E) -> 0 | G47: =IFERROR(SUMIF('ADV - FB'!D:D,"*adc46*",'ADV - FB'!H:H)/(SUMIF('ADV - FB'!D:D,"*adc46*",'ADV - FB'!G:G)),"-") -> - | H47: =SUMIF('ADV - FB'!D:D,"*adc46*",'ADV - FB'!I:I) -> 0 | I47: =IFERROR(J47/F47,"-") -> - | J47: =SUMIF('ADV - FB'!D:D,"*adc46*",'ADV - FB'!J:J) -> 0 | K47: =IFERROR(F47/H47,"-") -> - | L47: =IFERROR(SUMIF('ADV - FB'!D:D,"*adc46*",'ADV - FB'!E:E)/(SUMIF('ADV - FB'!D:D,"*adc46*",'ADV - FB'!F:F)),"-") -> -
A48: adc47 | B48: FALSE | F48: =SUMIF('ADV - FB'!D:D,"*adc47*",'ADV - FB'!E:E) -> 0 | G48: =IFERROR(SUMIF('ADV - FB'!D:D,"*adc47*",'ADV - FB'!H:H)/(SUMIF('ADV - FB'!D:D,"*adc47*",'ADV - FB'!G:G)),"-") -> - | H48: =SUMIF('ADV - FB'!D:D,"*adc47*",'ADV - FB'!I:I) -> 0 | I48: =IFERROR(J48/F48,"-") -> - | J48: =SUMIF('ADV - FB'!D:D,"*adc47*",'ADV - FB'!J:J) -> 0 | K48: =IFERROR(F48/H48,"-") -> - | L48: =IFERROR(SUMIF('ADV - FB'!D:D,"*adc47*",'ADV - FB'!E:E)/(SUMIF('ADV - FB'!D:D,"*adc47*",'ADV - FB'!F:F)),"-") -> -
A49: adc48 | B49: FALSE | F49: =SUMIF('ADV - FB'!D:D,"*adc48*",'ADV - FB'!E:E) -> 0 | G49: =IFERROR(SUMIF('ADV - FB'!D:D,"*adc48*",'ADV - FB'!H:H)/(SUMIF('ADV - FB'!D:D,"*adc48*",'ADV - FB'!G:G)),"-") -> - | H49: =SUMIF('ADV - FB'!D:D,"*adc48*",'ADV - FB'!I:I) -> 0 | I49: =IFERROR(J49/F49,"-") -> - | J49: =SUMIF('ADV - FB'!D:D,"*adc48*",'ADV - FB'!J:J) -> 0 | K49: =IFERROR(F49/H49,"-") -> - | L49: =IFERROR(SUMIF('ADV - FB'!D:D,"*adc48*",'ADV - FB'!E:E)/(SUMIF('ADV - FB'!D:D,"*adc48*",'ADV - FB'!F:F)),"-") -> -
A50: adc49 | B50: FALSE | F50: =SUMIF('ADV - FB'!D:D,"*adc49*",'ADV - FB'!E:E) -> 0 | G50: =IFERROR(SUMIF('ADV - FB'!D:D,"*adc49*",'ADV - FB'!H:H)/(SUMIF('ADV - FB'!D:D,"*adc49*",'ADV - FB'!G:G)),"-") -> - | H50: =SUMIF('ADV - FB'!D:D,"*adc49*",'ADV - FB'!I:I) -> 0 | I50: =IFERROR(J50/F50,"-") -> - | J50: =SUMIF('ADV - FB'!D:D,"*adc49*",'ADV - FB'!J:J) -> 0 | K50: =IFERROR(F50/H50,"-") -> - | L50: =IFERROR(SUMIF('ADV - FB'!D:D,"*adc49*",'ADV - FB'!E:E)/(SUMIF('ADV - FB'!D:D,"*adc49*",'ADV - FB'!F:F)),"-") -> -
A51: adc50 | B51: FALSE | F51: =SUMIF('ADV - FB'!D:D,"*adc50*",'ADV - FB'!E:E) -> 0 | G51: =IFERROR(SUMIF('ADV - FB'!D:D,"*adc50*",'ADV - FB'!H:H)/(SUMIF('ADV - FB'!D:D,"*adc50*",'ADV - FB'!G:G)),"-") -> - | H51: =SUMIF('ADV - FB'!D:D,"*adc50*",'ADV - FB'!I:I) -> 0 | I51: =IFERROR(J51/F51,"-") -> - | J51: =SUMIF('ADV - FB'!D:D,"*adc50*",'ADV - FB'!J:J) -> 0 | K51: =IFERROR(F51/H51,"-") -> - | L51: =IFERROR(SUMIF('ADV - FB'!D:D,"*adc50*",'ADV - FB'!E:E)/(SUMIF('ADV - FB'!D:D,"*adc50*",'ADV - FB'!F:F)),"-") -> -
A52: adc51 | B52: FALSE | F52: =SUMIF('ADV - FB'!D:D,"*adc51*",'ADV - FB'!E:E) -> 0 | G52: =IFERROR(SUMIF('ADV - FB'!D:D,"*adc51*",'ADV - FB'!H:H)/(SUMIF('ADV - FB'!D:D,"*adc51*",'ADV - FB'!G:G)),"-") -> - | H52: =SUMIF('ADV - FB'!D:D,"*adc51*",'ADV - FB'!I:I) -> 0 | I52: =IFERROR(J52/F52,"-") -> - | J52: =SUMIF('ADV - FB'!D:D,"*adc51*",'ADV - FB'!J:J) -> 0 | K52: =IFERROR(F52/H52,"-") -> - | L52: =IFERROR(SUMIF('ADV - FB'!D:D,"*adc51*",'ADV - FB'!E:E)/(SUMIF('ADV - FB'!D:D,"*adc51*",'ADV - FB'!F:F)),"-") -> -
A53: adc52 | B53: FALSE | F53: =SUMIF('ADV - FB'!D:D,"*adc52*",'ADV - FB'!E:E) -> 0 | G53: =IFERROR(SUMIF('ADV - FB'!D:D,"*adc52*",'ADV - FB'!H:H)/(SUMIF('ADV - FB'!D:D,"*adc52*",'ADV - FB'!G:G)),"-") -> - | H53: =SUMIF('ADV - FB'!D:D,"*adc52*",'ADV - FB'!I:I) -> 0 | I53: =IFERROR(J53/F53,"-") -> - | J53: =SUMIF('ADV - FB'!D:D,"*adc52*",'ADV - FB'!J:J) -> 0 | K53: =IFERROR(F53/H53,"-") -> - | L53: =IFERROR(SUMIF('ADV - FB'!D:D,"*adc52*",'ADV - FB'!E:E)/(SUMIF('ADV - FB'!D:D,"*adc52*",'ADV - FB'!F:F)),"-") -> -
A54: adc53 | B54: FALSE | F54: =SUMIF('ADV - FB'!D:D,"*adc53*",'ADV - FB'!E:E) -> 0 | G54: =IFERROR(SUMIF('ADV - FB'!D:D,"*adc53*",'ADV - FB'!H:H)/(SUMIF('ADV - FB'!D:D,"*adc53*",'ADV - FB'!G:G)),"-") -> - | H54: =SUMIF('ADV - FB'!D:D,"*adc53*",'ADV - FB'!I:I) -> 0 | I54: =IFERROR(J54/F54,"-") -> - | J54: =SUMIF('ADV - FB'!D:D,"*adc53*",'ADV - FB'!J:J) -> 0 | K54: =IFERROR(F54/H54,"-") -> - | L54: =IFERROR(SUMIF('ADV - FB'!D:D,"*adc53*",'ADV - FB'!E:E)/(SUMIF('ADV - FB'!D:D,"*adc53*",'ADV - FB'!F:F)),"-") -> -
A55: adc54 | B55: FALSE | F55: =SUMIF('ADV - FB'!D:D,"*adc54*",'ADV - FB'!E:E) -> 0 | G55: =IFERROR(SUMIF('ADV - FB'!D:D,"*adc54*",'ADV - FB'!H:H)/(SUMIF('ADV - FB'!D:D,"*adc54*",'ADV - FB'!G:G)),"-") -> - | H55: =SUMIF('ADV - FB'!D:D,"*adc54*",'ADV - FB'!I:I) -> 0 | I55: =IFERROR(J55/F55,"-") -> - | J55: =SUMIF('ADV - FB'!D:D,"*adc54*",'ADV - FB'!J:J) -> 0 | K55: =IFERROR(F55/H55,"-") -> - | L55: =IFERROR(SUMIF('ADV - FB'!D:D,"*adc54*",'ADV - FB'!E:E)/(SUMIF('ADV - FB'!D:D,"*adc54*",'ADV - FB'!F:F)),"-") -> -
A56: adc55 | B56: FALSE | F56: =SUMIF('ADV - FB'!D:D,"*adc55*",'ADV - FB'!E:E) -> 0 | G56: =IFERROR(SUMIF('ADV - FB'!D:D,"*adc55*",'ADV - FB'!H:H)/(SUMIF('ADV - FB'!D:D,"*adc55*",'ADV - FB'!G:G)),"-") -> - | H56: =SUMIF('ADV - FB'!D:D,"*adc55*",'ADV - FB'!I:I) -> 0 | I56: =IFERROR(J56/F56,"-") -> - | J56: =SUMIF('ADV - FB'!D:D,"*adc55*",'ADV - FB'!J:J) -> 0 | K56: =IFERROR(F56/H56,"-") -> - | L56: =IFERROR(SUMIF('ADV - FB'!D:D,"*adc55*",'ADV - FB'!E:E)/(SUMIF('ADV - FB'!D:D,"*adc55*",'ADV - FB'!F:F)),"-") -> -
A57: adc56 | B57: FALSE | F57: =SUMIF('ADV - FB'!D:D,"*adc56*",'ADV - FB'!E:E) -> 0 | G57: =IFERROR(SUMIF('ADV - FB'!D:D,"*adc56*",'ADV - FB'!H:H)/(SUMIF('ADV - FB'!D:D,"*adc56*",'ADV - FB'!G:G)),"-") -> - | H57: =SUMIF('ADV - FB'!D:D,"*adc56*",'ADV - FB'!I:I) -> 0 | I57: =IFERROR(J57/F57,"-") -> - | J57: =SUMIF('ADV - FB'!D:D,"*adc56*",'ADV - FB'!J:J) -> 0 | K57: =IFERROR(F57/H57,"-") -> - | L57: =IFERROR(SUMIF('ADV - FB'!D:D,"*adc56*",'ADV - FB'!E:E)/(SUMIF('ADV - FB'!D:D,"*adc56*",'ADV - FB'!F:F)),"-") -> -
A58: adc57 | B58: FALSE | F58: =SUMIF('ADV - FB'!D:D,"*adc57*",'ADV - FB'!E:E) -> 0 | G58: =IFERROR(SUMIF('ADV - FB'!D:D,"*adc57*",'ADV - FB'!H:H)/(SUMIF('ADV - FB'!D:D,"*adc57*",'ADV - FB'!G:G)),"-") -> - | H58: =SUMIF('ADV - FB'!D:D,"*adc57*",'ADV - FB'!I:I) -> 0 | I58: =IFERROR(J58/F58,"-") -> - | J58: =SUMIF('ADV - FB'!D:D,"*adc57*",'ADV - FB'!J:J) -> 0 | K58: =IFERROR(F58/H58,"-") -> - | L58: =IFERROR(SUMIF('ADV - FB'!D:D,"*adc57*",'ADV - FB'!E:E)/(SUMIF('ADV - FB'!D:D,"*adc57*",'ADV - FB'!F:F)),"-") -> -
A59: adc58 | B59: FALSE | F59: =SUMIF('ADV - FB'!D:D,"*adc58*",'ADV - FB'!E:E) -> 0 | G59: =IFERROR(SUMIF('ADV - FB'!D:D,"*adc58*",'ADV - FB'!H:H)/(SUMIF('ADV - FB'!D:D,"*adc1*",'ADV - FB'!G:G)),"-") -> - | H59: =SUMIF('ADV - FB'!D:D,"*adc58*",'ADV - FB'!I:I) -> 0 | I59: =IFERROR(J59/F59,"-") -> - | J59: =SUMIF('ADV - FB'!D:D,"*adc58*",'ADV - FB'!J:J) -> 0 | K59: =IFERROR(F59/H59,"-") -> - | L59: =IFERROR(SUMIF('ADV - FB'!D:D,"*adc58*",'ADV - FB'!E:E)/(SUMIF('ADV - FB'!D:D,"*adc58*",'ADV - FB'!F:F)),"-") -> -
A60: adc59 | B60: FALSE | F60: =SUMIF('ADV - FB'!D:D,"*adc59*",'ADV - FB'!E:E) -> 0 | G60: =IFERROR(SUMIF('ADV - FB'!D:D,"*adc59*",'ADV - FB'!H:H)/(SUMIF('ADV - FB'!D:D,"*adc59*",'ADV - FB'!G:G)),"-") -> - | H60: =SUMIF('ADV - FB'!D:D,"*adc59*",'ADV - FB'!I:I) -> 0 | I60: =IFERROR(J60/F60,"-") -> - | J60: =SUMIF('ADV - FB'!D:D,"*adc59*",'ADV - FB'!J:J) -> 0 | K60: =IFERROR(F60/H60,"-") -> - | L60: =IFERROR(SUMIF('ADV - FB'!D:D,"*adc59*",'ADV - FB'!E:E)/(SUMIF('ADV - FB'!D:D,"*adc59*",'ADV - FB'!F:F)),"-") -> -
A61: adc60 | B61: FALSE | F61: =SUMIF('ADV - FB'!D:D,"*adc60*",'ADV - FB'!E:E) -> 0 | G61: =IFERROR(SUMIF('ADV - FB'!D:D,"*adc60*",'ADV - FB'!H:H)/(SUMIF('ADV - FB'!D:D,"*adc60*",'ADV - FB'!G:G)),"-") -> - | H61: =SUMIF('ADV - FB'!D:D,"*adc50*",'ADV - FB'!I:I) -> 0 | I61: =IFERROR(J61/F61,"-") -> - | J61: =SUMIF('ADV - FB'!D:D,"*adc60*",'ADV - FB'!J:J) -> 0 | K61: =IFERROR(F61/H61,"-") -> - | L61: =IFERROR(SUMIF('ADV - FB'!D:D,"*adc60*",'ADV - FB'!E:E)/(SUMIF('ADV - FB'!D:D,"*adc60*",'ADV - FB'!F:F)),"-") -> -
A62: adc61 | B62: FALSE
A63: adc62 | B63: FALSE
A64: adc63 | B64: FALSE
A65: adc64 | B65: FALSE
A66: adc65 | B66: FALSE
A67: adc66 | B67: FALSE
A68: adc67 | B68: FALSE
A69: adc68 | B69: FALSE
A70: adc69 | B70: FALSE
A71: adc70 | B71: FALSE
A72: adc71 | B72: FALSE
A73: adc72 | B73: FALSE
... A100: adc99 | B100: FALSE
B101: FALSE
B102: FALSE
B103: FALSE
B104: FALSE
B105: FALSE
B106: FALSE
B107: FALSE
B108: FALSE
B109: FALSE
B110: FALSE
B111: FALSE
B112: FALSE
... B1000: FALSE

Sheet Ação por Métricas
B1: PLANEJAMENTO DE AÇÕES POR MÉTRICAS
B2: Canais / Ações | C2: CTR | D2: CPS | E2: SESSÕES | F2: TAXA DE CONVERSÃO | G2: TICKET MÉDIO | H2: FATURAMENTO
B3: 1 | C3: Analisar melhores Períodos de CTR | D3: Analisar melhores Períodos de CPS | E3: Analisar melhores Períodos de Sessões | F3: Analisar melhores Períodos de Taxa de Conversão | G3: Analisar melhores Períodos de Ticket Médio | H3: Analisar melhores Períodos de Faturamento
B4: 2 | C4: Teste A/B de Criativos | D4: Analisar melhores Períodos de CPM | E4: Iniciar em Canais com mais Chance de Crescimento | F4: Velocidade do Site | G4: Frete Fixo acima de TM 10%+ | H4: Campanha de Frete Grátis
B5: 3 | C5: Teste A/B de Copy | D5: Velocidade do Site | E5: Ampliar Aquisição em Canais com menor Representatividade | F5: Mapear Objeções | G5: Kit e Combo | H5: Ação com Desconto Especial
B6: 4 | C6: Teste A/B de Públicos | D6: Revisar LP ( Contexto e Estrutura ) | E6: Velocidade | F6: Mapear Motivações | G6: Brindes | H6: LiveShop
B7: 5 | C7: Otimizar Chamada 3 Primeiros Segundos | D7: Entender a Relação de Maior CTR x Menor CPS | E7: SEO | F7: Analisar Gatilhos e Incentivos | G7: Order Bump | H7: Recuperação de Pagamento
B8: 6 | C8: Usar Vídeos DSB | D8: Decentralizar Mídia | E8: Régua de Relacionamento | F8: Revisar Oferta | G8: Cupom Progressivo | H8: Forma de Pagamento
B9: 7 | C9: Segmentar Audiências | D9: Comentários no Anúncio | E9: Influencer | F9: Direcionar para Canais com mais Taxa de Conversão | G9: Frete Grátis acima de TM 15% | H9: Cupom de Madrugada
B10: 8 | C10: Trocar CTA | D10: Oferta Agressiva no Criativo | E10: Aumento de Verba | F10: Ajustar Canais com Menor Taxa de Conversão | G10: Compre Junto | H10: Focar em Recompra
B11: 9 | C11: Produtos Curva A | D11: Públicos Amplos | E11: Cross Public | F11: Intensificar entrega de Produtos com maior Taxa de Conversão | G11: Produtos Relacionados | H11: E-Mail Marketing
B12: 10 | C12: Posicionamento de ADS | D12: Criativo x Persona | E12: Criativo Virais | F12: Otimizar Frete | G12: Upsell | H12: Indique e Ganhe
B15: PLANEJAMENTO DE AÇÕES POR CANAL
B16: Canais / Ações | C16: Blog | D16: Direct | E16: E-Mail | F16: MetaAds | G16: Google Ads | H16: Instagram Perfil | I16: SEO | J16: Whatsapp | K16: Youtube | L16: TikTok | M16: Pinterest
B17: 1 | C17: Pesquisa de Palavras Chaves | D17: Website Otimizado | E17: Segmentação de Lista | F17: Ação 1 | G17: Ação 1 | H17: Ação 1 | I17: Ação 1 | J17: Ação 1 | K17: Ação 1 | L17: Ação 1 | M17: Ação 1
B18: 2 | C18: Conteúdo de Qualidade | D18: Conteúdo de Qualidade | E18: Personalização | F18: Ação 2 | G18: Ação 2 | H18: Ação 2 | I18: Ação 2 | J18: Ação 2 | K18: Ação 2 | L18: Ação 2 | M18: Ação 2
B19: 3 | C19: Regularidade das Postagens | D19: Google Ads | E19: Assunto Atraente | F19: Ação 3 | G19: Ação 3 | H19: Ação 3 | I19: Ação 3 | J19: Ação 3 | K19: Ação 3 | L19: Ação 3 | M19: Ação 3
B20: 4 | C20: Divulgar nas Redes Sociais | D20: Redes Sociais | E20: Conteúdo de Qualidade | F20: Ação 4 | G20: Ação 4 | H20: Ação 4 | I20: Ação 4 | J20: Ação 4 | K20: Ação 4 | L20: Ação 4 | M20: Ação 4
B21: 5 | C21: Guest Posting | D21: Google Meu Negócio | E21: Design Responsivo | F21: Ação 5 | G21: Ação 5 | H21: Ação 5 | I21: Ação 5 | J21: Ação 5 | K21: Ação 5 | L21: Ação 5 | M21: Ação 5
B22: 6 | C22: Divulgar no Email Marketing | D22: Avaliações dos Clientes | E22: CTAs (Call to Action) Claras | F22: Ação 6 | G22: Ação 6 | H22: Ação 6 | I22: Ação 6 | J22: Ação 6 | K22: Ação 6 | L22: Ação 6 | M22: Ação 6
B23: 7 | C23: SEO On Page | D23: Fóruns e Comunidades Online | E23: Testes A/B | F23: Ação 7 | G23: Ação 7 | H23: Ação 7 | I23: Ação 7 | J23: Ação 7 | K23: Ação 7 | L23: Ação 7 | M23: Ação 7
B24: 8 | C24: Rede com outros Blogs | D24: Marketing de Conteúdo | E24: Horário de Envio Estratégico | F24: Ação 8 | G24: Ação 8 | H24: Ação 8 | I24: Ação 8 | J24: Ação 8 | K24: Ação 8 | L24: Ação 8 | M24: Ação 8
B25: 9 | C25: Divulgar em Comunidades Online | D25: Influenciadores | E25: Automatização | F25: Ação 9 | G25: Ação 9 | H25: Ação 9 | I25: Ação 9 | J25: Ação 9 | K25: Ação 9 | L25: Ação 9 | M25: Ação 9
B26: 10 | C26: Acompanhar as Métricas | D26: Acompanhar as Métricas | E26: Acompanhar as Métricas | F26: Ação 10 | G26: Ação 10 | H26: Ação 10 | I26: Ação 10 | J26: Ação 10 | K26: Ação 10 | L26: Ação 10 | M26: Ação 10

Sheet ADV - FB
A1: Data | B1: Campanha | C1: Conjunto de Anuncio | D1: Anuncio | E1: Valor investido | F1: Visualização de Página | G1: Impressões | H1: Cliques (All) | I1: Leads | J1: Evento Contato | K1: Conversas Iniciadas | L1: Ad Prefix
A2: 46133 | B2: TP-leads-wpp-04.11 | C2: TP-Florida-13.02 | D2: Cirurgia-refrativa-florida | E2: 2.68 | G2: 28 | H2: 0 | L2: =IFERROR((midb(D2,1,(SEARCH(" ",D2,1)-1))),"")
A3: 46133 | B3: TP-leads-wpp-04.11 | C3: TP-Bolivia-13.11 | D3: V - ONCOLOGIA | E3: 2.22 | G3: 250 | H3: 7 | L3: =IFERROR((midb(D3,1,(SEARCH(" ",D3,1)-1))),"") -> V
A4: 46133 | B4: TP - [Trafego] [Visitas ao Perfil IG] | C4: Aberto | D4: AD 04 - TP - VÍDEO - JU E ANDRÉ — Cópia | E4: 0.47 | G4: 140 | H4: 5 | L4: =IFERROR((midb(D4,1,(SEARCH(" ",D4,1)-1))),"") -> AD
A5: 46132 | B5: TP-leads-wpp-04.11 | C5: TP-Florida-13.02 | D5: Cirurgia-refrativa-florida | E5: 29.96 | G5: 323 | H5: 8 | K5: 1 | L5: =IFERROR((midb(D5,1,(SEARCH(" ",D5,1)-1))),"")
A6: 46132 | B6: TP-leads-wpp-04.11 | C6: TP-Bolivia-13.11 | D6: V - ONCOLOGIA | E6: 21.83 | G6: 1762 | H6: 46 | L6: =IFERROR((midb(D6,1,(SEARCH(" ",D6,1)-1))),"") -> V
A7: 46132 | B7: TP-leads-wpp-04.11 | C7: TP-Bolivia-13.11 | D7: V - video andre-11.12 | E7: 0.04 | G7: 10 | H7: 0 | L7: =IFERROR((midb(D7,1,(SEARCH(" ",D7,1)-1))),"") -> V
A8: 46132 | B8: TP-leads-wpp-04.11 | C8: TP-Bolivia-13.11 | D8: V - video andre-02.12 | E8: 0.04 | G8: 7 | H8: 0 | L8: =IFERROR((midb(D8,1,(SEARCH(" ",D8,1)-1))),"") -> V
A9: 46132 | B9: TP-leads-wpp-04.11 | C9: TP-Bolivia-13.11 | D9: V -video novo-13.11 | E9: 2.95 | G9: 222 | H9: 8 | L9: =IFERROR((midb(D9,1,(SEARCH(" ",D9,1)-1))),"") -> V
A10: 46132 | B10: TP - [Trafego] [Visitas ao Perfil IG] | C10: Aberto | D10: AD 04 - TP - VÍDEO - JU E ANDRÉ — Cópia | E10: 10.25 | G10: 2976 | H10: 101 | L10: =IFERROR((midb(D10,1,(SEARCH(" ",D10,1)-1))),"") -> AD
A11: 46131 | B11: TP-leads-wpp-04.11 | C11: TP-Florida-13.02 | D11: Cirurgia-refrativa-florida | E11: 29.93 | G11: 276 | H11: 5 | L11: =IFERROR((midb(D11,1,(SEARCH(" ",D11,1)-1))),"")
A12: 46131 | B12: TP-leads-wpp-04.11 | C12: TP-Bolivia-13.11 | D12: V - ONCOLOGIA | E12: 23.53 | G12: 1830 | H12: 32 | K12: 1 | L12: =IFERROR((midb(D12,1,(SEARCH(" ",D12,1)-1))),"") -> V
A13: 46131 | B13: TP-leads-wpp-04.11 | C13: TP-Bolivia-13.11 | D13: V - video andre-02.12 | E13: 0.03 | G13: 2 | H13: 0 | L13: =IFERROR((midb(D13,1,(SEARCH(" ",D13,1)-1))),"") -> V
A14: 46131 | B14: TP-leads-wpp-04.11 | C14: TP-Bolivia-13.11 | D14: V - ju-1x25x-13.11 | E14: 1.9 | G14: 207 | H14: 1 | L14: =IFERROR((midb(D14,1,(SEARCH(" ",D14,1)-1))),"") -> V
A15: 46131 | B15: TP - [Trafego] [Visitas ao Perfil IG] | C15: Aberto | D15: AD 04 - TP - VÍDEO - JU E ANDRÉ — Cópia | E15: 11.14 | G15: 3160 | H15: 98 | K15: 1 | L15: =IFERROR((midb(D15,1,(SEARCH(" ",D15,1)-1))),"") -> AD
A16: 46130 | B16: TP-leads-wpp-04.11 | C16: TP-Florida-13.02 | D16: Cirurgia-refrativa-florida | E16: 25.69 | G16: 282 | H16: 5 | K16: 1 | L16: =IFERROR((midb(D16,1,(SEARCH(" ",D16,1)-1))),"")
A17: 46130 | B17: TP-leads-wpp-04.11 | C17: TP-Bolivia-13.11 | D17: V - ONCOLOGIA | E17: 15.05 | G17: 1323 | H17: 34 | K17: 2 | L17: =IFERROR((midb(D17,1,(SEARCH(" ",D17,1)-1))),"") -> V
A18: 46130 | B18: TP-leads-wpp-04.11 | C18: TP-Bolivia-13.11 | D18: V - video andre-11.12 | E18: 1.68 | G18: 115 | H18: 0 | L18: =IFERROR((midb(D18,1,(SEARCH(" ",D18,1)-1))),"") -> V
A19: 46130 | B19: TP-leads-wpp-04.11 | C19: TP-Bolivia-13.11 | D19: V - video andre-02.12 | E19: 0.4 | G19: 9 | H19: 1 | L19: =IFERROR((midb(D19,1,(SEARCH(" ",D19,1)-1))),"") -> V
A20: 46130 | B20: TP-leads-wpp-04.11 | C20: TP-Bolivia-13.11 | D20: V -video novo-13.11 | E20: 2.2 | G20: 170 | H20: 3 | K20: 1 | L20: =IFERROR((midb(D20,1,(SEARCH(" ",D20,1)-1))),"") -> V
A21: 46130 | B21: TP-leads-wpp-04.11 | C21: TP-Bolivia-13.11 | D21: V - ju-1x25x-13.11 | E21: 0.08 | G21: 5 | H21: 0 | L21: =IFERROR((midb(D21,1,(SEARCH(" ",D21,1)-1))),"") -> V
A22: 46130 | B22: TP - [Trafego] [Visitas ao Perfil IG] | C22: Aberto | D22: AD 04 - TP - VÍDEO - JU E ANDRÉ — Cópia | E22: 10.65 | G22: 2763 | H22: 82 | L22: =IFERROR((midb(D22,1,(SEARCH(" ",D22,1)-1))),"") -> AD
A23: 46129 | B23: TP-leads-wpp-04.11 | C23: TP-Florida-13.02 | D23: Cirurgia-refrativa-florida | E23: 30.29 | G23: 302 | H23: 4 | L23: =IFERROR((midb(D23,1,(SEARCH(" ",D23,1)-1))),"")
A24: 46129 | B24: TP-leads-wpp-04.11 | C24: TP-Bolivia-13.11 | D24: V - ONCOLOGIA | E24: 17.48 | G24: 1342 | H24: 32 | I24: 1 | K24: 3 | L24: =IFERROR((midb(D24,1,(SEARCH(" ",D24,1)-1))),"") -> V
A25: 46129 | B25: TP-leads-wpp-04.11 | C25: TP-Bolivia-13.11 | D25: V -video novo-13.11 | E25: 0.6 | G25: 65 | H25: 0 | L25: =IFERROR((midb(D25,1,(SEARCH(" ",D25,1)-1))),"") -> V
A26: 46129 | B26: TP - [Trafego] [Visitas ao Perfil IG] | C26: Aberto | D26: AD 04 - TP - VÍDEO - JU E ANDRÉ — Cópia | E26: 9.8 | G26: 2641 | H26: 88 | L26: =IFERROR((midb(D26,1,(SEARCH(" ",D26,1)-1))),"") -> AD
A27: 46128 | B27: TP-leads-wpp-04.11 | C27: TP-Florida-13.02 | D27: Cirurgia-refrativa-florida | E27: 29.79 | G27: 317 | H27: 1 | L27: =IFERROR((midb(D27,1,(SEARCH(" ",D27,1)-1))),"")
A28: 46128 | B28: TP-leads-wpp-04.11 | C28: TP-Bolivia-13.11 | D28: V - ONCOLOGIA | E28: 9.91 | G28: 814 | H28: 23 | K28: 1 | L28: =IFERROR((midb(D28,1,(SEARCH(" ",D28,1)-1))),"") -> V
A29: 46128 | B29: TP-leads-wpp-04.11 | C29: TP-Bolivia-13.11 | D29: V - video andre-11.12 | E29: 1.26 | G29: 111 | H29: 2 | L29: =IFERROR((midb(D29,1,(SEARCH(" ",D29,1)-1))),"") -> V
A30: 46128 | B30: TP-leads-wpp-04.11 | C30: TP-Bolivia-13.11 | D30: V - video andre-02.12 | E30: 0.52 | G30: 29 | H30: 0 | L30: =IFERROR((midb(D30,1,(SEARCH(" ",D30,1)-1))),"") -> V
A31: 46128 | B31: TP-leads-wpp-04.11 | C31: TP-Bolivia-13.11 | D31: V -video novo-13.11 | E31: 0.4 | G31: 49 | H31: 0 | L31: =IFERROR((midb(D31,1,(SEARCH(" ",D31,1)-1))),"") -> V
A32: 46128 | B32: TP-leads-wpp-04.11 | C32: TP-Bolivia-13.11 | D32: V - ju-1x25x-13.11 | E32: 5.18 | G32: 413 | H32: 10 | K32: 1 | L32: =IFERROR((midb(D32,1,(SEARCH(" ",D32,1)-1))),"") -> V
A33: 46128 | B33: TP - [Trafego] [Visitas ao Perfil IG] | C33: Aberto | D33: AD 04 - TP - VÍDEO - JU E ANDRÉ — Cópia | E33: 9.5 | G33: 2430 | H33: 82 | L33: =IFERROR((midb(D33,1,(SEARCH(" ",D33,1)-1))),"") -> AD
A34: 46127 | B34: TP-leads-wpp-04.11 | C34: TP-Florida-13.02 | D34: Cirurgia-refrativa-florida | E34: 32.64 | G34: 318 | H34: 8 | L34: =IFERROR((midb(D34,1,(SEARCH(" ",D34,1)-1))),"")
A35: 46127 | B35: TP-leads-wpp-04.11 | C35: TP-Bolivia-13.11 | D35: V - ONCOLOGIA | E35: 16.01 | G35: 1650 | H35: 57 | I35: 1 | L35: =IFERROR((midb(D35,1,(SEARCH(" ",D35,1)-1))),"") -> V
A36: 46127 | B36: TP-leads-wpp-04.11 | C36: TP-Bolivia-13.11 | D36: V - video andre-02.12 | E36: 0.35 | G36: 35 | H36: 1 | L36: =IFERROR((midb(D36,1,(SEARCH(" ",D36,1)-1))),"") -> V
A37: 46127 | B37: TP-leads-wpp-04.11 | C37: TP-Bolivia-13.11 | D37: V -video novo-13.11 | E37: 6.68 | G37: 460 | H37: 7 | L37: =IFERROR((midb(D37,1,(SEARCH(" ",D37,1)-1))),"") -> V
A38: 46127 | B38: TP - [Trafego] [Visitas ao Perfil IG] | C38: Aberto | D38: AD 04 - TP - VÍDEO - JU E ANDRÉ — Cópia | E38: 9.29 | G38: 2410 | H38: 62 | L38: =IFERROR((midb(D38,1,(SEARCH(" ",D38,1)-1))),"") -> AD
A39: 46126 | B39: TP-leads-wpp-04.11 | C39: TP-Florida-13.02 | D39: Cirurgia-refrativa-florida | E39: 44.24 | G39: 414 | H39: 8 | K39: 1 | L39: =IFERROR((midb(D39,1,(SEARCH(" ",D39,1)-1))),"")
A40: 46126 | B40: TP-leads-wpp-04.11 | C40: TP-Bolivia-13.11 | D40: V - ONCOLOGIA | E40: 21.02 | G40: 2236 | H40: 60 | K40: 2 | L40: =IFERROR((midb(D40,1,(SEARCH(" ",D40,1)-1))),"") -> V
A41: 46126 | B41: TP-leads-wpp-04.11 | C41: TP-Bolivia-13.11 | D41: V - video andre-02.12 | E41: 0.07 | G41: 3 | H41: 0 | L41: =IFERROR((midb(D41,1,(SEARCH(" ",D41,1)-1))),"") -> V
A42: 46126 | B42: TP-leads-wpp-04.11 | C42: TP-Bolivia-13.11 | D42: V -video novo-13.11 | E42: 1.79 | G42: 179 | H42: 6 | L42: =IFERROR((midb(D42,1,(SEARCH(" ",D42,1)-1))),"") -> V
A43: 46126 | B43: TP-leads-wpp-04.11 | C43: TP-Bolivia-13.11 | D43: V - ju-1x25x-13.11 | E43: 1.33 | G43: 112 | H43: 3 | L43: =IFERROR((midb(D43,1,(SEARCH(" ",D43,1)-1))),"") -> V
A44: 46126 | B44: TP - [Trafego] [Visitas ao Perfil IG] | C44: Aberto | D44: AD 04 - TP - VÍDEO - JU E ANDRÉ — Cópia | E44: 9.87 | G44: 3008 | H44: 79 | L44: =IFERROR((midb(D44,1,(SEARCH(" ",D44,1)-1))),"") -> AD
A45: 46125 | B45: TP-leads-wpp-04.11 | C45: TP-Florida-13.02 | D45: Cirurgia-refrativa-florida | E45: 44.23 | G45: 379 | H45: 7 | L45: =IFERROR((midb(D45,1,(SEARCH(" ",D45,1)-1))),"")
A46: 46125 | B46: TP-leads-wpp-04.11 | C46: TP-Bolivia-13.11 | D46: V - ONCOLOGIA | E46: 15.7 | G46: 1656 | H46: 45 | K46: 1 | L46: =IFERROR((midb(D46,1,(SEARCH(" ",D46,1)-1))),"") -> V
A47: 46125 | B47: TP-leads-wpp-04.11 | C47: TP-Bolivia-13.11 | D47: V - video andre-02.12 | E47: 2.55 | G47: 123 | H47: 1 | L47: =IFERROR((midb(D47,1,(SEARCH(" ",D47,1)-1))),"") -> V
A48: 46125 | B48: TP-leads-wpp-04.11 | C48: TP-Bolivia-13.11 | D48: V -video novo-13.11 | E48: 6.88 | G48: 581 | H48: 9 | K48: 1 | L48: =IFERROR((midb(D48,1,(SEARCH(" ",D48,1)-1))),"") -> V
A49: 46125 | B49: TP-leads-wpp-04.11 | C49: TP-Bolivia-13.11 | D49: V - ju-1x25x-13.11 | E49: 0.98 | G49: 70 | H49: 1 | L49: =IFERROR((midb(D49,1,(SEARCH(" ",D49,1)-1))),"") -> V
A50: 46125 | B50: TP - [Trafego] [Visitas ao Perfil IG] | C50: Aberto | D50: AD 04 - TP - VÍDEO - JU E ANDRÉ — Cópia | E50: 9.92 | G50: 3010 | H50: 106 | L50: =IFERROR((midb(D50,1,(SEARCH(" ",D50,1)-1))),"") -> AD
A51: 46124 | B51: TP-leads-wpp-04.11 | C51: TP-Florida-13.02 | D51: Cirurgia-refrativa-florida | E51: 29.41 | G51: 302 | H51: 5 | L51: =IFERROR((midb(D51,1,(SEARCH(" ",D51,1)-1))),"")
A52: 46124 | B52: TP-leads-wpp-04.11 | C52: TP-Bolivia-13.11 | D52: V - ONCOLOGIA | E52: 19.09 | G52: 1153 | H52: 31 | K52: 1 | L52: =IFERROR((midb(D52,1,(SEARCH(" ",D52,1)-1))),"") -> V
A53: 46124 | B53: TP-leads-wpp-04.11 | C53: TP-Bolivia-13.11 | D53: V -video novo-13.11 | E53: 1.12 | G53: 59 | H53: 1 | L53: =IFERROR((midb(D53,1,(SEARCH(" ",D53,1)-1))),"") -> V
A54: 46124 | B54: TP - [Trafego] [Visitas ao Perfil IG] | C54: Aberto | D54: AD 04 - TP - VÍDEO - JU E ANDRÉ — Cópia | E54: 10.94 | G54: 3157 | H54: 96 | L54: =IFERROR((midb(D54,1,(SEARCH(" ",D54,1)-1))),"") -> AD
A55: 46123 | B55: TP-leads-wpp-04.11 | C55: TP-Florida-13.02 | D55: Cirurgia-refrativa-florida | E55: 30.68 | G55: 293 | H55: 11 | L55: =IFERROR((midb(D55,1,(SEARCH(" ",D55,1)-1))),"")
A56: 46123 | B56: TP-leads-wpp-04.11 | C56: TP-Bolivia-13.11 | D56: V - ONCOLOGIA | E56: 13.51 | G56: 959 | H56: 20 | K56: 2 | L56: =IFERROR((midb(D56,1,(SEARCH(" ",D56,1)-1))),"") -> V
A57: 46123 | B57: TP-leads-wpp-04.11 | C57: TP-Bolivia-13.11 | D57: V - video andre-11.12 | E57: 0.55 | G57: 44 | H57: 0 | L57: =IFERROR((midb(D57,1,(SEARCH(" ",D57,1)-1))),"") -> V
A58: 46123 | B58: TP-leads-wpp-04.11 | C58: TP-Bolivia-13.11 | D58: V - video andre-02.12 | E58: 1.65 | G58: 85 | H58: 3 | L58: =IFERROR((midb(D58,1,(SEARCH(" ",D58,1)-1))),"") -> V
A59: 46123 | B59: TP-leads-wpp-04.11 | C59: TP-Bolivia-13.11 | D59: V -video novo-13.11 | E59: 0.34 | G59: 32 | H59: 0 | L59: =IFERROR((midb(D59,1,(SEARCH(" ",D59,1)-1))),"") -> V
A60: 46123 | B60: TP-leads-wpp-04.11 | C60: TP-Bolivia-13.11 | D60: V - ju-1x25x-13.11 | E60: 3.98 | G60: 380 | H60: 6 | L60: =IFERROR((midb(D60,1,(SEARCH(" ",D60,1)-1))),"") -> V
A61: 46123 | B61: TP - [Trafego] [Visitas ao Perfil IG] | C61: Aberto | D61: AD 04 - TP - VÍDEO - JU E ANDRÉ — Cópia | E61: 10.15 | G61: 2958 | H61: 85 | L61: =IFERROR((midb(D61,1,(SEARCH(" ",D61,1)-1))),"") -> AD
A62: 46122 | B62: TP-leads-wpp-04.11 | C62: TP-Florida-13.02 | D62: Cirurgia-refrativa-florida | E62: 32.17 | G62: 298 | H62: 6 | K62: 1 | L62: =IFERROR((midb(D62,1,(SEARCH(" ",D62,1)-1))),"")
A63: 46122 | B63: TP-leads-wpp-04.11 | C63: TP-Bolivia-13.11 | D63: V - ONCOLOGIA | E63: 15.26 | G63: 1747 | H63: 49 | I63: 1 | K63: 2 | L63: =IFERROR((midb(D63,1,(SEARCH(" ",D63,1)-1))),"") -> V
A64: 46122 | B64: TP-leads-wpp-04.11 | C64: TP-Bolivia-13.11 | D64: V - video andre-11.12 | E64: 0.04 | G64: 4 | H64: 0 | L64: =IFERROR((midb(D64,1,(SEARCH(" ",D64,1)-1))),"") -> V
A65: 46122 | B65: TP-leads-wpp-04.11 | C65: TP-Bolivia-13.11 | D65: V - video andre-02.12 | E65: 0.48 | G65: 44 | H65: 2 | L65: =IFERROR((midb(D65,1,(SEARCH(" ",D65,1)-1))),"") -> V
A66: 46122 | B66: TP-leads-wpp-04.11 | C66: TP-Bolivia-13.11 | D66: V -video novo-13.11 | E66: 5.25 | G66: 396 | H66: 4 | L66: =IFERROR((midb(D66,1,(SEARCH(" ",D66,1)-1))),"") -> V
A67: 46122 | B67: TP - [Trafego] [Visitas ao Perfil IG] | C67: Aberto | D67: AD 04 - TP - VÍDEO - JU E ANDRÉ — Cópia | E67: 9.8 | G67: 2787 | H67: 90 | L67: =IFERROR((midb(D67,1,(SEARCH(" ",D67,1)-1))),"") -> AD
A68: 46121 | B68: TP-leads-wpp-04.11 | C68: TP-Florida-13.02 | D68: Cirurgia-refrativa-florida | E68: 31.2 | G68: 334 | H68: 9 | L68: =IFERROR((midb(D68,1,(SEARCH(" ",D68,1)-1))),"")
A69: 46121 | B69: TP-leads-wpp-04.11 | C69: TP-Bolivia-13.11 | D69: V - ONCOLOGIA | E69: 22.9 | G69: 1936 | H69: 52 | I69: 2 | K69: 5 | L69: =IFERROR((midb(D69,1,(SEARCH(" ",D69,1)-1))),"") -> V
A70: 46121 | B70: TP-leads-wpp-04.11 | C70: TP-Bolivia-13.11 | D70: V - video andre-02.12 | E70: 0 | G70: 1 | H70: 0 | L70: =IFERROR((midb(D70,1,(SEARCH(" ",D70,1)-1))),"") -> V
A71: 46121 | B71: TP-leads-wpp-04.11 | C71: TP-Bolivia-13.11 | D71: V -video novo-13.11 | E71: 0.01 | G71: 2 | H71: 0 | L71: =IFERROR((midb(D71,1,(SEARCH(" ",D71,1)-1))),"") -> V
A72: 46121 | B72: TP-leads-wpp-04.11 | C72: TP-Bolivia-13.11 | D72: V - ju-1x25x-13.11 | E72: 0.85 | G72: 75 | H72: 3 | I72: 1 | K72: 1 | L72: =IFERROR((midb(D72,1,(SEARCH(" ",D72,1)-1))),"") -> V
A73: 46121 | B73: TP - [Trafego] [Visitas ao Perfil IG] | C73: Aberto | D73: AD 04 - TP - VÍDEO - JU E ANDRÉ — Cópia | E73: 9.88 | G73: 2627 | H73: 92 | L73: =IFERROR((midb(D73,1,(SEARCH(" ",D73,1)-1))),"") -> AD
A74: 46120 | B74: TP-leads-wpp-04.11 | C74: TP-Florida-13.02 | D74: Cirurgia-refrativa-florida | E74: 30.88 | G74: 294 | H74: 9 | K74: 3 | L74: =IFERROR((midb(D74,1,(SEARCH(" ",D74,1)-1))),"")
A75: 46120 | B75: TP-leads-wpp-04.11 | C75: TP-Bolivia-13.11 | D75: V - ONCOLOGIA | E75: 15.33 | G75: 1448 | H75: 30 | K75: 3 | L75: =IFERROR((midb(D75,1,(SEARCH(" ",D75,1)-1))),"") -> V
A76: 46120 | B76: TP-leads-wpp-04.11 | C76: TP-Bolivia-13.11 | D76: V - video andre-02.12 | E76: 4.54 | G76: 211 | H76: 4 | L76: =IFERROR((midb(D76,1,(SEARCH(" ",D76,1)-1))),"") -> V
A77: 46120 | B77: TP-leads-wpp-04.11 | C77: TP-Bolivia-13.11 | D77: V -video novo-13.11 | E77: 2.84 | G77: 283 | H77: 2 | L77: =IFERROR((midb(D77,1,(SEARCH(" ",D77,1)-1))),"") -> V
A78: 46120 | B78: TP-leads-wpp-04.11 | C78: TP-Bolivia-13.11 | D78: V - ju-1x25x-13.11 | E78: 0.86 | G78: 67 | H78: 1 | L78: =IFERROR((midb(D78,1,(SEARCH(" ",D78,1)-1))),"") -> V
A79: 46120 | B79: TP - [Trafego] [Visitas ao Perfil IG] | C79: Aberto | D79: AD 04 - TP - VÍDEO - JU E ANDRÉ — Cópia | E79: 9.89 | G79: 2703 | H79: 74 | L79: =IFERROR((midb(D79,1,(SEARCH(" ",D79,1)-1))),"") -> AD
A80: 46119 | B80: TP-leads-wpp-04.11 | C80: TP-Florida-13.02 | D80: Cirurgia-refrativa-florida | E80: 29.38 | G80: 323 | H80: 9 | L80: =IFERROR((midb(D80,1,(SEARCH(" ",D80,1)-1))),"")
A81: 46119 | B81: TP-leads-wpp-04.11 | C81: TP-Bolivia-13.11 | D81: V - ONCOLOGIA | E81: 10.97 | G81: 1211 | H81: 40 | I81: 1 | K81: 2 | L81: =IFERROR((midb(D81,1,(SEARCH(" ",D81,1)-1))),"") -> V
A82: 46119 | B82: TP-leads-wpp-04.11 | C82: TP-Bolivia-13.11 | D82: V -video novo-13.11 | E82: 13.07 | G82: 1147 | H82: 24 | K82: 2 | L82: =IFERROR((midb(D82,1,(SEARCH(" ",D82,1)-1))),"") -> V
A83: 46119 | B83: TP - [Trafego] [Visitas ao Perfil IG] | C83: Aberto | D83: AD 04 - TP - VÍDEO - JU E ANDRÉ — Cópia | E83: 9.32 | G83: 2912 | H83: 86 | L83: =IFERROR((midb(D83,1,(SEARCH(" ",D83,1)-1))),"") -> AD
A84: 46118 | B84: TP-leads-wpp-04.11 | C84: TP-Florida-13.02 | D84: Cirurgia-refrativa-florida | E84: 31.93 | G84: 329 | H84: 13 | K84: 2 | L84: =IFERROR((midb(D84,1,(SEARCH(" ",D84,1)-1))),"")
A85: 46118 | B85: TP-leads-wpp-04.11 | C85: TP-Bolivia-13.11 | D85: V - ONCOLOGIA | E85: 12.52 | G85: 1582 | H85: 45 | I85: 1 | K85: 3 | L85: =IFERROR((midb(D85,1,(SEARCH(" ",D85,1)-1))),"") -> V
A86: 46118 | B86: TP-leads-wpp-04.11 | C86: TP-Bolivia-13.11 | D86: V - video andre-11.12 | E86: 0.03 | G86: 8 | H86: 0 | L86: =IFERROR((midb(D86,1,(SEARCH(" ",D86,1)-1))),"") -> V
A87: 46118 | B87: TP-leads-wpp-04.11 | C87: TP-Bolivia-13.11 | D87: V - video andre-02.12 | E87: 3.69 | G87: 278 | H87: 7 | K87: 2 | L87: =IFERROR((midb(D87,1,(SEARCH(" ",D87,1)-1))),"") -> V
A88: 46118 | B88: TP-leads-wpp-04.11 | C88: TP-Bolivia-13.11 | D88: V -video novo-13.11 | E88: 8.31 | G88: 797 | H88: 14 | K88: 4 | L88: =IFERROR((midb(D88,1,(SEARCH(" ",D88,1)-1))),"") -> V
A89: 46118 | B89: TP-leads-wpp-04.11 | C89: TP-Bolivia-13.11 | D89: V - ju-1x25x-13.11 | E89: 0.22 | G89: 27 | H89: 0 | L89: =IFERROR((midb(D89,1,(SEARCH(" ",D89,1)-1))),"") -> V
A90: 46118 | B90: TP - [Trafego] [Visitas ao Perfil IG] | C90: Aberto | D90: AD 04 - TP - VÍDEO - JU E ANDRÉ — Cópia | E90: 9.93 | G90: 3231 | H90: 84 | L90: =IFERROR((midb(D90,1,(SEARCH(" ",D90,1)-1))),"") -> AD
A91: 46117 | B91: TP-leads-wpp-04.11 | C91: TP-Florida-13.02 | D91: Cirurgia-refrativa-florida | E91: 30.85 | G91: 343 | H91: 12 | K91: 1 | L91: =IFERROR((midb(D91,1,(SEARCH(" ",D91,1)-1))),"")
A92: 46117 | B92: TP-leads-wpp-04.11 | C92: TP-Bolivia-13.11 | D92: V - ONCOLOGIA | E92: 15.37 | G92: 2184 | H92: 56 | I92: 2 | K92: 3 | L92: =IFERROR((midb(D92,1,(SEARCH(" ",D92,1)-1))),"") -> V
A93: 46117 | B93: TP-leads-wpp-04.11 | C93: TP-Bolivia-13.11 | D93: V - video andre-11.12 | E93: 0.65 | G93: 46 | H93: 1 | L93: =IFERROR((midb(D93,1,(SEARCH(" ",D93,1)-1))),"") -> V
A94: 46117 | B94: TP-leads-wpp-04.11 | C94: TP-Bolivia-13.11 | D94: V - video andre-02.12 | E94: 0.07 | G94: 9 | H94: 0 | L94: =IFERROR((midb(D94,1,(SEARCH(" ",D94,1)-1))),"") -> V
A95: 46117 | B95: TP-leads-wpp-04.11 | C95: TP-Bolivia-13.11 | D95: V -video novo-13.11 | E95: 9.11 | G95: 895 | H95: 16 | K95: 3 | L95: =IFERROR((midb(D95,1,(SEARCH(" ",D95,1)-1))),"") -> V
A96: 46117 | B96: TP - [Trafego] [Visitas ao Perfil IG] | C96: Aberto | D96: AD 04 - TP - VÍDEO - JU E ANDRÉ — Cópia | E96: 10.92 | G96: 3877 | H96: 99 | L96: =IFERROR((midb(D96,1,(SEARCH(" ",D96,1)-1))),"") -> AD
A97: 46116 | B97: TP-leads-wpp-04.11 | C97: TP-Florida-13.02 | D97: Cirurgia-refrativa-florida | E97: 26.09 | G97: 356 | H97: 4 | L97: =IFERROR((midb(D97,1,(SEARCH(" ",D97,1)-1))),"")
A98: 46116 | B98: TP-leads-wpp-04.11 | C98: TP-Bolivia-13.11 | D98: V - ONCOLOGIA | E98: 15.1 | G98: 1800 | H98: 55 | K98: 5 | L98: =IFERROR((midb(D98,1,(SEARCH(" ",D98,1)-1))),"") -> V
A99: 46116 | B99: TP-leads-wpp-04.11 | C99: TP-Bolivia-13.11 | D99: V - video andre-02.12 | E99: 0.54 | G99: 22 | H99: 0 | L99: =IFERROR((midb(D99,1,(SEARCH(" ",D99,1)-1))),"") -> V
A100: 46116 | B100: TP-leads-wpp-04.11 | C100: TP-Bolivia-13.11 | D100: V -video novo-13.11 | E100: 3.74 | G100: 269 | H100: 5 | L100: =IFERROR((midb(D100,1,(SEARCH(" ",D100,1)-1))),"") -> V
...

Sheet ADV - GG
A1: Data | B1: Campanha | C1: Valor Investido | D1: Impressões | E1: Cliques | F1: DATA | G1: CAMPANHA | H1: CONVERSÕES

Sheet ADV - GA4
A1: Data | B1: Usuarios | C1: Sessões | D1: Novos Usuarios

Sheet Benchmark de Taxas
A1: Taxas de mercado extraídas de:
A2: https://ferramentas.resultadosdigitais.com.br/funil-de-vendas/
A3: Segmento | B3: Leads | C3: Oportunidades | D3: Vendas
A4: Selecione | B4: 0 | C4: 0 | D4: 0
A5: Agência de Marketing e Publicidade | B5: 0.04 | C5: 0.135 | D5: 0.24
A6: Consultorias e Treinamentos | B6: 0.045 | C6: 0.123 | D6: 0.379
A7: E-commerce | B7: 0.03 | C7: 0.211 | D7: 0.614
A8: Educação e Ensino | B8: 0.063 | C8: 0.121 | D8: 0.321
A9: Engenharia e Indústria em Geral | B9: 0.038 | C9: 0.176 | D9: 0.373
A10: Eventos | B10: 0.043 | C10: 0.102 | D10: 0.572
A11: Financeiro, Jurídico e Serviços Relacionados | B11: 0.046 | C11: 0.148 | D11: 0.239
A12: Hardware e Eletrônicos | B12: 0.055 | C12: 0.116 | D12: 0.607
A13: Imobiliárias | B13: 0.029 | C13: 0.131 | D13: 0.383
A14: Mídia e Comunicação | B14: 0.038 | C14: 0.108 | D14: 0.268
A15: ONGs | B15: 0.047 | C15: 0.126 | D15: 0.244
... A22: Varejo | B22: 0.026 | C22: 0.217 | D22: 0.169

Sheet Calendário Fevereiro
B1: FEVEREIRO 2025
B3: SEGUNDA-FEIRA | C3: TERÇA-FEIRA | D3: QUARTA-FEIRA | E3: QUINTA-FEIRA | F3: SEXTA-FEIRA | G3: SÁBADO | H3: DOMINGO
E4: 1 | F4: 2 | G4: 3 | H4: 4
B6: 5 | C6: 6 | D6: 7 | E6: 8 | F6: 9 | G6: 10 | H6: 11
B8: 12 | C8: 13 | D8: 14 | E8: 15 | F8: 16 | G8: 17 | H8: 18
B9: Carnaval | C9: Carnaval
B10: 19 | C10: 20 | D10: 21 | E10: 22 | F10: 23 | G10: 24 | H10: 25
B11: Dia do Esportista
B12: 26 | C12: 27 | D12: 28 | E12: 29
B15: OBSERVAÇÕES:
B21: LEGENDA:
B22: Feriados
B23: Datas de nicho
B24: Datas Importantes
B25: Essenciais no E-commerce
B26: Aquecimento

Sheet Calendário Março
B1: MARÇO 2025
B3: SEGUNDA-FEIRA | C3: TERÇA-FEIRA | D3: QUARTA-FEIRA | E3: QUINTA-FEIRA | F3: SEXTA-FEIRA | G3: SÁBADO | H3: DOMINGO | J3: LEGENDA:
F4: 1 | G4: 2 | H4: 3 | J4: Feriados
J5: Datas de nicho
B6: 4 | C6: 5 | D6: 6 | E6: 7 | F6: 8 | G6: 9 | H6: 10 | J6: Datas Importantes
F7: Dia da Mulher | J7: Essenciais no E-commerce
B8: 11 | C8: 12 | D8: 13 | E8: 14 | F8: 15 | G8: 16 | H8: 17 | J8: Aquecimento
F9: Dia do Consumidor
B10: 18 | C10: 19 | D10: 20 | E10: 21 | F10: 22 | G10: 23 | H10: 24
D11: Início do Outono
B12: 25 | C12: 26 | D12: 27 | E12: 28 | F12: 29 | G12: 30 | H12: 31
H13: Páscoa
B15: OBSERVAÇÕES:

Sheet Calendário Abril
B1: ABRIL 2025
B3: SEGUNDA-FEIRA | C3: TERÇA-FEIRA | D3: QUARTA-FEIRA | E3: QUINTA-FEIRA | F3: SEXTA-FEIRA | G3: SÁBADO | H3: DOMINGO | J3: LEGENDA:
B4: 1 | C4: 2 | D4: 3 | E4: 4 | F4: 5 | G4: 6 | H4: 7 | J4: Feriados
B5: Dia da Mentira | H5: Dia Mundial da Saúde | J5: Datas de nicho
B6: 8 | C6: 9 | D6: 10 | E6: 11 | F6: 12 | G6: 13 | H6: 14 | J6: Datas Importantes
G7: Dia do Beijo | H7: Dia do Café | J7: Essenciais no E-commerce
B8: 15 | C8: 16 | D8: 17 | E8: 18 | F8: 19 | G8: 20 | H8: 21 | J8: Aquecimento
B10: 22 | C10: 23 | D10: 24 | E10: 25 | F10: 26 | G10: 27 | H10: 28
B11: Dia Mundial da Terra
B12: 29 | C12: 30
B15: OBSERVAÇÕES:

Sheet Calendário Maio
B1: MAIO 2025
B3: SEGUNDA-FEIRA | C3: TERÇA-FEIRA | D3: QUARTA-FEIRA | E3: QUINTA-FEIRA | F3: SEXTA-FEIRA | G3: SÁBADO | H3: DOMINGO | J3: LEGENDA:
D4: 1 | E4: 2 | F4: 3 | G4: 4 | H4: 5 | J4: Feriados
D5: Dia do Trabalho | J5: Datas de nicho
B6: 6 | C6: 7 | D6: 8 | E6: 9 | F6: 10 | G6: 11 | H6: 12 | J6: Datas Importantes
H7: Dia das Mães | J7: Essenciais no E-commerce
B8: 13 | C8: 14 | D8: 15 | E8: 16 | F8: 17 | G8: 18 | H8: 19 | J8: Aquecimento
B10: 20 | C10: 21 | D10: 22 | E10: 23 | F10: 24 | G10: 25 | H10: 26
D11: Dia do Abraço | G11: Dia do Orgulho Nerd
B12: 27 | C12: 28 | D12: 29 | E12: 30 | F12: 31
B15: OBSERVAÇÕES:

Sheet Calendário Junho
B1: JUNHO 2025
B3: SEGUNDA-FEIRA | C3: TERÇA-FEIRA | D3: QUARTA-FEIRA | E3: QUINTA-FEIRA | F3: SEXTA-FEIRA | G3: SÁBADO | H3: DOMINGO | J3: LEGENDA:
G4: 1 | H4: 2 | J4: Feriados
J5: Datas de nicho
B6: 3 | C6: 4 | D6: 5 | E6: 6 | F6: 7 | G6: 8 | H6: 9 | J6: Datas Importantes
J7: Essenciais no E-commerce
B8: 10 | C8: 11 | D8: 12 | E8: 13 | F8: 14 | G8: 15 | H8: 16 | J8: Aquecimento
D9: Dia dos Namorados
B10: 17 | C10: 18 | E10: 20 | F10: 21 | G10: 22 | H10: 23
E11: Início do Inverno
B12: 24 | C12: 25 | D12: 26 | E12: 27 | F12: 28 | G12: 29 | H12: 30
F13: Dia do Orgulho LGBTQIA+
B15: OBSERVAÇÕES:

Sheet Calendário Julho
B1: JULHO 2025
B3: SEGUNDA-FEIRA | C3: TERÇA-FEIRA | D3: QUARTA-FEIRA | E3: QUINTA-FEIRA | F3: SEXTA-FEIRA | G3: SÁBADO | H3: DOMINGO | J3: LEGENDA:
B4: 1 | C4: 2 | D4: 3 | E4: 4 | F4: 5 | G4: 6 | H4: 7 | J4: Feriados
H5: Dia do Chocolate | J5: Datas de nicho
B6: 8 | C6: 9 | D6: 10 | E6: 11 | F6: 12 | G6: 13 | H6: 14 | J6: Datas Importantes
G7: Dia do Rock | J7: Essenciais no E-commerce
B8: 15 | C8: 16 | D8: 17 | E8: 18 | F8: 19 | G8: 20 | H8: 21 | J8: Aquecimento
B9: Dia do Homem
B10: 22 | C10: 23 | D10: 24 | E10: 25 | F10: 26 | G10: 27 | H10: 28
F11: Dia dos Avós
B12: 29 | C12: 30 | D12: 31
C13: Dia da Amizade
B15: OBSERVAÇÕES:

Sheet Calendário Agosto
B1: AGOSTO 2025
B3: SEGUNDA-FEIRA | C3: TERÇA-FEIRA | D3: QUARTA-FEIRA | E3: QUINTA-FEIRA | F3: SEXTA-FEIRA | G3: SÁBADO | H3: DOMINGO | J3: LEGENDA:
E4: 1 | F4: 2 | G4: 3 | H4: 4 | J4: Feriados
J5: Datas de nicho
B6: 5 | C6: 6 | D6: 7 | E6: 8 | F6: 9 | G6: 10 | H6: 11 | J6: Datas Importantes
H7: Dia dos Pais | J7: Essenciais no E-commerce
B8: 12 | C8: 13 | D8: 14 | E8: 15 | F8: 16 | G8: 17 | H8: 18 | J8: Aquecimento
E9: Dia do Homem
B10: 19 | C10: 20 | D10: 21 | E10: 22 | F10: 23 | G10: 24 | H10: 25
B12: 26 | C12: 27 | D12: 28 | E12: 29 | F12: 30 | G12: 31
B15: OBSERVAÇÕES:

Sheet Calendário Setembro
B1: SETEMBRO 2025
B3: SEGUNDA-FEIRA | C3: TERÇA-FEIRA | D3: QUARTA-FEIRA | E3: QUINTA-FEIRA | F3: SEXTA-FEIRA | G3: SÁBADO | H3: DOMINGO | J3: LEGENDA:
H4: 1 | J4: Feriados
J5: Datas de nicho
B6: 2 | C6: 3 | D6: 4 | E6: 5 | F6: 6 | G6: 7 | H6: 8 | J6: Datas Importantes
G7: Independência do Brasil | J7: Essenciais no E-commerce
B8: 9 | C8: 10 | D8: 11 | E8: 12 | F8: 13 | G8: 14 | H8: 15 | J8: Aquecimento
H9: Dia do Cliente
B10: 16 | C10: 17 | D10: 18 | E10: 19 | F10: 20 | G10: 21 | H10: 22
H11: Dia Mundial Sem Carro
B12: 23 | C12: 24 | D12: 25 | E12: 26 | F12: 27 | G12: 28 | H12: 29
B14: 30
B17: OBSERVAÇÕES:

Sheet Calendário Outubro
B1: OUTUBRO 2025
B3: SEGUNDA-FEIRA | C3: TERÇA-FEIRA | D3: QUARTA-FEIRA | E3: QUINTA-FEIRA | F3: SEXTA-FEIRA | G3: SÁBADO | H3: DOMINGO | J3: LEGENDA:
C4: 1 | D4: 2 | E4: 3 | F4: 4 | G4: 5 | H4: 6 | J4: Feriados
J5: Datas de nicho
B6: 7 | C6: 8 | D6: 9 | E6: 10 | F6: 11 | G6: 12 | H6: 13 | J6: Datas Importantes
G7: Dia das Crianças | J7: Essenciais no E-commerce
B8: 14 | C8: 15 | D8: 16 | E8: 17 | F8: 18 | G8: 19 | H8: 20 | J8: Aquecimento
B10: 21 | C10: 22 | D10: 23 | E10: 24 | F10: 25 | G10: 26 | H10: 27
B12: 28 | C12: 29 | D12: 30 | E12: 31
E13: Dia das Bruxas
B15: OBSERVAÇÕES:

Sheet Calendário Novembro
B1: NOVEMBRO 2025
B3: SEGUNDA-FEIRA | C3: TERÇA-FEIRA | D3: QUARTA-FEIRA | E3: QUINTA-FEIRA | F3: SEXTA-FEIRA | G3: SÁBADO | H3: DOMINGO | J3: LEGENDA:
F4: 1 | G4: 2 | H4: 3 | J4: Feriados
J5: Datas de nicho
B6: 4 | C6: 5 | D6: 6 | E6: 7 | F6: 8 | G6: 9 | H6: 10 | J6: Datas Importantes
J7: Essenciais no E-commerce
B8: 11 | C8: 12 | D8: 13 | E8: 14 | F8: 15 | G8: 16 | H8: 17 | J8: Aquecimento
B10: 18 | C10: 19 | D10: 20 | E10: 21 | F10: 22 | G10: 23 | H10: 24
F11: Black Friday
B12: 25 | C12: 26 | D12: 27 | E12: 28 | F12: 29 | G12: 30
B13: Cyber Monday
B15: OBSERVAÇÕES:

Sheet Calendário Dezembro
B1: DEZEMBRO 2025
B3: SEGUNDA-FEIRA | C3: TERÇA-FEIRA | D3: QUARTA-FEIRA | E3: QUINTA-FEIRA | F3: SEXTA-FEIRA | G3: SÁBADO | H3: DOMINGO | J3: LEGENDA:
H4: 1 | J4: Feriados
J5: Datas de nicho
B6: 2 | C6: 3 | D6: 4 | E6: 5 | F6: 6 | G6: 7 | H6: 8 | J6: Datas Importantes
J7: Essenciais no E-commerce
B8: 9 | C8: 10 | D8: 11 | E8: 12 | F8: 13 | G8: 14 | H8: 15 | J8: Aquecimento
B10: 16 | C10: 17 | D10: 18 | E10: 19 | F10: 20 | G10: 21 | H10: 22
B12: 23 | C12: 24 | D12: 25 | E12: 26 | F12: 27 | G12: 28 | H12: 29
D13: Natal
B14: 30 | C14: 31
C15: Ano Novo
B17: OBSERVAÇÕES:
